Workbook

Sheet Disbursement
A1: Borrower: | B1: Esquire Knit Composite Limited (EKCL)
A2: Currency: | B2: BDT
A3: Type | B3: IDCOL Loan
A7: Disbursement Number | B7: Disbursement Date | C7: Disbursement | D7: Cumulative Disbursement | E7: Source
A8: 1 | B8: 44921 | C8: 350000000 | D8: =C8 -> 350000000 | E8: AFD CBD 1026 01 W | F8: Reimbursement received
A9: 2 | B9: 45061 | C9: 277057493 | D9: =D8+C9 -> 627057493 | E9: AFD CBD 1026 01 W | F9: Reimbursement received

Sheet Summary
B1: =Accrual_EKCL!D27 -> 44927 | C1: =Accrual_EKCL!E27 -> 44958 | D1: =Accrual_EKCL!F27 -> 44986 | E1: =Accrual_EKCL!G27 -> 45017 | F1: =Accrual_EKCL!H27 -> 45047 | G1: =Accrual_EKCL!I27 -> 45078 | H1: =Accrual_EKCL!J27 -> 45108 | I1: =Accrual_EKCL!K27 -> 45139 | ... CT1: =Accrual_EKCL!CV27 -> 47849
A2: Principal
A3: Opening balance | B3: =Accrual_EKCL!D28 -> 350000000 | C3: =Accrual_EKCL!E28 -> 350000000 | D3: =Accrual_EKCL!F28 -> 350000000 | E3: =Accrual_EKCL!G28 -> 350000000 | F3: =Accrual_EKCL!H28 -> 350000000 | G3: =Accrual_EKCL!I28 -> 350000000 | H3: =Accrual_EKCL!J28 -> 627057493 | I3: =Accrual_EKCL!K28 -> 627057493 | ... L3: =Accrual_EKCL!N28 -> 627057493 | M3: =L3 -> 627057493 | N3: =M3 -> 627057493 | O3: =N3 -> 627057493 | P3: =O3 -> 627057493 | Q3: =P3 -> 627057493 | R3: =Q3 -> 627057493 | S3: =R3 -> 627057493 | T3: =S3 -> 627057493 | ... CT3: =CS3 -> 627057493
A4: Repayment due | B4: =Accrual_EKCL!D32 -> 0 | C4: =Accrual_EKCL!E32 -> 0 | D4: =Accrual_EKCL!F32 -> 0 | E4: =Accrual_EKCL!G32 -> 0 | F4: =Accrual_EKCL!H32 -> 0 | G4: =Accrual_EKCL!I32 -> 0 | H4: =Accrual_EKCL!J32 -> 0 | I4: =Accrual_EKCL!K32 -> 0 | ... CT4: =Accrual_EKCL!CV32 -> 6.2705749e+08
A5: Loan Repayment | B5: =B22 -> 0 | C5: =C22 -> 0 | D5: =D22 -> 0 | E5: =E22 -> 0 | F5: =F22 -> 0 | G5: =G22 -> 0 | H5: =H22 -> 0 | I5: =I22 -> 0 | ... CT5: =CT22 -> 6.2705749e+08
A6: Repayment overdue | B6: =IF((B4-B5)>0,(B4-B5),0) -> 0 | C6: =IF((C4-C5)>0,(C4-C5),0) -> 0 | D6: =IF((D4-D5)>0,(D4-D5),0) -> 0 | E6: =IF((E4-E5)>0,(E4-E5),0) -> 0 | F6: =IF((F4-F5)>0,(F4-F5),0) -> 0 | G6: =IF((G4-G5)>0,(G4-G5),0) -> 0 | H6: =IF((H4-H5)>0,(H4-H5),0) -> 0 | I6: =IF((I4-I5)>0,(I4-I5),0) -> 0 | ... CT6: =IF((CT4-CT5)>0,(CT4-CT5),0) -> 0
A7: Loan outstanding | B7: =B3-B5 -> 350000000 | C7: =C3-C5 -> 350000000 | D7: =D3-D5 -> 350000000 | E7: =E3-E5 -> 350000000 | F7: =F3-F5 -> 350000000 | G7: =G3-G5 -> 350000000 | H7: =H3-H5 -> 627057493 | I7: =I3-I5 -> 627057493 | ... CT7: =CT3-CT5 -> 0
A8: Interest
A9: Interest accrued | B9: =Accrual_EKCL!D30 -> 291666.67 | C9: =Accrual_EKCL!E30 -> 1798611.1 | D9: =Accrual_EKCL!F30 -> 3159722.2 | E9: =Accrual_EKCL!G30 -> 4666666.7 | F9: =Accrual_EKCL!H30 -> 6125000 | G9: =Accrual_EKCL!I30 -> 8286108 | H9: =Accrual_EKCL!J30 -> 10898848 | I9: =Accrual_EKCL!K30 -> 13598678 | ... CT9: =Accrual_EKCL!CV30 -> 1.4718717e+08
A10: Interest due | B10: 0 | C10: 0 | D10: 0 | E10: =EKCL_BDT_Loan!$C$35 -> 3840277.8 | F10: =E10 -> 3840277.8 | G10: =F10 -> 3840277.8 | H10: =EKCL_BDT_Loan!$D$35 -> 9505386.4 | I10: =H10 -> 9505386.4 | J10: =I10 -> 9505386.4 | K10: =EKCL_BDT_Loan!$E$35 -> 17430696 | L10: =K10 -> 17430696 | M10: =L10 -> 17430696 | N10: =EKCL_BDT_Loan!$F$35 -> 25356006 | O10: =N10 -> 25356006 | P10: =O10 -> 25356006 | Q10: =EKCL_BDT_Loan!$G$35 -> 33281316 | R10: =Q10 -> 33281316 | S10: =R10 -> 33281316 | T10: =EKCL_BDT_Loan!$H$35 -> 40968482 | U10: =T10 -> 40968482 | V10: =U10 -> 40968482 | W10: =EKCL_BDT_Loan!$I$35 -> 48659999 | X10: =W10 -> 48659999 | Y10: =X10 -> 48659999 | Z10: =EKCL_BDT_Loan!$J$35 -> 55861907 | AA10: =Z10 -> 55861907 | AB10: =AA10 -> 55861907 | AC10: =EKCL_BDT_Loan!$K$35 -> 62587352 | AD10: =AC10 -> 62587352 | AE10: =AD10 -> 62587352 | AF10: =EKCL_BDT_Loan!$L$35 -> 69512821 | AG10: =AF10 -> 69512821 | AH10: =AG10 -> 69512821 | AI10: =EKCL_BDT_Loan!$M$35 -> 76034750 | AJ10: =AI10 -> 76034750 | AK10: =AJ10 -> 76034750 | AL10: =EKCL_BDT_Loan!$N$35 -> 82229215 | AM10: =AL10 -> 82229215 | AN10: =AM10 -> 82229215 | AO10: =EKCL_BDT_Loan!$O$35 -> 88098684 | AP10: =AO10 -> 88098684 | AQ10: =AP10 -> 88098684 | AR10: =EKCL_BDT_Loan!$P$35 -> 93832667 | AS10: =AR10 -> 93832667 | AT10: =AS10 -> 93832667 | AU10: =EKCL_BDT_Loan!$Q$35 -> 99297408 | AV10: =AU10 -> 99297408 | AW10: =AV10 -> 99297408 | AX10: =EKCL_BDT_Loan!$R$35 -> 1.0443311e+08 | AY10: =AX10 -> 1.0443311e+08 | AZ10: =AY10 -> 1.0443311e+08 | BA10: =EKCL_BDT_Loan!$S$35 -> 1.0924235e+08 | BB10: =BA10 -> 1.0924235e+08 | BC10: =BB10 -> 1.0924235e+08 | BD10: =EKCL_BDT_Loan!$T$35 -> 1.1387901e+08 | BE10: =BD10 -> 1.1387901e+08 | BF10: =BE10 -> 1.1387901e+08 | BG10: =EKCL_BDT_Loan!$U$35 -> 1.182327e+08 | BH10: =BG10 -> 1.182327e+08 | BI10: =BH10 -> 1.182327e+08 | BJ10: =EKCL_BDT_Loan!$V$35 -> 1.2225569e+08 | BK10: =BJ10 -> 1.2225569e+08 | BL10: =BK10 -> 1.2225569e+08 | BM10: =EKCL_BDT_Loan!$W$35 -> 1.2599176e+08 | BN10: =BM10 -> 1.2599176e+08 | BO10: =BN10 -> 1.2599176e+08 | BP10: =EKCL_BDT_Loan!$X$35 -> 1.2947518e+08 | BQ10: =BP10 -> 1.2947518e+08 | BR10: =BQ10 -> 1.2947518e+08 | BS10: =EKCL_BDT_Loan!$Y$35 -> 1.3266122e+08 | BT10: =BS10 -> 1.3266122e+08 | BU10: =BT10 -> 1.3266122e+08 | BV10: =EKCL_BDT_Loan!$Z$35 -> 1.3551482e+08 | BW10: =BV10 -> 1.3551482e+08 | BX10: =BW10 -> 1.3551482e+08 | BY10: =EKCL_BDT_Loan!$AA$35 -> 1.3803883e+08 | BZ10: =BY10 -> 1.3803883e+08 | CA10: =BZ10 -> 1.3803883e+08 | CB10: =EKCL_BDT_Loan!$AB$35 -> 1.4031027e+08 | CC10: =CB10 -> 1.4031027e+08 | CD10: =CC10 -> 1.4031027e+08 | CE10: =EKCL_BDT_Loan!$AC$35 -> 1.4226918e+08 | CF10: =CE10 -> 1.4226918e+08 | CG10: =CF10 -> 1.4226918e+08 | CH10: =EKCL_BDT_Loan!$AD$35 -> 1.4389381e+08 | CI10: =CH10 -> 1.4389381e+08 | CJ10: =CI10 -> 1.4389381e+08 | CK10: =EKCL_BDT_Loan!$AE$35 -> 1.4518716e+08 | CL10: =CK10 -> 1.4518716e+08 | CM10: =CL10 -> 1.4518716e+08 | CN10: =EKCL_BDT_Loan!$AF$35 -> 1.4618486e+08 | CO10: =CN10 -> 1.4618486e+08 | CP10: =CO10 -> 1.4618486e+08 | CQ10: =EKCL_BDT_Loan!$AG$35 -> 1.4685412e+08 | CR10: =CQ10 -> 1.4685412e+08 | CS10: =CR10 -> 1.4685412e+08 | CT10: =EKCL_BDT_Loan!$AH$35 -> 1.4718717e+08
A11: interest received | B11: =B26 -> 0 | C11: =C26 -> 0 | D11: =D26 -> 0 | E11: =E26 -> 3840278 | F11: =F26 -> 3840278 | G11: =G26 -> 3840278 | H11: =H26 -> 9505387 | I11: =I26 -> 9505387 | ... CT11: =CT26 -> 1.4718717e+08
A12: Interest overdue | B12: 0 | C12: =IF((C10-C11)>0,(C10-C11),0) -> 0 | D12: =IF((D10-D11)>0,(D10-D11),0) -> 0 | E12: =IF((E10-E11)>0,(E10-E11),0) -> 0 | F12: =IF((F10-F11)>0,(F10-F11),0) -> 0 | G12: =IF((G10-G11)>0,(G10-G11),0) -> 0 | H12: =IF((H10-H11)>0,(H10-H11),0) -> 0 | I12: =IF((I10-I11)>0,(I10-I11),0) -> 0 | J12: =IF((J10-J11)>0,(J10-J11),0) -> 0 | ... CT12: =IF((CT10-CT11)>0,(CT10-CT11),0) -> 0
A13: Interest receivable | B13: =B9-B11 -> 291666.67 | C13: =C9-C11 -> 1798611.1 | D13: =D9-D11 -> 3159722.2 | E13: =E9-E11 -> 826388.67 | F13: =F9-F11 -> 2284722 | G13: =G9-G11 -> 4445830 | H13: =H9-H11 -> 1393460.5 | I13: =I9-I11 -> 4093291.4 | ... CT13: =CT9-CT11 -> 0
A14: LD and others | B14: =B28 -> 0 | C14: =C28 -> 0 | D14: =D28 -> 0 | E14: =E28 -> 0 | F14: =F28 -> 0 | G14: =G28 -> 0 | H14: =H28 -> 24642 | I14: =I28 -> 24642 | ... CT14: =CT28 -> 24642
B19: =B1 -> 44927 | C19: =C1 -> 44958 | D19: =D1 -> 44986 | E19: =E1 -> 45017 | F19: =F1 -> 45047 | G19: =G1 -> 45078 | H19: =H1 -> 45108 | I19: =I1 -> 45139 | ... CT19: =CT1 -> 47849
A20: Repayment receipts:
A21: Repayment received | C21: =C4-B5 -> 0 | F21: =F4-E5 -> 0 | I21: =I4-H5 -> 0 | N21: =N4-M5 -> 0 | O21: =O4-N5 -> 0 | Q21: =4979869+500000+1400000+11962351 -> 18842220 | R21: 0 | T21: =3037649+12798092+3242007 -> 19077748 | U21: 0 | W21: 19316220 | X21: 0 | Z21: 19557673 | AC21: =7333186+3478071 -> 10811257 | AF21: 0 | AI21: 0 | AL21: =AL4-AK5 -> 69894894 | AO21: =AO4-AN5 -> 20810971 | AR21: =AR4-AQ5 -> 21071108 | AU21: =AU4-AT5 -> 21334497 | AX21: =AX4-AW5 -> 21601178 | BA21: =BA4-AZ5 -> 21871192 | BD21: =BD4-BC5 -> 22144582 | BG21: =BG4-BF5 -> 22421390 | BJ21: =BJ4-BI5 -> 22701657 | BM21: =BM4-BL5 -> 22985428 | BP21: =BP4-BO5 -> 23272746 | BS21: =BS4-BR5 -> 23563655 | BV21: =BV4-BU5 -> 23858201 | BY21: =BY4-BX5 -> 24156428 | CB21: =CB4-CA5 -> 24458383 | CE21: =CE4-CD5 -> 24764113 | CH21: =CH4-CG5 -> 25073665 | CK21: =CK4-CJ5 -> 25387085 | CN21: =CN4-CM5 -> 25704424 | CQ21: =CQ4-CP5 -> 26025729 | CT21: =CT4-CS5 -> 26351051
A22: Repayment received (cumulative) | B22: =+B21 -> 0 | C22: =B22+C21 -> 0 | D22: =C22+D21 -> 0 | E22: =D22+E21 -> 0 | F22: =E22+F21 -> 0 | G22: =F22+G21 -> 0 | H22: =G22+H21 -> 0 | I22: =H22+I21 -> 0 | J22: =I22+J21 -> 0 | ... CT22: =CS22+CT21 -> 6.2705749e+08
A24: Interest receipts:
A25: Interest received | C25: =+C10-B11 -> 0 | E25: 3840278 | H25: 5665109 | K25: =10249+2500000+5000000+415061 -> 7925310 | N25: 7925310 | Q25: =183862+7741448 -> 7925310 | T25: =2258552+3000000+100000+2328613 -> 7687165 | W25: =4171387+3520131 -> 7691518 | Z25: 7201908 | AC25: 6725444 | AF25: 6925470 | AI25: =2500000+2500000+1521929 -> 6521929 | AL25: =AL10-AK11 -> 6194464.2 | AO25: =AO10-AN11 -> 5869468.5 | AR25: =AR10-AQ11 -> 5733983.2 | AU25: =AU10-AT11 -> 5464741.3 | AX25: =AX10-AW11 -> 5135697.6 | BA25: =BA10-AZ11 -> 4809246.6 | BD25: =BD10-BC11 -> 4636653.5 | BG25: =BG10-BF11 -> 4353695 | BJ25: =BJ10-BI11 -> 4022990.7 | BM25: =BM10-BL11 -> 3736067 | BP25: =BP10-BO11 -> 3483420 | BS25: =BS10-BR11 -> 3186046 | BV25: =BV10-BU11 -> 2853596.7 | BY25: =BY10-BX11 -> 2524011 | CB25: =CB10-CA11 -> 2271434.6 | CE25: =CE10-CD11 -> 1958910.9 | CH25: =CH10-CG11 -> 1624627.5 | CK25: =CK10-CJ11 -> 1293353.6 | CN25: =CN10-CM11 -> 997704.28 | CQ25: =CQ10-CP11 -> 669258.86 | CR25: =CR10-CQ11 -> 0 | CS25: =CS10-CR11 -> 0 | CT25: =CT10-CS11 -> 333048
A26: Interest received (cumulative) | B26: =+B25 -> 0 | C26: =B26+C25 -> 0 | D26: =C26+D25 -> 0 | E26: =D26+E25 -> 3840278 | F26: =E26+F25 -> 3840278 | G26: =F26+G25 -> 3840278 | H26: =G26+H25 -> 9505387 | I26: =H26+I25 -> 9505387 | J26: =I26+J25 -> 9505387 | ... CT26: =CS26+CT25 -> 1.4718717e+08
A27: LD/others | B27: 0 | C27: 0 | D27: 0 | E27: 0 | F27: 0 | G27: 0 | H27: 24642 | I27: 0 | J27: 0 | K27: 0 | L27: 0 | M27: 0 | N27: 0 | O27: 0 | P27: 0 | Q27: 0 | R27: 0 | S27: 0 | T27: 0 | U27: 0 | V27: 0 | W27: 0 | X27: 0 | Y27: 0 | Z27: 0 | AA27: 0 | AB27: 0 | AC27: 0 | AD27: 0 | AE27: 0 | AF27: 0 | AG27: 0 | AH27: 0 | AI27: 0 | AJ27: 0 | AK27: 0 | AL27: 0 | AM27: 0 | AN27: 0 | AO27: 0 | AP27: 0 | AQ27: 0 | AR27: 0 | AS27: 0 | AT27: 0 | AU27: 0 | AV27: 0 | AW27: 0 | AX27: 0 | AY27: 0 | AZ27: 0 | BA27: 0 | BB27: 0 | BC27: 0 | BD27: 0 | BE27: 0 | BF27: 0 | BG27: 0 | BH27: 0 | BI27: 0 | BJ27: 0 | BK27: 0 | BL27: 0 | BM27: 0 | BN27: 0 | BO27: 0 | BP27: 0 | BQ27: 0 | BR27: 0 | BS27: 0 | BT27: 0 | BU27: 0 | BV27: 0 | BW27: 0 | BX27: 0 | BY27: 0 | BZ27: 0 | CA27: 0 | CB27: 0 | CC27: 0 | CD27: 0 | CE27: 0 | CF27: 0 | CG27: 0 | CH27: 0 | CI27: 0 | CJ27: 0 | CK27: 0 | CL27: 0 | CM27: 0 | CN27: 0 | CO27: 0 | CP27: 0 | CQ27: 0 | CR27: 0 | CS27: 0 | CT27: 0
A28: LD/others (cumulative) | B28: =B27 -> 0 | C28: =B28+C27 -> 0 | D28: =C28+D27 -> 0 | E28: =D28+E27 -> 0 | F28: =E28+F27 -> 0 | G28: =F28+G27 -> 0 | H28: =G28+H27 -> 24642 | I28: =H28+I27 -> 24642 | J28: =I28+J27 -> 24642 | ... CT28: =CS28+CT27 -> 24642
A30: Actual Payment date | E30: 45033 | H30: 45172 | J30: 45211 | K30: 45320 | L30: 45404 | S30: 45470 | U30: 45582 | V30: 45582 | W30: 45585 | Y30: 45585 | Z30: 45585 | AA30: 45585 | AB30: 45622 | AD30: 45652 | AE30: 45889 | AI30: 45984 | AJ30: 45984 | AK30: 45986
A31: Actual Payment amount: | I31: 5700000 | N31: 8524233 | T31: 10000000 | U31: 3000000 | X31: 6500000 | Y31: 8500000 | AC31: 15000000 | AD31: 20000000 | AH31: 63100000 | AK31: 5000000
A32: Interest | E32: 3840278 | H32: 5665109 | I32: 10249 | J32: 2500000 | K32: 5000000 | L32: 415061 | M32: 7925310 | N32: 183862 | S32: 7741448 | T32: 2258552 | U32: 3000000 | V32: 100000 | W32: 2328613 | X32: 4171387 | Y32: 3520131 | AD32: 7201908 | AE32: 6725444 | AF32: 6925470 | AI32: 2500000 | AJ32: 2500000 | AK32: 1521929
A33: Principal | Y33: 4979869 | Z33: 500000 | AA33: 1400000 | AB33: 11962351 | AC33: 3037649 | AD33: 12798092 | AE33: 3242007 | AF33: 19316220 | AG33: 19557673 | AH33: 7333186 | AK33: 3478071
A34: LPC | H34: 24642
A35: Total | B35: =+SUM(B32:B34) -> 0 | C35: =+SUM(C32:C34) -> 0 | D35: =+SUM(D32:D34) -> 0 | E35: =+SUM(E32:E34) -> 3840278 | F35: =+SUM(F32:F34) -> 0 | G35: =+SUM(G32:G34) -> 0 | H35: =+SUM(H32:H34) -> 5689751 | I35: =+SUM(I32:I34) -> 10249 | ... CT35: =+SUM(CT32:CT34) -> 0

Sheet EKCL_BDT_Loan
A1: Project name: | C1: =Disbursement!B1 -> Esquire Knit Composite Limited (EKCL)
A3: Agreement date | C3: 44857
A5: Sanctioned Amount | C5: 750000000 | F5: Interest Grace | H5: 0 months
F6: Principal Grace | H6: 12 months
A7: First Drawdown Date | C7: =Disbursement!B8 -> 44921
F8: Interest Grace Ends | H8: =EDATE(C22,0) -> 44921
A9: Request Date | C9: 44868 | F9: Principal Grace Ends | H9: =EDATE(C22,12) -> 45286
A11: Interest Rate | C11: 0.05
F12: *If payment date is not a business day, then payment date shall be immediately the preceding business day.
A13: Tenure | C13: 96 months
A15: Principal | C15: Quarterly Installment
A17: Interest calculation | C17: 360 | D17: days basis
A19: Number of installments | C19: 28
A21: Drawdown
C22: =Disbursement!B8 -> 44921 | D22: =Disbursement!B9 -> 45061 | E22: =Disbursement!B10 -> 0
C23: =Disbursement!C8 -> 350000000 | D23: =Disbursement!C9 -> 277057493 | E23: =Disbursement!C10 -> 0
C24: =C23 -> 350000000 | D24: =D23+C24 -> 627057493 | E24: =E23+D24 -> 627057493
A26: Period | C26: =+C32 -> 45000 | D26: =+D32 -> 45092 | E26: =+E32 -> 45183 | F26: =+F32 -> 45274 | G26: =+G32 -> 45365 | H26: =+H32 -> 45456 | I26: =+I32 -> 45550 | J26: =+J32 -> 45641 | ... AH26: =+AH32 -> 47832
A27: Expected Interest Rate | C27: 0.05 | D27: 0.05 | E27: 0.05 | F27: 0.05 | G27: 0.05 | H27: 0.05 | I27: 0.05 | J27: 0.05 | K27: 0.05 | L27: 0.05 | M27: 0.05 | N27: 0.05 | O27: 0.05 | P27: 0.05 | Q27: 0.05 | R27: 0.05 | S27: 0.05 | T27: 0.05 | U27: 0.05 | V27: 0.05 | W27: 0.05 | X27: 0.05 | Y27: 0.05 | Z27: 0.05 | AA27: 0.05 | AB27: 0.05 | AC27: 0.05 | AD27: 0.05 | AE27: 0.05 | AF27: 0.05 | AG27: 0.05 | AH27: 0.05
A30: Repayment
A31: Repayment Period | G31: 1 | H31: 2 | I31: 3 | J31: 4 | K31: 5 | L31: 6 | M31: 7 | N31: 8 | O31: 9 | P31: 10 | Q31: 11 | R31: 12 | S31: 13 | T31: 14 | U31: 15 | V31: 16 | W31: 17 | X31: 18 | Y31: 19 | Z31: 20 | AA31: 21 | AB31: 22 | AC31: 23 | AD31: 24 | AE31: 25 | AF31: 26 | AG31: 27 | AH31: 28
A32: Repayment Date | C32: 45000 | D32: 45092 | E32: 45183 | F32: 45274 | G32: 45365 | H32: 45456 | I32: 45550 | J32: 45641 | K32: 45729 | L32: 45823 | M32: 45915 | N32: 46006 | O32: 46096 | P32: 46188 | Q32: 46280 | R32: 46371 | S32: 46461 | T32: 46553 | U32: 46645 | V32: 46736 | W32: 46827 | X32: 46919 | Y32: 47011 | Z32: 47102 | AA32: 47192 | AB32: 47284 | AC32: 47376 | AD32: 47467 | AE32: 47557 | AF32: 47649 | AG32: 47741 | AH32: 47832
A33: Opening Balance | C33: =C24 -> 350000000 | D33: =C39 -> 350000000 | E33: =D39 -> 627057493 | F33: =E39 -> 627057493 | G33: =F39 -> 627057493 | H33: =G39 -> 6.0821527e+08 | I33: =H39 -> 5.8913752e+08 | J33: =I39 -> 5.698213e+08 | K33: =J39 -> 5.5026363e+08 | ... AH33: =AG39 -> 26351051
A34: Interest Payment | C34: =C33*(C32-C22)*C27/360 -> 3840277.8 | D34: =(D33*(D22-C32)*D27/360)+(D39*(D32-D22)*D27/360) -> 5665108.7 | E34: =E33*(E32-D32)*E27/360 -> 7925310 | F34: =F33*(F32-E32)*F27/360 -> 7925310 | G34: =G33*(G32-F32)*G27/360 -> 7925310 | H34: =H33*(H32-G32)*H27/360 -> 7687165.3 | I34: =I33*(I32-H32)*I27/360 -> 7691517.7 | J34: =J33*(J32-I32)*J27/360 -> 7201908.2 | K34: =K33*(K32-J32)*K27/360 -> 6725444.4 | L34: =L33*(L32-K32)*L27/360 -> 6925469.4 | ... AH34: =AH33*(AH32-AG32)*AH27/360 -> 333048
A35: Cumulative interest | C35: =C34 -> 3840277.8 | D35: =D34+C35 -> 9505386.4 | E35: =E34+D35 -> 17430696 | F35: =F34+E35 -> 25356006 | G35: =G34+F35 -> 33281316 | H35: =H34+G35 -> 40968482 | I35: =I34+H35 -> 48659999 | J35: =J34+I35 -> 55861907 | K35: =K34+J35 -> 62587352 | ... AH35: =AH34+AG35 -> 1.4718717e+08
A36: Principal Payment | C36: 0 | D36: 0 | E36: 0 | F36: 0 | G36: =+-PPMT(G27/4,G31,$C$19,$G$33) -> 18842220 | H36: =+-PPMT(H27/4,H31,$C$19,$G$33) -> 19077748 | I36: =+-PPMT(I27/4,I31,$C$19,$G$33) -> 19316220 | J36: =+-PPMT(J27/4,J31,$C$19,$G$33) -> 19557673 | K36: =+-PPMT(K27/4,K31,$C$19,$G$33) -> 19802144 | L36: =+-PPMT(L27/4,L31,$C$19,$G$33) -> 20049670 | M36: =+-PPMT(M27/4,M31,$C$19,$G$33) -> 20300291 | N36: =+-PPMT(N27/4,N31,$C$19,$G$33) -> 20554045 | ... AH36: =+-PPMT(AH27/4,AH31,$C$19,$G$33) -> 26351051
A37: Cumulative repayment | C37: =C36 -> 0 | D37: =D36+C37 -> 0 | E37: =E36+D37 -> 0 | F37: =F36+E37 -> 0 | G37: =G36+F37 -> 18842220 | H37: =H36+G37 -> 37919969 | I37: =I36+H37 -> 57236189 | J37: =J36+I37 -> 76793861 | K37: =K36+J37 -> 96596005 | ... AH37: =AH36+AG37 -> 6.2705749e+08
A38: Total Debt Service | C38: =C36+C34 -> 3840277.8 | D38: =D36+D34 -> 5665108.7 | E38: =E36+E34 -> 7925310 | F38: =F36+F34 -> 7925310 | G38: =G36+G34 -> 26767530 | H38: =H36+H34 -> 26764913 | I38: =I36+I34 -> 27007738 | J38: =J36+J34 -> 26759581 | ... AH38: =AH36+AH34 -> 26684099
A39: Closing Balance | C39: =C33-C36 -> 350000000 | D39: =D33-D36+D23 -> 627057493 | E39: =E33-E36 -> 627057493 | F39: =F33-F36 -> 627057493 | G39: =G33-G36 -> 6.0821527e+08 | H39: =H33-H36 -> 5.8913752e+08 | I39: =I33-I36 -> 5.698213e+08 | J39: =J33-J36 -> 5.5026363e+08 | K39: =K33-K36 -> 5.3046149e+08 | L39: =L33-L36 -> 5.1041182e+08 | ... AH39: =AH33-AH36 -> 0
A43: Average Installment Size
A44: Month | C44: =C32 -> 45000 | D44: =D32 -> 45092 | E44: =E32 -> 45183 | F44: =F32 -> 45274 | G44: =G32 -> 45365 | H44: =H32 -> 45456 | I44: =I32 -> 45550 | J44: =J32 -> 45641 | ... AH44: =AH32 -> 47832
A45: Amount | C45: =AVERAGE($C$38:C38) -> 3840277.8 | D45: =AVERAGE($C$38:D38) -> 4752693.2 | E45: =AVERAGE($C$38:E38) -> 5810232.1 | F45: =AVERAGE($C$38:F38) -> 6339001.6 | G45: =AVERAGE($C$38:G38) -> 10424707 | H45: =AVERAGE($C$38:H38) -> 13148075 | I45: =AVERAGE($C$38:I38) -> 15128027 | J45: =AVERAGE($C$38:J38) -> 16581971 | ... AH45: =AVERAGE($C$38:AH38) -> 24195146

Sheet Accrual_EKCL
A1: Project name: | B1: =EKCL_BDT_Loan!C1 -> Esquire Knit Composite Limited (EKCL)
A3: Assumptions:
A5: Agreement date | B5: =+EKCL_BDT_Loan!C3 -> 44857
A7: Loan Amount | B7: =EKCL_BDT_Loan!C5 -> 750000000 | C7: BDT
A9: Drawdown Date | B9: =EKCL_BDT_Loan!C7 -> 44921
A11: Interest Rate | B11: =+EKCL_BDT_Loan!C11 -> 0.05
A12: Tenure | B12: =+EKCL_BDT_Loan!C13 -> 96 months
A13: Interest calculation | B13: 360 | C13: days basis
A14: Principal | B14: =EKCL_BDT_Loan!C15 -> Quarterly Installment
A16: Drawdown
C17: =EKCL_BDT_Loan!C22 -> 44921 | D17: =EKCL_BDT_Loan!D22 -> 45061 | E17: =EKCL_BDT_Loan!E22 -> 0
C18: =EKCL_BDT_Loan!C23 -> 350000000 | D18: =EKCL_BDT_Loan!D23 -> 277057493 | E18: =EKCL_BDT_Loan!E23 -> 0
C19: =C18 -> 350000000 | D19: =D18+C19 -> 627057493 | E19: =E18+D19 -> 627057493
A22: Interest Rate | D22: 0.05 | E22: 0.05 | F22: 0.05 | G22: 0.05 | H22: 0.05 | I22: 0.05 | J22: 0.05 | K22: 0.05 | L22: 0.05 | M22: 0.05 | N22: 0.05 | O22: 0.05 | P22: 0.05 | Q22: 0.05 | R22: 0.05 | S22: 0.05 | T22: 0.05 | U22: 0.05 | V22: 0.05 | W22: 0.05 | X22: 0.05 | Y22: 0.05 | Z22: 0.05 | AA22: 0.05 | AB22: 0.05 | AC22: 0.05 | AD22: 0.05 | AE22: 0.05 | AF22: 0.05 | AG22: 0.05 | AH22: 0.05 | AI22: 0.05 | AJ22: 0.05 | AK22: 0.05 | AL22: 0.05 | AM22: 0.05 | AN22: 0.05 | AO22: 0.05 | AP22: 0.05 | AQ22: 0.05 | AR22: 0.05 | AS22: 0.05 | AT22: 0.05 | AU22: 0.05 | AV22: 0.05 | AW22: 0.05 | AX22: 0.05 | AY22: 0.05 | AZ22: 0.05 | BA22: 0.05 | BB22: 0.05 | BC22: 0.05 | BD22: 0.05 | BE22: 0.05 | BF22: 0.05 | BG22: 0.05 | BH22: 0.05 | BI22: 0.05 | BJ22: 0.05 | BK22: 0.05 | BL22: 0.05 | BM22: 0.05 | BN22: 0.05 | BO22: 0.05 | BP22: 0.05 | BQ22: 0.05 | BR22: 0.05 | BS22: 0.05 | BT22: 0.05 | BU22: 0.05 | BV22: 0.05 | BW22: 0.05 | BX22: 0.05 | BY22: 0.05 | BZ22: 0.05 | CA22: 0.05 | CB22: 0.05 | CC22: 0.05 | CD22: 0.05 | CE22: 0.05 | CF22: 0.05 | CG22: 0.05 | CH22: 0.05 | CI22: 0.05 | CJ22: 0.05 | CK22: 0.05 | CL22: 0.05 | CM22: 0.05 | CN22: 0.05 | CO22: 0.05 | CP22: 0.05 | CQ22: 0.05 | CR22: 0.05 | CS22: 0.05 | CT22: 0.05 | CU22: 0.05 | CV22: 0.05
A26: Accrual of interest
A27: Months | D27: 44927 | E27: =EDATE(D27,1) -> 44958 | F27: =EDATE(E27,1) -> 44986 | G27: =EDATE(F27,1) -> 45017 | H27: =EDATE(G27,1) -> 45047 | I27: =EDATE(H27,1) -> 45078 | J27: =EDATE(I27,1) -> 45108 | K27: =EDATE(J27,1) -> 45139 | L27: =EDATE(K27,1) -> 45170 | ... CV27: =EDATE(CU27,1) -> 47849
A28: Opening Balance | D28: =C19 -> 350000000 | E28: =D34 -> 350000000 | F28: =E34 -> 350000000 | G28: =F34 -> 350000000 | H28: =G34 -> 350000000 | I28: =H34 -> 350000000 | J28: =I34 -> 627057493 | K28: =J34 -> 627057493 | L28: =K34 -> 627057493 | ... CV28: =CU34 -> 26351051
A29: Interest Payment | D29: =D28*(D27-C17)*D22/360 -> 291666.67 | E29: =E28*(E27-D27)*E22/360 -> 1506944.4 | F29: =F28*(F27-E27)*F22/360 -> 1361111.1 | G29: =G28*(G27-F27)*G22/360 -> 1506944.4 | H29: =H28*(H27-G27)*H22/360 -> 1458333.3 | I29: =(I28*(D17-H27)*I22/360)+(I34*(I27-D17)*I22/360) -> 2161108 | J29: =J28*(J27-I27)*J22/360 -> 2612739.6 | K29: =K28*(K27-J27)*K22/360 -> 2699830.9 | L29: =L28*(L27-K27)*L22/360 -> 2699830.9 | M29: =M28*(M27-L27)*M22/360 -> 2612739.6 | N29: =N28*(N27-M27)*N22/360 -> 2699830.9 | O29: =O28*(O27-N27)*O22/360 -> 2612739.6 | P29: =P28*(P27-O27)*P22/360 -> 2699830.9 | Q29: =Q28*(Q27-P27)*Q22/360 -> 2699830.9 | R29: =R28*(R27-Q27)*R22/360 -> 2525648.2 | S29: =(S28*(EKCL_BDT_Loan!G32-Accrual_EKCL!R27)*(Accrual_EKCL!S22/360))+(Accrual_EKCL!S34*(Accrual_EKCL!S27-EKCL_BDT_Loan!G32)*(Accrual_EKCL!S22/360)) -> 2652725.3 | T29: =T28*(T27-S27)*T22/360 -> 2534230.3 | U29: =U28*(U27-T27)*U22/360 -> 2618704.6 | V29: =(V28*(EKCL_BDT_Loan!H32-Accrual_EKCL!U27)*(Accrual_EKCL!V22/360))+(Accrual_EKCL!V34*(Accrual_EKCL!V27-EKCL_BDT_Loan!H32)*(Accrual_EKCL!V22/360)) -> 2486535.9 | W29: =W28*(W27-V27)*W22/360 -> 2536564.3 | X29: =X28*(X27-W27)*X22/360 -> 2536564.3 | Y29: =(Y28*(EKCL_BDT_Loan!I32-Accrual_EKCL!X27)*(Accrual_EKCL!Y22/360))+(Accrual_EKCL!Y34*(Accrual_EKCL!Y27-EKCL_BDT_Loan!I32)*(Accrual_EKCL!Y22/360)) -> 2411814.8 | Z29: =Z28*(Z27-Y27)*Z22/360 -> 2453397.3 | AA29: =AA28*(AA27-Z27)*AA22/360 -> 2374255.4 | AB29: =(AB28*(EKCL_BDT_Loan!J32-Accrual_EKCL!AA27)*(Accrual_EKCL!AB22/360))+(Accrual_EKCL!AB34*(Accrual_EKCL!AB27-EKCL_BDT_Loan!J32)*(Accrual_EKCL!AB22/360)) -> 2407219.4 | AC29: =AC28*(AC27-AB27)*AC22/360 -> 2369190.6 | AD29: =AD28*(AD27-AC27)*AD22/360 -> 2139914.1 | AE29: =(AE28*(EKCL_BDT_Loan!K32-Accrual_EKCL!AD27)*(Accrual_EKCL!AE22/360))+(Accrual_EKCL!AE34*(Accrual_EKCL!AE27-EKCL_BDT_Loan!K32)*(Accrual_EKCL!AE22/360)) -> 2316935 | AF29: =AF28*(AF27-AE27)*AF22/360 -> 2210256.2 | AG29: =AG28*(AG27-AF27)*AG22/360 -> 2283931.4 | AH29: =(AH28*(EKCL_BDT_Loan!L32-Accrual_EKCL!AG27)*(Accrual_EKCL!AH22/360))+(Accrual_EKCL!AH34*(Accrual_EKCL!AH27-EKCL_BDT_Loan!L32)*(Accrual_EKCL!AH22/360)) -> 2165701.4 | AI29: =AI28*(AI27-AH27)*AI22/360 -> 2197606.4 | AJ29: =AJ28*(AJ27-AI27)*AJ22/360 -> 2197606.4 | AK29: =(AK28*(EKCL_BDT_Loan!M32-Accrual_EKCL!AJ27)*(Accrual_EKCL!AK22/360))+(Accrual_EKCL!AK34*(Accrual_EKCL!AK27-EKCL_BDT_Loan!M32)*(Accrual_EKCL!AK22/360)) -> 2081604.1 | AL29: =AL28*(AL27-AK27)*AL22/360 -> 2110202.4 | AM29: =AM28*(AM27-AL27)*AM22/360 -> 2042131.4 | AN29: =(AN28*(EKCL_BDT_Loan!N32-Accrual_EKCL!AM27)*(Accrual_EKCL!AN22/360))+(Accrual_EKCL!AN34*(Accrual_EKCL!AN27-EKCL_BDT_Loan!N32)*(Accrual_EKCL!AN22/360)) -> 2061672 | AO29: =AO28*(AO27-AN27)*AO22/360 -> 2021705.8 | AP29: =AP28*(AP27-AO27)*AP22/360 -> 1826056.9 | AQ29: =(AQ28*(EKCL_BDT_Loan!O32-Accrual_EKCL!AP27)*(Accrual_EKCL!AQ22/360))+(Accrual_EKCL!AQ34*(Accrual_EKCL!AQ27-EKCL_BDT_Loan!O32)*(Accrual_EKCL!AQ22/360)) -> 1972568.8 | AR29: =AR28*(AR27-AQ27)*AR22/360 -> 1869777.1 | AS29: =AS28*(AS27-AR27)*AS22/360 -> 1932103 | AT29: =(AT28*(EKCL_BDT_Loan!P32-Accrual_EKCL!AS27)*(Accrual_EKCL!AT22/360))+(Accrual_EKCL!AT34*(Accrual_EKCL!AT27-EKCL_BDT_Loan!P32)*(Accrual_EKCL!AT22/360)) -> 1822952.4 | AU29: =AU28*(AU27-AT27)*AU22/360 -> 1841380.2 | AV29: =AV28*(AV27-AU27)*AV22/360 -> 1841380.2 | AW29: =(AW28*(EKCL_BDT_Loan!Q32-Accrual_EKCL!AV27)*(Accrual_EKCL!AW22/360))+(Accrual_EKCL!AW34*(Accrual_EKCL!AW27-EKCL_BDT_Loan!Q32)*(Accrual_EKCL!AW22/360)) -> 1734570.9 | AX29: =AX28*(AX27-AW27)*AX22/360 -> 1749523.3 | AY29: =AY28*(AY27-AX27)*AY22/360 -> 1693087.1 | AZ29: =(AZ28*(EKCL_BDT_Loan!R32-Accrual_EKCL!AY27)*(Accrual_EKCL!AZ22/360))+(Accrual_EKCL!AZ34*(Accrual_EKCL!AZ27-EKCL_BDT_Loan!R32)*(Accrual_EKCL!AZ22/360)) -> 1698520.6 | BA29: =BA28*(BA27-AZ27)*BA22/360 -> 1656518.3 | BB29: =BB28*(BB27-BA27)*BB22/360 -> 1496210.1 | BC29: =(BC28*(EKCL_BDT_Loan!S32-Accrual_EKCL!BB27)*(Accrual_EKCL!BC22/360))+(Accrual_EKCL!BC34*(Accrual_EKCL!BC27-EKCL_BDT_Loan!S32)*(Accrual_EKCL!BC22/360)) -> 1604878 | BD29: =BD28*(BD27-BC27)*BD22/360 -> 1511952.2 | BE29: =BE28*(BE27-BD27)*BE22/360 -> 1562350.6 | BF29: =(BF28*(EKCL_BDT_Loan!T32-Accrual_EKCL!BE27)*(Accrual_EKCL!BF22/360))+(Accrual_EKCL!BF34*(Accrual_EKCL!BF27-EKCL_BDT_Loan!T32)*(Accrual_EKCL!BF22/360)) -> 1462742.1 | BG29: =BG28*(BG27-BF27)*BG22/360 -> 1467005.9 | BH29: =BH28*(BH27-BG27)*BH22/360 -> 1467005.9 | BI29: =(BI28*(EKCL_BDT_Loan!U32-Accrual_EKCL!BH27)*(Accrual_EKCL!BI22/360))+(Accrual_EKCL!BI34*(Accrual_EKCL!BI27-EKCL_BDT_Loan!U32)*(Accrual_EKCL!BI22/360)) -> 1369857.8 | BJ29: =BJ28*(BJ27-BI27)*BJ22/360 -> 1370469.4 | BK29: =BK28*(BK27-BJ27)*BK22/360 -> 1326260.7 | BL29: =(BL28*(EKCL_BDT_Loan!V32-Accrual_EKCL!BK27)*(Accrual_EKCL!BL22/360))+(Accrual_EKCL!BL34*(Accrual_EKCL!BL27-EKCL_BDT_Loan!V32)*(Accrual_EKCL!BL22/360)) -> 1316868.2 | BM29: =BM28*(BM27-BL27)*BM22/360 -> 1272726.1 | BN29: =BN28*(BN27-BM27)*BN22/360 -> 1190614.8 | BO29: =(BO28*(EKCL_BDT_Loan!W32-Accrual_EKCL!BN27)*(Accrual_EKCL!BO22/360))+(Accrual_EKCL!BO34*(Accrual_EKCL!BO27-EKCL_BDT_Loan!W32)*(Accrual_EKCL!BO22/360)) -> 1218455 | BP29: =BP28*(BP27-BO27)*BP22/360 -> 1135897.8 | BQ29: =BQ28*(BQ27-BP27)*BQ22/360 -> 1173761.1 | BR29: =(BR28*(EKCL_BDT_Loan!X32-Accrual_EKCL!BQ27)*(Accrual_EKCL!BR22/360))+(Accrual_EKCL!BR34*(Accrual_EKCL!BR27-EKCL_BDT_Loan!X32)*(Accrual_EKCL!BR22/360)) -> 1084180.6 | BS29: =BS28*(BS27-BR27)*BS22/360 -> 1073559 | BT29: =BT28*(BT27-BS27)*BT22/360 -> 1073559 | BU29: =(BU28*(EKCL_BDT_Loan!Y32-Accrual_EKCL!BT27)*(Accrual_EKCL!BU22/360))+(Accrual_EKCL!BU34*(Accrual_EKCL!BU27-EKCL_BDT_Loan!Y32)*(Accrual_EKCL!BU22/360)) -> 986564.38 | BV29: =BV28*(BV27-BU27)*BV22/360 -> 972104.37 | BW29: =BW28*(BW27-BV27)*BW22/360 -> 940746.16 | BX29: =(BX28*(EKCL_BDT_Loan!Z32-Accrual_EKCL!BW27)*(Accrual_EKCL!BX22/360))+(Accrual_EKCL!BX34*(Accrual_EKCL!BX27-EKCL_BDT_Loan!Z32)*(Accrual_EKCL!BX22/360)) -> 915772.51 | BY29: =BY28*(BY27-BX27)*BY22/360 -> 869381.56 | BZ29: =BZ28*(BZ27-BY27)*BZ22/360 -> 785247.86 | CA29: =(CA28*(EKCL_BDT_Loan!AA32-Accrual_EKCL!BZ27)*(Accrual_EKCL!CA22/360))+(Accrual_EKCL!CA34*(Accrual_EKCL!CA27-EKCL_BDT_Loan!AA32)*(Accrual_EKCL!CA22/360)) -> 812345.55 | CB29: =CB28*(CB27-CA27)*CB22/360 -> 740685.21 | CC29: =CC28*(CC27-CB27)*CC22/360 -> 765374.72 | CD29: =(CD28*(EKCL_BDT_Loan!AB32-Accrual_EKCL!CC27)*(Accrual_EKCL!CD22/360))+(Accrual_EKCL!CD34*(Accrual_EKCL!CD27-EKCL_BDT_Loan!AB32)*(Accrual_EKCL!CD22/360)) -> 686333.25 | CE29: =CE28*(CE27-CD27)*CE22/360 -> 660067.79 | CF29: =CF28*(CF27-CE27)*CF22/360 -> 660067.79 | CG29: =(CG28*(EKCL_BDT_Loan!AC32-Accrual_EKCL!CF27)*(Accrual_EKCL!CG22/360))+(Accrual_EKCL!CG34*(Accrual_EKCL!CG27-EKCL_BDT_Loan!AC32)*(Accrual_EKCL!CG22/360)) -> 583743.92 | CH29: =CH28*(CH27-CG27)*CH22/360 -> 553444.53 | CI29: =CI28*(CI27-CH27)*CI22/360 -> 535591.48 | CJ29: =(CJ28*(EKCL_BDT_Loan!AD32-Accrual_EKCL!CI27)*(Accrual_EKCL!CJ22/360))+(Accrual_EKCL!CJ34*(Accrual_EKCL!CJ27-EKCL_BDT_Loan!AD32)*(Accrual_EKCL!CJ22/360)) -> 494242.82 | CK29: =CK28*(CK27-CJ27)*CK22/360 -> 445488.47 | CL29: =CL28*(CL27-CK27)*CL22/360 -> 402376.68 | CM29: =(CM28*(EKCL_BDT_Loan!AE32-Accrual_EKCL!CL27)*(Accrual_EKCL!CM22/360))+(Accrual_EKCL!CM34*(Accrual_EKCL!CM27-EKCL_BDT_Loan!AE32)*(Accrual_EKCL!CM22/360)) -> 385546.74 | CN29: =CN28*(CN27-CM27)*CN22/360 -> 325338.35 | CO29: =CO28*(CO27-CN27)*CO22/360 -> 336182.96 | CP29: =(CP28*(EKCL_BDT_Loan!AF32-Accrual_EKCL!CO27)*(Accrual_EKCL!CP22/360))+(Accrual_EKCL!CP34*(Accrual_EKCL!CP27-EKCL_BDT_Loan!AF32)*(Accrual_EKCL!CP22/360)) -> 268217.41 | CQ29: =CQ28*(CQ27-CP27)*CQ22/360 -> 225511.14 | CR29: =CR28*(CR27-CQ27)*CR22/360 -> 225511.14 | CS29: =(CS28*(EKCL_BDT_Loan!AG32-Accrual_EKCL!CR27)*(Accrual_EKCL!CS22/360))+(Accrual_EKCL!CS34*(Accrual_EKCL!CS27-EKCL_BDT_Loan!AG32)*(Accrual_EKCL!CS22/360)) -> 160401.63 | CT29: =CT28*(CT27-CS27)*CT22/360 -> 113455.91 | CU29: =CU28*(CU27-CT27)*CU22/360 -> 109796.05 | CV29: =(CV28*(EKCL_BDT_Loan!AH32-Accrual_EKCL!CU27)*(Accrual_EKCL!CV22/360))+(Accrual_EKCL!CV34*(Accrual_EKCL!CV27-EKCL_BDT_Loan!AH32)*(Accrual_EKCL!CV22/360)) -> 51238.155
A30: Cumulative interest | D30: =D29 -> 291666.67 | E30: =D30+E29 -> 1798611.1 | F30: =E30+F29 -> 3159722.2 | G30: =F30+G29 -> 4666666.7 | H30: =G30+H29 -> 6125000 | I30: =H30+I29 -> 8286108 | J30: =I30+J29 -> 10898848 | K30: =J30+K29 -> 13598678 | L30: =K30+L29 -> 16298509 | ... CV30: =CU30+CV29 -> 1.4718717e+08
A31: Principal Payment | D31: 0 | E31: =EKCL_BDT_Loan!$C$36 -> 0 | F31: 0 | G31: 0 | H31: =EKCL_BDT_Loan!$D$36 -> 0 | I31: 0 | J31: 0 | K31: =EKCL_BDT_Loan!$E$36 -> 0 | L31: 0 | M31: 0 | N31: =EKCL_BDT_Loan!$F$36 -> 0 | O31: =EKCL_BDT_Loan!$F$36 -> 0 | P31: =EKCL_BDT_Loan!$F$36 -> 0 | Q31: =EKCL_BDT_Loan!$F$36 -> 0 | R31: =EKCL_BDT_Loan!$F$36 -> 0 | S31: =EKCL_BDT_Loan!G36 -> 18842220 | T31: 0 | U31: 0 | V31: =+EKCL_BDT_Loan!$H$36 -> 19077748 | W31: 0 | X31: 0 | Y31: =EKCL_BDT_Loan!$I$36 -> 19316220 | Z31: 0 | AA31: 0 | AB31: =EKCL_BDT_Loan!$J$36 -> 19557673 | AC31: 0 | AD31: 0 | AE31: =EKCL_BDT_Loan!$K$36 -> 19802144 | AF31: 0 | AG31: 0 | AH31: =EKCL_BDT_Loan!$L$36 -> 20049670 | AI31: 0 | AJ31: 0 | AK31: =EKCL_BDT_Loan!$M$36 -> 20300291 | AL31: 0 | AM31: 0 | AN31: =EKCL_BDT_Loan!$N$36 -> 20554045 | AO31: 0 | AP31: 0 | AQ31: =EKCL_BDT_Loan!$O$36 -> 20810971 | AR31: 0 | AS31: 0 | AT31: =EKCL_BDT_Loan!$P$36 -> 21071108 | AU31: 0 | AV31: 0 | AW31: =EKCL_BDT_Loan!$Q$36 -> 21334497 | AX31: 0 | AY31: 0 | AZ31: =EKCL_BDT_Loan!$R$36 -> 21601178 | BA31: 0 | BB31: 0 | BC31: =EKCL_BDT_Loan!$S$36 -> 21871192 | BD31: 0 | BE31: 0 | BF31: =EKCL_BDT_Loan!$T$36 -> 22144582 | BG31: 0 | BH31: 0 | BI31: =EKCL_BDT_Loan!$U$36 -> 22421390 | BJ31: 0 | BK31: 0 | BL31: =EKCL_BDT_Loan!$V$36 -> 22701657 | BM31: 0 | BN31: 0 | BO31: =EKCL_BDT_Loan!$W$36 -> 22985428 | BP31: 0 | BQ31: 0 | BR31: =EKCL_BDT_Loan!$X$36 -> 23272746 | BS31: 0 | BT31: 0 | BU31: =EKCL_BDT_Loan!$Y$36 -> 23563655 | BV31: 0 | BW31: 0 | BX31: =EKCL_BDT_Loan!$Z$36 -> 23858201 | BY31: 0 | BZ31: 0 | CA31: =EKCL_BDT_Loan!$AA$36 -> 24156428 | CB31: 0 | CC31: 0 | CD31: =EKCL_BDT_Loan!$AB$36 -> 24458383 | CE31: 0 | CF31: 0 | CG31: =EKCL_BDT_Loan!$AC$36 -> 24764113 | CH31: 0 | CI31: 0 | CJ31: =EKCL_BDT_Loan!$AD$36 -> 25073665 | CK31: 0 | CL31: 0 | CM31: =EKCL_BDT_Loan!$AE$36 -> 25387085 | CN31: 0 | CO31: 0 | CP31: =EKCL_BDT_Loan!$AF$36 -> 25704424 | CQ31: 0 | CR31: 0 | CS31: =EKCL_BDT_Loan!$AG$36 -> 26025729 | CT31: 0 | CU31: 0 | CV31: =EKCL_BDT_Loan!$AH$36 -> 26351051
A32: Cumulative repayment | D32: =D31 -> 0 | E32: =D32+E31 -> 0 | F32: =E32+F31 -> 0 | G32: =F32+G31 -> 0 | H32: =G32+H31 -> 0 | I32: =H32+I31 -> 0 | J32: =I32+J31 -> 0 | K32: =J32+K31 -> 0 | L32: =K32+L31 -> 0 | ... CV32: =CU32+CV31 -> 6.2705749e+08
A33: Total Debt Service | D33: =D31+D29 -> 291666.67 | E33: =E31+E29 -> 1506944.4 | F33: =F31+F29 -> 1361111.1 | G33: =G31+G29 -> 1506944.4 | H33: =H31+H29 -> 1458333.3 | I33: =I31+I29 -> 2161108 | J33: =J31+J29 -> 2612739.6 | K33: =K31+K29 -> 2699830.9 | ... CV33: =CV31+CV29 -> 26402289
A34: Closing Balance | D34: =D28-D31 -> 350000000 | E34: =E28-E31 -> 350000000 | F34: =F28-F31 -> 350000000 | G34: =G28-G31 -> 350000000 | H34: =H28-H31 -> 350000000 | I34: =I28-I31+D18 -> 627057493 | J34: =J28-J31 -> 627057493 | K34: =K28-K31 -> 627057493 | L34: =L28-L31 -> 627057493 | M34: =M28-M31 -> 627057493 | N34: =N28-N31 -> 627057493 | O34: =O28-O31 -> 627057493 | P34: =P28-P31 -> 627057493 | Q34: =Q28-Q31 -> 627057493 | ... CV34: =CV28-CV31 -> 0
CU36: Check | CV36: =SUM(D29:CV29)-SUM(EKCL_BDT_Loan!C34:AH34) -> 0
GB37: =SUM(D29:CV29)-SUM(EKCL_BDT_Loan!C34:AH34) -> 0

Sheet Repayment Schedule
A1: Project name: | B1: =Disbursement!B1 -> Esquire Knit Composite Limited (EKCL)
A3: Agreement date | B3: =+EKCL_BDT_Loan!C3 -> 44857
A5: Loan Amount | B5: =+EKCL_BDT_Loan!C5 -> 750000000
A7: First Drawdown Date | B7: =Disbursement!B8 -> 44921
A9: Request Date | B9: =+EKCL_BDT_Loan!C9 -> 44868
A11: Interest Rate | B11: =+EKCL_BDT_Loan!C11 -> 0.05
A13: Tenor | B13: =+EKCL_BDT_Loan!C13 -> 96 months
A15: Principal | B15: =+EKCL_BDT_Loan!C15 -> Quarterly Installment
A17: Interest calculation | B17: =+EKCL_BDT_Loan!C17 -> 360 | C17: days basis
A19: Number of installments | B19: 28
A21: Drawdown
C22: =Disbursement!B8 -> 44921
C23: =Disbursement!D9 -> 627057493
C24: =C23 -> 627057493
A27: Repayment Date | B27: Opening Balance | C27: Interest Payment | D27: Cumulative interest | E27: Principal Payment | F27: Cumulative repayment | G27: Total Debt Service | H27: Closing Balance
A28: {=+TRANSPOSE(EKCL_BDT_Loan!C32:AH39)} -> 45000 | B28: 350000000 | C28: 3840277.8 | D28: 3840277.8 | E28: 0 | F28: 0 | G28: 3840277.8 | H28: 350000000
A29: 45092 | B29: 350000000 | C29: 5665108.7 | D29: 9505386.4 | E29: 0 | F29: 0 | G29: 5665108.7 | H29: 627057493
A30: 45183 | B30: 627057493 | C30: 7925310 | D30: 17430696 | E30: 0 | F30: 0 | G30: 7925310 | H30: 627057493
A31: 45274 | B31: 627057493 | C31: 7925310 | D31: 25356006 | E31: 0 | F31: 0 | G31: 7925310 | H31: 627057493
A32: 45365 | B32: 627057493 | C32: 7925310 | D32: 33281316 | E32: 18842220 | F32: 18842220 | G32: 26767530 | H32: 6.0821527e+08
A33: 45456 | B33: 6.0821527e+08 | C33: 7687165.3 | D33: 40968482 | E33: 19077748 | F33: 37919969 | G33: 26764913 | H33: 5.8913752e+08
A34: 45550 | B34: 5.8913752e+08 | C34: 7691517.7 | D34: 48659999 | E34: 19316220 | F34: 57236189 | G34: 27007738 | H34: 5.698213e+08
A35: 45641 | B35: 5.698213e+08 | C35: 7201908.2 | D35: 55861907 | E35: 19557673 | F35: 76793861 | G35: 26759581 | H35: 5.5026363e+08
A36: 45729 | B36: 5.5026363e+08 | C36: 6725444.4 | D36: 62587352 | E36: 19802144 | F36: 96596005 | G36: 26527588 | H36: 5.3046149e+08
A37: 45823 | B37: 5.3046149e+08 | C37: 6925469.4 | D37: 69512821 | E37: 20049670 | F37: 1.1664568e+08 | G37: 26975140 | H37: 5.1041182e+08
A38: 45915 | B38: 5.1041182e+08 | C38: 6521928.8 | D38: 76034750 | E38: 20300291 | F38: 1.3694597e+08 | G38: 26822220 | H38: 4.9011153e+08
A39: 46006 | B39: 4.9011153e+08 | C39: 6194465.1 | D39: 82229215 | E39: 20554045 | F39: 1.5750001e+08 | G39: 26748510 | H39: 4.6955748e+08
A40: 46096 | B40: 4.6955748e+08 | C40: 5869468.5 | D40: 88098684 | E40: 20810971 | F40: 1.7831098e+08 | G40: 26680439 | H40: 4.4874651e+08
... A59: 47832 | B59: 26351051 | C59: 333048 | D59: 1.4718717e+08 | E59: 26351051 | F59: 6.2705749e+08 | G59: 26684099 | H59: 0
