Workbook

Sheet Disbursement
A1: Borrower: | B1: Green Housing Energy Ltd. (GHEL-15 SIPs) | G1: Grant
A2: Currency: | B2: BDT | G2: Source: KfW
A3: Type | B3: IDCOL Loan
A4: Source: | B4: IDA-5158
A7: Disbursement Number | B7: Disbursement Date | C7: Disbursement | D7: Cumulative Disbursement | G7: Disbursement Number | H7: Disbursement Date | I7: Disbursement | J7: Cumulative Disbursement
A8: 1 | B8: 42059 | C8: 8598240 | D8: =C8 -> 8598240 | G8: 1 | H8: 42067 | I8: 10032160 | J8: =I8 -> 10032160
A9: 2 | B9: 42059 | C9: 4601262 | D9: =D8+C9 -> 13199502 | G9: 2 | H9: 42067 | I9: 5067508 | J9: =J8+I9 -> 15099668
A10: 3 | B10: 42540 | C10: 1240166 | D10: =D9+C10 -> 14439668

Sheet Summary
B1: =Accrual_GHEL!B23 -> 42064 | C1: =Accrual_GHEL!C23 -> 42095 | D1: =Accrual_GHEL!D23 -> 42125 | E1: =Accrual_GHEL!E23 -> 42156 | F1: =Accrual_GHEL!F23 -> 42186 | G1: =Accrual_GHEL!G23 -> 42217 | H1: =Accrual_GHEL!H23 -> 42248 | I1: =Accrual_GHEL!I23 -> 42278 | ... CU1: =Accrual_GHEL!CU23 -> 45017
A2: Principal
A3: Opening balance | B3: =Accrual_GHEL!B24 -> 13199502 | C3: =Accrual_GHEL!C24 -> 13199502 | D3: =Accrual_GHEL!D24 -> 13199502 | E3: =Accrual_GHEL!E24 -> 13199502 | F3: =Accrual_GHEL!F24 -> 13199502 | G3: =Accrual_GHEL!G24 -> 13199502 | H3: =Accrual_GHEL!H24 -> 13199502 | I3: =Accrual_GHEL!I24 -> 13199502 | ... L3: =Accrual_GHEL!L24 -> 13199502 | M3: =L3 -> 13199502 | N3: =M3 -> 13199502 | O3: =N3 -> 13199502 | P3: =O3 -> 13199502 | Q3: =P3 -> 13199502 | R3: =Q3+GHEL_Loan!E20 -> 14439668 | S3: =R3 -> 14439668 | T3: =S3 -> 14439668 | U3: =T3 -> 14439668 | V3: =U3 -> 14439668 | W3: =V3 -> 14439668 | X3: =W3 -> 14439668 | Y3: =X3 -> 14439668 | Z3: =Y3 -> 14439668 | ... CR3: =CQ3 -> 14439668
A4: Repayment due | B4: =Accrual_GHEL!B28 -> 0 | C4: =Accrual_GHEL!C28 -> 0 | D4: =Accrual_GHEL!D28 -> 0 | E4: =Accrual_GHEL!E28 -> 0 | F4: =Accrual_GHEL!F28 -> 0 | G4: =Accrual_GHEL!G28 -> 0 | H4: =Accrual_GHEL!H28 -> 0 | I4: =Accrual_GHEL!I28 -> 0 | ... CR4: =Accrual_GHEL!CR28 -> 14439668
A5: Loan Repayment | B5: =B22 -> 0 | C5: =C22 -> 0 | D5: =D22 -> 0 | E5: =E22 -> 0 | F5: =F22 -> 0 | G5: =G22 -> 0 | H5: =H22 -> 0 | I5: =I22 -> 0 | ... CR5: =CR22 -> 14439668
A6: Repayment overdue | B6: =IF((B4-B5)>0,(B4-B5),0) -> 0 | C6: =IF((C4-C5)>0,(C4-C5),0) -> 0 | D6: =IF((D4-D5)>0,(D4-D5),0) -> 0 | E6: =IF((E4-E5)>0,(E4-E5),0) -> 0 | F6: =IF((F4-F5)>0,(F4-F5),0) -> 0 | G6: =IF((G4-G5)>0,(G4-G5),0) -> 0 | H6: =IF((H4-H5)>0,(H4-H5),0) -> 0 | I6: =IF((I4-I5)>0,(I4-I5),0) -> 0 | ... CR6: =IF((CR4-CR5)>0,(CR4-CR5),0) -> 0
A7: Loan outstanding | B7: =B3-B5 -> 13199502 | C7: =C3-C5 -> 13199502 | D7: =D3-D5 -> 13199502 | E7: =E3-E5 -> 13199502 | F7: =F3-F5 -> 13199502 | G7: =G3-G5 -> 13199502 | H7: =H3-H5 -> 13199502 | I7: =I3-I5 -> 13199502 | ... CR7: =CR3-CR5 -> 0
A8: Interest
A9: Interest accrued | B9: =Accrual_GHEL!B26 -> 10999.585 | C9: =Accrual_GHEL!C26 -> 79197.012 | D9: =Accrual_GHEL!D26 -> 145194.52 | E9: =Accrual_GHEL!E26 -> 213391.95 | F9: =Accrual_GHEL!F26 -> 279389.46 | G9: =Accrual_GHEL!G26 -> 347586.89 | H9: =Accrual_GHEL!H26 -> 415784.31 | I9: =Accrual_GHEL!I26 -> 481781.82 | ... CR9: =Accrual_GHEL!CR26 -> 3714420.9
A10: Interest due | B10: 0 | C10: 0 | D10: =GHEL_Loan!$B$29 -> 0 | E10: =D10 -> 0 | F10: =GHEL_Loan!$C$29 -> 244190.79 | G10: =F10 -> 244190.79 | H10: =G10 -> 244190.79 | I10: =GHEL_Loan!$D$29 -> 446583.15 | J10: =I10 -> 446583.15 | K10: =J10 -> 446583.15 | L10: =GHEL_Loan!$E$29 -> 646775.6 | M10: =L10 -> 646775.6 | N10: =M10 -> 646775.6 | O10: =GHEL_Loan!$F$29 -> 840064.86 | P10: =O10 -> 840064.86 | Q10: =P10 -> 840064.86 | R10: =GHEL_Loan!$G$29 -> 1028499.1 | S10: =R10 -> 1028499.1 | T10: =S10 -> 1028499.1 | U10: =GHEL_Loan!$H$29 -> 1228143.5 | V10: =U10 -> 1228143.5 | W10: =V10 -> 1228143.5 | X10: =GHEL_Loan!$I$29 -> 1418808.9 | Y10: =X10 -> 1418808.9 | Z10: =Y10 -> 1418808.9 | AA10: =GHEL_Loan!$J$29 -> 1599836.3 | AB10: =AA10 -> 1599836.3 | AC10: =AB10 -> 1599836.3 | AD10: =GHEL_Loan!$K$29 -> 1777176.1 | AE10: =AD10 -> 1777176.1 | AF10: =AE10 -> 1777176.1 | AG10: =GHEL_Loan!$L$29 -> 1950493.1 | AH10: =AG10 -> 1950493.1 | AI10: =AH10 -> 1950493.1 | AJ10: =GHEL_Loan!$M$29 -> 2110652.1 | AK10: =AJ10 -> 2110652.1 | AL10: =AK10 -> 2110652.1 | AM10: =GHEL_Loan!$N$29 -> 2258155.9 | AN10: =AM10 -> 2258155.9 | AO10: =AN10 -> 2258155.9 | AP10: =GHEL_Loan!$O$29 -> 2407838.8 | AQ10: =AP10 -> 2407838.8 | AR10: =AQ10 -> 2407838.8 | AS10: =GHEL_Loan!$P$29 -> 2545117.9 | AT10: =AS10 -> 2545117.9 | AU10: =AT10 -> 2545117.9 | AV10: =GHEL_Loan!$Q$29 -> 2676195.2 | AW10: =AV10 -> 2676195.2 | AX10: =AW10 -> 2676195.2 | AY10: =GHEL_Loan!$R$29 -> 2798221.1 | AZ10: =AY10 -> 2798221.1 | BA10: =AZ10 -> 2798221.1 | BB10: =GHEL_Loan!$S$29 -> 2911363.2 | BC10: =BB10 -> 2911363.2 | BD10: =BC10 -> 2911363.2 | BE10: =GHEL_Loan!$T$29 -> 3018135.8 | BF10: =BE10 -> 3018135.8 | BG10: =BF10 -> 3018135.8 | BH10: =GHEL_Loan!$U$29 -> 3117281.9 | BI10: =BH10 -> 3117281.9 | BJ10: =BI10 -> 3117281.9 | BK10: =GHEL_Loan!$V$29 -> 3208801.3 | BL10: =BK10 -> 3208801.3 | BM10: =BL10 -> 3208801.3 | BN10: =GHEL_Loan!$W$29 -> 3293616 | BO10: =BN10 -> 3293616 | BP10: =BO10 -> 3293616 | BQ10: =GHEL_Loan!$X$29 -> 3370720.3 | BR10: =BQ10 -> 3370720.3 | BS10: =BR10 -> 3370720.3 | BT10: =GHEL_Loan!$Y$29 -> 3439359.8 | BU10: =BT10 -> 3439359.8 | BV10: =BU10 -> 3439359.8 | BW10: =GHEL_Loan!$Z$29 -> 3499702.3 | BX10: =BW10 -> 3499702.3 | BY10: =BX10 -> 3499702.3 | BZ10: =GHEL_Loan!$AA$29 -> 3553675.3 | CA10: =BZ10 -> 3553675.3 | CB10: =CA10 -> 3553675.3 | CC10: =GHEL_Loan!$AB$29 -> 3599937.8 | CD10: =CC10 -> 3599937.8 | CE10: =CD10 -> 3599937.8 | CF10: =GHEL_Loan!$AC$29 -> 3638070.9 | CG10: =CF10 -> 3638070.9 | CH10: =CG10 -> 3638070.9 | CI10: =GHEL_Loan!$AD$29 -> 3668242.2 | CJ10: =CI10 -> 3668242.2 | CK10: =CJ10 -> 3668242.2 | CL10: =GHEL_Loan!$AE$29 -> 3691373.4 | CM10: =CL10 -> 3691373.4 | CN10: =CM10 -> 3691373.4 | CO10: =GHEL_Loan!$AF$29 -> 3706794.3 | CP10: =CO10 -> 3706794.3 | CQ10: =CP10 -> 3706794.3 | CR10: =GHEL_Loan!$AG$29 -> 3714420.9
A11: interest received | B11: =B26 -> 0 | C11: =C26 -> 0 | D11: =D26 -> 0 | E11: =E26 -> 0 | F11: =F26 -> 244190 | G11: =G26 -> 244190 | H11: =H26 -> 244190 | I11: =I26 -> 446582 | ... CR11: =CR26 -> 3714420.9
A12: Interest overdue | B12: =IF((B10-B11)>0,(B10-B11),0) -> 0 | C12: =IF((C10-C11)>0,(C10-C11),0) -> 0 | D12: =IF((D10-D11)>0,(D10-D11),0) -> 0 | E12: =IF((E10-E11)>0,(E10-E11),0) -> 0 | F12: =IF((F10-F11)>0,(F10-F11),0) -> 0.787 | G12: =IF((G10-G11)>0,(G10-G11),0) -> 0.787 | H12: =IF((H10-H11)>0,(H10-H11),0) -> 0.787 | I12: =IF((I10-I11)>0,(I10-I11),0) -> 1.151 | ... CR12: =IF((CR10-CR11)>0,(CR10-CR11),0) -> 0
A13: Interest receivable | B13: =B9-B11 -> 10999.585 | C13: =C9-C11 -> 79197.012 | D13: =D9-D11 -> 145194.52 | E13: =E9-E11 -> 213391.95 | F13: =F9-F11 -> 35199.459 | G13: =G9-G11 -> 103396.89 | H13: =H9-H11 -> 171594.31 | I13: =I9-I11 -> 35199.823 | ... CR13: =CR9-CR11 -> 0
A14: LD and others | B14: =B28 -> 0 | C14: =C28 -> 0 | D14: =D28 -> 0 | E14: =E28 -> 0 | F14: =F28 -> 0 | G14: =G28 -> 0 | H14: =H28 -> 0 | I14: =I28 -> 814 | ... CR14: =CR28 -> 25968
B19: =B1 -> 42064 | C19: =C1 -> 42095 | D19: =D1 -> 42125 | E19: =E1 -> 42156 | F19: =F1 -> 42186 | G19: =G1 -> 42217 | H19: =H1 -> 42248 | I19: =I1 -> 42278 | ... CU19: =CU1 -> 45017
A20: Repayment receipts:
A21: Repayment received | B21: =Accrual_GHEL!B27 -> 0 | C21: =Accrual_GHEL!C27 -> 0 | D21: =Accrual_GHEL!D27 -> 0 | E21: =Accrual_GHEL!E27 -> 0 | F21: =Accrual_GHEL!F27 -> 0 | I21: =Accrual_GHEL!I27 -> 0 | L21: 455155 | O21: 455155 | R21: =222772+232383 -> 455155 | U21: 502854 | X21: =22660+110884+200000 -> 333544 | AA21: 0 | AD21: 0 | AG21: 0 | AJ21: 0 | AM21: 0 | AP21: 0 | AS21: 0 | AV21: 0 | AY21: 0 | BB21: 0 | BE21: 0 | BH21: 0 | BK21: =BK4-BJ5 -> 6706411.7 | BN21: =BN4-BM5 -> 502853.93 | BQ21: =BQ4-BP5 -> 502853.93 | BT21: =BT4-BS5 -> 502853.93 | BW21: =BW4-BV5 -> 502853.93 | BZ21: =BZ4-BY5 -> 502853.93 | CC21: =CC4-CB5 -> 502853.93 | CF21: =CF4-CE5 -> 502853.93 | CI21: =CI4-CH5 -> 502853.93 | CL21: =CL4-CK5 -> 502853.93 | CO21: =CO4-CN5 -> 502853.93 | CR21: =CR4-CQ5 -> 502853.93
A22: Repayment received (cumulative) | B22: =B21 -> 0 | C22: =B22+C21 -> 0 | D22: =C22+D21 -> 0 | E22: =D22+E21 -> 0 | F22: =E22+F21 -> 0 | G22: =F22+G21 -> 0 | H22: =G22+H21 -> 0 | I22: =H22+I21 -> 0 | J22: =I22+J21 -> 0 | ... CR22: =CQ22+CR21 -> 14439668
A24: Interest receipts:
A25: Interest received | B25: 0 | C25: =C10-B11 -> 0 | D25: =D10-C11 -> 0 | E25: =E10-D11 -> 0 | F25: 244190 | I25: 202392 | L25: 200192 | O25: =2200+191089 -> 193289 | R25: 188434 | U25: 199644 | X25: 190665 | AA25: 181028 | AD25: 177340 | AG25: 173317 | AJ25: 160159 | AM25: 147504 | AP25: 149683 | AS25: 137279 | AV25: 131077 | AY25: 122026 | BB25: 20205 | BE25: 0 | BH25: 0 | BK25: =BK10-BJ11 -> 390377.29 | BN25: =BN10-BM11 -> 84814.697 | BQ25: =BQ10-BP11 -> 77104.27 | BT25: =BT10-BS11 -> 68639.562 | BW25: =BW10-BV11 -> 60342.472 | BZ25: =BZ10-BY11 -> 53972.989 | CC25: =CC10-CB11 -> 46262.562 | CF25: =CF10-CE11 -> 38133.09 | CI25: =CI10-CH11 -> 30171.236 | CL25: =CL10-CK11 -> 23131.281 | CO25: =CO10-CN11 -> 15420.854 | CR25: =CR10-CQ11 -> 7626.618
A26: Interest received (cumulative) | B26: =B25 -> 0 | C26: =B26+C25 -> 0 | D26: =C26+D25 -> 0 | E26: =D26+E25 -> 0 | F26: =E26+F25 -> 244190 | G26: =F26+G25 -> 244190 | H26: =G26+H25 -> 244190 | I26: =H26+I25 -> 446582 | J26: =I26+J25 -> 446582 | ... CR26: =CQ26+CR25 -> 3714420.9
A27: LD/others | B27: 0 | C27: 0 | D27: 0 | E27: 0 | G27: 0 | H27: 0 | I27: 814 | J27: 0 | K27: 0 | M27: 0 | N27: 0 | O27: 12057 | P27: 0 | Q27: 0 | R27: 13097 | S27: 0 | T27: 0 | U27: 0 | V27: 0 | W27: 0 | X27: 0 | Y27: 0 | Z27: 0 | AA27: 0 | AB27: 0 | AC27: 0 | AD27: 0 | AE27: 0 | AF27: 0 | AG27: 0 | AH27: 0 | AI27: 0 | AJ27: 0 | AK27: 0 | AL27: 0 | AM27: 0 | AN27: 0 | AO27: 0 | AP27: 0 | AQ27: 0 | AR27: 0 | AS27: 0 | AT27: 0 | AU27: 0 | AV27: 0 | AW27: 0 | AX27: 0 | AY27: 0 | AZ27: 0 | BA27: 0 | BB27: 0 | BC27: 0 | BD27: 0 | BE27: 0 | BF27: 0 | BG27: 0 | BH27: 0 | BI27: 0 | BJ27: 0 | BK27: 0 | BL27: 0 | BM27: 0 | BN27: 0 | BO27: 0 | BP27: 0 | BQ27: 0 | BR27: 0 | BS27: 0 | BT27: 0 | BU27: 0 | BV27: 0 | BW27: 0 | BX27: 0 | BY27: 0 | BZ27: 0 | CA27: 0 | CB27: 0 | CC27: 0 | CD27: 0 | CE27: 0 | CF27: 0 | CG27: 0 | CH27: 0 | CI27: 0 | CJ27: 0 | CK27: 0 | CL27: 0 | CM27: 0 | CN27: 0 | CO27: 0 | CP27: 0 | CQ27: 0 | CR27: 0
A28: LD/others (cumulative) | B28: =B27 -> 0 | C28: =B28+C27 -> 0 | D28: =C28+D27 -> 0 | E28: =D28+E27 -> 0 | F28: =E28+F27 -> 0 | G28: =F28+G27 -> 0 | H28: =G28+H27 -> 0 | I28: =H28+I27 -> 814 | J28: =I28+J27 -> 814 | ... CR28: =CQ28+CR27 -> 25968
A30: Actual Payment date | F30: 42185 | I30: 42284 | K30: 42443 | N30: 42541 | R30: 42849 | U30: 42926 | V30: 42939 | W30: 42956 | AS30: 43793
A31: Actual Payment amount: | L31: 202392 | P31: 1940165 | T31: 5551970 | AZ31: 11000000
A32: Interest | F32: 244190 | I32: 202392 | K32: 200192 | L32: 2200 | O32: 191089 | P32: 188434 | R32: 199644 | S32: 190665 | T32: 181028 | U32: 177340 | AS32: 173317 | AT32: 160159 | AU32: 147504 | AV32: 149683 | AW32: 137279 | AX32: 131077 | AY32: 122026 | AZ32: 20205
A33: Principal | N33: 455155 | O33: 455155 | P33: 222772 | R33: 232383 | S33: 502854 | U33: 22660 | V33: 110884 | W33: 200000
A34: LPC | I34: 814 | O34: 12057 | P34: 13097
A35: Total | B35: =SUM(B32:B34) -> 0 | C35: =SUM(C32:C34) -> 0 | D35: =SUM(D32:D34) -> 0 | E35: =SUM(E32:E34) -> 0 | F35: =SUM(F32:F34) -> 244190 | G35: =SUM(G32:G34) -> 0 | H35: =SUM(H32:H34) -> 0 | I35: =SUM(I32:I34) -> 203206 | ... DO35: =SUM(DO32:DO34) -> 0
AY37: Status on 30 Sep'19
AZ38: Principal Overdue | BA38: Interest Overdue | BB38: Total Overdue (Excl. LPC) | BC38: Downpayment Required for Rescheduling | BD38: Payment by GHEL on 24 Nov'19 | BE38: Payment Assigned
AY39: GHEL-SHS | AZ39: 61539186 | BA39: 14668649 | BB39: =+AZ39+BA39 -> 76207836 | BC39: =+BB39*30% -> 22862351 | BD39: 11000000 | BE39: =+BD39-SUM(BE40:BE44) -> 6727319
AY40: GHEL-Biogas | AZ40: 6375500.1 | BA40: 653815.11 | BB40: =+AZ40+BA40 -> 7029315.2 | BC40: =+BB40*15% -> 1054397.3 | BE40: =+ROUNDUP(BC40,0) -> 1054398
AY41: GHEL SIP-1 | AZ41: 1492402 | BA41: 193009 | BB41: =+AZ41+BA41 -> 1685411 | BC41: =+BB41*15% -> 252811.65 | BE41: =+ROUNDUP(BC41,0) -> 252812
AY42: GHEL SIP-2 | AZ42: 5700704 | BA42: 1240959 | BB42: =+AZ42+BA42 -> 6941663 | BC42: =+BB42*15% -> 1041249.4 | BE42: =+ROUNDUP(BC42,0) -> 1041250
AY43: GHEL SMG-1 | AZ43: 4456414 | BA43: 663877 | BB43: =+AZ43+BA43 -> 5120291 | BC43: =+BB43*15% -> 768043.65 | BE43: =+ROUNDUP(BC43,0) -> 768044
AY44: GHEL SMG-2 | AZ44: 4911505 | BA44: 2796339 | BB44: =+AZ44+BA44 -> 7707844 | BC44: =+BB44*15% -> 1156176.6 | BE44: =+ROUNDUP(BC44,0) -> 1156177
BD45: Total | BE45: =+SUM(BE39:BE44) -> 11000000

Sheet GHEL_Loan
A1: Project name: | C1: =Disbursement!B1 -> Green Housing Energy Ltd. (GHEL-15 SIPs)
A3: Financial Close | C3: 42035
A5: Loan Amount | C5: 15099668
A7: Request Date | C7: 42050
A8: Drawdown Date | C8: =Disbursement!B8 -> 42059
A10: Interest Rate | C10: 0.06
A11: Tenor | C11: 8 | D11: years
A12: Principal | C12: Level Principal
A13: Interest calculation | C13: 360 | D13: days basis
A14: Number of installments | C14: 29 | F14: =EDATE(C8,3) -> 42148 | G14: interest Grace period ends
A15: Principal Grace Period | C15: 270 | D15: days
A16: Principal Grace Period Ends | C16: =EDATE(C8,9) -> 42332
A18: Drawdown
C19: =Disbursement!B8 -> 42059 | D19: =Disbursement!B9 -> 42059 | E19: =Disbursement!B10 -> 42540
C20: =Disbursement!C8 -> 8598240 | D20: =Disbursement!C9 -> 4601262 | E20: =Disbursement!C10 -> 1240166
C21: =C20 -> 8598240 | D21: =C21+D20 -> 13199502 | E21: =D21+E20 -> 14439668
A24: Repayment
A25: Repayment Period | E25: 1 | F25: 2 | G25: 3 | H25: 4 | I25: 5 | J25: 6 | K25: 7 | L25: 8 | M25: 9 | N25: 10 | O25: 11 | P25: 12 | Q25: 13 | R25: 14 | S25: 15 | T25: 16 | U25: 17 | V25: 18 | W25: 19 | X25: 20 | Y25: 21 | Z25: 22 | AA25: 23 | AB25: 24 | AC25: 25 | AD25: 26 | AE25: 27 | AF25: 28 | AG25: 29
A26: Repayment Date | B26: 42078 | C26: 42170 | D26: 42262 | E26: 42353 | F26: 42444 | G26: 42536 | H26: 42628 | I26: 42719 | J26: 42809 | K26: 42901 | L26: 42995 | M26: 43086 | N26: 43174 | O26: 43268 | P26: 43359 | Q26: 43451 | R26: 43542 | S26: 43632 | T26: 43723 | U26: 43814 | V26: 43905 | W26: 43997 | X26: 44089 | Y26: 44180 | Z26: 44270 | AA26: 44362 | AB26: 44454 | AC26: 44545 | AD26: 44635 | AE26: 44727 | AF26: 44819 | AG26: 44910
A27: Opening Balance | B27: =D21 -> 13199502 | C27: =B33 -> 13199502 | D27: =C33 -> 13199502 | E27: =D33 -> 13199502 | F27: =E33 -> 12744347 | G27: =F33 -> 12289192 | H27: =G33+E20 -> 13074202 | I27: =H33 -> 12571348 | J27: =I33 -> 12068494 | K27: =J33 -> 11565640 | L27: =K33 -> 11062787 | M27: =L33 -> 10559933 | N27: =M33 -> 10057079 | O27: =N33 -> 9554224.7 | P27: =O33 -> 9051370.8 | ... AG27: =AF33 -> 502853.93
A28: Interest Payment | B28: 0 | C28: =D21*$C$10*(C26-D19)/360 -> 244190.79 | D28: =C33*$C$10*(D26-C26)/360 -> 202392.36 | E28: =D33*$C$10*(E26-D26)/360 -> 200192.45 | F28: =E33*$C$10*(F26-E26)/360 -> 193289.26 | G28: =F33*$C$10*(G26-F26)/360 -> 188434.27 | H28: =G33*(E19-G26)*$C$10/360+H27*(H26-E19)*$C$10/360 -> 199644.32 | I28: =H33*$C$10*(I26-H26)/360 -> 190665.45 | J28: =I33*$C$10*(J26-I26)/360 -> 181027.42 | K28: =J33*$C$10*(K26-J26)/360 -> 177339.82 | L28: =K33*$C$10*(L26-K26)/360 -> 173316.99 | M28: =L33*$C$10*(M26-L26)/360 -> 160158.98 | N28: =M33*$C$10*(N26-M26)/360 -> 147503.82 | O28: =N33*$C$10*(O26-N26)/360 -> 149682.85 | P28: =O33*$C$10*(P26-O26)/360 -> 137279.12 | ... AG28: =AF33*$C$10*(AG26-AF26)/360 -> 7626.618
A29: Cumulative interest | B29: =B28 -> 0 | C29: =B29+C28 -> 244190.79 | D29: =C29+D28 -> 446583.15 | E29: =D29+E28 -> 646775.6 | F29: =F28+E29 -> 840064.86 | G29: =G28+F29 -> 1028499.1 | H29: =H28+G29 -> 1228143.5 | I29: =I28+H29 -> 1418808.9 | J29: =J28+I29 -> 1599836.3 | K29: =K28+J29 -> 1777176.1 | L29: =L28+K29 -> 1950493.1 | M29: =M28+L29 -> 2110652.1 | ... AG29: =AG28+AF29 -> 3714420.9
A30: Principal Payment | B30: 0 | C30: 0 | D30: 0 | E30: =$E$27/29 -> 455155.24 | F30: =$E$27/29 -> 455155.24 | G30: =$E$27/29 -> 455155.24 | H30: =$H$27/26 -> 502853.93 | I30: =$H$27/26 -> 502853.93 | J30: =$H$27/26 -> 502853.93 | K30: =$H$27/26 -> 502853.93 | L30: =$H$27/26 -> 502853.93 | M30: =$H$27/26 -> 502853.93 | N30: =$H$27/26 -> 502853.93 | O30: =$H$27/26 -> 502853.93 | ... AG30: =$H$27/26 -> 502853.93
A31: Cumulative repayment | B31: =B30 -> 0 | C31: =C30+B31 -> 0 | D31: =D30+C31 -> 0 | E31: =E30+D31 -> 455155.24 | F31: =F30+E31 -> 910310.48 | G31: =G30+F31 -> 1365465.7 | H31: =H30+G31 -> 1868319.7 | I31: =I30+H31 -> 2371173.6 | J31: =J30+I31 -> 2874027.5 | ... AG31: =AG30+AF31 -> 14439668
A32: Total Debt Service | B32: =B30+B28 -> 0 | C32: =C30+C28 -> 244190.79 | D32: =D30+D28 -> 202392.36 | E32: =E30+E28 -> 655347.69 | F32: =F30+F28 -> 648444.5 | G32: =G30+G28 -> 643589.51 | H32: =H30+H28 -> 702498.26 | I32: =I30+I28 -> 693519.38 | ... AG32: =AG30+AG28 -> 510480.55
A33: Closing Balance | B33: =B27-B30 -> 13199502 | C33: =C27-C30 -> 13199502 | D33: =D27-D30 -> 13199502 | E33: =E27-E30 -> 12744347 | F33: =F27-F30 -> 12289192 | G33: =G27-G30 -> 11834036 | H33: =H27-H30 -> 12571348 | I33: =I27-I30 -> 12068494 | ... AG33: =AG27-AG30 -> -2.910383e-09
A35: Average Installment Size
B36: =B26 -> 42078 | C36: =C26 -> 42170 | D36: =D26 -> 42262 | E36: =E26 -> 42353 | F36: =F26 -> 42444 | G36: =G26 -> 42536 | H36: =H26 -> 42628 | I36: =I26 -> 42719 | ... AG36: =AG26 -> 44910
C37: =AVERAGE(C32) -> 244190.79 | D37: =AVERAGE($C$32:D32) -> 223291.58 | E37: =AVERAGE($C$32:E32) -> 367310.28 | F37: =AVERAGE($C$32:F32) -> 437593.83 | G37: =AVERAGE($C$32:G32) -> 478792.97 | H37: =AVERAGE($C$32:H32) -> 516077.18 | I37: =AVERAGE($C$32:I32) -> 541426.07 | J37: =AVERAGE($C$32:J32) -> 559232.98 | K37: =AVERAGE($C$32:K32) -> 572673.07 | ... AG37: =AVERAGE($C$32:AG32) -> 585615.77

Sheet Accrual_GHEL
A1: Project name: | B1: =GHEL_Loan!C1 -> Green Housing Energy Ltd. (GHEL-15 SIPs)
A3: Assumptions:
A5: Financial Close | B5: =GHEL_Loan!C3 -> 42035
A7: Loan Amount | B7: =GHEL_Loan!C5 -> 15099668 | C7: BDT
A9: Drawdown Date | B9: =GHEL_Loan!C8 -> 42059
A11: Interest Rate | B11: =GHEL_Loan!C10 -> 0.06
A12: Tenor | B12: =GHEL_Loan!C11 -> 8 | C12: years
A13: Interest calculation | B13: 360 | C13: days basis
A14: Principal | B14: =GHEL_Loan!C12 -> Level Principal
A16: Drawdown
B17: =GHEL_Loan!C19 -> 42059 | C17: =GHEL_Loan!D19 -> 42059 | D17: =GHEL_Loan!E19 -> 42540
B18: =GHEL_Loan!C20 -> 8598240 | C18: =GHEL_Loan!D20 -> 4601262 | D18: =GHEL_Loan!E20 -> 1240166
B19: =B18 -> 8598240 | C19: =C18+B19 -> 13199502 | D19: =D18+C19 -> 14439668
A22: Accrual of interest
A23: Months | B23: 42064 | C23: =EDATE(B23,1) -> 42095 | D23: =EDATE(C23,1) -> 42125 | E23: =EDATE(D23,1) -> 42156 | F23: =EDATE(E23,1) -> 42186 | G23: =EDATE(F23,1) -> 42217 | H23: =EDATE(G23,1) -> 42248 | I23: =EDATE(H23,1) -> 42278 | J23: =EDATE(I23,1) -> 42309 | ... XFD23: =EDATE(XFC23,1) -> 540682
A24: Opening Balance | B24: =C19 -> 13199502 | C24: =B30 -> 13199502 | D24: =C30 -> 13199502 | E24: =D30 -> 13199502 | F24: =E30 -> 13199502 | G24: =F30 -> 13199502 | H24: =G30 -> 13199502 | I24: =H30 -> 13199502 | J24: =I30 -> 13199502 | ... R24: =Q30 -> 12289192 | S24: =R30+D18 -> 13074202 | T24: =S30 -> 13074202 | U24: =T30 -> 13074202 | V24: =U30 -> 12571348 | W24: =V30 -> 12571348 | X24: =W30 -> 12571348 | Y24: =X30 -> 12068494 | Z24: =Y30 -> 12068494 | AA24: =Z30 -> 12068494 | ... CR24: =CQ30 -> 502853.93
A25: Interest Payment | B25: =B24*(B23-C17)*$B$11/360 -> 10999.585 | C25: =B30*(C23-B23)*$B$11/360 -> 68197.427 | D25: =C30*(D23-C23)*$B$11/360 -> 65997.51 | E25: =D30*(E23-D23)*$B$11/360 -> 68197.427 | F25: =E30*(F23-E23)*$B$11/360 -> 65997.51 | G25: =F30*(G23-F23)*$B$11/360 -> 68197.427 | H25: =G30*(H23-G23)*$B$11/360 -> 68197.427 | I25: =H30*(I23-H23)*$B$11/360 -> 65997.51 | J25: =I30*(J23-I23)*$B$11/360 -> 68197.427 | K25: =J30*(K23-J23)*$B$11/360 -> 65997.51 | L25: =L24*(GHEL_Loan!$E$26-K23)*$B$11/360+L30*(L23-GHEL_Loan!$E$26)*$B$11/360 -> 66907.82 | M25: =L30*(M23-L23)*$B$11/360 -> 65845.792 | N25: =M30*(N23-M23)*$B$11/360 -> 61597.676 | O25: =O24*(GHEL_Loan!$F$26-N23)*$B$11/360+O30*(O23-GHEL_Loan!$F$26)*$B$11/360 -> 64556.185 | P25: =O30*(P23-O23)*$B$11/360 -> 61445.958 | Q25: =P30*(Q23-P23)*$B$11/360 -> 63494.156 | R25: =R24*(GHEL_Loan!$G$26-Q23)*$B$11/360+R30*(D17-GHEL_Loan!$G$26)*$B$11/360+(R30+D18)*(R23-D17)*$B$11/360 -> 62712.542 | S25: =S24*(S23-R23)*$B$11/360 -> 67550.045 | T25: =S30*(T23-S23)*$B$11/360 -> 67550.045 | U25: =U24*(GHEL_Loan!$H$26-T23)*$B$11/360+U30*(U23-GHEL_Loan!$H$26)*$B$11/360 -> 64030.068 | V25: =U30*(V23-U23)*$B$11/360 -> 64951.966 | W25: =V30*(W23-V23)*$B$11/360 -> 62856.742 | X25: =X24*(GHEL_Loan!$I$26-W23)*$B$11/360+X30*(X23-GHEL_Loan!$I$26)*$B$11/360 -> 63527.214 | Y25: =X30*(Y23-X23)*$B$11/360 -> 62353.888 | Z25: =Y30*(Z23-Y23)*$B$11/360 -> 56319.641 | AA25: =AA24*(GHEL_Loan!$J$26-Z23)*$B$11/360+AA30*(AA23-GHEL_Loan!$J$26)*$B$11/360 -> 60929.135 | AB25: =AA30*(AB23-AA23)*$B$11/360 -> 57828.202 | AC25: =AB30*(AC23-AB23)*$B$11/360 -> 59755.809 | AD25: =AD24*(GHEL_Loan!$K$26-AC23)*$B$11/360+AD30*(AD23-GHEL_Loan!$K$26)*$B$11/360 -> 56487.259 | AE25: =AD30*(AE23-AD23)*$B$11/360 -> 57157.73 | AF25: =AE30*(AF23-AE23)*$B$11/360 -> 57157.73 | AG25: =AG24*(GHEL_Loan!$L$26-AF23)*$B$11/360+AG30*(AG23-GHEL_Loan!$L$26)*$B$11/360 -> 54140.607 | AH25: =AG30*(AH23-AG23)*$B$11/360 -> 54559.652 | AI25: =AH30*(AI23-AH23)*$B$11/360 -> 52799.663 | AJ25: =AJ24*(GHEL_Loan!$M$26-AI23)*$B$11/360+AJ30*(AJ23-GHEL_Loan!$M$26)*$B$11/360 -> 53302.517 | AK25: =AJ30*(AK23-AJ23)*$B$11/360 -> 51961.573 | AL25: =AK30*(AL23-AK23)*$B$11/360 -> 46933.034 | AM25: =AM24*(GHEL_Loan!$N$26-AL23)*$B$11/360+AM30*(AM23-GHEL_Loan!$N$26)*$B$11/360 -> 50536.82 | AN25: =AM30*(AN23-AM23)*$B$11/360 -> 47771.124 | AO25: =AN30*(AO23-AN23)*$B$11/360 -> 49363.494 | AP25: =AP24*(GHEL_Loan!$O$26-AO23)*$B$11/360+AP30*(AP23-GHEL_Loan!$O$26)*$B$11/360 -> 46597.798 | AQ25: =AP30*(AQ23-AP23)*$B$11/360 -> 46765.416 | AR25: =AQ30*(AR23-AQ23)*$B$11/360 -> 46765.416 | AS25: =AS24*(GHEL_Loan!$P$26-AR23)*$B$11/360+AS30*(AS23-GHEL_Loan!$P$26)*$B$11/360 -> 43999.719 | AT25: =AS30*(AT23-AS23)*$B$11/360 -> 44167.337 | AU25: =AT30*(AU23-AT23)*$B$11/360 -> 42742.584 | AV25: =AV24*(GHEL_Loan!$Q$26-AU23)*$B$11/360+AV30*(AV23-GHEL_Loan!$Q$26)*$B$11/360 -> 42910.202 | AW25: =AV30*(AW23-AV23)*$B$11/360 -> 41569.259 | AX25: =AW30*(AX23-AW23)*$B$11/360 -> 37546.427 | AY25: =AY24*(GHEL_Loan!$R$26-AX23)*$B$11/360+AY30*(AY23-GHEL_Loan!$R$26)*$B$11/360 -> 40395.933 | AZ25: =AY30*(AZ23-AY23)*$B$11/360 -> 37714.045 | BA25: =AZ30*(BA23-AZ23)*$B$11/360 -> 38971.18 | BB25: =BB24*(GHEL_Loan!$S$26-BA23)*$B$11/360+BB30*(BB23-GHEL_Loan!$S$26)*$B$11/360 -> 36456.91 | BC25: =BB30*(BC23-BB23)*$B$11/360 -> 36373.101 | BD25: =BC30*(BD23-BC23)*$B$11/360 -> 36373.101 | BE25: =BE24*(GHEL_Loan!$T$26-BD23)*$B$11/360+BE30*(BE23-GHEL_Loan!$T$26)*$B$11/360 -> 33858.832 | BF25: =BE30*(BF23-BE23)*$B$11/360 -> 33775.023 | BG25: =BF30*(BG23-BF23)*$B$11/360 -> 32685.506 | BH25: =BH24*(GHEL_Loan!$U$26-BG23)*$B$11/360+BH30*(BH23-GHEL_Loan!$U$26)*$B$11/360 -> 32350.27 | BI25: =BH30*(BI23-BH23)*$B$11/360 -> 31176.944 | BJ25: =BI30*(BJ23-BI23)*$B$11/360 -> 29165.528 | BK25: =BK24*(GHEL_Loan!$V$26-BJ23)*$B$11/360+BK30*(BK23-GHEL_Loan!$V$26)*$B$11/360 -> 29752.191 | BL25: =BK30*(BL23-BK23)*$B$11/360 -> 27656.966 | BM25: =BL30*(BM23-BL23)*$B$11/360 -> 28578.865 | BN25: =BN24*(GHEL_Loan!$W$26-BM23)*$B$11/360+BN30*(BN23-GHEL_Loan!$W$26)*$B$11/360 -> 26316.023 | BO25: =BN30*(BO23-BN23)*$B$11/360 -> 25980.787 | BP25: =BO30*(BP23-BO23)*$B$11/360 -> 25980.787 | BQ25: =BQ24*(GHEL_Loan!$X$26-BP23)*$B$11/360+BQ30*(BQ23-GHEL_Loan!$X$26)*$B$11/360 -> 23801.753 | BR25: =BQ30*(BR23-BQ23)*$B$11/360 -> 23382.708 | BS25: =BR30*(BS23-BR23)*$B$11/360 -> 22628.427 | BT25: =BT24*(GHEL_Loan!$Y$26-BS23)*$B$11/360+BT30*(BT23-GHEL_Loan!$Y$26)*$B$11/360 -> 21957.955 | BU25: =BT30*(BU23-BT23)*$B$11/360 -> 20784.629 | BV25: =BU30*(BV23-BU23)*$B$11/360 -> 18773.214 | BW25: =BW24*(GHEL_Loan!$Z$26-BV23)*$B$11/360+BW30*(BW23-GHEL_Loan!$Z$26)*$B$11/360 -> 19359.876 | BX25: =BW30*(BX23-BW23)*$B$11/360 -> 17599.888 | BY25: =BX30*(BY23-BX23)*$B$11/360 -> 18186.551 | BZ25: =BZ24*(GHEL_Loan!$AA$26-BY23)*$B$11/360+BZ30*(BZ23-GHEL_Loan!$AA$26)*$B$11/360 -> 16258.944 | CA25: =BZ30*(CA23-BZ23)*$B$11/360 -> 15588.472 | CB25: =CA30*(CB23-CA23)*$B$11/360 -> 15588.472 | CC25: =CC24*(GHEL_Loan!$AB$26-CB23)*$B$11/360+CC30*(CC23-GHEL_Loan!$AB$26)*$B$11/360 -> 13744.674 | CD25: =CC30*(CD23-CC23)*$B$11/360 -> 12990.393 | CE25: =CD30*(CE23-CD23)*$B$11/360 -> 12571.348 | CF25: =CF24*(GHEL_Loan!$AC$26-CE23)*$B$11/360+CF30*(CF23-GHEL_Loan!$AC$26)*$B$11/360 -> 11565.64 | CG25: =CF30*(CG23-CF23)*$B$11/360 -> 10392.315 | CH25: =CG30*(CH23-CG23)*$B$11/360 -> 9386.6068 | CI25: =CI24*(GHEL_Loan!$AD$26-CH23)*$B$11/360+CI30*(CI23-GHEL_Loan!$AD$26)*$B$11/360 -> 8967.5618 | CJ25: =CI30*(CJ23-CI23)*$B$11/360 -> 7542.809 | CK25: =CJ30*(CK23-CJ23)*$B$11/360 -> 7794.236 | CL25: =CL24*(GHEL_Loan!$AE$26-CK23)*$B$11/360+CL30*(CL23-GHEL_Loan!$AE$26)*$B$11/360 -> 6201.8652 | CM25: =CL30*(CM23-CL23)*$B$11/360 -> 5196.1573 | CN25: =CM30*(CN23-CM23)*$B$11/360 -> 5196.1573 | CO25: =CO24*(GHEL_Loan!$AF$26-CN23)*$B$11/360+CO30*(CO23-GHEL_Loan!$AF$26)*$B$11/360 -> 3687.5955 | CP25: =CO30*(CP23-CO23)*$B$11/360 -> 2598.0787 | CQ25: =CP30*(CQ23-CP23)*$B$11/360 -> 2514.2697 | CR25: =CR24*(GHEL_Loan!$AG$26-CQ23)*$B$11/360+CR30*(CR23-GHEL_Loan!$AG$26)*$B$11/360 -> 1173.3258
A26: Cumulative interest | B26: =B25 -> 10999.585 | C26: =B26+C25 -> 79197.012 | D26: =C26+D25 -> 145194.52 | E26: =D26+E25 -> 213391.95 | F26: =E26+F25 -> 279389.46 | G26: =F26+G25 -> 347586.89 | H26: =G26+H25 -> 415784.31 | I26: =H26+I25 -> 481781.82 | J26: =I26+J25 -> 549979.25 | ... CR26: =CQ26+CR25 -> 3714420.9
A27: Principal Payment | B27: 0 | C27: 0 | D27: 0 | E27: 0 | F27: 0 | G27: 0 | H27: 0 | I27: 0 | J27: 0 | K27: 0 | L27: =GHEL_Loan!$E$30 -> 455155.24 | O27: =GHEL_Loan!$F$30 -> 455155.24 | R27: =GHEL_Loan!$G$30 -> 455155.24 | U27: =GHEL_Loan!$H$30 -> 502853.93 | X27: =GHEL_Loan!$I$30 -> 502853.93 | AA27: =GHEL_Loan!$J$30 -> 502853.93 | AD27: =GHEL_Loan!$K$30 -> 502853.93 | AG27: =GHEL_Loan!$L$30 -> 502853.93 | AJ27: =GHEL_Loan!$M$30 -> 502853.93 | AM27: =GHEL_Loan!$N$30 -> 502853.93 | AP27: =GHEL_Loan!$O$30 -> 502853.93 | AS27: =GHEL_Loan!$P$30 -> 502853.93 | AV27: =GHEL_Loan!$Q$30 -> 502853.93 | AY27: =GHEL_Loan!$R$30 -> 502853.93 | BB27: =GHEL_Loan!$S$30 -> 502853.93 | BE27: =GHEL_Loan!$T$30 -> 502853.93 | BH27: =GHEL_Loan!$U$30 -> 502853.93 | BK27: =GHEL_Loan!$V$30 -> 502853.93 | BN27: =GHEL_Loan!$W$30 -> 502853.93 | BQ27: =GHEL_Loan!$X$30 -> 502853.93 | BT27: =GHEL_Loan!$Y$30 -> 502853.93 | BW27: =GHEL_Loan!$Z$30 -> 502853.93 | BZ27: =GHEL_Loan!$AA$30 -> 502853.93 | CC27: =GHEL_Loan!$AB$30 -> 502853.93 | CF27: =GHEL_Loan!$AC$30 -> 502853.93 | CI27: =GHEL_Loan!$AD$30 -> 502853.93 | CL27: =GHEL_Loan!$AE$30 -> 502853.93 | CO27: =GHEL_Loan!$AF$30 -> 502853.93 | CR27: =GHEL_Loan!$AG$30 -> 502853.93
A28: Cumulative repayment | B28: =B27 -> 0 | C28: =B28+C27 -> 0 | D28: =C28+D27 -> 0 | E28: =D28+E27 -> 0 | F28: =E28+F27 -> 0 | G28: =F28+G27 -> 0 | H28: =G28+H27 -> 0 | I28: =H28+I27 -> 0 | J28: =I28+J27 -> 0 | ... CR28: =CQ28+CR27 -> 14439668
A29: Total Debt Service | B29: =B27+B25 -> 10999.585 | C29: =C27+C25 -> 68197.427 | D29: =D27+D25 -> 65997.51 | E29: =E27+E25 -> 68197.427 | F29: =F27+F25 -> 65997.51 | G29: =G27+G25 -> 68197.427 | H29: =H27+H25 -> 68197.427 | I29: =I27+I25 -> 65997.51 | ... CR29: =CR27+CR25 -> 504027.26
A30: Closing Balance | B30: =B24-B27 -> 13199502 | C30: =C24-C27 -> 13199502 | D30: =D24-D27 -> 13199502 | E30: =E24-E27 -> 13199502 | F30: =F24-F27 -> 13199502 | G30: =G24-G27 -> 13199502 | H30: =H24-H27 -> 13199502 | I30: =I24-I27 -> 13199502 | ... CR30: =CR24-CR27 -> -2.910383e-09
CR32: =CR26-GHEL_Loan!AG29 -> 0

Sheet Repayment Schedule
A1: Project name: | C1: =GHEL_Loan!C1 -> Green Housing Energy Ltd. (GHEL-15 SIPs)
A3: =Accrual_GHEL!A3 -> Assumptions:
A5: Financial Close | C5: =GHEL_Loan!C3 -> 42035
A7: Loan Amount | C7: =GHEL_Loan!C5 -> 15099668
A9: Drawdown Date | C9: =Accrual_GHEL!B9 -> 42059
A11: Interest Rate | C11: =GHEL_Loan!C10 -> 0.06
A12: Tenor | C12: =GHEL_Loan!C11 -> 8 | D12: years
A13: Principal | C13: =GHEL_Loan!C12 -> Level Principal
A14: Interest calculation | C14: =GHEL_Loan!C13 -> 360 | D14: days basis
A15: Number of installments | C15: =GHEL_Loan!C14 -> 29
A17: Drawdown
C18: =GHEL_Loan!C19 -> 42059 | D18: =GHEL_Loan!D19 -> 42059
C19: =GHEL_Loan!C20 -> 8598240 | D19: =GHEL_Loan!D20 -> 4601262
C20: =C19 -> 8598240 | D20: =D19+C20 -> 13199502
A23: {=TRANSPOSE(GHEL_Loan!A26:AG33)} -> Repayment Date | B23: Opening Balance | C23: Interest Payment | D23: Cumulative interest | E23: Principal Payment | F23: Cumulative repayment | G23: Total Debt Service | H23: Closing Balance
A24: 42078 | B24: 13199502 | C24: 0 | D24: 0 | E24: 0 | F24: 0 | G24: 0 | H24: 13199502
A25: 42170 | B25: 13199502 | C25: 244190.79 | D25: 244190.79 | E25: 0 | F25: 0 | G25: 244190.79 | H25: 13199502
A26: 42262 | B26: 13199502 | C26: 202392.36 | D26: 446583.15 | E26: 0 | F26: 0 | G26: 202392.36 | H26: 13199502
A27: 42353 | B27: 13199502 | C27: 200192.45 | D27: 646775.6 | E27: 455155.24 | F27: 455155.24 | G27: 655347.69 | H27: 12744347
A28: 42444 | B28: 12744347 | C28: 193289.26 | D28: 840064.86 | E28: 455155.24 | F28: 910310.48 | G28: 648444.5 | H28: 12289192
A29: 42536 | B29: 12289192 | C29: 188434.27 | D29: 1028499.1 | E29: 455155.24 | F29: 1365465.7 | G29: 643589.51 | H29: 11834036
A30: 42628 | B30: 13074202 | C30: 199644.32 | D30: 1228143.5 | E30: 502853.93 | F30: 1868319.7 | G30: 702498.26 | H30: 12571348
A31: 42719 | B31: 12571348 | C31: 190665.45 | D31: 1418808.9 | E31: 502853.93 | F31: 2371173.6 | G31: 693519.38 | H31: 12068494
A32: 42809 | B32: 12068494 | C32: 181027.42 | D32: 1599836.3 | E32: 502853.93 | F32: 2874027.5 | G32: 683881.35 | H32: 11565640
A33: 42901 | B33: 11565640 | C33: 177339.82 | D33: 1777176.1 | E33: 502853.93 | F33: 3376881.5 | G33: 680193.75 | H33: 11062787
A34: 42995 | B34: 11062787 | C34: 173316.99 | D34: 1950493.1 | E34: 502853.93 | F34: 3879735.4 | G34: 676170.92 | H34: 10559933
A35: 43086 | B35: 10559933 | C35: 160158.98 | D35: 2110652.1 | E35: 502853.93 | F35: 4382589.3 | G35: 663012.91 | H35: 10057079
... A55: 44910 | B55: 502853.93 | C55: 7626.618 | D55: 3714420.9 | E55: 502853.93 | F55: 14439668 | G55: 510480.55 | H55: -2.910383e-09
