Workbook

Sheet Disbursement
A1: Borrower: | B1: Hydron Bangladesh Private Ltd. | G1: Grant
A2: Currency: | B2: BDT | G2: Source: ADB
A3: Type: | B3: IDCOL Loan
A4: Source: | B4: RERED II (IDA 5158)
A7: Disbursement Number | B7: Disbursement Date | C7: Disbursement | D7: Cumulative Disbursement | G7: No. | H7: Date | I7: Amount | J7: Cumulative Amount
A8: 1 | B8: 41827 | C8: 10120161 | D8: =C8 -> 10120161 | G8: 1 | H8: 41826 | I8: 16866936 | J8: =I8 -> 16866936
A9: 2 | B9: 41921 | C9: 5028348 | D9: =C9+D8 -> 15148509 | G9: 2 | H9: 41921 | I9: 3017009 | J9: =J8+I9 -> 19883945
A10: 3 | B10: 41980 | C10: 2190418 | D10: =C10+D9 -> 17338927 | G10: 3 | H10: 41984 | I10: 12800265 | J10: =J9+I10 -> 32684210

Sheet Summary
B1: =Accrual_Hydron!B23 -> 41791 | C1: =Accrual_Hydron!C23 -> 41821 | D1: =Accrual_Hydron!D23 -> 41852 | E1: =Accrual_Hydron!E23 -> 41883 | F1: =Accrual_Hydron!F23 -> 41913 | G1: =Accrual_Hydron!G23 -> 41944 | H1: =Accrual_Hydron!H23 -> 41974 | I1: =Accrual_Hydron!I23 -> 42005 | ... DS1: =Accrual_Hydron!DS23 -> 45474
A2: Principal
A3: Opening balance | B3: =Accrual_Hydron!B24 -> 0 | C3: =Accrual_Hydron!C24 -> 0 | D3: =Accrual_Hydron!D24 -> 10120161 | E3: =Accrual_Hydron!E24 -> 10120161 | F3: =Accrual_Hydron!F24 -> 10120161 | G3: =Accrual_Hydron!G24 -> 15148509 | H3: =Accrual_Hydron!H24 -> 15148509 | I3: =Accrual_Hydron!I24 -> 17338927 | ... AD3: =Accrual_Hydron!AD24 -> 17338927 | AE3: =AD3 -> 17338927 | AF3: =AE3 -> 17338927 | AG3: =AF3 -> 17338927 | AH3: =AG3 -> 17338927 | AI3: =AH3 -> 17338927 | AJ3: =AI3 -> 17338927 | AK3: =AJ3 -> 17338927 | AL3: =AK3 -> 17338927 | ... DS3: =DR3 -> 17338927
A4: Repayment due | B4: =Accrual_Hydron!B28 -> 0 | C4: =Accrual_Hydron!C28 -> 0 | D4: =Accrual_Hydron!D28 -> 0 | E4: =Accrual_Hydron!E28 -> 0 | F4: =Accrual_Hydron!F28 -> 0 | G4: =Accrual_Hydron!G28 -> 0 | H4: =Accrual_Hydron!H28 -> 0 | I4: =Accrual_Hydron!I28 -> 0 | ... DS4: =Accrual_Hydron!DS28 -> 17338927
A5: Loan Repayment | B5: =B22 -> 0 | C5: =C22 -> 0 | D5: =D22 -> 0 | E5: =E22 -> 0 | F5: =F22 -> 0 | G5: =G22 -> 0 | H5: =H22 -> 0 | I5: =I22 -> 0 | ... DS5: =DS22 -> 17338927
A6: Repayment overdue | B6: =IF((B4-B5)>0,(B4-B5),0) -> 0 | C6: =IF((C4-C5)>0,(C4-C5),0) -> 0 | D6: =IF((D4-D5)>0,(D4-D5),0) -> 0 | E6: =IF((E4-E5)>0,(E4-E5),0) -> 0 | F6: =IF((F4-F5)>0,(F4-F5),0) -> 0 | G6: =IF((G4-G5)>0,(G4-G5),0) -> 0 | H6: =IF((H4-H5)>0,(H4-H5),0) -> 0 | I6: =IF((I4-I5)>0,(I4-I5),0) -> 0 | ... DS6: =IF((DS4-DS5)>0,(DS4-DS5),0) -> 0
A7: Loan outstanding | B7: =B3-B5 -> 0 | C7: =C3-C5 -> 0 | D7: =D3-D5 -> 10120161 | E7: =E3-E5 -> 10120161 | F7: =F3-F5 -> 10120161 | G7: =G3-G5 -> 15148509 | H7: =H3-H5 -> 15148509 | I7: =I3-I5 -> 17338927 | ... DS7: =DS3-DS5 -> 0
A8: Interest
A9: Interest accrued | B9: =Accrual_Hydron!B26 -> 0 | C9: =Accrual_Hydron!C26 -> 0 | D9: =Accrual_Hydron!D26 -> 42167.338 | E9: =Accrual_Hydron!E26 -> 94454.836 | F9: =Accrual_Hydron!F26 -> 145055.64 | G9: =Accrual_Hydron!G26 -> 216618.47 | H9: =Accrual_Hydron!H26 -> 292361.02 | I9: =Accrual_Hydron!I26 -> 379755.06 | ... DS9: =Accrual_Hydron!DS26 -> 6311293.6
A10: Interest due | B10: =Hydron_Loan!B33 -> 0 | C10: =B10 -> 0 | D10: =C10 -> 0 | E10: =D10 -> 0 | F10: 0 | G10: =F10 -> 0 | H10: =G10 -> 0 | I10: =Hydron_Loan!$C$33 -> 0 | J10: =I10 -> 0 | K10: =J10 -> 0 | L10: =Hydron_Loan!$D$33 -> 634059.32 | M10: =L10 -> 634059.32 | N10: =M10 -> 634059.32 | O10: =Hydron_Loan!$E$33 -> 899922.87 | P10: =O10 -> 899922.87 | Q10: =P10 -> 899922.87 | R10: =Hydron_Loan!$F$33 -> 1165786.4 | S10: =R10 -> 1165786.4 | T10: =S10 -> 1165786.4 | U10: =Hydron_Loan!$G$33 -> 1428760.1 | V10: =U10 -> 1428760.1 | W10: =V10 -> 1428760.1 | X10: =Hydron_Loan!$H$33 -> 1691733.9 | Y10: =X10 -> 1691733.9 | Z10: =Y10 -> 1691733.9 | AA10: =Hydron_Loan!$I$33 -> 1957597.4 | AB10: =AA10 -> 1957597.4 | AC10: =AB10 -> 1957597.4 | AD10: =Hydron_Loan!$J$33 -> 2229240.6 | AE10: =AD10 -> 2229240.6 | AF10: =AE10 -> 2229240.6 | AG10: =Hydron_Loan!$K$33 -> 2483996.4 | AH10: =AG10 -> 2483996.4 | AI10: =AH10 -> 2483996.4 | AJ10: =Hydron_Loan!$L$33 -> 2722406.6 | AK10: =AJ10 -> 2722406.6 | AL10: =AK10 -> 2722406.6 | AM10: =Hydron_Loan!$M$33 -> 2968583.3 | AN10: =AM10 -> 2968583.3 | AO10: =AN10 -> 2968583.3 | AP10: =Hydron_Loan!$N$33 -> 3196156.7 | AQ10: =AP10 -> 3196156.7 | AR10: =AQ10 -> 3196156.7 | AS10: =Hydron_Loan!$O$33 -> 3418040.8 | AT10: =AS10 -> 3418040.8 | AU10: =AT10 -> 3418040.8 | AV10: =Hydron_Loan!$P$33 -> 3629359 | AW10: =AV10 -> 3629359 | AX10: =AW10 -> 3629359 | AY10: =Hydron_Loan!$Q$33 -> 3837064.9 | AZ10: =AY10 -> 3837064.9 | BA10: =AZ10 -> 3837064.9 | BB10: =Hydron_Loan!$R$33 -> 4036462.5 | BC10: =BB10 -> 4036462.5 | BD10: =BC10 -> 4036462.5 | BE10: =Hydron_Loan!$S$33 -> 4225474.9 | BF10: =BE10 -> 4225474.9 | BG10: =BF10 -> 4225474.9 | BH10: =Hydron_Loan!$T$33 -> 4404282.6 | BI10: =BH10 -> 4404282.6 | BJ10: =BI10 -> 4404282.6 | BK10: =Hydron_Loan!$U$33 -> 4578755.5 | BL10: =BK10 -> 4578755.5 | BM10: =BL10 -> 4578755.5 | BN10: =Hydron_Loan!$V$33 -> 4744920.2 | BO10: =BN10 -> 4744920.2 | BP10: =BO10 -> 4744920.2 | BQ10: =Hydron_Loan!$W$33 -> 4901060.9 | BR10: =BQ10 -> 4901060.9 | BS10: =BR10 -> 4901060.9 | BT10: =Hydron_Loan!$X$33 -> 5048983.6 | BU10: =BT10 -> 5048983.6 | BV10: =BU10 -> 5048983.6 | BW10: =Hydron_Loan!$Y$33 -> 5190223.6 | BX10: =BW10 -> 5190223.6 | BY10: =BX10 -> 5190223.6 | BZ10: =Hydron_Loan!$Z$33 -> 5323155.4 | CA10: =BZ10 -> 5323155.4 | CB10: =CA10 -> 5323155.4 | CC10: =Hydron_Loan!$AA$33 -> 5446424.3 | CD10: =CC10 -> 5446424.3 | CE10: =CD10 -> 5446424.3 | CF10: =Hydron_Loan!$AB$33 -> 5560211 | CG10: =CF10 -> 5560211 | CH10: =CG10 -> 5560211 | CI10: =Hydron_Loan!$AC$33 -> 5668218.1 | CJ10: =CI10 -> 5668218.1 | CK10: =CJ10 -> 5668218.1 | CL10: =Hydron_Loan!$AD$33 -> 5767916.9 | CM10: =CL10 -> 5767916.9 | CN10: =CM10 -> 5767916.9 | CO10: =Hydron_Loan!$AE$33 -> 5858314.1 | CP10: =CO10 -> 5858314.1 | CQ10: =CP10 -> 5858314.1 | CR10: =Hydron_Loan!$AF$33 -> 5939590.4 | CS10: =CR10 -> 5939590.4 | CT10: =CS10 -> 5939590.4 | CU10: =Hydron_Loan!$AG$33 -> 6014364.5 | CV10: =CU10 -> 6014364.5 | CW10: =CV10 -> 6014364.5 | CX10: =Hydron_Loan!$AH$33 -> 6080830.4 | CY10: =CX10 -> 6080830.4 | CZ10: =CY10 -> 6080830.4 | DA10: =Hydron_Loan!$AI$33 -> 6138355.9 | DB10: =DA10 -> 6138355.9 | DC10: =DB10 -> 6138355.9 | DD10: =Hydron_Loan!$AJ$33 -> 6187121.6 | DE10: =DD10 -> 6187121.6 | DF10: =DE10 -> 6187121.6 | DG10: =Hydron_Loan!$AK$33 -> 6228662.8 | DH10: =DG10 -> 6228662.8 | DI10: =DH10 -> 6228662.8 | DJ10: =Hydron_Loan!$AL$33 -> 6261895.7 | DK10: =DJ10 -> 6261895.7 | DL10: =DK10 -> 6261895.7 | DM10: =Hydron_Loan!$AM$33 -> 6286549.5 | DN10: =DM10 -> 6286549.5 | DO10: =DN10 -> 6286549.5 | DP10: =Hydron_Loan!$AN$33 -> 6302985.4 | DQ10: =DP10 -> 6302985.4 | DR10: =DQ10 -> 6302985.4 | DS10: =Hydron_Loan!$AO$33 -> 6311293.6
A11: interest received | B11: =B26 -> 0 | C11: =C26 -> 0 | D11: =D26 -> 0 | E11: =E26 -> 0 | F11: =F26 -> 0 | G11: =G26 -> 0 | H11: =H26 -> 0 | I11: =I26 -> 0 | ... DS11: =DS26 -> 6311293.6
A12: Interest overdue | B12: =IF((B10-B11)>0,(B10-B11),0) -> 0 | C12: =IF((C10-C11)>0,(C10-C11),0) -> 0 | D12: =IF((D10-D11)>0,(D10-D11),0) -> 0 | E12: =IF((E10-E11)>0,(E10-E11),0) -> 0 | F12: =IF((F10-F11)>0,(F10-F11),0) -> 0 | G12: =IF((G10-G11)>0,(G10-G11),0) -> 0 | H12: =IF((H10-H11)>0,(H10-H11),0) -> 0 | I12: =IF((I10-I11)>0,(I10-I11),0) -> 0 | ... DS12: =IF((DS10-DS11)>0,(DS10-DS11),0) -> 0
A13: Interest receivable | B13: =B9-B11 -> 0 | C13: =C9-C11 -> 0 | D13: =D9-D11 -> 42167.338 | E13: =E9-E11 -> 94454.836 | F13: =F9-F11 -> 145055.64 | G13: =G9-G11 -> 216618.47 | H13: =H9-H11 -> 292361.02 | I13: =I9-I11 -> 379755.06 | ... DS13: =DS9-DS11 -> 0
A14: LD and others | B14: =B28 -> 0 | C14: =C28 -> 0 | D14: =D28 -> 0 | E14: =E28 -> 0 | F14: =F28 -> 0 | G14: =G28 -> 0 | H14: =H28 -> 0 | I14: =I28 -> 0 | ... DS14: =DS28 -> 0
B19: =B1 -> 41791 | C19: =C1 -> 41821 | D19: =D1 -> 41852 | E19: =E1 -> 41883 | F19: =F1 -> 41913 | G19: =G1 -> 41944 | H19: =H1 -> 41974 | I19: =I1 -> 42005 | ... DS19: =DS1 -> 45474
A20: Repayment receipts:
A21: Repayment received | C21: =Accrual_Hydron!C27 -> 0 | L21: =Accrual_Hydron!L27 -> 0 | O21: =Accrual_Hydron!O27 -> 0 | R21: =Accrual_Hydron!R27 -> 0 | U21: =Accrual_Hydron!U27 -> 0 | X21: =Accrual_Hydron!X27 -> 0 | AA21: =Accrual_Hydron!AA27 -> 0 | AD21: 0 | AG21: 0 | AJ21: 0 | AM21: 0 | AP21: =AP4-AO5 -> 2709207.3 | AQ21: =AQ4-AP5 -> 0 | AR21: =AR4-AQ5 -> 0 | AS21: =AS4-AR5 -> 541841.47 | AT21: =AT4-AS5 -> 0 | AU21: =AU4-AT5 -> 0 | AV21: =AV4-AU5 -> 541841.47 | AW21: =AW4-AV5 -> 0 | ... DS21: =DS4-DR5 -> 541841.47
A22: Repayment received (cumulative) | B22: =B21 -> 0 | C22: =B22+C21 -> 0 | D22: =C22+D21 -> 0 | E22: =D22+E21 -> 0 | F22: =E22+F21 -> 0 | G22: =F22+G21 -> 0 | H22: =G22+H21 -> 0 | I22: =H22+I21 -> 0 | J22: =I22+J21 -> 0 | ... DS22: =DR22+DS21 -> 17338927
A24: Interest receipts:
A25: Interest received | B25: =B10 -> 0 | C25: =C10-B11 -> 0 | E25: =E10-D11 -> 0 | F25: =F10-E11 -> 0 | H25: =H10-G11 -> 0 | I25: =I10-H11 -> 0 | L25: 0 | O25: 0 | R25: 0 | U25: 0 | X25: 0 | AA25: 0 | AD25: 0 | AG25: 0 | AJ25: 0 | AM25: 0 | AP25: =AP10-AO11 -> 3196156.7 | AS25: =AS10-AR11 -> 221884.08 | AV25: =AV10-AU11 -> 211318.17 | AY25: =AY10-AX11 -> 207705.9 | BB25: =BB10-BA11 -> 199397.66 | BE25: =BE10-BD11 -> 189012.37 | BH25: =BH10-BG11 -> 178807.68 | BK25: =BK10-BJ11 -> 174472.95 | BN25: =BN10-BM11 -> 166164.72 | BQ25: =BQ10-BP11 -> 156140.65 | BT25: =BT10-BS11 -> 147922.72 | BW25: =BW10-BV11 -> 141240.01 | BZ25: =BZ10-BY11 -> 132931.77 | CC25: =CC10-CB11 -> 123268.93 | CF25: =CF10-CE11 -> 113786.71 | CI25: =CI10-CH11 -> 108007.07 | CL25: =CL10-CK11 -> 99698.83 | CO25: =CO10-CN11 -> 90397.218 | CR25: =CR10-CQ11 -> 81276.22 | CU25: =CU10-CT11 -> 74774.123 | CX25: =CX10-CW11 -> 66465.887 | DA25: =DA10-CZ11 -> 57525.503 | DD25: =DD10-DC11 -> 48765.732 | DG25: =DG10-DF11 -> 41541.179 | DJ25: =DJ10-DI11 -> 33232.943 | DM25: =DM10-DL11 -> 24653.787 | DP25: =DP10-DO11 -> 16435.858 | DS25: =DS10-DR11 -> 8308.2359
A26: Interest received (cumulative) | B26: =B25 -> 0 | C26: =B26+C25 -> 0 | D26: =C26+D25 -> 0 | E26: =D26+E25 -> 0 | F26: =E26+F25 -> 0 | G26: =F26+G25 -> 0 | H26: =G26+H25 -> 0 | I26: =H26+I25 -> 0 | J26: =I26+J25 -> 0 | ... DS26: =DR26+DS25 -> 6311293.6
A27: LD/others | B27: 0 | C27: 0 | D27: 0 | E27: 0 | F27: 0 | G27: 0 | H27: 0 | I27: 0 | K27: 0 | L27: 0 | N27: 0 | O27: 0 | Q27: 0 | R27: 0 | T27: 0 | U27: 0 | V27: 0 | W27: 0 | X27: 0 | Y27: 0 | Z27: 0 | AA27: 0 | AB27: 0 | AC27: 0 | AD27: 0 | AE27: 0 | AF27: 0 | AG27: 0 | AH27: 0 | AI27: 0 | AJ27: 0 | AK27: 0 | AL27: 0 | AM27: 0 | AN27: 0 | AO27: 0 | AP27: 0 | AQ27: 0 | AR27: 0 | AS27: 0 | AT27: 0 | AU27: 0 | AV27: 0 | AW27: 0 | AX27: 0 | AY27: 0 | AZ27: 0 | BA27: 0 | BB27: 0 | BC27: 0 | BD27: 0 | BE27: 0 | BF27: 0 | BG27: 0 | BH27: 0 | BI27: 0 | BJ27: 0 | BK27: 0 | BL27: 0 | BM27: 0 | BN27: 0 | BO27: 0 | BP27: 0 | BQ27: 0 | BR27: 0 | BS27: 0 | BT27: 0 | BU27: 0 | BV27: 0 | BW27: 0 | BX27: 0 | BY27: 0 | BZ27: 0 | CA27: 0 | CB27: 0 | CC27: 0 | CD27: 0 | CE27: 0 | CF27: 0 | CG27: 0 | CH27: 0 | CI27: 0 | CJ27: 0 | CK27: 0 | CL27: 0 | CM27: 0 | CN27: 0 | CO27: 0 | CP27: 0 | CQ27: 0 | CR27: 0 | CS27: 0 | CT27: 0 | CU27: 0 | CV27: 0 | CW27: 0 | CX27: 0 | CY27: 0 | CZ27: 0 | DA27: 0 | DB27: 0 | DC27: 0 | DD27: 0 | DE27: 0 | DF27: 0 | DG27: 0 | DH27: 0 | DI27: 0 | DJ27: 0 | DK27: 0 | DL27: 0 | DM27: 0 | DN27: 0 | DO27: 0 | DP27: 0 | DQ27: 0 | DR27: 0 | DS27: 0
A28: LD/others (cumulative) | B28: =B27 -> 0 | C28: =B28+C27 -> 0 | D28: =C28+D27 -> 0 | E28: =D28+E27 -> 0 | F28: =E28+F27 -> 0 | G28: =F28+G27 -> 0 | H28: =G28+H27 -> 0 | I28: =H28+I27 -> 0 | J28: =I28+J27 -> 0 | ... DS28: =DR28+DS27 -> 0
A30: Actual Payment date
A31: Actual Payment amount:
A32: Interest
A33: Principal
A34: LPC
A35: Total | B35: =SUM(B32:B34) -> 0 | C35: =SUM(C32:C34) -> 0 | D35: =SUM(D32:D34) -> 0 | E35: =SUM(E32:E34) -> 0 | F35: =SUM(F32:F34) -> 0 | G35: =SUM(G32:G34) -> 0 | H35: =SUM(H32:H34) -> 0 | I35: =SUM(I32:I34) -> 0 | ... DS35: =SUM(DS32:DS34) -> 0

Sheet Hydron_Loan
A1: Project name: | C1: Hydron Bangladesh Private Ltd.
A5: Financial Close | C5: 41639
A7: Loan Amount | C7: 19610526
A9: Drawdown Date | C9: =Disbursement!B8 -> 41827
A11: Interest Rate | C11: 0.06
A12: Tenor | C12: 10 years
A13: Interest Grace | C13: 6 | D13: months | E13: =EDATE(C20,C13) -> 42011
A14: Principal Grace | C14: 2 | D14: years | E14: =EDATE(C20,24) -> 42558
A15: Principal | C15: Level Principal
A16: Interest calculation | C16: 360 | D16: days basis
A17: Number of installments | C17: 32
A19: Drawdown
C20: =Disbursement!B8 -> 41827 | D20: =Disbursement!B9 -> 41921 | E20: =Disbursement!B10 -> 41980
C21: =Disbursement!C8 -> 10120161 | D21: =Disbursement!C9 -> 5028348 | E21: =Disbursement!C10 -> 2190418
C22: =C21 -> 10120161 | D22: =C22+D21 -> 15148509 | E22: =D22+E21 -> 17338927
A28: Repayment
A29: Repayment Period | J29: 1 | K29: 2 | L29: 3 | M29: 4 | N29: 5 | O29: 6 | P29: 7 | Q29: 8 | R29: 9 | S29: 10 | T29: 11 | U29: 12 | V29: 13 | W29: 14 | X29: 15 | Y29: 16 | Z29: 17 | AA29: 18 | AB29: 19 | AC29: 20 | AD29: 21 | AE29: 22 | AF29: 23 | AG29: 24 | AH29: 25 | AI29: 26 | AJ29: 27 | AK29: 28 | AL29: 29 | AM29: 30 | AN29: 31 | AO29: 32
A30: Repayment Date | B30: 41912 | C30: 42003 | D30: 42093 | E30: 42185 | F30: 42277 | G30: 42368 | H30: 42459 | I30: 42551 | J30: 42645 | K30: 42736 | L30: 42824 | M30: 42918 | N30: 43008 | O30: 43099 | P30: 43189 | Q30: 43281 | R30: 43373 | S30: 43464 | T30: 43554 | U30: 43646 | V30: 43738 | W30: 43829 | X30: 43920 | Y30: 44012 | Z30: 44104 | AA30: 44195 | AB30: 44285 | AC30: 44377 | AD30: 44469 | AE30: 44560 | AF30: 44650 | AG30: 44742 | AH30: 44834 | AI30: 44925 | AJ30: 45015 | AK30: 45107 | AL30: 45199 | AM30: 45290 | AN30: 45381 | AO30: 45473
A31: Opening Balance | B31: =C21 -> 10120161 | C31: =B37+D21+E21 -> 17338927 | D31: =C37 -> 17338927 | E31: =D37 -> 17338927 | F31: =E37 -> 17338927 | G31: =F37 -> 17338927 | H31: =G37 -> 17338927 | I31: =H37 -> 17338927 | J31: =I37 -> 17338927 | K31: =J37 -> 16797086 | ... AO31: =AN37 -> 541841.47
A32: Interest Payment | B32: 0 | C32: 0 | D32: =C22*(D20-C20)*$C$11/360+D22*(E20-D20)*$C$11/360+E22*(D30-E20)*$C$11/360 -> 634059.32 | E32: =D37*(E30-D30)*$C$11/360 -> 265863.55 | F32: =E37*(F30-E30)*$C$11/360 -> 265863.55 | G32: =F37*(G30-F30)*$C$11/360 -> 262973.73 | H32: =G37*(H30-G30)*$C$11/360 -> 262973.73 | I32: =H37*(I30-H30)*$C$11/360 -> 265863.55 | J32: =I37*(J30-I30)*$C$11/360 -> 271643.19 | K32: =J37*(K30-J30)*$C$11/360 -> 254755.8 | L32: =K37*(L30-K30)*$C$11/360 -> 238410.25 | ... AO32: =AN37*(AO30-AN30)*$C$11/360 -> 8308.2359
A33: Cumulative interest | B33: 0 | C33: =C32 -> 0 | D33: =D32+C33 -> 634059.32 | E33: =E32+D33 -> 899922.87 | F33: =F32+E33 -> 1165786.4 | G33: =G32+F33 -> 1428760.1 | H33: =H32+G33 -> 1691733.9 | I33: =I32+H33 -> 1957597.4 | J33: =J32+I33 -> 2229240.6 | K33: =K32+J33 -> 2483996.4 | ... AO33: =AO32+AN33 -> 6311293.6
A34: Principal Payment | B34: 0 | C34: 0 | D34: 0 | E34: 0 | F34: 0 | G34: 0 | H34: 0 | I34: 0 | J34: =$I$37/32 -> 541841.47 | K34: =J34 -> 541841.47 | L34: =K34 -> 541841.47 | M34: =L34 -> 541841.47 | N34: =M34 -> 541841.47 | O34: =N34 -> 541841.47 | P34: =O34 -> 541841.47 | Q34: =P34 -> 541841.47 | R34: =Q34 -> 541841.47 | ... AO34: =AN34 -> 541841.47
A35: Cumulative repayment | B35: 0 | C35: =C34+B35 -> 0 | D35: =D34+C35 -> 0 | E35: =E34+D35 -> 0 | F35: =F34+E35 -> 0 | G35: =G34+F35 -> 0 | H35: =H34+G35 -> 0 | I35: =I34+H35 -> 0 | J35: =J34+I35 -> 541841.47 | ... AO35: =AO34+AN35 -> 17338927
A36: Total Debt Service | B36: 0 | C36: =C32+C34 -> 0 | D36: =D34+D32 -> 634059.32 | E36: =E34+E32 -> 265863.55 | F36: =F34+F32 -> 265863.55 | G36: =G34+G32 -> 262973.73 | H36: =H34+H32 -> 262973.73 | I36: =I34+I32 -> 265863.55 | J36: =J34+J32 -> 813484.66 | K36: =K34+K32 -> 796597.27 | ... AO36: =AO34+AO32 -> 550149.7
A37: Closing Balance | B37: =B31-B34 -> 10120161 | C37: =C31-C34 -> 17338927 | D37: =D31-D34 -> 17338927 | E37: =E31-E34 -> 17338927 | F37: =F31-F34 -> 17338927 | G37: =G31-G34 -> 17338927 | H37: =H31-H34 -> 17338927 | I37: =I31-I34 -> 17338927 | ... AO37: =AO31-AO34 -> 0
D41: Avg. Installment Size | E41: =AVERAGE(J36:AO36) -> 677894.48
D43: Revised avg. installment | E43: =AVERAGE(D36:H36) -> 338346.77
A46: Average Installment Size
A47: Month | D47: =D30 -> 42093 | E47: =E30 -> 42185 | F47: =F30 -> 42277 | G47: =G30 -> 42368 | H47: =H30 -> 42459 | I47: =I30 -> 42551 | J47: =J30 -> 42645 | K47: =K30 -> 42736 | ... AO47: =AO30 -> 45473
A48: Amount | D48: =AVERAGE(D36) -> 634059.32 | E48: =AVERAGE($D$36:E36) -> 449961.43 | F48: =AVERAGE($D$36:F36) -> 388595.47 | G48: =AVERAGE($D$36:G36) -> 357190.04 | H48: =AVERAGE($D$36:H36) -> 338346.77 | I48: =AVERAGE($D$36:I36) -> 326266.24 | J48: =AVERAGE($D$36:J36) -> 395868.87 | K48: =AVERAGE($D$36:K36) -> 445959.92 | L48: =AVERAGE($D$36:L36) -> 483103.45 | ... AO48: =AVERAGE($D$36:AO36) -> 622374.23

Sheet Accrual_Hydron
A1: Project name: | B1: =Hydron_Loan!C1 -> Hydron Bangladesh Private Ltd.
A3: Assumptions:
A5: Financial Close | B5: =Hydron_Loan!C5 -> 41639
A7: Loan Amount | B7: =Hydron_Loan!C7 -> 19610526 | C7: BDT
A9: Drawdown Date | B9: =Hydron_Loan!C9 -> 41827
A11: Interest Rate | B11: 0.06
A12: Tenor | B12: 10 years
A13: Interest calculation | B13: 360 | C13: days basis
A14: Principal | B14: =Hydron_Loan!C15 -> Level Principal
A16: Drawdown
B17: =Hydron_Loan!C20 -> 41827 | C17: =Hydron_Loan!D20 -> 41921 | D17: =Hydron_Loan!E20 -> 41980
B18: =Hydron_Loan!C21 -> 10120161 | C18: =Hydron_Loan!D21 -> 5028348 | D18: =Hydron_Loan!E21 -> 2190418
B19: =B18 -> 10120161 | C19: =B19+C18 -> 15148509 | D19: =C19+D18 -> 17338927
A22: Accrual of interest
A23: Months | B23: 41791 | C23: 41821 | D23: 41852 | E23: 41883 | F23: 41913 | G23: 41944 | H23: 41974 | I23: 42005 | J23: 42036 | K23: 42064 | L23: 42095 | M23: 42125 | N23: 42156 | O23: 42186 | P23: 42217 | Q23: 42248 | R23: 42278 | S23: 42309 | T23: 42339 | U23: 42370 | V23: 42401 | W23: 42430 | X23: 42461 | Y23: 42491 | Z23: 42522 | AA23: 42552 | AB23: 42583 | AC23: 42614 | AD23: 42644 | AE23: 42675 | AF23: 42705 | AG23: 42736 | AH23: 42767 | AI23: 42795 | AJ23: 42826 | AK23: 42856 | AL23: 42887 | AM23: 42917 | AN23: 42948 | AO23: 42979 | AP23: 43009 | AQ23: 43040 | AR23: 43070 | AS23: 43101 | AT23: 43132 | AU23: 43160 | AV23: 43191 | AW23: 43221 | AX23: 43252 | AY23: 43282 | AZ23: 43313 | BA23: 43344 | BB23: 43374 | BC23: 43405 | BD23: 43435 | BE23: 43466 | BF23: 43497 | BG23: 43525 | BH23: 43556 | BI23: 43586 | BJ23: 43617 | BK23: 43647 | BL23: 43678 | BM23: 43709 | BN23: 43739 | BO23: 43770 | BP23: 43800 | BQ23: 43831 | BR23: 43862 | BS23: 43891 | BT23: 43922 | BU23: 43952 | BV23: 43983 | BW23: 44013 | BX23: 44044 | BY23: 44075 | BZ23: 44105 | CA23: 44136 | CB23: 44166 | CC23: 44197 | CD23: 44228 | CE23: 44256 | CF23: 44287 | CG23: 44317 | CH23: 44348 | CI23: 44378 | CJ23: 44409 | CK23: 44440 | CL23: 44470 | CM23: 44501 | CN23: 44531 | CO23: 44562 | CP23: 44593 | CQ23: 44621 | CR23: 44652 | CS23: 44682 | CT23: 44713 | CU23: 44743 | CV23: 44774 | CW23: 44805 | CX23: 44835 | CY23: 44866 | CZ23: 44896 | DA23: 44927 | DB23: 44958 | DC23: 44986 | DD23: 45017 | DE23: 45047 | DF23: 45078 | DG23: 45108 | DH23: 45139 | DI23: 45170 | DJ23: 45200 | DK23: 45231 | DL23: 45261 | DM23: 45292 | DN23: 45323 | DO23: 45352 | DP23: 45383 | DQ23: =EDATE(DP23,1) -> 45413 | DR23: =EDATE(DQ23,1) -> 45444 | DS23: =EDATE(DR23,1) -> 45474
A24: Opening Balance | B24: 0 | C24: 0 | D24: =B18 -> 10120161 | E24: =D30 -> 10120161 | F24: =E30 -> 10120161 | G24: =F30+C18 -> 15148509 | H24: =G30 -> 15148509 | I24: =H30+D18 -> 17338927 | J24: =I30 -> 17338927 | K24: =J30 -> 17338927 | L24: =K30 -> 17338927 | M24: =L30 -> 17338927 | N24: =M30 -> 17338927 | O24: =N30 -> 17338927 | P24: =O30 -> 17338927 | Q24: =P30 -> 17338927 | ... DS24: =DR30 -> 541841.47
A25: Interest Payment | B25: =B24*(B23-B17)*$B$11/360 -> 0 | C25: =C24*(B17-C23)*$B$11/360 -> 0 | D25: =D24*(D23-B17)*$B$11/360 -> 42167.338 | E25: =E24*(E23-D23)*$B$11/360 -> 52287.499 | F25: =F24*(F23-E23)*$B$11/360 -> 50600.805 | G25: =F30*(C17-F23)*$B$11/360+C19*(G23-C17)*$B$11/360 -> 71562.832 | H25: =G30*(H23-G23)*$B$11/360 -> 75742.545 | I25: =H30*(D17-H23)*$B$11/360+D19*(I23-D17)*$B$11/360 -> 87394.038 | J25: =J24*(J23-I23)*$B$11/360 -> 89584.456 | K25: =K24*(K23-J23)*$B$11/360 -> 80914.993 | L25: =L24*(L23-K23)*$B$11/360 -> 89584.456 | M25: =M24*(M23-L23)*$B$11/360 -> 86694.635 | N25: =N24*(N23-M23)*$B$11/360 -> 89584.456 | O25: =O24*(O23-N23)*$B$11/360 -> 86694.635 | P25: =P24*(P23-O23)*$B$11/360 -> 89584.456 | Q25: =Q24*(Q23-P23)*$B$11/360 -> 89584.456 | ... AC25: =AC24*(AC23-AB23)*$B$11/360 -> 89584.456 | AD25: =AD24*(Hydron_Loan!J30-AC23)*$B$11/360+AD30*(AD23-Hydron_Loan!J30)*$B$11/360 -> 86784.942 | AE25: =AE24*(AE23-AD23)*$B$11/360 -> 86784.942 | AF25: =AF24*(AF23-AE23)*$B$11/360 -> 83985.428 | AG25: =AG24*(Hydron_Loan!K30-AF23)*$B$11/360+AG30*(AG23-Hydron_Loan!K30)*$B$11/360 -> 86784.942 | AH25: =AH24*(AH23-AG23)*$B$11/360 -> 83985.428 | AI25: =AI24*(AI23-AH23)*$B$11/360 -> 75857.806 | AJ25: =AJ24*(Hydron_Loan!L30-AI23)*$B$11/360+AJ30*(AJ23-Hydron_Loan!L30)*$B$11/360 -> 83804.814 | AK25: =AK24*(AK23-AJ23)*$B$11/360 -> 78567.013 | AL25: =AL24*(AL23-AK23)*$B$11/360 -> 81185.913 | AM25: =AM24*(Hydron_Loan!M30-AL23)*$B$11/360+AM30*(AM23-Hydron_Loan!M30)*$B$11/360 -> 78657.32 | AN25: =AN24*(AN23-AM23)*$B$11/360 -> 78386.399 | AO25: =AO24*(AO23-AN23)*$B$11/360 -> 78386.399 | AP25: =AP24*(Hydron_Loan!N30-AO23)*$B$11/360+AP30*(AP23-Hydron_Loan!N30)*$B$11/360 -> 75767.499 | AQ25: =AQ24*(AQ23-AP23)*$B$11/360 -> 75586.885 | AR25: =AR24*(AR23-AQ23)*$B$11/360 -> 73148.598 | AS25: =AS24*(Hydron_Loan!O30-AR23)*$B$11/360+AS30*(AS23-Hydron_Loan!O30)*$B$11/360 -> 75406.271 | AT25: =AT24*(AT23-AS23)*$B$11/360 -> 72787.371 | AU25: =AU24*(AU23-AT23)*$B$11/360 -> 65743.432 | AV25: =AV24*(Hydron_Loan!P30-AU23)*$B$11/360+AV30*(AV23-Hydron_Loan!P30)*$B$11/360 -> 72606.757 | AW25: =AW24*(AW23-AV23)*$B$11/360 -> 67730.184 | AX25: =AX24*(AX23-AW23)*$B$11/360 -> 69987.856 | AY25: =AY24*(Hydron_Loan!Q30-AX23)*$B$11/360+AY30*(AY23-Hydron_Loan!Q30)*$B$11/360 -> 67639.877 | AZ25: =AZ24*(AZ23-AY23)*$B$11/360 -> 67188.342 | BA25: =BA24*(BA23-AZ23)*$B$11/360 -> 67188.342 | BB25: =BB24*(Hydron_Loan!R30-BA23)*$B$11/360+BB30*(BB23-Hydron_Loan!R30)*$B$11/360 -> 64930.669 | BC25: =BC24*(BC23-BB23)*$B$11/360 -> 64388.828 | BD25: =BD24*(BD23-BC23)*$B$11/360 -> 62311.769 | BE25: =BE24*(Hydron_Loan!S30-BD23)*$B$11/360+BE30*(BE23-Hydron_Loan!S30)*$B$11/360 -> 64208.214 | BF25: =BF24*(BF23-BE23)*$B$11/360 -> 61589.314 | BG25: =BG24*(BG23-BF23)*$B$11/360 -> 55629.057 | BH25: =BH24*(Hydron_Loan!T30-BG23)*$B$11/360+BH30*(BH23-Hydron_Loan!T30)*$B$11/360 -> 61408.7 | BI25: =BI24*(BI23-BH23)*$B$11/360 -> 56893.354 | BJ25: =BJ24*(BJ23-BI23)*$B$11/360 -> 58789.799 | BK25: =BK24*(Hydron_Loan!U30-BJ23)*$B$11/360+BK30*(BK23-Hydron_Loan!U30)*$B$11/360 -> 56803.047 | BL25: =BL24*(BL23-BK23)*$B$11/360 -> 55990.285 | BM25: =BM24*(BM23-BL23)*$B$11/360 -> 55990.285 | BN25: =BN24*(Hydron_Loan!V30-BM23)*$B$11/360+BN30*(BN23-Hydron_Loan!V30)*$B$11/360 -> 54093.84 | BO25: =BO24*(BO23-BN23)*$B$11/360 -> 53190.771 | BP25: =BP24*(BP23-BO23)*$B$11/360 -> 51474.94 | BQ25: =BQ24*(Hydron_Loan!W30-BP23)*$B$11/360+BQ30*(BQ23-Hydron_Loan!W30)*$B$11/360 -> 53010.157 | BR25: =BR24*(BR23-BQ23)*$B$11/360 -> 50391.257 | BS25: =BS24*(BS23-BR23)*$B$11/360 -> 47140.208 | BT25: =BT24*(Hydron_Loan!X30-BS23)*$B$11/360+BT30*(BT23-Hydron_Loan!X30)*$B$11/360 -> 50210.643 | BU25: =BU24*(BU23-BT23)*$B$11/360 -> 46056.525 | BV25: =BV24*(BV23-BU23)*$B$11/360 -> 47591.742 | BW25: =BW24*(Hydron_Loan!Y30-BV23)*$B$11/360+BW30*(BW23-Hydron_Loan!Y30)*$B$11/360 -> 45966.218 | BX25: =BX24*(BX23-BW23)*$B$11/360 -> 44792.228 | BY25: =BY24*(BY23-BX23)*$B$11/360 -> 44792.228 | BZ25: =BZ24*(Hydron_Loan!Z30-BY23)*$B$11/360+BZ30*(BZ23-Hydron_Loan!Z30)*$B$11/360 -> 43257.011 | CA25: =CA24*(CA23-BZ23)*$B$11/360 -> 41992.714 | CB25: =CB24*(CB23-CA23)*$B$11/360 -> 40638.11 | CC25: =CC24*(Hydron_Loan!AA30-CB23)*$B$11/360+CC30*(CC23-Hydron_Loan!AA30)*$B$11/360 -> 41812.1 | CD25: =CD24*(CD23-CC23)*$B$11/360 -> 39193.2 | CE25: =CE24*(CE23-CD23)*$B$11/360 -> 35400.309 | CF25: =CF24*(Hydron_Loan!AB30-CE23)*$B$11/360+CF30*(CF23-Hydron_Loan!AB30)*$B$11/360 -> 39012.586 | CG25: =CG24*(CG23-CF23)*$B$11/360 -> 35219.695 | CH25: =CH24*(CH23-CG23)*$B$11/360 -> 36393.685 | CI25: =CI24*(Hydron_Loan!AC30-CH23)*$B$11/360+CI30*(CI23-Hydron_Loan!AC30)*$B$11/360 -> 35129.389 | CJ25: =CJ24*(CJ23-CI23)*$B$11/360 -> 33594.171 | CK25: =CK24*(CK23-CJ23)*$B$11/360 -> 33594.171 | CL25: =CL24*(Hydron_Loan!AD30-CK23)*$B$11/360+CL30*(CL23-Hydron_Loan!AD30)*$B$11/360 -> 32420.181 | CM25: =CM24*(CM23-CL23)*$B$11/360 -> 30794.657 | CN25: =CN24*(CN23-CM23)*$B$11/360 -> 29801.281 | CO25: =CO24*(Hydron_Loan!AE30-CN23)*$B$11/360+CO30*(CO23-Hydron_Loan!AE30)*$B$11/360 -> 30614.043 | CP25: =CP24*(CP23-CO23)*$B$11/360 -> 27995.143 | CQ25: =CQ24*(CQ23-CP23)*$B$11/360 -> 25285.935 | CR25: =CR24*(Hydron_Loan!AF30-CQ23)*$B$11/360+CR30*(CR23-Hydron_Loan!AF30)*$B$11/360 -> 27814.529 | CS25: =CS24*(CS23-CR23)*$B$11/360 -> 24382.866 | CT25: =CT24*(CT23-CS23)*$B$11/360 -> 25195.628 | CU25: =CU24*(Hydron_Loan!AG30-CT23)*$B$11/360+CU30*(CU23-Hydron_Loan!AG30)*$B$11/360 -> 24292.559 | CV25: =CV24*(CV23-CU23)*$B$11/360 -> 22396.114 | CW25: =CW24*(CW23-CV23)*$B$11/360 -> 22396.114 | CX25: =CX24*(Hydron_Loan!AH30-CW23)*$B$11/360+CX30*(CX23-Hydron_Loan!AH30)*$B$11/360 -> 21583.352 | CY25: =CY24*(CY23-CX23)*$B$11/360 -> 19596.6 | CZ25: =CZ24*(CZ23-CY23)*$B$11/360 -> 18964.451 | DA25: =DA24*(Hydron_Loan!AI30-CZ23)*$B$11/360+DA30*(DA23-Hydron_Loan!AI30)*$B$11/360 -> 19415.986 | DB25: =DB24*(DB23-DA23)*$B$11/360 -> 16797.086 | DC25: =DC24*(DC23-DB23)*$B$11/360 -> 15171.561 | DD25: =DD24*(Hydron_Loan!AJ30-DC23)*$B$11/360+DD30*(DD23-Hydron_Loan!AJ30)*$B$11/360 -> 16616.472 | DE25: =DE24*(DE23-DD23)*$B$11/360 -> 13546.037 | DF25: =DF24*(DF23-DE23)*$B$11/360 -> 13997.571 | DG25: =DG24*(Hydron_Loan!AK30-DF23)*$B$11/360+DG30*(DG23-Hydron_Loan!AK30)*$B$11/360 -> 13455.73 | DH25: =DH24*(DH23-DG23)*$B$11/360 -> 11198.057 | DI25: =DI24*(DI23-DH23)*$B$11/360 -> 11198.057 | DJ25: =DJ24*(Hydron_Loan!AL30-DI23)*$B$11/360+DJ30*(DJ23-Hydron_Loan!AL30)*$B$11/360 -> 10746.522 | DK25: =DK24*(DK23-DJ23)*$B$11/360 -> 8398.5428 | DL25: =DL24*(DL23-DK23)*$B$11/360 -> 8127.622 | DM25: =DM24*(Hydron_Loan!AM30-DL23)*$B$11/360+DM30*(DM23-Hydron_Loan!AM30)*$B$11/360 -> 8217.9289 | DN25: =DN24*(DN23-DM23)*$B$11/360 -> 5599.0285 | DO25: =DO24*(DO23-DN23)*$B$11/360 -> 5237.8009 | DP25: =DP24*(Hydron_Loan!AN30-DO23)*$B$11/360+DP30*(DP23-Hydron_Loan!AN30)*$B$11/360 -> 5418.4147 | DQ25: =DQ24*(DQ23-DP23)*$B$11/360 -> 2709.2073 | DR25: =DR24*(DR23-DQ23)*$B$11/360 -> 2799.5143 | DS25: =DS24*(Hydron_Loan!AO30-DR23)*$B$11/360+DS30*(DS23-Hydron_Loan!AO30)*$B$11/360 -> 2618.9004
A26: Cumulative interest | B26: =B25 -> 0 | C26: =B26+C25 -> 0 | D26: =C26+D25 -> 42167.338 | E26: =D26+E25 -> 94454.836 | F26: =E26+F25 -> 145055.64 | G26: =F26+G25 -> 216618.47 | H26: =G26+H25 -> 292361.02 | I26: =H26+I25 -> 379755.06 | J26: =I26+J25 -> 469339.51 | ... DS26: =DR26+DS25 -> 6311293.6
A27: Principal Payment | B27: 0 | C27: 0 | D27: 0 | E27: 0 | F27: 0 | G27: =Hydron_Loan!D34 -> 0 | H27: 0 | I27: 0 | J27: 0 | K27: 0 | L27: =Hydron_Loan!E34 -> 0 | M27: 0 | N27: 0 | O27: =Hydron_Loan!F34 -> 0 | P27: 0 | Q27: 0 | R27: =Hydron_Loan!G34 -> 0 | S27: 0 | T27: 0 | U27: =Hydron_Loan!H34 -> 0 | V27: 0 | W27: 0 | X27: =Hydron_Loan!I34 -> 0 | Y27: 0 | Z27: 0 | AA27: 0 | AB27: 0 | AC27: 0 | AD27: =Hydron_Loan!J34 -> 541841.47 | AE27: 0 | AF27: 0 | AG27: =Hydron_Loan!K34 -> 541841.47 | AH27: 0 | AI27: 0 | AJ27: =Hydron_Loan!L34 -> 541841.47 | AK27: 0 | AL27: 0 | AM27: =Hydron_Loan!M34 -> 541841.47 | AN27: 0 | AO27: 0 | AP27: =Hydron_Loan!N34 -> 541841.47 | AQ27: 0 | AR27: 0 | AS27: =Hydron_Loan!O34 -> 541841.47 | AT27: 0 | AU27: 0 | AV27: =Hydron_Loan!P34 -> 541841.47 | AW27: 0 | AX27: 0 | AY27: =Hydron_Loan!Q34 -> 541841.47 | AZ27: 0 | BA27: 0 | BB27: =Hydron_Loan!R34 -> 541841.47 | BC27: 0 | BD27: 0 | BE27: =Hydron_Loan!S34 -> 541841.47 | BF27: 0 | BG27: 0 | BH27: =Hydron_Loan!T34 -> 541841.47 | BI27: 0 | BJ27: 0 | BK27: =Hydron_Loan!U34 -> 541841.47 | BL27: 0 | BM27: 0 | BN27: =Hydron_Loan!V34 -> 541841.47 | BO27: 0 | BP27: 0 | BQ27: =Hydron_Loan!W34 -> 541841.47 | BR27: 0 | BS27: 0 | BT27: =Hydron_Loan!X34 -> 541841.47 | BU27: 0 | BV27: 0 | BW27: =Hydron_Loan!Y34 -> 541841.47 | BX27: 0 | BY27: 0 | BZ27: =Hydron_Loan!Z34 -> 541841.47 | CA27: 0 | CB27: 0 | CC27: =Hydron_Loan!AA34 -> 541841.47 | CD27: 0 | CE27: 0 | CF27: =Hydron_Loan!AB34 -> 541841.47 | CG27: 0 | CH27: 0 | CI27: =Hydron_Loan!AC34 -> 541841.47 | CJ27: 0 | CK27: 0 | CL27: =Hydron_Loan!AD34 -> 541841.47 | CM27: 0 | CN27: 0 | CO27: =Hydron_Loan!AE34 -> 541841.47 | CP27: 0 | CQ27: 0 | CR27: =Hydron_Loan!AF34 -> 541841.47 | CS27: 0 | CT27: 0 | CU27: =Hydron_Loan!AG34 -> 541841.47 | CV27: 0 | CW27: 0 | CX27: =Hydron_Loan!AH34 -> 541841.47 | CY27: 0 | CZ27: 0 | DA27: =Hydron_Loan!AI34 -> 541841.47 | DB27: 0 | DC27: 0 | DD27: =Hydron_Loan!AJ34 -> 541841.47 | DE27: 0 | DF27: 0 | DG27: =Hydron_Loan!AK34 -> 541841.47 | DH27: 0 | DI27: 0 | DJ27: =Hydron_Loan!AL34 -> 541841.47 | DK27: 0 | DL27: 0 | DM27: =Hydron_Loan!AM34 -> 541841.47 | DN27: 0 | DO27: 0 | DP27: =Hydron_Loan!AN34 -> 541841.47 | DQ27: 0 | DR27: 0 | DS27: =Hydron_Loan!AO34 -> 541841.47
A28: Cumulative repayment | B28: =B27 -> 0 | C28: =B28+C27 -> 0 | D28: =C28+D27 -> 0 | E28: =D28+E27 -> 0 | F28: =E28+F27 -> 0 | G28: =F28+G27 -> 0 | H28: =G28+H27 -> 0 | I28: =H28+I27 -> 0 | J28: =I28+J27 -> 0 | ... DS28: =DR28+DS27 -> 17338927
A29: Total Debt Service | B29: =B27+B25 -> 0 | C29: =C27+C25 -> 0 | D29: =D27+D25 -> 42167.338 | E29: =E27+E25 -> 52287.499 | F29: =F27+F25 -> 50600.805 | G29: =G27+G25 -> 71562.832 | H29: =H27+H25 -> 75742.545 | I29: =I27+I25 -> 87394.038 | ... DS29: =DS27+DS25 -> 544460.37
A30: Closing Balance | B30: =B24-B27 -> 0 | C30: =C24-C27 -> 0 | D30: =D24-D27 -> 10120161 | E30: =E24-E27 -> 10120161 | F30: =F24-F27 -> 10120161 | G30: =G24-G27 -> 15148509 | H30: =H24-H27 -> 15148509 | I30: =I24-I27 -> 17338927 | ... DS30: =DS24-DS27 -> 0
DS33: =DS26-Hydron_Loan!AO33 -> 0

Sheet Repayment Schedule
A1: Project name: | C1: =Hydron_Loan!C1 -> Hydron Bangladesh Private Ltd.
A5: Financial Close | C5: =Hydron_Loan!C5 -> 41639
A7: Loan Amount | C7: =Hydron_Loan!C7 -> 19610526
A9: Drawdown Date | C9: =Accrual_Hydron!B9 -> 41827
A11: Interest Rate | C11: =Hydron_Loan!C11 -> 0.06
A12: Tenor | C12: =Hydron_Loan!C12 -> 10 years
A13: Principal | C13: =Hydron_Loan!C15 -> Level Principal
A14: Interest calculation | C14: =Hydron_Loan!C16 -> 360 | D14: days basis
A15: Number of installments | C15: =Hydron_Loan!C17 -> 32
A17: Drawdown
C18: =Hydron_Loan!C20 -> 41827 | D18: =Hydron_Loan!D20 -> 41921 | E18: =Hydron_Loan!E20 -> 41980
C19: =Hydron_Loan!C21 -> 10120161 | D19: =Hydron_Loan!D21 -> 5028348 | E19: =Hydron_Loan!E21 -> 2190418
C20: =C19 -> 10120161 | D20: =C20+D19 -> 15148509 | E20: =D20+E19 -> 17338927
A23: {=TRANSPOSE(Hydron_Loan!A30:AO37)} -> Repayment Date | B23: Opening Balance | C23: Interest Payment | D23: Cumulative interest | E23: Principal Payment | F23: Cumulative repayment | G23: Total Debt Service | H23: Closing Balance
A24: 41912 | B24: 10120161 | C24: 0 | D24: 0 | E24: 0 | F24: 0 | G24: 0 | H24: 10120161
A25: 42003 | B25: 17338927 | C25: 0 | D25: 0 | E25: 0 | F25: 0 | G25: 0 | H25: 17338927
A26: 42093 | B26: 17338927 | C26: 634059.32 | D26: 634059.32 | E26: 0 | F26: 0 | G26: 634059.32 | H26: 17338927
A27: 42185 | B27: 17338927 | C27: 265863.55 | D27: 899922.87 | E27: 0 | F27: 0 | G27: 265863.55 | H27: 17338927
A28: 42277 | B28: 17338927 | C28: 265863.55 | D28: 1165786.4 | E28: 0 | F28: 0 | G28: 265863.55 | H28: 17338927
A29: 42368 | B29: 17338927 | C29: 262973.73 | D29: 1428760.1 | E29: 0 | F29: 0 | G29: 262973.73 | H29: 17338927
A30: 42459 | B30: 17338927 | C30: 262973.73 | D30: 1691733.9 | E30: 0 | F30: 0 | G30: 262973.73 | H30: 17338927
A31: 42551 | B31: 17338927 | C31: 265863.55 | D31: 1957597.4 | E31: 0 | F31: 0 | G31: 265863.55 | H31: 17338927
A32: 42645 | B32: 17338927 | C32: 271643.19 | D32: 2229240.6 | E32: 541841.47 | F32: 541841.47 | G32: 813484.66 | H32: 16797086
A33: 42736 | B33: 16797086 | C33: 254755.8 | D33: 2483996.4 | E33: 541841.47 | F33: 1083682.9 | G33: 796597.27 | H33: 16255244
A34: 42824 | B34: 16255244 | C34: 238410.25 | D34: 2722406.6 | E34: 541841.47 | F34: 1625524.4 | G34: 780251.71 | H34: 15713403
A35: 42918 | B35: 15713403 | C35: 246176.64 | D35: 2968583.3 | E35: 541841.47 | F35: 2167365.9 | G35: 788018.11 | H35: 15171561
... A63: 45473 | B63: 541841.47 | C63: 8308.2359 | D63: 6311293.6 | E63: 541841.47 | F63: 17338927 | G63: 550149.7 | H63: 0
