Workbook

Sheet Disbursement
A1: Borrower: | B1: Imperial Hospital Limited (IHL)
A2: Currency: | B2: BDT
A3: Type | B3: IDCOL Loan
A4: Source : | B4: IDCOL Current Account
A7: Disbursement Number | B7: Disbursement Date | C7: Disbursement | D7: Cumulative Disbursement | E7: Source
A8: 1 | B8: 43118 | C8: 150000000 | D8: =C8+C9 -> 150000000 | E8: IDCOL Current Account

Sheet Summary
B1: =Accrual_IHL!B23 -> 43132 | C1: =Accrual_IHL!C23 -> 43160 | D1: =Accrual_IHL!D23 -> 43191 | E1: =Accrual_IHL!E23 -> 43221 | F1: =Accrual_IHL!F23 -> 43252 | G1: =Accrual_IHL!G23 -> 43282 | H1: =Accrual_IHL!H23 -> 43313 | I1: =Accrual_IHL!I23 -> 43344 | ... CG1: =Accrual_IHL!CG23 -> 45658
A2: Principal
A3: Opening balance | B3: =Accrual_IHL!B24 -> 150000000 | C3: =Accrual_IHL!C24 -> 150000000 | D3: =Accrual_IHL!D24+IHL_Loan!B29 -> 1.5295833e+08 | E3: =Accrual_IHL!E24 -> 1.5295833e+08 | F3: =Accrual_IHL!F24 -> 1.5295833e+08 | G3: =Accrual_IHL!G24+IHL_Loan!C29 -> 1.5686727e+08 | H3: =Accrual_IHL!H24 -> 1.5686727e+08 | I3: =Accrual_IHL!I24 -> 1.5686727e+08 | J3: =Accrual_IHL!J24+IHL_Loan!D29 -> 1.608761e+08 | K3: =Accrual_IHL!K24 -> 1.608761e+08 | L3: =Accrual_IHL!L24 -> 1.608761e+08 | M3: =Accrual_IHL!M24+IHL_Loan!E29 -> 1.6494269e+08 | N3: =Accrual_IHL!N24 -> 1.6494269e+08 | O3: =Accrual_IHL!O24 -> 1.6494269e+08 | P3: =Accrual_IHL!P24+IHL_Loan!F29 -> 1.6906626e+08 | Q3: =Accrual_IHL!Q24 -> 1.6906626e+08 | R3: =Accrual_IHL!R24 -> 1.6906626e+08 | S3: =Accrual_IHL!S24+IHL_Loan!G29 -> 1.7338684e+08 | T3: =Accrual_IHL!T24 -> 1.7338684e+08 | U3: =Accrual_IHL!U24 -> 1.7338684e+08 | V3: =Accrual_IHL!V24+IHL_Loan!H29 -> 1.7781784e+08 | W3: =Accrual_IHL!W24 -> 1.7781784e+08 | X3: =Accrual_IHL!X24 -> 1.7781784e+08 | Y3: =Accrual_IHL!Y24+IHL_Loan!I29 -> 1.8231268e+08 | Z3: =Accrual_IHL!Z24+IHL_Loan!J29 -> 1.8271781e+08 | AA3: =Z3 -> 1.8271781e+08 | AB3: =AA3 -> 1.8271781e+08 | AC3: =AB3 -> 1.8271781e+08 | AD3: =AC3 -> 1.8271781e+08 | AE3: =AD3 -> 1.8271781e+08 | AF3: =AE3 -> 1.8271781e+08 | AG3: =AF3 -> 1.8271781e+08 | AH3: =AG3 -> 1.8271781e+08 | ... CG3: =CF3 -> 1.8271781e+08
A4: Repayment due | B4: =Accrual_IHL!B28 -> 0 | C4: =Accrual_IHL!C28 -> 0 | D4: =Accrual_IHL!D28 -> 0 | E4: =Accrual_IHL!E28 -> 0 | F4: =Accrual_IHL!F28 -> 0 | G4: =Accrual_IHL!G28 -> 0 | H4: =Accrual_IHL!H28 -> 0 | I4: =Accrual_IHL!I28 -> 0 | ... CG4: =Accrual_IHL!CG28 -> 1.8271781e+08
A5: Loan Repayment | B5: =B22 -> 0 | C5: =C22 -> 0 | D5: =D22 -> 0 | E5: =E22 -> 0 | F5: =F22 -> 0 | G5: =G22 -> 0 | H5: =H22 -> 0 | I5: =I22 -> 0 | ... CG5: =CG22 -> 1.8271781e+08
A6: Repayment overdue | B6: =IF((B4-B5)>0,(B4-B5),0) -> 0 | C6: =IF((C4-C5)>0,(C4-C5),0) -> 0 | D6: =IF((D4-D5)>0,(D4-D5),0) -> 0 | E6: =IF((E4-E5)>0,(E4-E5),0) -> 0 | F6: =IF((F4-F5)>0,(F4-F5),0) -> 0 | G6: =IF((G4-G5)>0,(G4-G5),0) -> 0 | H6: =IF((H4-H5)>0,(H4-H5),0) -> 0 | I6: =IF((I4-I5)>0,(I4-I5),0) -> 0 | ... CG6: =IF((CG4-CG5)>0,(CG4-CG5),0) -> 0
A7: Loan outstanding | B7: =B3-B5 -> 150000000 | C7: =C3-C5 -> 150000000 | D7: =D3-D5 -> 1.5295833e+08 | E7: =E3-E5 -> 1.5295833e+08 | F7: =F3-F5 -> 1.5295833e+08 | G7: =G3-G5 -> 1.5686727e+08 | H7: =H3-H5 -> 1.5686727e+08 | I7: =I3-I5 -> 1.5686727e+08 | ... CG7: =CG3-CG5 -> 0
A8: Interest
A9: Interest accrued | B9: =Accrual_IHL!B26 -> 583333.33 | C9: =Accrual_IHL!C26 -> 1750000 | D9: =Accrual_IHL!D26 -> 3043310.2 | E9: =Accrual_IHL!E26 -> 4317963 | F9: =Accrual_IHL!F26 -> 5635104.2 | G9: =Accrual_IHL!G26 -> 6910842.8 | H9: =Accrual_IHL!H26 -> 8261644.2 | I9: =Accrual_IHL!I26 -> 9612445.7 | ... CG9: =Accrual_IHL!CG26 -> 84779886
A10: Interest due | B10: 0 | C10: =IHL_Loan!$B$30 -> 0 | D10: =C10 -> 0 | E10: =D10 -> 0 | F10: =IHL_Loan!$C$30 -> 0 | G10: =F10 -> 0 | H10: =G10 -> 0 | I10: =IHL_Loan!$D$30 -> 0 | J10: =I10 -> 0 | K10: =J10 -> 0 | L10: =IHL_Loan!$E$30 -> 0 | M10: =L10 -> 0 | N10: =M10 -> 0 | O10: =IHL_Loan!$F$30 -> 0 | P10: =O10 -> 0 | Q10: =P10 -> 0 | R10: =IHL_Loan!$G$30 -> 0 | S10: =R10 -> 0 | T10: =S10 -> 0 | U10: =IHL_Loan!$H$30 -> 0 | V10: =U10 -> 0 | W10: =V10 -> 0 | X10: =IHL_Loan!$I$30 -> 0 | Y10: =X10 -> 0 | Z10: =Y10 -> 0 | AA10: =Z10 -> 0 | AB10: =IHL_Loan!$K$30 -> 4212660.7 | AC10: =AB10 -> 4212660.7 | AD10: =AC10 -> 4212660.7 | AE10: =IHL_Loan!$L$30 -> 8690240.7 | AF10: =AE10 -> 8690240.7 | AG10: =AF10 -> 8690240.7 | AH10: =IHL_Loan!$M$30 -> 12982716 | AI10: =AH10 -> 12982716 | AJ10: =AI10 -> 12982716 | AK10: =IHL_Loan!$N$30 -> 17040761 | AL10: =AK10 -> 17040761 | AM10: =AL10 -> 17040761 | AN10: =IHL_Loan!$O$30 -> 20862643 | AO10: =AN10 -> 20862643 | AP10: =AO10 -> 20862643 | AQ10: =IHL_Loan!$P$30 -> 24567594 | AR10: =AQ10 -> 24567594 | AS10: =AR10 -> 24567594 | AT10: =IHL_Loan!$Q$30 -> 28067695 | AU10: =AT10 -> 28067695 | AV10: =AU10 -> 28067695 | AW10: =IHL_Loan!$R$30 -> 31321950 | AX10: =AW10 -> 31321950 | AY10: =AX10 -> 31321950 | AZ10: =IHL_Loan!$S$30 -> 34328779 | BA10: =AZ10 -> 34328779 | BB10: =BA10 -> 34328779 | BC10: =IHL_Loan!$T$30 -> 37179736 | BD10: =BC10 -> 37179736 | BE10: =BD10 -> 37179736 | BF10: =IHL_Loan!$U$30 -> 39775494 | BG10: =BF10 -> 39775494 | BH10: =BG10 -> 39775494 | BI10: =IHL_Loan!$V$30 -> 42140590 | BJ10: =BI10 -> 42140590 | BK10: =BJ10 -> 42140590 | BL10: =IHL_Loan!$W$30 -> 44269195 | BM10: =BL10 -> 44269195 | BN10: =BM10 -> 44269195 | BO10: =IHL_Loan!$X$30 -> 46155329 | BP10: =BO10 -> 46155329 | BQ10: =BP10 -> 46155329 | BR10: =IHL_Loan!$Y$30 -> 47792864 | BS10: =BR10 -> 47792864 | BT10: =BS10 -> 47792864 | BU10: =IHL_Loan!$Z$30 -> 49175517 | BV10: =BU10 -> 49175517 | BW10: =BV10 -> 49175517 | BX10: =IHL_Loan!$AA$30 -> 50296843 | BY10: =BX10 -> 50296843 | BZ10: =BY10 -> 50296843 | CA10: =IHL_Loan!$AB$30 -> 51178371 | CB10: =CA10 -> 51178371 | CC10: =CB10 -> 51178371 | CD10: =IHL_Loan!$AC$30 -> 51764140 | CE10: =CD10 -> 51764140 | CF10: =CE10 -> 51764140 | CG10: =IHL_Loan!$AD$30 -> 52062072
A11: interest received | B11: =B26 -> 0 | C11: =C26 -> 0 | D11: =D26 -> 0 | E11: =E26 -> 0 | F11: =F26 -> 0 | G11: =G26 -> 0 | H11: =H26 -> 0 | I11: =I26 -> 0 | ... CG11: =CG26 -> 52062072
A12: Interest overdue | B12: =IF((B10-B11)>0,(B10-B11),0) -> 0 | C12: =IF((C10-C11)>0,(C10-C11),0) -> 0 | D12: =IF((D10-D11)>0,(D10-D11),0) -> 0 | E12: =IF((E10-E11)>0,(E10-E11),0) -> 0 | F12: =IF((F10-F11)>0,(F10-F11),0) -> 0 | G12: =IF((G10-G11)>0,(G10-G11),0) -> 0 | H12: =IF((H10-H11)>0,(H10-H11),0) -> 0 | I12: =IF((I10-I11)>0,(I10-I11),0) -> 0 | ... CG12: =IF((CG10-CG11)>0,(CG10-CG11),0) -> 0
A13: Interest receivable | B13: =B9-B11 -> 583333.33 | C13: =C9-C11 -> 1750000 | D13: =D9-D11 -> 3043310.2 | E13: =E9-E11 -> 4317963 | F13: =F9-F11 -> 5635104.2 | G13: =G9-G11 -> 6910842.8 | H13: =H9-H11 -> 8261644.2 | I13: =I9-I11 -> 9612445.7 | ... CG13: =CG9-CG11 -> 32717814
A14: LD and others | B14: =B28 -> 0 | C14: =C28 -> 0 | D14: =D28 -> 0 | E14: =E28 -> 0 | F14: =F28 -> 0 | G14: =G28 -> 0 | H14: =H28 -> 0 | I14: =I28 -> 0 | ... CG14: =CG28 -> 0
B19: =B1 -> 43132 | C19: =C1 -> 43160 | D19: =D1 -> 43191 | E19: =E1 -> 43221 | F19: =F1 -> 43252 | G19: =G1 -> 43282 | H19: =H1 -> 43313 | I19: =I1 -> 43344 | ... CG19: =CG1 -> 45658
A20: Repayment receipts:
A21: Repayment received | D21: =D4-C5 -> 0 | G21: =G4-F5 -> 0 | J21: =J4-I5 -> 0 | M21: =M4-L5 -> 0 | P21: =P4-O5 -> 0 | S21: =S4-R5 -> 0 | V21: =V4-U5 -> 0 | Y21: =Y4-X5 -> 0 | AB21: 0 | AE21: 0 | AH21: =AH4-AG5 -> 22179754 | AK21: =AK4-AJ5 -> 7662777.7 | AN21: =AN4-AM5 -> 7898941.1 | AQ21: =AQ4-AP5 -> 8015872.2 | AT21: =AT4-AS5 -> 8220722.3 | AW21: =AW4-AV5 -> 8466568.4 | AZ21: =AZ4-AY5 -> 8713993.7 | BC21: =BC4-BB5 -> 8869866.2 | BF21: =BF4-BE5 -> 9125065.4 | BI21: =BI4-BH5 -> 9355726.7 | BL21: =BL4-BK5 -> 9592218.7 | BO21: =BO4-BN5 -> 9834688.7 | BR21: =BR4-BQ5 -> 10083288 | BU21: =BU4-BT5 -> 10338171 | BX21: =BX4-BW5 -> 10599497 | CA21: =CA4-BZ5 -> 10839295 | CD21: =CD4-CC5 -> 11135055 | CG21: =CG4-CF5 -> 11786314
A22: Repayment received (cumulative) | B22: =B21 -> 0 | C22: =B22+C21 -> 0 | D22: =C22+D21 -> 0 | E22: =D22+E21 -> 0 | F22: =E22+F21 -> 0 | G22: =F22+G21 -> 0 | H22: =G22+H21 -> 0 | I22: =H22+I21 -> 0 | J22: =I22+J21 -> 0 | ... CG22: =CF22+CG21 -> 1.8271781e+08
A24: Interest receipts:
A25: Interest received | D25: =D10-C11 -> 0 | G25: =G10-F11 -> 0 | J25: =J10-I11 -> 0 | M25: =M10-L11 -> 0 | P25: =P10-O11 -> 0 | S25: =S10-R11 -> 0 | V25: =V10-U11 -> 0 | Y25: =Y10-X11 -> 0 | AB25: 0 | AE25: 0 | AH25: =AH10-AG11 -> 12982716 | AI25: =AI10-AH11 -> 0 | AJ25: =AJ10-AI11 -> 0 | AK25: =AK10-AJ11 -> 4058045.4 | AL25: =AL10-AK11 -> 0 | AM25: =AM10-AL11 -> 0 | AN25: =AN10-AM11 -> 3821882.1 | AO25: =AO10-AN11 -> 0 | ... CG25: =CG10-CF11 -> 297931.83
A26: Interest received (cumulative) | B26: =B25 -> 0 | C26: =B26+C25 -> 0 | D26: =C26+D25 -> 0 | E26: =D26+E25 -> 0 | F26: =E26+F25 -> 0 | G26: =F26+G25 -> 0 | H26: =G26+H25 -> 0 | I26: =H26+I25 -> 0 | J26: =I26+J25 -> 0 | ... CG26: =CF26+CG25 -> 52062072
A27: LD/others | B27: 0 | C27: 0 | D27: 0 | E27: 0 | F27: 0 | G27: 0 | H27: 0 | I27: 0 | J27: 0 | K27: 0 | L27: 0 | M27: 0 | N27: 0 | O27: 0 | P27: 0 | Q27: 0 | R27: 0 | S27: 0 | T27: 0 | U27: 0 | V27: 0 | W27: 0 | X27: 0 | Y27: 0 | Z27: 0 | AA27: 0 | AB27: 0 | AC27: 0 | AD27: 0 | AE27: 0 | AF27: 0 | AG27: 0 | AH27: 0 | AI27: 0 | AJ27: 0 | AK27: 0 | AL27: 0 | AM27: 0 | AN27: 0 | AO27: 0 | AP27: 0 | AQ27: 0 | AR27: 0 | AS27: 0 | AT27: 0 | AU27: 0 | AV27: 0 | AW27: 0 | AX27: 0 | AY27: 0 | AZ27: 0 | BA27: 0 | BB27: 0 | BC27: 0 | BD27: 0 | BE27: 0 | BF27: 0 | BG27: 0 | BH27: 0 | BI27: 0 | BJ27: 0 | BK27: 0 | BL27: 0 | BM27: 0 | BN27: 0 | BO27: 0 | BP27: 0 | BQ27: 0 | BR27: 0 | BS27: 0 | BT27: 0 | BU27: 0 | BV27: 0 | BW27: 0 | BX27: 0 | BY27: 0 | BZ27: 0 | CA27: 0 | CB27: 0 | CC27: 0 | CD27: 0 | CE27: 0 | CF27: 0 | CG27: 0
A28: LD/others (cumulative) | B28: =B27 -> 0 | C28: =B28+C27 -> 0 | D28: =C28+D27 -> 0 | E28: =D28+E27 -> 0 | F28: =E28+F27 -> 0 | G28: =F28+G27 -> 0 | H28: =G28+H27 -> 0 | I28: =H28+I27 -> 0 | J28: =I28+J27 -> 0 | ... CG28: =CF28+CG27 -> 0
A30: Actual Payment date
A31: Actual Payment amount:
A32: Interest
A33: Principal
A34: LPC
A35: Total | B35: =SUM(B32:B34) -> 0 | C35: =SUM(C32:C34) -> 0 | D35: =SUM(D32:D34) -> 0 | E35: =SUM(E32:E34) -> 0 | F35: =SUM(F32:F34) -> 0 | G35: =SUM(G32:G34) -> 0 | H35: =SUM(H32:H34) -> 0 | I35: =SUM(I32:I34) -> 0 | ... CG35: =SUM(CG32:CG34) -> 0

Sheet IHL_Loan
A1: Project name: | C1: =Disbursement!B1 -> Imperial Hospital Limited (IHL)
A3: Agreement signing date | C3: 42831
A5: Loan Amount | C5: 1.8276043e+08 | G5: *If payment date is not a business day, then payment date shall be immediately the preceeding business day.
A7: Payment frequency | C7: Quarterly
A8: Interest Rate | C8: 0.1
A9: Maturity date | C9: 84 | D9: months | E9: =EDATE(C16,C9) -> 45675
A10: Moratorium period (Principal) | C10: 24 | D10: months | E10: =EDATE(C16,C10) -> 43848
A11: Principal | C11: Annuity
A12: Interest calculation | C12: 360 | D12: days basis
A13: Number of installments | C13: 20
A15: Drawdown
C16: =Disbursement!B8 -> 43118
C17: =Disbursement!C8 -> 150000000
C18: =C17 -> 150000000
A21: Period | B21: =B27 -> 43189 | C21: =C27 -> 43281 | D21: =D27 -> 43373 | E21: =E27 -> 43464 | F21: =F27 -> 43554 | G21: =G27 -> 43646 | H21: =H27 -> 43738 | I21: =I27 -> 43829 | ... AD21: =AD27 -> 45656
A22: Expected Interest Rate | B22: 0.1 | C22: 0.1 | D22: 0.1 | E22: 0.1 | F22: 0.1 | G22: 0.1 | H22: 0.1 | I22: 0.1 | J22: 0.1 | K22: 0.1 | L22: 0.1 | M22: 0.1 | N22: 0.1 | O22: 0.1 | P22: 0.1 | Q22: 0.1 | R22: 0.1 | S22: 0.1 | T22: 0.1 | U22: 0.1 | V22: 0.1 | W22: 0.1 | X22: 0.1 | Y22: 0.1 | Z22: 0.1 | AA22: 0.1 | AB22: 0.1 | AC22: 0.1 | AD22: 0.1
A25: Repayment | B25: Interest capitalized
A26: Repayment Period | K26: 1 | L26: =K26+1 -> 2 | M26: =L26+1 -> 3 | N26: =M26+1 -> 4 | O26: =N26+1 -> 5 | P26: =O26+1 -> 6 | Q26: =P26+1 -> 7 | R26: =Q26+1 -> 8 | S26: =R26+1 -> 9 | ... AD26: =AC26+1 -> 20
A27: Repayment Date | B27: 43189 | C27: 43281 | D27: 43373 | E27: 43464 | F27: 43554 | G27: 43646 | H27: 43738 | I27: 43829 | J27: 43837 | K27: 43920 | L27: 44012 | M27: 44104 | N27: 44195 | O27: 44285 | P27: 44377 | Q27: 44469 | R27: 44560 | S27: 44650 | T27: 44742 | U27: 44833 | V27: 44924 | W27: 45015 | X27: 45106 | Y27: 45197 | Z27: 45288 | AA27: 45379 | AB27: 45473 | AC27: 45565 | AD27: 45656
A28: Opening Balance | B28: =C17 -> 150000000 | C28: =B34 -> 1.5295833e+08 | D28: =C34 -> 1.5686727e+08 | E28: =D34 -> 1.608761e+08 | F28: =E34 -> 1.6494269e+08 | G28: =F34 -> 1.6906626e+08 | H28: =G34 -> 1.7338684e+08 | I28: =H34 -> 1.7781784e+08 | J28: =I34 -> 1.8231268e+08 | ... AD28: =AC34 -> 11786314
A29: Interest Payment | B29: =C18*(B27-C16)*$B$22/360 -> 2958333.3 | C29: =B34*(C27-B27)*$B$22/360 -> 3908935.2 | D29: =C34*(D27-C27)*$B$22/360 -> 4008830.2 | E29: =D34*(E27-D27)*$B$22/360 -> 4066590.3 | F29: =E34*(F27-E27)*$B$22/360 -> 4123567.2 | G29: =F34*(G27-F27)*$B$22/360 -> 4320582.1 | H29: =G34*(H27-G27)*$B$22/360 -> 4430997 | I29: =H34*(I27-H27)*$B$22/360 -> 4494839.7 | J29: =I34*(J27-I27)*$B$22/360 -> 405139.28 | K29: =K28*(K27-J27)*K22/360 -> 4212660.7 | L29: =L28*(L27-K27)*L22/360 -> 4477580 | M29: =M28*(M27-L27)*M22/360 -> 4292474.9 | N29: =N28*(N27-M27)*N22/360 -> 4058045.4 | O29: =O28*(O27-N27)*O22/360 -> 3821882.1 | P29: =P28*(P27-O27)*P22/360 -> 3704951 | Q29: =Q28*(Q27-P27)*Q22/360 -> 3500100.9 | R29: =R28*(R27-Q27)*R22/360 -> 3254254.7 | ... AD29: =AD28*(AD27-AC27)*AD22/360 -> 297931.83
A30: Cumulative interest | B30: 0 | C30: 0 | D30: 0 | E30: 0 | F30: 0 | G30: 0 | H30: 0 | I30: 0 | J30: 0 | K30: =K29+J30 -> 4212660.7 | L30: =L29+K30 -> 8690240.7 | M30: =M29+L30 -> 12982716 | N30: =N29+M30 -> 17040761 | O30: =O29+N30 -> 20862643 | P30: =P29+O30 -> 24567594 | Q30: =Q29+P30 -> 28067695 | R30: =R29+Q30 -> 31321950 | ... AD30: =AD29+AC30 -> 52062072
A31: Principal Payment | B31: 0 | C31: 0 | D31: 0 | E31: 0 | F31: 0 | G31: 0 | H31: 0 | I31: 0 | J31: 0 | K31: =K33-K29 -> 7508162.4 | L31: =L33-L29 -> 7243243.2 | M31: =M33-M29 -> 7428348.3 | N31: =N33-N29 -> 7662777.7 | O31: =O33-O29 -> 7898941.1 | P31: =P33-P29 -> 8015872.2 | Q31: =Q33-Q29 -> 8220722.3 | R31: =R33-R29 -> 8466568.4 | ... AC31: =AC33-AC29 -> 11135055 | AD31: =AC34 -> 11786314
A32: Cumulative repayment | B32: 0 | C32: =C31+B32 -> 0 | D32: =D31+C32 -> 0 | E32: =E31+D32 -> 0 | F32: =F31+E32 -> 0 | G32: =G31+F32 -> 0 | H32: =H31+G32 -> 0 | I32: =I31+H32 -> 0 | J32: =J31+I32 -> 0 | K32: =K31+I32 -> 7508162.4 | L32: =L31+K32 -> 14751406 | M32: =M31+L32 -> 22179754 | N32: =N31+M32 -> 29842532 | O32: =O31+N32 -> 37741473 | P32: =P31+O32 -> 45757345 | Q32: =Q31+P32 -> 53978067 | R32: =R31+Q32 -> 62444636 | S32: =S31+R32 -> 71158629 | ... AD32: =AD31+AC32 -> 1.8271781e+08
A33: Total Debt Service | B33: 0 | C33: 0 | D33: 0 | E33: 0 | F33: 0 | G33: 0 | H33: 0 | I33: 0 | J33: 0 | K33: =-PMT(K22/4,20,$J$34) -> 11720823 | L33: =-PMT(L22/4,20,$J$34) -> 11720823 | M33: =-PMT(M22/4,20,$J$34) -> 11720823 | N33: =-PMT(N22/4,20,$J$34) -> 11720823 | O33: =-PMT(O22/4,20,$J$34) -> 11720823 | P33: =-PMT(P22/4,20,$J$34) -> 11720823 | Q33: =-PMT(Q22/4,20,$J$34) -> 11720823 | R33: =-PMT(R22/4,20,$J$34) -> 11720823 | ... AC33: =-PMT(AC22/4,20,$J$34) -> 11720823 | AD33: =AD29+AD31 -> 12084246
A34: Closing Balance | B34: =B28+B29 -> 1.5295833e+08 | C34: =C28+C29 -> 1.5686727e+08 | D34: =D28+D29 -> 1.608761e+08 | E34: =E28+E29 -> 1.6494269e+08 | F34: =F28+F29 -> 1.6906626e+08 | G34: =G28+G29 -> 1.7338684e+08 | H34: =H28+H29 -> 1.7781784e+08 | I34: =I28+I29 -> 1.8231268e+08 | J34: =J28+J29 -> 1.8271781e+08 | K34: =K28-K31 -> 1.7520965e+08 | L34: =L28-L31 -> 1.6796641e+08 | M34: =M28-M31 -> 1.6053806e+08 | N34: =N28-N31 -> 1.5287528e+08 | O34: =O28-O31 -> 1.4497634e+08 | P34: =P28-P31 -> 1.3696047e+08 | Q34: =Q28-Q31 -> 1.2873975e+08 | R34: =R28-R31 -> 1.2027318e+08 | ... AD34: =AD28-AD31 -> 0
A37: Interest Capitalized | B37: =SUM(B29:J29) -> 32717814
A42: Average Installment Size | B42: =B27 -> 43189 | C42: =C27 -> 43281 | D42: =D27 -> 43373 | E42: =E27 -> 43464 | F42: =F27 -> 43554 | G42: =G27 -> 43646 | H42: =H27 -> 43738 | I42: =I27 -> 43829 | K42: =K27 -> 43920 | L42: =L27 -> 44012 | M42: =M27 -> 44104 | N42: =N27 -> 44195 | O42: =O27 -> 44285 | P42: =P27 -> 44377 | Q42: =Q27 -> 44469 | R42: =R27 -> 44560 | ... AD42: =AD27 -> 45656
B43: =AVERAGE($K$33) -> 11720823 | C43: =AVERAGE($K$33) -> 11720823 | D43: =AVERAGE($K$33) -> 11720823 | E43: =AVERAGE($K$33) -> 11720823 | F43: =AVERAGE($K$33) -> 11720823 | G43: =AVERAGE($K$33) -> 11720823 | H43: =AVERAGE($K$33) -> 11720823 | I43: =AVERAGE($K$33) -> 11720823 | K43: =AVERAGE($K$33) -> 11720823 | L43: =AVERAGE($K$33:L33) -> 11720823 | M43: =AVERAGE($K$33:M33) -> 11720823 | N43: =AVERAGE($K$33:N33) -> 11720823 | O43: =AVERAGE($K$33:O33) -> 11720823 | P43: =AVERAGE($K$33:P33) -> 11720823 | Q43: =AVERAGE($K$33:Q33) -> 11720823 | R43: =AVERAGE($K$33:R33) -> 11720823 | S43: =AVERAGE($K$33:S33) -> 11720823 | ... AD43: =AVERAGE($K$33:AD33) -> 11738994
A49: Particulars | C49: 43131 | D49: =EOMONTH(C49,1) -> 43159 | E49: =EOMONTH(D49,1) -> 43190 | F49: =EOMONTH(E49,1) -> 43220 | G49: =EOMONTH(F49,1) -> 43251 | H49: =EOMONTH(G49,1) -> 43281 | I49: =EOMONTH(H49,1) -> 43312 | J49: =EOMONTH(I49,1) -> 43343 | K49: =EOMONTH(J49,1) -> 43373 | ... CH49: =EOMONTH(CG49,1) -> 45657
A50: Total interest accrued | C50: =SUM(Accrual_IHL!$B$25) -> 583333.33 | D50: =SUM(Accrual_IHL!$B$25:C25) -> 1750000 | E50: =SUM(Accrual_IHL!$B$25:D25) -> 3043310.2 | F50: =SUM(Accrual_IHL!$B$25:E25) -> 4317963 | G50: =SUM(Accrual_IHL!$B$25:F25) -> 5635104.2 | H50: =SUM(Accrual_IHL!$B$25:G25) -> 6910842.8 | I50: =SUM(Accrual_IHL!$B$25:H25) -> 8261644.2 | J50: =SUM(Accrual_IHL!$B$25:I25) -> 9612445.7 | K50: =SUM(Accrual_IHL!$B$25:J25) -> 10920787 | ... CH50: =SUM(Accrual_IHL!$B$25:CG25) -> 84779886
A51: Total interest capitalized | C51: 0 | D51: 0 | E51: =SUM($B$29) -> 2958333.3 | F51: =SUM($B$29) -> 2958333.3 | G51: =SUM($B$29) -> 2958333.3 | H51: =SUM($B$29:$C$29) -> 6867268.5 | I51: =SUM($B$29:$C$29) -> 6867268.5 | J51: =SUM($B$29:$C$29) -> 6867268.5 | K51: =SUM($B$29:$D$29) -> 10876099 | L51: =SUM($B$29:$D$29) -> 10876099 | M51: =SUM($B$29:$D$29) -> 10876099 | N51: =SUM($B$29:$E$29) -> 14942689 | O51: =SUM($B$29:$E$29) -> 14942689 | P51: =SUM($B$29:$E$29) -> 14942689 | Q51: =SUM($B$29:$F$29) -> 19066256 | R51: =SUM($B$29:$F$29) -> 19066256 | S51: =SUM($B$29:$F$29) -> 19066256 | T51: =SUM($B$29:$G$29) -> 23386838 | U51: =SUM($B$29:$G$29) -> 23386838 | V51: =SUM($B$29:$G$29) -> 23386838 | W51: =SUM($B$29:$H$29) -> 27817835 | X51: =SUM($B$29:$H$29) -> 27817835 | Y51: =SUM($B$29:$H$29) -> 27817835 | Z51: =SUM($B$29:$I$29) -> 32312675 | AA51: =SUM($B$29:$J$29) -> 32717814 | AB51: =SUM($B$29:$J$29) -> 32717814 | AC51: =SUM($B$29:$J$29) -> 32717814 | AD51: =SUM($B$29:$J$29) -> 32717814 | AE51: =SUM($B$29:$J$29) -> 32717814 | AF51: =SUM($B$29:$J$29) -> 32717814 | AG51: =SUM($B$29:$J$29) -> 32717814 | AH51: =SUM($B$29:$J$29) -> 32717814 | ... CH51: =SUM($B$29:$J$29) -> 32717814
A52: Net interest accrued | C52: =C50-C51 -> 583333.33 | D52: =D50-D51 -> 1750000 | E52: =E50-E51 -> 84976.852 | F52: =F50-F51 -> 1359629.6 | G52: =G50-G51 -> 2676770.8 | H52: =H50-H51 -> 43574.241 | I52: =I50-I51 -> 1394375.7 | J52: =J50-J51 -> 2745177.2 | ... CH52: =CH50-CH51 -> 52062072
A53: Total interest received | C53: =Summary!B26 -> 0 | D53: =Summary!C26 -> 0 | E53: =Summary!D26 -> 0 | F53: =Summary!E26 -> 0 | G53: =Summary!F26 -> 0 | H53: =Summary!G26 -> 0 | I53: =Summary!H26 -> 0 | J53: =Summary!I26 -> 0 | ... CH53: =Summary!CG26 -> 52062072
A54: Total interest receivable | C54: =C52-C53 -> 583333.33 | D54: =D52-D53 -> 1750000 | E54: =E52-E53 -> 84976.852 | F54: =F52-F53 -> 1359629.6 | G54: =G52-G53 -> 2676770.8 | H54: =H52-H53 -> 43574.241 | I54: =I52-I53 -> 1394375.7 | J54: =J52-J53 -> 2745177.2 | ... CH54: =CH52-CH53 -> 0

Sheet Accrual_IHL
A1: Project name: | B1: =IHL_Loan!C1 -> Imperial Hospital Limited (IHL)
A3: Assumptions:
A5: Agreement signing date | B5: =IHL_Loan!C3 -> 42831
A7: Loan Amount | B7: =IHL_Loan!C5 -> 1.8276043e+08 | C7: BDT
A9: Interest Rate | B9: =IHL_Loan!C8 -> 0.1
A10: Tenor | B10: 7 years
A11: Interest calculation | B11: 360 | C11: days basis
A12: Principal | B12: =IHL_Loan!C11 -> Annuity
A14: Drawdown
C15: =IHL_Loan!C16 -> 43118
C16: =IHL_Loan!C17 -> 150000000
C17: =C16 -> 150000000
A19: Period | B19: 43069 | C19: =EDATE(B19,1) -> 43099 | D19: =EDATE(C19,1) -> 43130 | E19: =EDATE(D19,1) -> 43159 | F19: =EDATE(E19,1) -> 43187 | G19: =EDATE(F19,1) -> 43218 | H19: =EDATE(G19,1) -> 43248 | I19: =EDATE(H19,1) -> 43279 | J19: =EDATE(I19,1) -> 43309 | ... CG19: =EDATE(CF19,1) -> 45593
A20: Expected Interest Rate | B20: 0.1 | C20: 0.1 | D20: 0.1 | E20: 0.1 | F20: 0.1 | G20: 0.1 | H20: 0.1 | I20: 0.1 | J20: 0.1 | K20: 0.1 | L20: 0.1 | M20: 0.1 | N20: 0.1 | O20: 0.1 | P20: 0.1 | Q20: 0.1 | R20: 0.1 | S20: 0.1 | T20: 0.1 | U20: 0.1 | V20: 0.1 | W20: 0.1 | X20: 0.1 | Y20: 0.1 | Z20: 0.1 | AA20: 0.1 | AB20: 0.1 | AC20: 0.1 | AD20: 0.1 | AE20: 0.1 | AF20: 0.1 | AG20: 0.1 | AH20: 0.1 | AI20: 0.1 | AJ20: 0.1 | AK20: 0.1 | AL20: 0.1 | AM20: 0.1 | AN20: 0.1 | AO20: 0.1 | AP20: 0.1 | AQ20: 0.1 | AR20: 0.1 | AS20: 0.1 | AT20: 0.1 | AU20: 0.1 | AV20: 0.1 | AW20: 0.1 | AX20: 0.1 | AY20: 0.1 | AZ20: 0.1 | BA20: 0.1 | BB20: 0.1 | BC20: 0.1 | BD20: 0.1 | BE20: 0.1 | BF20: 0.1 | BG20: 0.1 | BH20: 0.1 | BI20: 0.1 | BJ20: 0.1 | BK20: 0.1 | BL20: 0.1 | BM20: 0.1 | BN20: 0.1 | BO20: 0.1 | BP20: 0.1 | BQ20: 0.1 | BR20: 0.1 | BS20: 0.1 | BT20: 0.1 | BU20: 0.1 | BV20: 0.1 | BW20: 0.1 | BX20: 0.1 | BY20: 0.1 | BZ20: 0.1 | CA20: 0.1 | CB20: 0.1 | CC20: 0.1 | CD20: 0.1 | CE20: 0.1 | CF20: 0.1 | CG20: 0.1
A22: Accrual of interest
A23: Months | B23: 43132 | C23: =EDATE(B23,1) -> 43160 | D23: =EDATE(C23,1) -> 43191 | E23: =EDATE(D23,1) -> 43221 | F23: =EDATE(E23,1) -> 43252 | G23: =EDATE(F23,1) -> 43282 | H23: =EDATE(G23,1) -> 43313 | I23: =EDATE(H23,1) -> 43344 | J23: =EDATE(I23,1) -> 43374 | ... CG23: =EDATE(CF23,1) -> 45658
A24: Opening Balance | B24: =C16 -> 150000000 | C24: =B30+F16 -> 150000000 | D24: =C30 -> 150000000 | E24: =D30 -> 1.5295833e+08 | F24: =E30 -> 1.5295833e+08 | G24: =F30 -> 1.5295833e+08 | H24: =G30 -> 1.5686727e+08 | I24: =H30 -> 1.5686727e+08 | J24: =I30 -> 1.5686727e+08 | K24: =J30 -> 1.608761e+08 | ... CG24: =CF30 -> 11786314
A25: Interest Payment | B25: =B24*(B23-C15)*B20/360 -> 583333.33 | C25: =C24*(C23-B23)*C20/360 -> 1166666.7 | D25: =D24*(IHL_Loan!$B$27-C23)*D20/360+D30*(D23-IHL_Loan!$B$27)*D20/360 -> 1293310.2 | E25: =E24*(E23-D23)*E20/360 -> 1274652.8 | F25: =F24*(F23-E23)*F20/360 -> 1317141.2 | G25: =G24*(IHL_Loan!$C$27-F23)*G20/360+G30*(G23-IHL_Loan!$C$27)*G20/360 -> 1275738.6 | H25: =H24*(H23-G23)*H20/360 -> 1350801.5 | I25: =I24*(I23-H23)*I20/360 -> 1350801.5 | J25: =J24*(IHL_Loan!$D$27-I23)*J20/360+J30*(J23-IHL_Loan!$D$27)*J20/360 -> 1308340.8 | K25: =K24*(K23-J23)*K20/360 -> 1385322 | L25: =L24*(L23-K23)*L20/360 -> 1340634.2 | M25: =M24*(IHL_Loan!$E$27-L23)*M20/360+M30*(M23-IHL_Loan!$E$27)*M20/360 -> 1387581.2 | N25: =N24*(N23-M23)*N20/360 -> 1420339.8 | O25: =O24*(IHL_Loan!$F$27-N23)*N20/360+O30*(O23-IHL_Loan!$F$27)*O20/360 -> 1282887.6 | P25: =P24*(IHL_Loan!$F$27-O23)*P20/360+P30*(P23-IHL_Loan!$F$27)*P20/360 -> 1422630.7 | Q25: =Q24*(Q23-P23)*Q20/360 -> 1408885.5 | R25: =R24*(IHL_Loan!$G$27-Q23)*Q20/360+R30*(R23-IHL_Loan!$G$27)*R20/360 -> 1455848.3 | S25: =S24*(IHL_Loan!$G$27-R23)*S20/360+S30*(S23-IHL_Loan!$G$27)*S20/360 -> 1410085.6 | T25: =T24*(T23-S23)*T20/360 -> 1493053.3 | U25: =U24*(IHL_Loan!$H$27-T23)*T20/360+U30*(U23-IHL_Loan!$H$27)*U20/360 -> 1493053.3 | V25: =V24*(IHL_Loan!$H$27-U23)*V20/360+V30*(V23-IHL_Loan!$H$27)*V20/360 -> 1446121.2 | W25: =W24*(W23-V23)*W20/360 -> 1531209.1 | X25: =X24*(IHL_Loan!$I$27-W23)*W20/360+X30*(X23-IHL_Loan!$I$27)*X20/360 -> 1481815.3 | Y25: =Y24*(IHL_Loan!$I$27-X23)*Y20/360+Y30*(Y23-IHL_Loan!$I$27)*Y20/360 -> 1533706.3 | Z25: =Z24*(IHL_Loan!$J$27-Y23)*Z20/360+Z30*(Z23-IHL_Loan!$J$27)*Z20/360 -> 1572728.2 | AA25: =AA24*(AA23-Z23)*AA20/360 -> 1471893.5 | AB25: =AB24*(IHL_Loan!$K$27-AA23)*AA20/360+AB30*(AB23-IHL_Loan!$K$27)*AB20/360 -> 1569232.2 | AC25: =AC24*(AC23-AB23)*AC20/360 -> 1460080.4 | AD25: =AD24*(AD23-AC23)*AD20/360 -> 1508749.8 | AE25: =AE24*(IHL_Loan!$L$27-AD23)*AD20/360+AE30*(AE23-IHL_Loan!$L$27)*AE20/360 -> 1458068.4 | AF25: =AF24*(AF23-AE23)*AF20/360 -> 1446377.4 | AG25: =AG24*(AG23-AF23)*AG20/360 -> 1446377.4 | AH25: =AH24*(IHL_Loan!$M$27-AG23)*AG20/360+AH30*(AH23-IHL_Loan!$M$27)*AH20/360 -> 1397656.6 | AI25: =AI24*(AI23-AH23)*AI20/360 -> 1382411.1 | AJ25: =AJ24*(AJ23-AI23)*AJ20/360 -> 1337817.2 | AK25: =AK24*(IHL_Loan!$N$27-AJ23)*AJ20/360+AK30*(AK23-IHL_Loan!$N$27)*AK20/360 -> 1378154 | AL25: =AL24*(AL23-AK23)*AL20/360 -> 1316426 | AM25: =AM24*(AM23-AL23)*AM20/360 -> 1189030 | AN25: =AN24*(IHL_Loan!$O$27-AM23)*AM20/360+AN30*(AN23-IHL_Loan!$O$27)*AN20/360 -> 1312037.7 | AO25: =AO24*(AO23-AN23)*AO20/360 -> 1208136.2 | AP25: =AP24*(AP23-AO23)*AP20/360 -> 1248407.4 | AQ25: =AQ24*(IHL_Loan!$P$27-AP23)*AP20/360+AQ30*(AQ23-IHL_Loan!$P$27)*AQ20/360 -> 1205909.5 | AR25: =AR24*(AR23-AQ23)*AR20/360 -> 1179381.8 | AS25: =AS24*(AS23-AR23)*AS20/360 -> 1179381.8 | AT25: =AT24*(IHL_Loan!$Q$27-AS23)*AS20/360+AT30*(AT23-IHL_Loan!$Q$27)*AT20/360 -> 1139053.7 | AU25: =AU24*(AU23-AT23)*AU20/360 -> 1108592.3 | AV25: =AV24*(AV23-AU23)*AV20/360 -> 1072831.2 | AW25: =AW24*(IHL_Loan!$R$27-AV23)*AV20/360+AW30*(AW23-IHL_Loan!$R$27)*AW20/360 -> 1103888.6 | AX25: =AX24*(AX23-AW23)*AX20/360 -> 1035685.7 | AY25: =AY24*(AY23-AX23)*AY20/360 -> 935458.06 | AZ25: =AZ24*(IHL_Loan!$S$27-AY23)*AY20/360+AZ30*(AZ23-IHL_Loan!$S$27)*AZ20/360 -> 1030844.6 | BA25: =BA24*(BA23-AZ23)*BA20/360 -> 929659.88 | BB25: =BB24*(BB23-BA23)*BB20/360 -> 960648.54 | BC25: =BC24*(IHL_Loan!$T$27-BB23)*BB20/360+BC30*(BC23-IHL_Loan!$T$27)*BC20/360 -> 927196.02 | BD25: =BD24*(BD23-BC23)*BD20/360 -> 884269.13 | BE25: =BE24*(BE23-BD23)*BE20/360 -> 884269.13 | BF25: =BF24*(IHL_Loan!$U$27-BE23)*BE20/360+BF30*(BF23-IHL_Loan!$U$27)*BF20/360 -> 850674.84 | BG25: =BG24*(BG23-BF23)*BG20/360 -> 805692.18 | BH25: =BH24*(BH23-BG23)*BH20/360 -> 779702.11 | BI25: =BI24*(IHL_Loan!$V$27-BH23)*BH20/360+BI30*(BI23-IHL_Loan!$V$27)*BI20/360 -> 797895.74 | BJ25: =BJ24*(BJ23-BI23)*BJ20/360 -> 725128.98 | BK25: =BK24*(BK23-BJ23)*BK20/360 -> 654955.21 | BL25: =BL24*(IHL_Loan!$W$27-BK23)*BK20/360+BL30*(BL23-IHL_Loan!$W$27)*BL20/360 -> 719799.97 | BM25: =BM24*(BM23-BL23)*BM20/360 -> 621802.57 | BN25: =BN24*(BN23-BM23)*BN20/360 -> 642529.32 | BO25: =BO24*(IHL_Loan!$X$27-BN23)*BN20/360+BO30*(BO23-IHL_Loan!$X$27)*BO20/360 -> 616338.85 | BP25: =BP24*(BP23-BO23)*BP20/360 -> 557841.72 | BQ25: =BQ24*(BQ23-BP23)*BQ20/360 -> 557841.72 | BR25: =BR24*(IHL_Loan!$Y$27-BQ23)*BQ20/360+BR30*(BR23-IHL_Loan!$Y$27)*BR20/360 -> 531444.09 | BS25: =BS24*(BS23-BR23)*BS20/360 -> 471013.41 | BT25: =BT24*(BT23-BS23)*BT20/360 -> 455819.43 | BU25: =BU24*(IHL_Loan!$Z$27-BT23)*BT20/360+BU30*(BU23-IHL_Loan!$Z$27)*BU20/360 -> 459526.55 | BV25: =BV24*(BV23-BU23)*BV20/360 -> 381990.27 | BW25: =BW24*(BW23-BV23)*BW20/360 -> 357345.74 | BX25: =BX24*(IHL_Loan!$AA$27-BW23)*BW20/360+BX30*(BX23-IHL_Loan!$AA$27)*BX20/360 -> 370213.05 | BY25: =BY24*(BY23-BX23)*BY20/360 -> 281338.86 | BZ25: =BZ24*(BZ23-BY23)*BZ20/360 -> 290716.83 | CA25: =CA24*(IHL_Loan!$AB$27-BZ23)*BZ20/360+CA30*(CA23-IHL_Loan!$AB$27)*CA20/360 -> 278327.95 | CB25: =CB24*(CB23-CA23)*CB20/360 -> 197378.46 | CC25: =CC24*(CC23-CB23)*CC20/360 -> 197378.46 | CD25: =CD24*(IHL_Loan!$AC$27-CC23)*CC20/360+CD30*(CD23-IHL_Loan!$AC$27)*CD20/360 -> 187918.34 | CE25: =CE24*(CE23-CD23)*CE20/360 -> 101493.26 | CF25: =CF24*(CF23-CE23)*CF20/360 -> 98219.284 | CG25: =CG24*(IHL_Loan!$AD$27-CF23)*CF20/360+CG30*(CG23-IHL_Loan!$AD$27)*CG20/360 -> 94945.308
A26: Cumulative interest | B26: =B25 -> 583333.33 | C26: =B26+C25 -> 1750000 | D26: =C26+D25 -> 3043310.2 | E26: =D26+E25 -> 4317963 | F26: =E26+F25 -> 5635104.2 | G26: =F26+G25 -> 6910842.8 | H26: =G26+H25 -> 8261644.2 | I26: =H26+I25 -> 9612445.7 | J26: =I26+J25 -> 10920787 | ... CG26: =CF26+CG25 -> 84779886
A27: Principal Payment | B27: 0 | C27: =B27 -> 0 | D27: =C27 -> 0 | E27: =D27 -> 0 | F27: =E27 -> 0 | G27: =F27 -> 0 | H27: =G27 -> 0 | I27: =H27 -> 0 | J27: =I27 -> 0 | ... N27: =M27 -> 0 | O27: =IHL_Loan!$F$31 -> 0 | P27: =M27 -> 0 | Q27: =N27 -> 0 | R27: =IHL_Loan!$G$31 -> 0 | S27: =P27 -> 0 | T27: =Q27 -> 0 | U27: =IHL_Loan!$H$31 -> 0 | V27: =S27 -> 0 | W27: =T27 -> 0 | X27: =IHL_Loan!$I$31 -> 0 | Y27: =V27 -> 0 | Z27: =W27 -> 0 | AA27: 0 | AB27: =IHL_Loan!$K$31 -> 7508162.4 | AC27: =Z27 -> 0 | AD27: =AA27 -> 0 | AE27: =IHL_Loan!$L$31 -> 7243243.2 | AF27: =AC27 -> 0 | AG27: =AD27 -> 0 | AH27: =IHL_Loan!$M$31 -> 7428348.3 | AI27: =AF27 -> 0 | AJ27: =AG27 -> 0 | AK27: =IHL_Loan!$N$31 -> 7662777.7 | AL27: =AI27 -> 0 | AM27: =AJ27 -> 0 | AN27: =IHL_Loan!$O$31 -> 7898941.1 | AO27: =AL27 -> 0 | AP27: =AM27 -> 0 | AQ27: =IHL_Loan!$P$31 -> 8015872.2 | AR27: =AO27 -> 0 | AS27: =AP27 -> 0 | AT27: =IHL_Loan!$Q$31 -> 8220722.3 | AU27: =AR27 -> 0 | AV27: =AS27 -> 0 | AW27: =IHL_Loan!$R$31 -> 8466568.4 | AX27: =AU27 -> 0 | AY27: =AV27 -> 0 | AZ27: =IHL_Loan!$S$31 -> 8713993.7 | BA27: =AX27 -> 0 | BB27: =AY27 -> 0 | BC27: =IHL_Loan!$T$31 -> 8869866.2 | BD27: =BA27 -> 0 | BE27: =BB27 -> 0 | BF27: =IHL_Loan!$U$31 -> 9125065.4 | BG27: =BD27 -> 0 | BH27: =BE27 -> 0 | BI27: =IHL_Loan!$V$31 -> 9355726.7 | BJ27: =BG27 -> 0 | BK27: =BH27 -> 0 | BL27: =IHL_Loan!$W$31 -> 9592218.7 | BM27: =BJ27 -> 0 | BN27: =BK27 -> 0 | BO27: =IHL_Loan!$X$31 -> 9834688.7 | BP27: =BM27 -> 0 | BQ27: =BN27 -> 0 | BR27: =IHL_Loan!$Y$31 -> 10083288 | BS27: =BP27 -> 0 | BT27: =BQ27 -> 0 | BU27: =IHL_Loan!$Z$31 -> 10338171 | BV27: =BS27 -> 0 | BW27: =BT27 -> 0 | BX27: =IHL_Loan!$AA$31 -> 10599497 | BY27: =BV27 -> 0 | BZ27: =BW27 -> 0 | CA27: =IHL_Loan!$AB$31 -> 10839295 | CB27: =BY27 -> 0 | CC27: =BZ27 -> 0 | CD27: =IHL_Loan!$AC$31 -> 11135055 | CE27: =CB27 -> 0 | CF27: =CC27 -> 0 | CG27: =IHL_Loan!$AD$31 -> 11786314
A28: Cumulative repayment | B28: =B27 -> 0 | C28: =B28+C27 -> 0 | D28: =C28+D27 -> 0 | E28: =D28+E27 -> 0 | F28: =E28+F27 -> 0 | G28: =F28+G27 -> 0 | H28: =G28+H27 -> 0 | I28: =H28+I27 -> 0 | J28: =I28+J27 -> 0 | ... CG28: =CF28+CG27 -> 1.8271781e+08
A29: Total Debt Service | B29: =B27+B25 -> 583333.33 | C29: =C27+C25 -> 1166666.7 | D29: =D27+D25 -> 1293310.2 | E29: =E27+E25 -> 1274652.8 | F29: =F27+F25 -> 1317141.2 | G29: =G27+G25 -> 1275738.6 | H29: =H27+H25 -> 1350801.5 | I29: =I27+I25 -> 1350801.5 | ... CG29: =CG27+CG25 -> 11881259
A30: Closing Balance | B30: =B24-B27 -> 150000000 | C30: =C24-C27 -> 150000000 | D30: =IHL_Loan!$B$34 -> 1.5295833e+08 | E30: =E24-E27 -> 1.5295833e+08 | F30: =F24-F27 -> 1.5295833e+08 | G30: =IHL_Loan!$C$34 -> 1.5686727e+08 | H30: =H24-H27 -> 1.5686727e+08 | I30: =I24-I27 -> 1.5686727e+08 | J30: =IHL_Loan!$D$34 -> 1.608761e+08 | K30: =K24-K27 -> 1.608761e+08 | L30: =L24-L27 -> 1.608761e+08 | M30: =IHL_Loan!$E$34 -> 1.6494269e+08 | N30: =N24-N27 -> 1.6494269e+08 | O30: =O24-O27 -> 1.6494269e+08 | P30: =IHL_Loan!$F$34 -> 1.6906626e+08 | Q30: =Q24-Q27 -> 1.6906626e+08 | R30: =R24-R27 -> 1.6906626e+08 | S30: =IHL_Loan!$G$34 -> 1.7338684e+08 | T30: =T24-T27 -> 1.7338684e+08 | U30: =U24-U27 -> 1.7338684e+08 | V30: =IHL_Loan!$H$34 -> 1.7781784e+08 | W30: =W24-W27 -> 1.7781784e+08 | X30: =X24-X27 -> 1.7781784e+08 | Y30: =IHL_Loan!$I$34 -> 1.8231268e+08 | Z30: =IHL_Loan!$J$34 -> 1.8271781e+08 | AA30: =AA24-AA27 -> 1.8271781e+08 | AB30: =AB24-AB27 -> 1.7520965e+08 | AC30: =AC24-AC27 -> 1.7520965e+08 | AD30: =AD24-AD27 -> 1.7520965e+08 | AE30: =AE24-AE27 -> 1.6796641e+08 | AF30: =AF24-AF27 -> 1.6796641e+08 | AG30: =AG24-AG27 -> 1.6796641e+08 | AH30: =AH24-AH27 -> 1.6053806e+08 | ... CG30: =CG24-CG27 -> 0
CG33: =SUM(B25:CG25)-SUM(IHL_Loan!B29:AD29) -> 0

Sheet Repayment Schedule
A1: Project name: | C1: =IHL_Loan!C1 -> Imperial Hospital Limited (IHL)
A3: Financial Close | C3: =IHL_Loan!C3 -> 42831
A5: Loan Amount | C5: =IHL_Loan!C5 -> 1.8276043e+08
A7: Interest Rate | C7: =IHL_Loan!C8 -> 0.1
A9: Number of installments | C9: =IHL_Loan!C13 -> 20
A11: Drawdown
C12: =IHL_Loan!C16 -> 43118
C13: =IHL_Loan!C17 -> 150000000
C14: =C13 -> 150000000
A16: Repayment Date | B16: Opening Balance | C16: Interest Payment | D16: Cumulative interest | E16: Principal Payment | F16: Cumulative repayment | G16: Total Debt Service | H16: Closing Balance
A17: {=TRANSPOSE(IHL_Loan!B27:AD34)} -> 43189 | B17: 150000000 | C17: 2958333.3 | D17: 0 | E17: 0 | F17: 0 | G17: 0 | H17: 1.5295833e+08
A18: 43281 | B18: 1.5295833e+08 | C18: 3908935.2 | D18: 0 | E18: 0 | F18: 0 | G18: 0 | H18: 1.5686727e+08
A19: 43373 | B19: 1.5686727e+08 | C19: 4008830.2 | D19: 0 | E19: 0 | F19: 0 | G19: 0 | H19: 1.608761e+08
A20: 43464 | B20: 1.608761e+08 | C20: 4066590.3 | D20: 0 | E20: 0 | F20: 0 | G20: 0 | H20: 1.6494269e+08
A21: 43554 | B21: 1.6494269e+08 | C21: 4123567.2 | D21: 0 | E21: 0 | F21: 0 | G21: 0 | H21: 1.6906626e+08
A22: 43646 | B22: 1.6906626e+08 | C22: 4320582.1 | D22: 0 | E22: 0 | F22: 0 | G22: 0 | H22: 1.7338684e+08
A23: 43738 | B23: 1.7338684e+08 | C23: 4430997 | D23: 0 | E23: 0 | F23: 0 | G23: 0 | H23: 1.7781784e+08
A24: 43829 | B24: 1.7781784e+08 | C24: 4494839.7 | D24: 0 | E24: 0 | F24: 0 | G24: 0 | H24: 1.8231268e+08
A25: 43837 | B25: 1.8231268e+08 | C25: 405139.28 | D25: 0 | E25: 0 | F25: 0 | G25: 0 | H25: 1.8271781e+08
A26: 43920 | B26: 1.8271781e+08 | C26: 4212660.7 | D26: 4212660.7 | E26: 7508162.4 | F26: 7508162.4 | G26: 11720823 | H26: 1.7520965e+08
A27: 44012 | B27: 1.7520965e+08 | C27: 4477580 | D27: 8690240.7 | E27: 7243243.2 | F27: 14751406 | G27: 11720823 | H27: 1.6796641e+08
A28: 44104 | B28: 1.6796641e+08 | C28: 4292474.9 | D28: 12982716 | E28: 7428348.3 | F28: 22179754 | G28: 11720823 | H28: 1.6053806e+08
A29: 44195 | B29: 1.6053806e+08 | C29: 4058045.4 | D29: 17040761 | E29: 7662777.7 | F29: 29842532 | G29: 11720823 | H29: 1.5287528e+08
... A45: 45656 | B45: 11786314 | C45: 297931.83 | D45: 52062072 | E45: 11786314 | F45: 1.8271781e+08 | G45: 12084246 | H45: 0
