Workbook

Sheet Disbursement
A1: Borrower: | B1: Makrail Auto Green Bricks Limited (MAGBL)
A2: Currency: | B2: BDT
A3: Type | B3: IDCOL Loan
A7: Disbursement Number | B7: Disbursement Date | C7: Disbursement | D7: Cumulative Disbursement
A8: 1 | B8: 42549 | C8: 55000000 | D8: =C8 -> 55000000
A9: 2 | B9: 42705 | C9: 40000000 | D9: =D8+C9 -> 95000000
A10: 3 | B10: 42752 | C10: 69750000 | D10: =D9+C10 -> 164750000

Sheet Summary
B1: =Accrual_MAGBL!B23 -> 42552 | C1: =Accrual_MAGBL!C23 -> 42583 | D1: =Accrual_MAGBL!D23 -> 42614 | E1: =Accrual_MAGBL!E23 -> 42644 | F1: =Accrual_MAGBL!F23 -> 42675 | G1: =Accrual_MAGBL!G23 -> 42705 | H1: =Accrual_MAGBL!H23 -> 42736 | I1: =Accrual_MAGBL!I23 -> 42767 | ... CH1: =Accrual_MAGBL!CH23 -> 45108
A2: Principal
A3: Opening balance | B3: =Accrual_MAGBL!B24 -> 55000000 | C3: =Accrual_MAGBL!C24 -> 55000000 | D3: =Accrual_MAGBL!D24 -> 55000000 | E3: =Accrual_MAGBL!E24+'MAGBL_Loan (IDCOL)'!B29 -> 56086250 | F3: =Accrual_MAGBL!F24 -> 56086250 | G3: =Accrual_MAGBL!G24 -> 56086250 | H3: =Accrual_MAGBL!H24+'MAGBL_Loan (IDCOL)'!C29 -> 97502212 | I3: =Accrual_MAGBL!I24 -> 1.6725221e+08 | J3: =Accrual_MAGBL!J24 -> 1.6725221e+08 | K3: =Accrual_MAGBL!K24+'MAGBL_Loan (IDCOL)'!D29 -> 1.7043995e+08 | L3: =Accrual_MAGBL!L24 -> 1.7043995e+08 | M3: =Accrual_MAGBL!M24 -> 1.7043995e+08 | N3: =Accrual_MAGBL!N24+'MAGBL_Loan (IDCOL)'!E29 -> 1.74914e+08 | O3: =N3 -> 1.74914e+08 | P3: =O3 -> 1.74914e+08 | Q3: =P3 -> 1.74914e+08 | R3: =Q3 -> 1.74914e+08 | S3: =R3 -> 1.74914e+08 | T3: =S3 -> 1.74914e+08 | U3: =T3 -> 1.74914e+08 | V3: =U3 -> 1.74914e+08 | ... CH3: =CG3 -> 1.74914e+08
A4: Repayment due | B4: =Accrual_MAGBL!B28 -> 0 | C4: =Accrual_MAGBL!C28 -> 0 | D4: =Accrual_MAGBL!D28 -> 0 | E4: =Accrual_MAGBL!E28 -> 0 | F4: =Accrual_MAGBL!F28 -> 0 | G4: =Accrual_MAGBL!G28 -> 0 | H4: =Accrual_MAGBL!H28 -> 0 | I4: =Accrual_MAGBL!I28 -> 0 | ... CH4: =Accrual_MAGBL!CH28 -> 1.74914e+08
A5: Loan Repayment | B5: =B22 -> 0 | C5: =C22 -> 0 | D5: =D22 -> 0 | E5: =E22 -> 0 | F5: =F22 -> 0 | G5: =G22 -> 0 | H5: =H22 -> 0 | I5: =I22 -> 0 | ... CH5: =CH22 -> 1.74914e+08
A6: Repayment overdue | B6: =IF((B4-B5)>0,(B4-B5),0) -> 0 | C6: =IF((C4-C5)>0,(C4-C5),0) -> 0 | D6: =IF((D4-D5)>0,(D4-D5),0) -> 0 | E6: =IF((E4-E5)>0,(E4-E5),0) -> 0 | F6: =IF((F4-F5)>0,(F4-F5),0) -> 0 | G6: =IF((G4-G5)>0,(G4-G5),0) -> 0 | H6: =IF((H4-H5)>0,(H4-H5),0) -> 0 | I6: =IF((I4-I5)>0,(I4-I5),0) -> 0 | ... CH6: =IF((CH4-CH5)>0,(CH4-CH5),0) -> 0
A7: Loan outstanding | B7: =B3-B5 -> 55000000 | C7: =C3-C5 -> 55000000 | D7: =D3-D5 -> 55000000 | E7: =E3-E5 -> 56086250 | F7: =F3-F5 -> 56086250 | G7: =G3-G5 -> 56086250 | H7: =H3-H5 -> 97502212 | I7: =I3-I5 -> 1.6725221e+08 | ... CH7: =CH3-CH5 -> 0
A8: Interest
A9: Interest accrued | B9: =Accrual_MAGBL!B26 -> 41250 | C9: =Accrual_MAGBL!C26 -> 467500 | D9: =Accrual_MAGBL!D26 -> 893750 | E9: =Accrual_MAGBL!E26 -> 1310595 | F9: =Accrual_MAGBL!F26 -> 1745263.4 | G9: =Accrual_MAGBL!G26 -> 2165910.3 | H9: =Accrual_MAGBL!H26 -> 2916596.6 | I9: =Accrual_MAGBL!I26 -> 3933801.2 | ... CH9: =Accrual_MAGBL!CH26 -> 63725514
A10: Interest due | B10: 0 | C10: =B10 -> 0 | D10: =C10 -> 0 | E10: ='MAGBL_Loan (IDCOL)'!$B$30 -> 0 | F10: =E10 -> 0 | G10: =F10 -> 0 | H10: ='MAGBL_Loan (IDCOL)'!$C$30 -> 0 | I10: =H10 -> 0 | J10: =I10 -> 0 | K10: ='MAGBL_Loan (IDCOL)'!$D$30 -> 0 | L10: =K10 -> 0 | M10: =L10 -> 0 | N10: ='MAGBL_Loan (IDCOL)'!$E$30 -> 0 | O10: =N10 -> 0 | P10: =O10 -> 0 | Q10: ='MAGBL_Loan (IDCOL)'!$F$30 -> 3410823 | R10: =Q10 -> 3410823 | S10: =R10 -> 3410823 | T10: ='MAGBL_Loan (IDCOL)'!$G$30 -> 7263255.6 | U10: =T10 -> 7263255.6 | V10: =U10 -> 7263255.6 | W10: ='MAGBL_Loan (IDCOL)'!$H$30 -> 10985973 | X10: =W10 -> 10985973 | Y10: =X10 -> 10985973 | Z10: ='MAGBL_Loan (IDCOL)'!$I$30 -> 14576057 | AA10: =Z10 -> 14576057 | AB10: =AA10 -> 14576057 | AC10: ='MAGBL_Loan (IDCOL)'!$J$30 -> 18030523 | AD10: =AC10 -> 18030523 | AE10: =AD10 -> 18030523 | AF10: ='MAGBL_Loan (IDCOL)'!$K$30 -> 21346319 | AG10: =AF10 -> 21346319 | AH10: =AG10 -> 21346319 | AI10: ='MAGBL_Loan (IDCOL)'!$L$30 -> 24520326 | AJ10: =AI10 -> 24520326 | AK10: =AJ10 -> 24520326 | AL10: ='MAGBL_Loan (IDCOL)'!$M$30 -> 27549353 | AM10: =AL10 -> 27549353 | AN10: =AM10 -> 27549353 | AO10: ='MAGBL_Loan (IDCOL)'!$N$30 -> 30525109 | AP10: =AO10 -> 30525109 | AQ10: =AP10 -> 30525109 | AR10: ='MAGBL_Loan (IDCOL)'!$O$30 -> 33254318 | AS10: =AR10 -> 33254318 | AT10: =AS10 -> 33254318 | AU10: ='MAGBL_Loan (IDCOL)'!$P$30 -> 35828538 | AV10: =AU10 -> 35828538 | AW10: =AV10 -> 35828538 | AX10: ='MAGBL_Loan (IDCOL)'!$Q$30 -> 38270830 | AY10: =AX10 -> 38270830 | AZ10: =AY10 -> 38270830 | BA10: ='MAGBL_Loan (IDCOL)'!$R$30 -> 40549301 | BB10: =BA10 -> 40549301 | BC10: =BB10 -> 40549301 | BD10: ='MAGBL_Loan (IDCOL)'!$S$30 -> 42637319 | BE10: =BD10 -> 42637319 | BF10: =BE10 -> 42637319 | BG10: ='MAGBL_Loan (IDCOL)'!$T$30 -> 44534840 | BH10: =BG10 -> 44534840 | BI10: =BH10 -> 44534840 | BJ10: ='MAGBL_Loan (IDCOL)'!$U$30 -> 46299397 | BK10: =BJ10 -> 46299397 | BL10: =BK10 -> 46299397 | BM10: ='MAGBL_Loan (IDCOL)'!$V$30 -> 47884885 | BN10: =BM10 -> 47884885 | BO10: =BN10 -> 47884885 | BP10: ='MAGBL_Loan (IDCOL)'!$W$30 -> 49272029 | BQ10: =BP10 -> 49272029 | BR10: =BQ10 -> 49272029 | BS10: ='MAGBL_Loan (IDCOL)'!$X$30 -> 50460781 | BT10: =BS10 -> 50460781 | BU10: =BT10 -> 50460781 | BV10: ='MAGBL_Loan (IDCOL)'!$Y$30 -> 51484518 | BW10: =BV10 -> 51484518 | BX10: =BW10 -> 51484518 | BY10: ='MAGBL_Loan (IDCOL)'!$Z$30 -> 52312517 | BZ10: =BY10 -> 52312517 | CA10: =BZ10 -> 52312517 | CB10: ='MAGBL_Loan (IDCOL)'!$AA$30 -> 52933548 | CC10: =CB10 -> 52933548 | CD10: =CC10 -> 52933548 | CE10: ='MAGBL_Loan (IDCOL)'!$AB$30 -> 53347557 | CF10: =CE10 -> 53347557 | CG10: =CF10 -> 53347557 | CH10: ='MAGBL_Loan (IDCOL)'!$AC$30 -> 53561516
A11: interest received | B11: =B26 -> 0 | C11: =C26 -> 0 | D11: =D26 -> 0 | E11: =E26 -> 0 | F11: =F26 -> 0 | G11: =G26 -> 0 | H11: =H26 -> 0 | I11: =I26 -> 0 | ... CH11: =CH26 -> 53561516
A12: Interest overdue | B12: =IF((B10-B11)>0,(B10-B11),0) -> 0 | C12: =IF((C10-C11)>0,(C10-C11),0) -> 0 | D12: =IF((D10-D11)>0,(D10-D11),0) -> 0 | E12: =IF((E10-E11)>0,(E10-E11),0) -> 0 | F12: =IF((F10-F11)>0,(F10-F11),0) -> 0 | G12: =IF((G10-G11)>0,(G10-G11),0) -> 0 | H12: =IF((H10-H11)>0,(H10-H11),0) -> 0 | I12: =IF((I10-I11)>0,(I10-I11),0) -> 0 | ... CH12: =IF((CH10-CH11)>0,(CH10-CH11),0) -> 0
A13: Interest receivable | B13: =B9-B11 -> 41250 | C13: =C9-C11 -> 467500 | D13: =D9-D11 -> 893750 | E13: =E9-E11 -> 1310595 | F13: =F9-F11 -> 1745263.4 | G13: =G9-G11 -> 2165910.3 | H13: =H9-H11 -> 2916596.6 | I13: =I9-I11 -> 3933801.2 | ... CH13: =CH9-CH11 -> 10163998
A14: LD and others | B14: =B28 -> 0 | C14: =C28 -> 0 | D14: =D28 -> 0 | E14: =E28 -> 0 | F14: =F28 -> 0 | G14: =G28 -> 0 | H14: =H28 -> 0 | I14: =I28 -> 0 | ... CH14: =CH28 -> 0
B19: =B1 -> 42552 | C19: =C1 -> 42583 | D19: =D1 -> 42614 | E19: =E1 -> 42644 | F19: =F1 -> 42675 | G19: =G1 -> 42705 | H19: =H1 -> 42736 | I19: =I1 -> 42767 | ... CH19: =CH1 -> 45108
A20: Repayment receipts:
A21: Repayment received | B21: 0 | C21: =C4-B5 -> 0 | D21: =D4-C5 -> 0 | E21: =E4-D5 -> 0 | F21: =F4-E5 -> 0 | G21: =G4-F5 -> 0 | H21: =H4-G5 -> 0 | I21: =I4-H5 -> 0 | J21: =J4-I5 -> 0 | ... P21: =P4-O5 -> 0 | Q21: 0 | T21: =T4-S5 -> 11278063 | U21: =U4-T5 -> 0 | V21: =V4-U5 -> 0 | W21: =W4-V5 -> 5830054.7 | X21: =X4-W5 -> 0 | Y21: =Y4-X5 -> 0 | Z21: =Z4-Y5 -> 5961231 | AA21: =AA4-Z5 -> 0 | ... CH21: =CH4-CG5 -> 9302555.8
A22: Repayment received (cumulative) | B22: =B21 -> 0 | C22: =B22+C21 -> 0 | D22: =C22+D21 -> 0 | E22: =D22+E21 -> 0 | F22: =E22+F21 -> 0 | G22: =F22+G21 -> 0 | H22: =G22+H21 -> 0 | I22: =H22+I21 -> 0 | J22: =I22+J21 -> 0 | ... CH22: =CG22+CH21 -> 1.74914e+08
A24: Interest receipts:
A25: Interest received | B25: 0 | C25: =C10-B11 -> 0 | D25: =D10-C11 -> 0 | E25: =E10-D11 -> 0 | F25: =F10-E11 -> 0 | G25: =G10-F11 -> 0 | H25: =H10-G11 -> 0 | I25: =I10-H11 -> 0 | J25: =J10-I11 -> 0 | ... P25: =P10-O11 -> 0 | Q25: 0 | T25: =T10-S11 -> 7263255.6 | U25: =U10-T11 -> 0 | V25: =V10-U11 -> 0 | W25: =W10-V11 -> 3722717.5 | X25: =X10-W11 -> 0 | Y25: =Y10-X11 -> 0 | Z25: =Z10-Y11 -> 3590083.8 | AA25: =AA10-Z11 -> 0 | ... CH25: =CH10-CG11 -> 213958.78
A26: Interest received (cumulative) | B26: =B25 -> 0 | C26: =B26+C25 -> 0 | D26: =C26+D25 -> 0 | E26: =D26+E25 -> 0 | F26: =E26+F25 -> 0 | G26: =F26+G25 -> 0 | H26: =G26+H25 -> 0 | I26: =H26+I25 -> 0 | J26: =I26+J25 -> 0 | ... CH26: =CG26+CH25 -> 53561516
A27: LD/others | B27: 0 | C27: 0 | D27: 0 | E27: 0 | F27: 0 | G27: 0 | H27: 0 | I27: 0 | J27: 0 | K27: 0 | L27: 0 | M27: 0 | N27: 0 | O27: 0 | P27: 0 | Q27: 0 | R27: 0 | S27: 0 | T27: 0 | U27: 0 | V27: 0 | W27: 0 | X27: 0 | Y27: 0 | Z27: 0 | AA27: 0 | AB27: 0 | AC27: 0 | AD27: 0 | AE27: 0 | AF27: 0 | AG27: 0 | AH27: 0 | AI27: 0 | AJ27: 0 | AK27: 0 | AL27: 0 | AM27: 0 | AN27: 0 | AO27: 0 | AP27: 0 | AQ27: 0 | AR27: 0 | AS27: 0 | AT27: 0 | AU27: 0 | AV27: 0 | AW27: 0 | AX27: 0 | AY27: 0 | AZ27: 0 | BA27: 0 | BB27: 0 | BC27: 0 | BD27: 0 | BE27: 0 | BF27: 0 | BG27: 0 | BH27: 0 | BI27: 0 | BJ27: 0 | BK27: 0 | BL27: 0 | BM27: 0 | BN27: 0 | BO27: 0 | BP27: 0 | BQ27: 0 | BR27: 0 | BS27: 0 | BT27: 0 | BU27: 0 | BV27: 0 | BW27: 0 | BX27: 0 | BY27: 0 | BZ27: 0 | CA27: 0 | CB27: 0 | CC27: 0 | CD27: 0 | CE27: 0 | CF27: 0 | CG27: 0 | CH27: 0
A28: LD/others (cumulative) | B28: =B27 -> 0 | C28: =B28+C27 -> 0 | D28: =C28+D27 -> 0 | E28: =D28+E27 -> 0 | F28: =E28+F27 -> 0 | G28: =F28+G27 -> 0 | H28: =G28+H27 -> 0 | I28: =H28+I27 -> 0 | J28: =I28+J27 -> 0 | ... CH28: =CG28+CH27 -> 0
A30: Actual Payment date
A31: Actual Payment amount:
A32: Interest
A33: Principal
A34: LPC
A35: Total | B35: =SUM(B32:B34) -> 0 | C35: =SUM(C32:C34) -> 0 | D35: =SUM(D32:D34) -> 0 | E35: =SUM(E32:E34) -> 0 | F35: =SUM(F32:F34) -> 0 | G35: =SUM(G32:G34) -> 0 | H35: =SUM(H32:H34) -> 0 | I35: =SUM(I32:I34) -> 0 | ... CH35: =SUM(CH32:CH34) -> 0

Sheet MAGBL_Loan (IDCOL)
A1: Project name: | C1: =Disbursement!B1 -> Makrail Auto Green Bricks Limited (MAGBL)
A3: Agreement signing date | C3: 42467
A5: Loan Amount | C5: 175000000
A7: Payment frequency | C7: Quarterly
A8: Interest Rate | C8: 0.09
A9: Maturity date | C9: 84 | D9: months
A10: Moratorium period (interest and principal) | C10: 12 | D10: months
A11: Principal | C11: Level Principal
A12: Interest calculation | C12: 360 | D12: days basis
A13: Number of installments | C13: 24
A15: Drawdown
C16: =Disbursement!B8 -> 42549 | D16: =Disbursement!B9 -> 42705 | E16: =Disbursement!B10 -> 42752
C17: =Disbursement!C8 -> 55000000 | D17: =Disbursement!C9 -> 40000000 | E17: =Disbursement!C10 -> 69750000
C18: =C17 -> 55000000 | D18: =C18+D17 -> 95000000 | E18: =D18+E17 -> 164750000
A21: Period | B21: =B27 -> 42628 | C21: =C27 -> 42719 | D21: =D27 -> 42809 | E21: =E27 -> 42914 | F21: =F27 -> 42992 | G21: =G27 -> 43083 | H21: =H27 -> 43174 | I21: =I27 -> 43265 | ... AC21: =AC27 -> 45092
A22: Expected Interest Rate | B22: 0.09 | C22: 0.09 | D22: 0.09 | E22: 0.09 | F22: 0.09 | G22: 0.09 | H22: 0.09 | I22: 0.09 | J22: 0.09 | K22: 0.09 | L22: 0.09 | M22: 0.09 | N22: 0.09 | O22: 0.09 | P22: 0.09 | Q22: 0.09 | R22: 0.09 | S22: 0.09 | T22: 0.09 | U22: 0.09 | V22: 0.09 | W22: 0.09 | X22: 0.09 | Y22: 0.09 | Z22: 0.09 | AA22: 0.09 | AB22: 0.09 | AC22: 0.09
A25: Repayment | B25: Interest Capitalized
A26: Repayment Period | F26: 1 | G26: =F26+1 -> 2 | H26: =G26+1 -> 3 | I26: =H26+1 -> 4 | J26: =I26+1 -> 5 | K26: =J26+1 -> 6 | L26: =K26+1 -> 7 | M26: =L26+1 -> 8 | N26: =M26+1 -> 9 | ... AC26: =AB26+1 -> 24
A27: Repayment Date | B27: 42628 | C27: 42719 | D27: 42809 | E27: 42914 | F27: 42992 | G27: 43083 | H27: 43174 | I27: 43265 | J27: 43356 | K27: 43447 | L27: 43538 | M27: 43629 | N27: 43723 | O27: 43814 | P27: 43905 | Q27: 43997 | R27: 44089 | S27: 44180 | T27: 44270 | U27: 44362 | V27: 44454 | W27: 44545 | X27: 44635 | Y27: 44727 | Z27: 44819 | AA27: 44910 | AB27: 45000 | AC27: 45092
A28: Opening Balance | B28: =C17 -> 55000000 | C28: =B34+D17 -> 96086250 | D28: =C34+E17 -> 1.6725221e+08 | E28: =D34 -> 1.7043995e+08 | F28: =E34 -> 1.74914e+08 | G28: =F34 -> 1.693377e+08 | H28: =G34 -> 1.6363593e+08 | I28: =H34 -> 1.5780588e+08 | J28: =I34 -> 1.5184465e+08 | K28: =J34 -> 1.4574929e+08 | L28: =K34 -> 1.3951679e+08 | ... AC28: =AB34 -> 9302555.8
A29: Interest Payment | B29: =C18*(B27-C16)*B22/360 -> 1086250 | C29: =B34*(D16-B27)*C22/360+C28*(C27-D16)*C22/360 -> 1415962.2 | D29: =C34*(E16-C27)*D22/360+(C34+E17)*(D27-E16)*D22/360 -> 3187737.3 | E29: =E28*(E27-D27)*E22/360 -> 4474048.7 | F29: =F28*(F27-E27)*F22/360 -> 3410823 | G29: =G28*(G27-F27)*G22/360 -> 3852432.7 | H29: =H28*(H27-G27)*H22/360 -> 3722717.5 | I29: =I28*(I27-H27)*I22/360 -> 3590083.8 | J29: =J28*(J27-I27)*J22/360 -> 3454465.8 | K29: =K28*(K27-J27)*K22/360 -> 3315796.4 | L29: =L28*(L27-K27)*L22/360 -> 3174006.9 | ... AC29: =AC28*(AC27-AB27)*AC22/360 -> 213958.78
A30: Cumulative interest | B30: 0 | C30: 0 | D30: 0 | E30: 0 | F30: =F29+E30 -> 3410823 | G30: =G29+F30 -> 7263255.6 | H30: =H29+G30 -> 10985973 | I30: =I29+H30 -> 14576057 | J30: =J29+I30 -> 18030523 | K30: =K29+J30 -> 21346319 | L30: =L29+K30 -> 24520326 | M30: =M29+L30 -> 27549353 | ... AC30: =AC29+AB30 -> 53561516
A31: Principal Payment | B31: 0 | C31: 0 | D31: 0 | E31: 0 | F31: =-PPMT(F22/4,F26,$C$13,$F$28) -> 5576298.3 | G31: =-PPMT(G22/4,G26,$C$13,$F$28) -> 5701765 | H31: =-PPMT(H22/4,H26,$C$13,$F$28) -> 5830054.7 | I31: =-PPMT(I22/4,I26,$C$13,$F$28) -> 5961231 | J31: =-PPMT(J22/4,J26,$C$13,$F$28) -> 6095358.7 | K31: =-PPMT(K22/4,K26,$C$13,$F$28) -> 6232504.2 | L31: =-PPMT(L22/4,L26,$C$13,$F$28) -> 6372735.6 | M31: =-PPMT(M22/4,M26,$C$13,$F$28) -> 6516122.1 | ... AC31: =-PPMT(AC22/4,AC26,$C$13,$F$28) -> 9302555.8
A32: Cumulative repayment | B32: 0 | C32: =C31+B32 -> 0 | D32: =D31+C32 -> 0 | E32: =E31+D32 -> 0 | F32: =F31+E32 -> 5576298.3 | G32: =G31+F32 -> 11278063 | H32: =H31+G32 -> 17108118 | I32: =I31+H32 -> 23069349 | J32: =J31+I32 -> 29164708 | ... AC32: =AC31+AB32 -> 1.74914e+08
A33: Total Debt Service | B33: 0 | C33: 0 | D33: 0 | E33: 0 | F33: =F29+F31 -> 8987121.3 | G33: =G29+G31 -> 9554197.7 | H33: =H29+H31 -> 9552772.2 | I33: =I29+I31 -> 9551314.7 | J33: =J29+J31 -> 9549824.4 | K33: =K29+K31 -> 9548300.6 | L33: =L29+L31 -> 9546742.5 | M33: =M29+M31 -> 9545149.3 | ... AC33: =AC29+AC31 -> 9516514.5
A34: Closing Balance | B34: =B28+B29 -> 56086250 | C34: =C28+C29 -> 97502212 | D34: =D28+D29 -> 1.7043995e+08 | E34: =E28+E29 -> 1.74914e+08 | F34: =F28-F31 -> 1.693377e+08 | G34: =G28-G31 -> 1.6363593e+08 | H34: =H28-H31 -> 1.5780588e+08 | I34: =I28-I31 -> 1.5184465e+08 | J34: =J28-J31 -> 1.4574929e+08 | K34: =K28-K31 -> 1.3951679e+08 | L34: =L28-L31 -> 1.3314405e+08 | M34: =M28-M31 -> 1.2662793e+08 | ... AC34: =AC28-AC31 -> -1.8626451e-08
A36: Total Interest Capitalized | B36: =SUM(B29:E29) -> 10163998
A39: Particulars | B39: 42551 | C39: =EOMONTH(B39,1) -> 42582 | D39: =EOMONTH(C39,1) -> 42613 | E39: =EOMONTH(D39,1) -> 42643 | F39: =EOMONTH(E39,1) -> 42674 | G39: =EOMONTH(F39,1) -> 42704 | H39: =EOMONTH(G39,1) -> 42735 | I39: =EOMONTH(H39,1) -> 42766 | J39: =EOMONTH(I39,1) -> 42794 | ... CH39: =EOMONTH(CG39,1) -> 45107
A40: Total interest accrued | B40: =SUM(Accrual_MAGBL!$B$25) -> 41250 | C40: =SUM(Accrual_MAGBL!$B$25:C25) -> 467500 | D40: =SUM(Accrual_MAGBL!$B$25:D25) -> 893750 | E40: =SUM(Accrual_MAGBL!$B$25:E25) -> 1310595 | F40: =SUM(Accrual_MAGBL!$B$25:F25) -> 1745263.4 | G40: =SUM(Accrual_MAGBL!$B$25:G25) -> 2165910.3 | H40: =SUM(Accrual_MAGBL!$B$25:H25) -> 2916596.6 | I40: =SUM(Accrual_MAGBL!$B$25:I25) -> 3933801.2 | J40: =SUM(Accrual_MAGBL!$B$25:J25) -> 5104566.7 | ... AC40: =SUM(Accrual_MAGBL!$B$25:AC25) -> 28850393 | AD40: =SUM(Accrual_MAGBL!$B$25:AI25) -> 35283472 | AE40: =SUM(Accrual_MAGBL!$B$25:AJ25) -> 36282053 | AF40: =SUM(Accrual_MAGBL!$B$25:AK25) -> 37313919 | AG40: =SUM(Accrual_MAGBL!$B$25:AL25) -> 38283177 | AH40: =SUM(Accrual_MAGBL!$B$25:AM25) -> 39264543 | AI40: =SUM(Accrual_MAGBL!$B$25:AN25) -> 40245910 | AJ40: =SUM(Accrual_MAGBL!$B$25:AO25) -> 41168968 | AK40: =SUM(Accrual_MAGBL!$B$25:AP25) -> 42098699 | ... CB40: =SUM(Accrual_MAGBL!$B$25:CG25) -> 63692955 | CC40: =SUM(Accrual_MAGBL!$B$25:CG25) -> 63692955 | CD40: =SUM(Accrual_MAGBL!$B$25:CG25) -> 63692955 | CE40: =SUM(Accrual_MAGBL!$B$25:CG25) -> 63692955 | CF40: =SUM(Accrual_MAGBL!$B$25:CG25) -> 63692955 | CG40: =SUM(Accrual_MAGBL!$B$25:CG25) -> 63692955 | CH40: =SUM(Accrual_MAGBL!$B$25:CH25) -> 63725514
A41: Total interest capitalized | B41: 0 | C41: 0 | D41: 0 | E41: =SUM($B$29) -> 1086250 | F41: =SUM($B$29) -> 1086250 | G41: =SUM($B$29) -> 1086250 | H41: =SUM($B$29:$C$29) -> 2502212.2 | I41: =SUM($B$29:$C$29) -> 2502212.2 | J41: =SUM($B$29:$C$29) -> 2502212.2 | K41: =SUM($B$29:$D$29) -> 5689949.5 | L41: =SUM($B$29:$D$29) -> 5689949.5 | M41: =SUM($B$29:$D$29) -> 5689949.5 | N41: =SUM($B$29:$E$29) -> 10163998 | O41: =SUM($B$29:$E$29) -> 10163998 | P41: =SUM($B$29:$E$29) -> 10163998 | Q41: =SUM($B$29:$E$29) -> 10163998 | R41: =SUM($B$29:$E$29) -> 10163998 | S41: =SUM($B$29:$E$29) -> 10163998 | T41: =SUM($B$29:$E$29) -> 10163998 | U41: =SUM($B$29:$E$29) -> 10163998 | ... CH41: =SUM($B$29:$E$29) -> 10163998
A42: Net interest accrued | B42: =B40-B41 -> 41250 | C42: =C40-C41 -> 467500 | D42: =D40-D41 -> 893750 | E42: =E40-E41 -> 224345 | F42: =F40-F41 -> 659013.44 | G42: =G40-G41 -> 1079660.3 | H42: =H40-H41 -> 414384.4 | I42: =I40-I41 -> 1431589 | ... CH42: =CH40-CH41 -> 53561516
A43: Total interest received | B43: =Summary!B26 -> 0 | C43: =Summary!C26 -> 0 | D43: =Summary!D26 -> 0 | E43: =Summary!E26 -> 0 | F43: =Summary!F26 -> 0 | G43: =Summary!G26 -> 0 | H43: =Summary!H26 -> 0 | I43: =Summary!I26 -> 0 | ... CH43: =Summary!CH26 -> 53561516
A44: Total interest receivable | B44: =B42-B43 -> 41250 | C44: =C42-C43 -> 467500 | D44: =D42-D43 -> 893750 | E44: =E42-E43 -> 224345 | F44: =F42-F43 -> 659013.44 | G44: =G42-G43 -> 1079660.3 | H44: =H42-H43 -> 414384.4 | I44: =I42-I43 -> 1431589 | ... CH44: =CH42-CH43 -> 0
A47: Agency Fee
A48: Date | B48: 42832 | C48: =EDATE(B48,12) -> 43197 | D48: =EDATE(C48,12) -> 43562 | E48: =EDATE(D48,12) -> 43928 | F48: =EDATE(E48,12) -> 44293 | G48: =EDATE(F48,12) -> 44658 | H48: =EDATE(G48,12) -> 45023
A49: Amount (BDT) | B49: 150000 | C49: 150000 | D49: 150000 | E49: 150000 | F49: 150000 | G49: 150000 | H49: 150000
A51: Average Installment Size | B51: =B27 -> 42628 | C51: =C27 -> 42719 | D51: =D27 -> 42809 | E51: =E27 -> 42914 | F51: =F27 -> 42992 | G51: =G27 -> 43083 | H51: =H27 -> 43174 | I51: =I27 -> 43265 | ... AC51: =AC27 -> 45092
B52: =AVERAGE($F$33) -> 8987121.3 | C52: =AVERAGE($F$33) -> 8987121.3 | D52: =AVERAGE($F$33) -> 8987121.3 | E52: =AVERAGE($F$33) -> 8987121.3 | F52: =AVERAGE($F$33) -> 8987121.3 | G52: =AVERAGE($F$33:G33) -> 9270659.5 | H52: =AVERAGE($F$33:H33) -> 9364697.1 | I52: =AVERAGE($F$33:I33) -> 9411351.5 | J52: =AVERAGE($F$33:J33) -> 9439046.1 | K52: =AVERAGE($F$33:K33) -> 9457255.2 | L52: =AVERAGE($F$33:L33) -> 9470039.1 | M52: =AVERAGE($F$33:M33) -> 9479427.8 | N52: =AVERAGE($F$33:N33) -> 9497101.5 | ... AC52: =AVERAGE($F$33:AC33) -> 9519813.1

Sheet Accrual_MAGBL
A1: Project name: | B1: ='MAGBL_Loan (IDCOL)'!C1 -> Makrail Auto Green Bricks Limited (MAGBL)
A3: Assumptions:
A5: Agreement signing date | B5: ='MAGBL_Loan (IDCOL)'!C3 -> 42467
A7: Loan Amount | B7: ='MAGBL_Loan (IDCOL)'!C5 -> 175000000 | C7: BDT
A9: Interest Rate | B9: ='MAGBL_Loan (IDCOL)'!C8 -> 0.09
A10: Tenor | B10: 7 years
A11: Interest calculation | B11: 360 | C11: days basis
A12: Principal | B12: ='MAGBL_Loan (IDCOL)'!C11 -> Level Principal
A14: Drawdown
C15: ='MAGBL_Loan (IDCOL)'!C16 -> 42549 | D15: ='MAGBL_Loan (IDCOL)'!D16 -> 42705 | E15: ='MAGBL_Loan (IDCOL)'!E16 -> 42752
C16: ='MAGBL_Loan (IDCOL)'!C17 -> 55000000 | D16: ='MAGBL_Loan (IDCOL)'!D17 -> 40000000 | E16: ='MAGBL_Loan (IDCOL)'!E17 -> 69750000
C17: =C16 -> 55000000 | D17: =C17+D16 -> 95000000 | E17: =D17+E16 -> 164750000
A19: Period | B19: 42536 | C19: =EDATE(B19,1) -> 42566 | D19: =EDATE(C19,1) -> 42597 | E19: =EDATE(D19,1) -> 42628 | F19: =EDATE(E19,1) -> 42658 | G19: =EDATE(F19,1) -> 42689 | H19: =EDATE(G19,1) -> 42719 | I19: =EDATE(H19,1) -> 42750 | J19: =EDATE(I19,1) -> 42781 | ... CH19: =EDATE(CG19,1) -> 45092
A20: Expected Interest Rate | B20: 0.09 | C20: 0.09 | D20: 0.09 | E20: 0.09 | F20: 0.09 | G20: 0.09 | H20: 0.09 | I20: 0.09 | J20: 0.09 | K20: 0.09 | L20: 0.09 | M20: 0.09 | N20: 0.09 | O20: 0.09 | P20: 0.09 | Q20: 0.09 | R20: 0.09 | S20: 0.09 | T20: 0.09 | U20: 0.09 | V20: 0.09 | W20: 0.09 | X20: 0.09 | Y20: 0.09 | Z20: 0.09 | AA20: 0.09 | AB20: 0.09 | AC20: 0.09 | AD20: 0.09 | AE20: 0.09 | AF20: 0.09 | AG20: 0.09 | AH20: 0.09 | AI20: 0.09 | AJ20: 0.09 | AK20: 0.09 | AL20: 0.09 | AM20: 0.09 | AN20: 0.09 | AO20: 0.09 | AP20: 0.09 | AQ20: 0.09 | AR20: 0.09 | AS20: 0.09 | AT20: 0.09 | AU20: 0.09 | AV20: 0.09 | AW20: 0.09 | AX20: 0.09 | AY20: 0.09 | AZ20: 0.09 | BA20: 0.09 | BB20: 0.09 | BC20: 0.09 | BD20: 0.09 | BE20: 0.09 | BF20: 0.09 | BG20: 0.09 | BH20: 0.09 | BI20: 0.09 | BJ20: 0.09 | BK20: 0.09 | BL20: 0.09 | BM20: 0.09 | BN20: 0.09 | BO20: 0.09 | BP20: 0.09 | BQ20: 0.09 | BR20: 0.09 | BS20: 0.09 | BT20: 0.09 | BU20: 0.09 | BV20: 0.09 | BW20: 0.09 | BX20: 0.09 | BY20: 0.09 | BZ20: 0.09 | CA20: 0.09 | CB20: 0.09 | CC20: 0.09 | CD20: 0.09 | CE20: 0.09 | CF20: 0.09 | CG20: 0.09 | CH20: 0.09
A22: Accrual of interest
A23: Months | B23: 42552 | C23: =EDATE(B23,1) -> 42583 | D23: =EDATE(C23,1) -> 42614 | E23: =EDATE(D23,1) -> 42644 | F23: =EDATE(E23,1) -> 42675 | G23: =EDATE(F23,1) -> 42705 | H23: =EDATE(G23,1) -> 42736 | I23: =EDATE(H23,1) -> 42767 | J23: =EDATE(I23,1) -> 42795 | ... CH23: =EDATE(CG23,1) -> 45108
A24: Opening Balance | B24: =C17 -> 55000000 | C24: =B30 -> 55000000 | D24: =C30 -> 55000000 | E24: =D30 -> 55000000 | F24: =E30 -> 56086250 | G24: =F30 -> 56086250 | H24: =G30+D16 -> 96086250 | I24: =H30+E16 -> 1.6725221e+08 | J24: =I30 -> 1.6725221e+08 | K24: =J30 -> 1.6725221e+08 | L24: =K30 -> 1.7043995e+08 | M24: =L30 -> 1.7043995e+08 | N24: =M30 -> 1.7043995e+08 | O24: =N30 -> 1.74914e+08 | P24: =O30 -> 1.74914e+08 | Q24: =P30 -> 1.74914e+08 | ... CH24: =CG30 -> 9302555.8
A25: Interest Payment | B25: =C17*(B23-C15)*B20/360 -> 41250 | C25: =C24*(C23-B23)*C20/360 -> 426250 | D25: =D24*(D23-C23)*D20/360 -> 426250 | E25: =E24*('MAGBL_Loan (IDCOL)'!$B$27-D23)*D20/360+E30*(E23-'MAGBL_Loan (IDCOL)'!$B$27)*E20/360 -> 416845 | F25: =F24*(F23-E23)*F20/360 -> 434668.44 | G25: =G24*(G23-F23)*G20/360 -> 420646.88 | H25: =H24*('MAGBL_Loan (IDCOL)'!$C$27-D15)*H20/360+H30*(H23-'MAGBL_Loan (IDCOL)'!$C$27)*H20/360 -> 750686.28 | I25: =H30*(E15-H23)*H20/360+(H30+E16)*(I23-E15)*I20/360 -> 1017204.6 | J25: =J24*(J23-I23)*J20/360 -> 1170765.5 | K25: =K24*('MAGBL_Loan (IDCOL)'!$D$27-J23)*J20/360+K30*(K23-'MAGBL_Loan (IDCOL)'!$D$27)*K20/360 -> 1309752.5 | L25: =L24*(L23-K23)*L20/360 -> 1278299.6 | M25: =M24*(M23-L23)*M20/360 -> 1320909.6 | N25: =N24*('MAGBL_Loan (IDCOL)'!$E$27-M23)*M20/360+N30*(N23-'MAGBL_Loan (IDCOL)'!$E$27)*N20/360 -> 1281655.2 | O25: =O24*(O23-N23)*O20/360 -> 1355583.5 | P25: =P24*(P23-O23)*P20/360 -> 1355583.5 | Q25: =Q24*('MAGBL_Loan (IDCOL)'!$F$27-P23)*P20/360+Q30*(Q23-'MAGBL_Loan (IDCOL)'!$F$27)*Q20/360 -> 1288155.7 | R25: =R24*(R23-Q23)*R20/360 -> 1312367.2 | S25: =S24*(S23-R23)*S20/360 -> 1270032.7 | T25: =T24*('MAGBL_Loan (IDCOL)'!$G$27-S23)*S20/360+T30*(T23-'MAGBL_Loan (IDCOL)'!$G$27)*T20/360 -> 1286709.2 | U25: =U24*(U23-T23)*U20/360 -> 1268178.5 | V25: =V24*(V23-U23)*V20/360 -> 1145451.5 | W25: =W24*('MAGBL_Loan (IDCOL)'!$H$27-V23)*V20/360+W30*(W23-'MAGBL_Loan (IDCOL)'!$H$27)*W20/360 -> 1243400.8 | X25: =X24*(X23-W23)*X20/360 -> 1183544.1 | Y25: =Y24*(Y23-X23)*Y20/360 -> 1222995.6 | Z25: =Z24*('MAGBL_Loan (IDCOL)'!$I$27-Y23)*Y20/360+Z30*(Z23-'MAGBL_Loan (IDCOL)'!$I$27)*Z20/360 -> 1158208.9 | AA25: =AA24*(AA23-Z23)*AA20/360 -> 1176796 | AB25: =AB24*(AB23-AA23)*AB20/360 -> 1176796 | AC25: =AC24*('MAGBL_Loan (IDCOL)'!$J$27-AB23)*AB20/360+AC30*(AC23-'MAGBL_Loan (IDCOL)'!$J$27)*AC20/360 -> 1111405.8 | AD25: =AD24*(AD23-AC23)*AD20/360 -> 1129557 | AE25: =AE24*(AE23-AD23)*AE20/360 -> 1093119.7 | AF25: =AF24*('MAGBL_Loan (IDCOL)'!$K$27-AE23)*AE20/360+AF30*(AF23-'MAGBL_Loan (IDCOL)'!$K$27)*AF20/360 -> 1099952.6 | AG25: =AG24*(AG23-AF23)*AG20/360 -> 1081255.1 | AH25: =AH24*(AH23-AG23)*AH20/360 -> 976617.5 | AI25: =AI24*('MAGBL_Loan (IDCOL)'!$L$27-AH23)*AH20/360+AI30*(AI23-'MAGBL_Loan (IDCOL)'!$L$27)*AI20/360 -> 1052577.8 | AJ25: =AJ24*(AJ23-AI23)*AJ20/360 -> 998580.38 | AK25: =AK24*(AK23-AJ23)*AK20/360 -> 1031866.4 | AL25: =AL24*('MAGBL_Loan (IDCOL)'!$M$27-AK23)*AK20/360+AL30*(AL23-'MAGBL_Loan (IDCOL)'!$M$27)*AL20/360 -> 969257.83 | AM25: =AM24*(AM23-AL23)*AM20/360 -> 981366.45 | AN25: =AN24*(AN23-AM23)*AN20/360 -> 981366.45 | AO25: =AO24*('MAGBL_Loan (IDCOL)'!$N$27-AN23)*AN20/360+AO30*(AO23-'MAGBL_Loan (IDCOL)'!$N$27)*AO20/360 -> 923058.52 | AP25: =AP24*(AP23-AO23)*AP20/360 -> 929730.25 | AQ25: =AQ24*(AQ23-AP23)*AQ20/360 -> 899738.95 | AR25: =AR24*('MAGBL_Loan (IDCOL)'!$O$27-AQ23)*AQ20/360+AR30*(AR23-'MAGBL_Loan (IDCOL)'!$O$27)*AR20/360 -> 900776.5 | AS25: =AS24*(AS23-AR23)*AS20/360 -> 876932.24 | AT25: =AT24*(AT23-AS23)*AT20/360 -> 820355.97 | AU25: =AU24*('MAGBL_Loan (IDCOL)'!$P$27-AT23)*AT20/360+AU30*(AU23-'MAGBL_Loan (IDCOL)'!$P$27)*AU20/360 -> 847327.04 | AV25: =AV24*(AV23-AU23)*AV20/360 -> 796399.62 | AW25: =AW24*(AW23-AV23)*AW20/360 -> 822946.28 | AX25: =AX24*('MAGBL_Loan (IDCOL)'!$Q$27-AW23)*AW20/360+AX30*(AX23-'MAGBL_Loan (IDCOL)'!$Q$27)*AX20/360 -> 767908.97 | AY25: =AY24*(AY23-AX23)*AY20/360 -> 767745.63 | AZ25: =AZ24*(AZ23-AY23)*AZ20/360 -> 767745.63 | BA25: =BA24*('MAGBL_Loan (IDCOL)'!$R$27-AZ23)*AZ20/360+BA30*(BA23-'MAGBL_Loan (IDCOL)'!$R$27)*BA20/360 -> 713847.94 | BB25: =BB24*(BB23-BA23)*BB20/360 -> 711302.96 | BC25: =BC24*(BC23-BB23)*BC20/360 -> 688357.71 | BD25: =BD24*('MAGBL_Loan (IDCOL)'!$S$27-BC23)*BC20/360+BD30*(BD23-'MAGBL_Loan (IDCOL)'!$S$27)*BD20/360 -> 679654.11 | BE25: =BE24*(BE23-BD23)*BE20/360 -> 653590.34 | BF25: =BF24*(BF23-BE23)*BF20/360 -> 590339.66 | BG25: =BG24*('MAGBL_Loan (IDCOL)'!$T$27-BF23)*BF20/360+BG30*(BG23-'MAGBL_Loan (IDCOL)'!$T$27)*BG20/360 -> 621229.38 | BH25: =BH24*(BH23-BG23)*BH20/360 -> 575399.21 | BI25: =BI24*(BI23-BH23)*BI20/360 -> 594579.18 | BJ25: =BJ24*('MAGBL_Loan (IDCOL)'!$U$27-BI23)*BI20/360+BJ30*(BJ23-'MAGBL_Loan (IDCOL)'!$U$27)*BJ20/360 -> 544256.55 | BK25: =BK24*(BK23-BJ23)*BK20/360 -> 534240.27 | BL25: =BL24*(BL23-BK23)*BL20/360 -> 534240.27 | BM25: =BM24*('MAGBL_Loan (IDCOL)'!$V$27-BL23)*BL20/360+BM30*(BM23-'MAGBL_Loan (IDCOL)'!$V$27)*BM20/360 -> 485163.34 | BN25: =BN24*(BN23-BM23)*BN20/360 -> 472543.74 | BO25: =BO24*(BO23-BN23)*BO20/360 -> 457300.39 | BP25: =BP24*('MAGBL_Loan (IDCOL)'!$W$27-BO23)*BO20/360+BP30*(BP23-'MAGBL_Loan (IDCOL)'!$W$27)*BP20/360 -> 437948.9 | BQ25: =BQ24*(BQ23-BP23)*BQ20/360 -> 409459.03 | BR25: =BR24*(BR23-BQ23)*BR20/360 -> 369833.97 | BS25: =BS24*('MAGBL_Loan (IDCOL)'!$X$27-BR23)*BR20/360+BS30*(BS23-'MAGBL_Loan (IDCOL)'!$X$27)*BS20/360 -> 374085.81 | BT25: =BT24*(BT23-BS23)*BT20/360 -> 333827.34 | BU25: =BU24*(BU23-BT23)*BU20/360 -> 344954.92 | BV25: =BV24*('MAGBL_Loan (IDCOL)'!$Y$27-BU23)*BU20/360+BV30*(BV23-'MAGBL_Loan (IDCOL)'!$Y$27)*BV20/360 -> 299785.82 | BW25: =BW24*(BW23-BV23)*BW20/360 -> 278999.47 | BX25: =BX24*(BX23-BW23)*BX20/360 -> 278999.47 | BY25: =BY24*('MAGBL_Loan (IDCOL)'!$Z$27-BX23)*BX20/360+BY30*(BY23-'MAGBL_Loan (IDCOL)'!$Z$27)*BY20/360 -> 235192.03 | BZ25: =BZ24*(BZ23-BY23)*BZ20/360 -> 211560.02 | CA25: =CA24*(CA23-BZ23)*CA20/360 -> 204735.5 | CB25: =CB24*('MAGBL_Loan (IDCOL)'!$AA$27-CA23)*CA20/360+CB30*(CB23-'MAGBL_Loan (IDCOL)'!$AA$27)*CB20/360 -> 173744.97 | CC25: =CC24*(CC23-CB23)*CC20/360 -> 142603.18 | CD25: =CD24*(CD23-CC23)*CD20/360 -> 128802.87 | CE25: =CE24*('MAGBL_Loan (IDCOL)'!$AB$27-CD23)*CD20/360+CE30*(CE23-'MAGBL_Loan (IDCOL)'!$AB$27)*CE20/360 -> 103937.3 | CF25: =CF24*(CF23-CE23)*CF20/360 -> 69769.168 | CG25: =CG24*(CG23-CF23)*CG20/360 -> 72094.807 | CH25: =CH24*('MAGBL_Loan (IDCOL)'!$AC$27-CG23)*CG20/360+CH30*(CH23-'MAGBL_Loan (IDCOL)'!$AC$27)*CH20/360 -> 32558.945
A26: Cumulative interest | B26: =B25 -> 41250 | C26: =B26+C25 -> 467500 | D26: =C26+D25 -> 893750 | E26: =D26+E25 -> 1310595 | F26: =E26+F25 -> 1745263.4 | G26: =F26+G25 -> 2165910.3 | H26: =G26+H25 -> 2916596.6 | I26: =H26+I25 -> 3933801.2 | J26: =I26+J25 -> 5104566.7 | ... CH26: =CG26+CH25 -> 63725514
A27: Principal Payment | B27: 0 | C27: 0 | D27: 0 | E27: 0 | F27: 0 | G27: 0 | H27: 0 | I27: 0 | J27: 0 | K27: 0 | L27: 0 | M27: 0 | N27: 0 | O27: 0 | P27: 0 | Q27: ='MAGBL_Loan (IDCOL)'!$F$31 -> 5576298.3 | R27: =O27 -> 0 | S27: =P27 -> 0 | T27: ='MAGBL_Loan (IDCOL)'!$G$31 -> 5701765 | U27: =R27 -> 0 | V27: =S27 -> 0 | W27: ='MAGBL_Loan (IDCOL)'!$H$31 -> 5830054.7 | X27: =U27 -> 0 | Y27: =V27 -> 0 | Z27: ='MAGBL_Loan (IDCOL)'!$I$31 -> 5961231 | AA27: =X27 -> 0 | AB27: =Y27 -> 0 | AC27: ='MAGBL_Loan (IDCOL)'!$J$31 -> 6095358.7 | AD27: =AA27 -> 0 | AE27: =AB27 -> 0 | AF27: ='MAGBL_Loan (IDCOL)'!$K$31 -> 6232504.2 | AG27: =AD27 -> 0 | AH27: =AE27 -> 0 | AI27: ='MAGBL_Loan (IDCOL)'!$L$31 -> 6372735.6 | AJ27: =AG27 -> 0 | AK27: =AH27 -> 0 | AL27: ='MAGBL_Loan (IDCOL)'!$M$31 -> 6516122.1 | AM27: =AJ27 -> 0 | AN27: =AK27 -> 0 | AO27: ='MAGBL_Loan (IDCOL)'!$N$31 -> 6662734.9 | AP27: =AM27 -> 0 | AQ27: =AN27 -> 0 | AR27: ='MAGBL_Loan (IDCOL)'!$O$31 -> 6812646.4 | AS27: =AP27 -> 0 | AT27: =AQ27 -> 0 | AU27: ='MAGBL_Loan (IDCOL)'!$P$31 -> 6965930.9 | AV27: =AS27 -> 0 | AW27: =AT27 -> 0 | AX27: ='MAGBL_Loan (IDCOL)'!$Q$31 -> 7122664.4 | AY27: =AV27 -> 0 | AZ27: =AW27 -> 0 | BA27: ='MAGBL_Loan (IDCOL)'!$R$31 -> 7282924.3 | BB27: =AY27 -> 0 | BC27: =AZ27 -> 0 | BD27: ='MAGBL_Loan (IDCOL)'!$S$31 -> 7446790.1 | BE27: =BB27 -> 0 | BF27: =BC27 -> 0 | BG27: ='MAGBL_Loan (IDCOL)'!$T$31 -> 7614342.9 | BH27: =BE27 -> 0 | BI27: =BF27 -> 0 | BJ27: ='MAGBL_Loan (IDCOL)'!$U$31 -> 7785665.6 | BK27: =BH27 -> 0 | BL27: =BI27 -> 0 | BM27: ='MAGBL_Loan (IDCOL)'!$V$31 -> 7960843.1 | BN27: =BK27 -> 0 | BO27: =BL27 -> 0 | BP27: ='MAGBL_Loan (IDCOL)'!$W$31 -> 8139962.1 | BQ27: =BN27 -> 0 | BR27: =BO27 -> 0 | BS27: ='MAGBL_Loan (IDCOL)'!$X$31 -> 8323111.2 | BT27: =BQ27 -> 0 | BU27: =BR27 -> 0 | BV27: ='MAGBL_Loan (IDCOL)'!$Y$31 -> 8510381.2 | BW27: =BT27 -> 0 | BX27: =BU27 -> 0 | BY27: ='MAGBL_Loan (IDCOL)'!$Z$31 -> 8701864.8 | BZ27: =BW27 -> 0 | CA27: =BX27 -> 0 | CB27: ='MAGBL_Loan (IDCOL)'!$AA$31 -> 8897656.8 | CC27: =BZ27 -> 0 | CD27: =CA27 -> 0 | CE27: ='MAGBL_Loan (IDCOL)'!$AB$31 -> 9097854 | CF27: =CC27 -> 0 | CG27: =CD27 -> 0 | CH27: ='MAGBL_Loan (IDCOL)'!$AC$31 -> 9302555.8
A28: Cumulative repayment | B28: =B27 -> 0 | C28: =B28+C27 -> 0 | D28: =C28+D27 -> 0 | E28: =D28+E27 -> 0 | F28: =E28+F27 -> 0 | G28: =F28+G27 -> 0 | H28: =G28+H27 -> 0 | I28: =H28+I27 -> 0 | J28: =I28+J27 -> 0 | ... CH28: =CG28+CH27 -> 1.74914e+08
A29: Total Debt Service | B29: =B27+B25 -> 41250 | C29: =C27+C25 -> 426250 | D29: =D27+D25 -> 426250 | E29: =E27+E25 -> 416845 | F29: =F27+F25 -> 434668.44 | G29: =G27+G25 -> 420646.88 | H29: =H27+H25 -> 750686.28 | I29: =I27+I25 -> 1017204.6 | ... CH29: =CH27+CH25 -> 9335114.7
A30: Closing Balance | B30: =B24-B27 -> 55000000 | C30: =C24-C27 -> 55000000 | D30: =D24-D27 -> 55000000 | E30: ='MAGBL_Loan (IDCOL)'!B34 -> 56086250 | F30: =F24-F27 -> 56086250 | G30: =G24-G27 -> 56086250 | H30: ='MAGBL_Loan (IDCOL)'!C34 -> 97502212 | I30: =I24-I27 -> 1.6725221e+08 | J30: =J24-J27 -> 1.6725221e+08 | K30: ='MAGBL_Loan (IDCOL)'!D34 -> 1.7043995e+08 | L30: =L24-L27 -> 1.7043995e+08 | M30: =M24-M27 -> 1.7043995e+08 | N30: ='MAGBL_Loan (IDCOL)'!E34 -> 1.74914e+08 | O30: =O24-O27 -> 1.74914e+08 | P30: =P24-P27 -> 1.74914e+08 | Q30: =Q24-Q27 -> 1.693377e+08 | R30: =R24-R27 -> 1.693377e+08 | S30: =S24-S27 -> 1.693377e+08 | T30: =T24-T27 -> 1.6363593e+08 | U30: =U24-U27 -> 1.6363593e+08 | V30: =V24-V27 -> 1.6363593e+08 | ... CH30: =CH24-CH27 -> -1.8626451e-08
CH32: =CH26-SUM('MAGBL_Loan (IDCOL)'!B29:AC29) -> 0

Sheet Repayment Schedule
A1: Project name: | C1: ='MAGBL_Loan (IDCOL)'!C1 -> Makrail Auto Green Bricks Limited (MAGBL)
A3: Agreement signing date | C3: ='MAGBL_Loan (IDCOL)'!C3 -> 42467
A5: Loan Amount | C5: ='MAGBL_Loan (IDCOL)'!C5 -> 175000000
A7: Interest Rate | C7: ='MAGBL_Loan (IDCOL)'!C8 -> 0.09
A9: Number of installments | C9: ='MAGBL_Loan (IDCOL)'!C13 -> 24
A11: Drawdown (IDCOL)
C12: ='MAGBL_Loan (IDCOL)'!C16 -> 42549 | D12: ='MAGBL_Loan (IDCOL)'!D16 -> 42705 | E12: ='MAGBL_Loan (IDCOL)'!E16 -> 42752
C13: ='MAGBL_Loan (IDCOL)'!C17 -> 55000000 | D13: ='MAGBL_Loan (IDCOL)'!D17 -> 40000000 | E13: ='MAGBL_Loan (IDCOL)'!E17 -> 69750000
C14: ='MAGBL_Loan (IDCOL)'!C18 -> 55000000 | D14: ='MAGBL_Loan (IDCOL)'!D18 -> 95000000 | E14: ='MAGBL_Loan (IDCOL)'!E18 -> 164750000
A16: Repayment Date | B16: Opening Balance | C16: Interest Payment | D16: Cumulative interest | E16: Principal Payment | F16: Cumulative repayment | G16: Total Debt Service | H16: Closing Balance
A17: {=TRANSPOSE('MAGBL_Loan (IDCOL)'!B27:AC34)} -> 42628 | B17: 55000000 | C17: 1086250 | D17: 0 | E17: 0 | F17: 0 | G17: 0 | H17: 56086250
A18: 42719 | B18: 96086250 | C18: 1415962.2 | D18: 0 | E18: 0 | F18: 0 | G18: 0 | H18: 97502212
A19: 42809 | B19: 1.6725221e+08 | C19: 3187737.3 | D19: 0 | E19: 0 | F19: 0 | G19: 0 | H19: 1.7043995e+08
A20: 42914 | B20: 1.7043995e+08 | C20: 4474048.7 | D20: 0 | E20: 0 | F20: 0 | G20: 0 | H20: 1.74914e+08
A21: 42992 | B21: 1.74914e+08 | C21: 3410823 | D21: 3410823 | E21: 5576298.3 | F21: 5576298.3 | G21: 8987121.3 | H21: 1.693377e+08
A22: 43083 | B22: 1.693377e+08 | C22: 3852432.7 | D22: 7263255.6 | E22: 5701765 | F22: 11278063 | G22: 9554197.7 | H22: 1.6363593e+08
A23: 43174 | B23: 1.6363593e+08 | C23: 3722717.5 | D23: 10985973 | E23: 5830054.7 | F23: 17108118 | G23: 9552772.2 | H23: 1.5780588e+08
A24: 43265 | B24: 1.5780588e+08 | C24: 3590083.8 | D24: 14576057 | E24: 5961231 | F24: 23069349 | G24: 9551314.7 | H24: 1.5184465e+08
A25: 43356 | B25: 1.5184465e+08 | C25: 3454465.8 | D25: 18030523 | E25: 6095358.7 | F25: 29164708 | G25: 9549824.4 | H25: 1.4574929e+08
A26: 43447 | B26: 1.4574929e+08 | C26: 3315796.4 | D26: 21346319 | E26: 6232504.2 | F26: 35397212 | G26: 9548300.6 | H26: 1.3951679e+08
A27: 43538 | B27: 1.3951679e+08 | C27: 3174006.9 | D27: 24520326 | E27: 6372735.6 | F27: 41769947 | G27: 9546742.5 | H27: 1.3314405e+08
A28: 43629 | B28: 1.3314405e+08 | C28: 3029027.2 | D28: 27549353 | E28: 6516122.1 | F28: 48286070 | G28: 9545149.3 | H28: 1.2662793e+08
A29: 43723 | B29: 1.2662793e+08 | C29: 2975756.3 | D29: 30525109 | E29: 6662734.9 | F29: 54948804 | G29: 9638491.2 | H29: 1.1996519e+08
... A44: 45092 | B44: 9302555.8 | C44: 213958.78 | D44: 53561516 | E44: 9302555.8 | F44: 1.74914e+08 | G44: 9516514.5 | H44: -1.8626451e-08

Sheet MAGBL_Loan (BIFFL)
A1: Project name: | C1: =Disbursement!B1 -> Makrail Auto Green Bricks Limited (MAGBL)
A3: Agreement signing date | C3: 42467
A5: Loan Amount | C5: 175000000
A7: Payment frequency | C7: Quarterly
A8: Interest Rate | C8: 0.09
A9: Maturity date | C9: 84 | D9: months
A10: Moratorium period (interest and principal) | C10: 12 | D10: months
A11: Principal | C11: Level Principal
A12: Interest calculation | C12: 360 | D12: days basis
A13: Number of installments | C13: 24
A15: Drawdown
C16: 42549 | D16: 42695 | E16: 42753
C17: 55000000 | D17: 40000000 | E17: 69750000
C18: =C17 -> 55000000 | D18: =C18+D17 -> 95000000 | E18: =D18+E17 -> 164750000
A21: Period | B21: =B27 -> 42628 | C21: =C27 -> 42719 | D21: =D27 -> 42809 | E21: =E27 -> 42914 | F21: =F27 -> 42992 | G21: =G27 -> 43083 | H21: =H27 -> 43174 | I21: =I27 -> 43265 | ... AC21: =AC27 -> 45092
A22: Expected Interest Rate | B22: 0.09 | C22: 0.09 | D22: 0.09 | E22: 0.09 | F22: 0.09 | G22: 0.09 | H22: 0.09 | I22: 0.09 | J22: 0.09 | K22: 0.09 | L22: 0.09 | M22: 0.09 | N22: 0.09 | O22: 0.09 | P22: 0.09 | Q22: 0.09 | R22: 0.09 | S22: 0.09 | T22: 0.09 | U22: 0.09 | V22: 0.09 | W22: 0.09 | X22: 0.09 | Y22: 0.09 | Z22: 0.09 | AA22: 0.09 | AB22: 0.09 | AC22: 0.09
A25: Repayment | B25: Interest Capitalized
A26: Repayment Period | F26: 1 | G26: =F26+1 -> 2 | H26: =G26+1 -> 3 | I26: =H26+1 -> 4 | J26: =I26+1 -> 5 | K26: =J26+1 -> 6 | L26: =K26+1 -> 7 | M26: =L26+1 -> 8 | N26: =M26+1 -> 9 | ... AC26: =AB26+1 -> 24
A27: Repayment Date | B27: ='MAGBL_Loan (IDCOL)'!B27 -> 42628 | C27: ='MAGBL_Loan (IDCOL)'!C27 -> 42719 | D27: ='MAGBL_Loan (IDCOL)'!D27 -> 42809 | E27: ='MAGBL_Loan (IDCOL)'!E27 -> 42914 | F27: ='MAGBL_Loan (IDCOL)'!F27 -> 42992 | G27: ='MAGBL_Loan (IDCOL)'!G27 -> 43083 | H27: ='MAGBL_Loan (IDCOL)'!H27 -> 43174 | I27: ='MAGBL_Loan (IDCOL)'!I27 -> 43265 | ... AC27: ='MAGBL_Loan (IDCOL)'!AC27 -> 45092
A28: Opening Balance | B28: =C17 -> 55000000 | C28: =B34+D17 -> 96086250 | D28: =C34+E17 -> 1.6735221e+08 | E28: =D34 -> 1.7052476e+08 | F28: =E34 -> 1.7500104e+08 | G28: =F34 -> 1.6942196e+08 | H28: =G34 -> 1.6371736e+08 | I28: =H34 -> 1.5788441e+08 | J28: =I34 -> 1.5192021e+08 | K28: =J34 -> 1.4582182e+08 | L28: =K34 -> 1.3958621e+08 | ... AC28: =AB34 -> 9307184.8
A29: Interest Payment | B29: =C18*(B27-C16)*B22/360 -> 1086250 | C29: =B34*(D16-B27)*C22/360+C28*(C27-D16)*C22/360 -> 1515962.2 | D29: =C34*(E16-C27)*D22/360+(C34+E17)*(D27-E16)*D22/360 -> 3172549.8 | E29: =E28*(E27-D27)*E22/360 -> 4476275 | F29: =F28*(F27-E27)*F22/360 -> 3412520.2 | G29: =G28*(G27-F27)*G22/360 -> 3854349.7 | H29: =H28*(H27-G27)*H22/360 -> 3724570 | I29: =I28*(I27-H27)*I22/360 -> 3591870.2 | J29: =J28*(J27-I27)*J22/360 -> 3456184.7 | K29: =K28*(K27-J27)*K22/360 -> 3317446.3 | L29: =L28*(L27-K27)*L22/360 -> 3175586.3 | ... AC29: =AC28*(AC27-AB27)*AC22/360 -> 214065.25
A30: Cumulative interest | B30: 0 | C30: 0 | D30: 0 | E30: 0 | F30: =F29+E30 -> 3412520.2 | G30: =G29+F30 -> 7266869.9 | H30: =H29+G30 -> 10991440 | I30: =I29+H30 -> 14583310 | J30: =J29+I30 -> 18039495 | K30: =K29+J30 -> 21356941 | L30: =L29+K30 -> 24532527 | M30: =M29+L30 -> 27563062 | ... AC30: =AC29+AB30 -> 53588169
A31: Principal Payment | B31: 0 | C31: 0 | D31: 0 | E31: 0 | F31: =-PPMT(F22/4,F26,$C$13,$F$28) -> 5579073.1 | G31: =-PPMT(G22/4,G26,$C$13,$F$28) -> 5704602.3 | H31: =-PPMT(H22/4,H26,$C$13,$F$28) -> 5832955.8 | I31: =-PPMT(I22/4,I26,$C$13,$F$28) -> 5964197.3 | J31: =-PPMT(J22/4,J26,$C$13,$F$28) -> 6098391.8 | K31: =-PPMT(K22/4,K26,$C$13,$F$28) -> 6235605.6 | L31: =-PPMT(L22/4,L26,$C$13,$F$28) -> 6375906.7 | M31: =-PPMT(M22/4,M26,$C$13,$F$28) -> 6519364.6 | ... AC31: =-PPMT(AC22/4,AC26,$C$13,$F$28) -> 9307184.8
A32: Cumulative repayment | B32: 0 | C32: =C31+B32 -> 0 | D32: =D31+C32 -> 0 | E32: =E31+D32 -> 0 | F32: =F31+E32 -> 5579073.1 | G32: =G31+F32 -> 11283675 | H32: =H31+G32 -> 17116631 | I32: =I31+H32 -> 23080829 | J32: =J31+I32 -> 29179220 | ... AC32: =AC31+AB32 -> 1.7500104e+08
A33: Total Debt Service | B33: 0 | C33: 0 | D33: 0 | E33: 0 | F33: =F29+F31 -> 8991593.3 | G33: =G29+G31 -> 9558951.9 | H33: =H29+H31 -> 9557525.8 | I33: =I29+I31 -> 9556067.6 | J33: =J29+J31 -> 9554576.5 | K33: =K29+K31 -> 9553051.9 | L33: =L29+L31 -> 9551493 | M33: =M29+M31 -> 9549899 | ... AC33: =AC29+AC31 -> 9521250
A34: Closing Balance | B34: =B28+B29 -> 56086250 | C34: =C28+C29 -> 97602212 | D34: =D28+D29 -> 1.7052476e+08 | E34: =E28+E29 -> 1.7500104e+08 | F34: =F28-F31 -> 1.6942196e+08 | G34: =G28-G31 -> 1.6371736e+08 | H34: =H28-H31 -> 1.5788441e+08 | I34: =I28-I31 -> 1.5192021e+08 | J34: =J28-J31 -> 1.4582182e+08 | K34: =K28-K31 -> 1.3958621e+08 | L34: =L28-L31 -> 1.332103e+08 | M34: =M28-M31 -> 1.2669094e+08 | ... AC34: =AC28-AC31 -> 1.4901161e-08
A36: Total Interest Capitalized | B36: =SUM(B29:E29) -> 10251037

Sheet Repayment Schedule (BIFFL)
A1: Project name: | C1: ='MAGBL_Loan (IDCOL)'!C1 -> Makrail Auto Green Bricks Limited (MAGBL)
A3: Agreement signing date | C3: ='MAGBL_Loan (IDCOL)'!C3 -> 42467
A5: Loan Amount | C5: ='MAGBL_Loan (IDCOL)'!C5 -> 175000000
A7: Interest Rate | C7: ='MAGBL_Loan (IDCOL)'!C8 -> 0.09
A9: Number of installments | C9: ='MAGBL_Loan (IDCOL)'!C13 -> 24
A11: Drawdown (BIFFL)
C12: ='MAGBL_Loan (BIFFL)'!C16 -> 42549 | D12: ='MAGBL_Loan (BIFFL)'!D16 -> 42695 | E12: ='MAGBL_Loan (BIFFL)'!E16 -> 42753
C13: ='MAGBL_Loan (BIFFL)'!C17 -> 55000000 | D13: ='MAGBL_Loan (BIFFL)'!D17 -> 40000000 | E13: ='MAGBL_Loan (BIFFL)'!E17 -> 69750000
C14: ='MAGBL_Loan (IDCOL)'!C18 -> 55000000 | D14: =D13+C14 -> 95000000 | E14: =E13+D14 -> 164750000
A16: Repayment Date | B16: Opening Balance | C16: Interest Payment | D16: Cumulative interest | E16: Principal Payment | F16: Cumulative repayment | G16: Total Debt Service | H16: Closing Balance
A17: {=TRANSPOSE('MAGBL_Loan (BIFFL)'!B27:AC34)} -> 42628 | B17: 55000000 | C17: 1086250 | D17: 0 | E17: 0 | F17: 0 | G17: 0 | H17: 56086250
A18: 42719 | B18: 96086250 | C18: 1515962.2 | D18: 0 | E18: 0 | F18: 0 | G18: 0 | H18: 97602212
A19: 42809 | B19: 1.6735221e+08 | C19: 3172549.8 | D19: 0 | E19: 0 | F19: 0 | G19: 0 | H19: 1.7052476e+08
A20: 42914 | B20: 1.7052476e+08 | C20: 4476275 | D20: 0 | E20: 0 | F20: 0 | G20: 0 | H20: 1.7500104e+08
A21: 42992 | B21: 1.7500104e+08 | C21: 3412520.2 | D21: 3412520.2 | E21: 5579073.1 | F21: 5579073.1 | G21: 8991593.3 | H21: 1.6942196e+08
A22: 43083 | B22: 1.6942196e+08 | C22: 3854349.7 | D22: 7266869.9 | E22: 5704602.3 | F22: 11283675 | G22: 9558951.9 | H22: 1.6371736e+08
A23: 43174 | B23: 1.6371736e+08 | C23: 3724570 | D23: 10991440 | E23: 5832955.8 | F23: 17116631 | G23: 9557525.8 | H23: 1.5788441e+08
A24: 43265 | B24: 1.5788441e+08 | C24: 3591870.2 | D24: 14583310 | E24: 5964197.3 | F24: 23080829 | G24: 9556067.6 | H24: 1.5192021e+08
A25: 43356 | B25: 1.5192021e+08 | C25: 3456184.7 | D25: 18039495 | E25: 6098391.8 | F25: 29179220 | G25: 9554576.5 | H25: 1.4582182e+08
A26: 43447 | B26: 1.4582182e+08 | C26: 3317446.3 | D26: 21356941 | E26: 6235605.6 | F26: 35414826 | G26: 9553051.9 | H26: 1.3958621e+08
A27: 43538 | B27: 1.3958621e+08 | C27: 3175586.3 | D27: 24532527 | E27: 6375906.7 | F27: 41790733 | G27: 9551493 | H27: 1.332103e+08
A28: 43629 | B28: 1.332103e+08 | C28: 3030534.4 | D28: 27563062 | E28: 6519364.6 | F28: 48310097 | G28: 9549899 | H28: 1.2669094e+08
A29: 43723 | B29: 1.2669094e+08 | C29: 2977237.1 | D29: 30540299 | E29: 6666050.3 | F29: 54976147 | G29: 9643287.4 | H29: 1.2002489e+08
... A44: 45092 | B44: 9307184.8 | C44: 214065.25 | D44: 53588169 | E44: 9307184.8 | F44: 1.7500104e+08 | G44: 9521250 | H44: 1.4901161e-08
