Workbook

Sheet Disbursement
A1: Borrower: | B1: Meghna Cement Mills Limited (MCML)
A2: Currency: | B2: BDT
A3: Type | B3: IDCOL Loan
A4: Source : | B4: JICA BD P90
A7: Disbursement Number | B7: Disbursement Date | C7: Disbursement | D7: Cumulative Disbursement | E7: Source
A8: 1 | B8: 42935 | C8: 123820000 | D8: =C8 -> 123820000 | E8: IDCOL Current Account/JICA BD P90
A9: 2 | B9: 43151 | C9: 950080000 | D9: =D8+C9 -> 1073900000 | E9: IDCOL Current Account/JICA BD P90
A10: 3 | B10: 43382 | C10: 196100000 | D10: =D9+C10 -> 1270000000 | E10: IDCOL Current Account/JICA BD P90

Sheet Summary
B1: ='Accrual_MCML '!B22 -> 42948 | C1: ='Accrual_MCML '!C22 -> 42979 | D1: ='Accrual_MCML '!D22 -> 43009 | E1: ='Accrual_MCML '!E22 -> 43040 | F1: ='Accrual_MCML '!F22 -> 43070 | G1: ='Accrual_MCML '!G22 -> 43101 | H1: ='Accrual_MCML '!H22 -> 43132 | I1: ='Accrual_MCML '!I22 -> 43160 | ... DQ1: ='Accrual_MCML '!DQ22 -> 46569
A2: Principal
A3: Opening balance | B3: ='Accrual_MCML '!B23 -> 123820000 | C3: ='Accrual_MCML '!C23 -> 123820000 | D3: ='Accrual_MCML '!D23 -> 123820000 | E3: ='Accrual_MCML '!E23 -> 123820000 | F3: ='Accrual_MCML '!F23 -> 123820000 | G3: ='Accrual_MCML '!G23 -> 123820000 | H3: ='Accrual_MCML '!H23 -> 123820000 | I3: ='Accrual_MCML '!I23 -> 1073900000 | ... Q3: ='Accrual_MCML '!Q23 -> 1270000000 | R3: =Q3 -> 1270000000 | S3: =R3 -> 1270000000 | T3: =S3 -> 1270000000 | U3: =T3 -> 1270000000 | V3: =U3 -> 1270000000 | W3: =V3 -> 1270000000 | X3: =W3 -> 1270000000 | Y3: =X3 -> 1270000000 | ... DQ3: =DP3 -> 1270000000
A4: Repayment due | B4: ='Accrual_MCML '!B27 -> 0 | C4: ='Accrual_MCML '!C27 -> 0 | D4: ='Accrual_MCML '!D27 -> 0 | E4: ='Accrual_MCML '!E27 -> 0 | F4: ='Accrual_MCML '!F27 -> 0 | G4: ='Accrual_MCML '!G27 -> 0 | H4: ='Accrual_MCML '!H27 -> 0 | I4: ='Accrual_MCML '!I27 -> 0 | ... DQ4: ='Accrual_MCML '!DQ27 -> 1.27e+09
A5: Loan Repayment | B5: =B22 -> 0 | C5: =C22 -> 0 | D5: =D22 -> 0 | E5: =E22 -> 0 | F5: =F22 -> 0 | G5: =G22 -> 0 | H5: =H22 -> 0 | I5: =I22 -> 0 | ... DQ5: =DQ22 -> 1.27e+09
A6: Repayment overdue | B6: =IF((B4-B5)>0,(B4-B5),0) -> 0 | C6: =IF((C4-C5)>0,(C4-C5),0) -> 0 | D6: =IF((D4-D5)>0,(D4-D5),0) -> 0 | E6: =IF((E4-E5)>0,(E4-E5),0) -> 0 | F6: =IF((F4-F5)>0,(F4-F5),0) -> 0 | G6: =IF((G4-G5)>0,(G4-G5),0) -> 0 | H6: =IF((H4-H5)>0,(H4-H5),0) -> 0 | I6: =IF((I4-I5)>0,(I4-I5),0) -> 0 | ... DQ6: =IF((DQ4-DQ5)>0,(DQ4-DQ5),0) -> 0
A7: Loan outstanding | B7: =B3-B5 -> 123820000 | C7: =C3-C5 -> 123820000 | D7: =D3-D5 -> 123820000 | E7: =E3-E5 -> 123820000 | F7: =F3-F5 -> 123820000 | G7: =G3-G5 -> 123820000 | H7: =H3-H5 -> 123820000 | I7: =I3-I5 -> 1073900000 | ... DQ7: =DQ3-DQ5 -> 0
A8: Interest
A9: Interest accrued | B9: ='Accrual_MCML '!B25 -> 312989.44 | C9: ='Accrual_MCML '!C25 -> 1059348.9 | D9: ='Accrual_MCML '!D25 -> 1781632.2 | E9: ='Accrual_MCML '!E25 -> 2527991.7 | F9: ='Accrual_MCML '!F25 -> 3250275 | G9: ='Accrual_MCML '!G25 -> 3810904.4 | H9: ='Accrual_MCML '!H25 -> 4237395.6 | I9: ='Accrual_MCML '!I25 -> 6285253.3 | ... DQ9: ='Accrual_MCML '!DQ25 -> 2.87773e+08
A10: Interest due | B10: 0 | C10: =B10 -> 0 | D10: =MCML_Loan!$B$29 -> 1372338.3 | E10: =D10 -> 1372338.3 | F10: =E10 -> 1372338.3 | G10: =MCML_Loan!$C$29 -> 3563264.4 | H10: =G10 -> 3563264.4 | I10: =H10 -> 3563264.4 | J10: =MCML_Loan!$D$29 -> 9064191.1 | K10: =J10 -> 9064191.1 | L10: =K10 -> 9064191.1 | M10: =MCML_Loan!$E$29 -> 19922513 | N10: =M10 -> 19922513 | O10: =N10 -> 19922513 | P10: =MCML_Loan!$F$29 -> 30780836 | Q10: =P10 -> 30780836 | R10: =Q10 -> 30780836 | S10: =MCML_Loan!$G$29 -> 44117644 | T10: =S10 -> 44117644 | U10: =T10 -> 44117644 | V10: =MCML_Loan!$H$29 -> 56958755 | W10: =V10 -> 56958755 | X10: =W10 -> 56958755 | Y10: =MCML_Loan!$I$29 -> 69799866 | Z10: =Y10 -> 69799866 | AA10: =Z10 -> 69799866 | AB10: =MCML_Loan!$J$29 -> 83064311 | AC10: =AB10 -> 83064311 | AD10: =AC10 -> 83064311 | AE10: =MCML_Loan!$K$29 -> 95504137 | AF10: =MCML_Loan!$L$29 -> 99605179 | AG10: =MCML_Loan!$M$29 -> 1.0340501e+08 | AH10: =MCML_Loan!$N$29 -> 1.0742763e+08 | AI10: =MCML_Loan!$O$29 -> 1.1141083e+08 | AJ10: =MCML_Loan!$P$29 -> 1.1510006e+08 | AK10: =MCML_Loan!$Q$29 -> 1.1912999e+08 | AL10: =MCML_Loan!$R$29 -> 1.2286952e+08 | AM10: =MCML_Loan!$S$29 -> 1.2644704e+08 | AN10: =MCML_Loan!$T$29 -> 1.3047536e+08 | AO10: =MCML_Loan!$U$29 -> 1.3409855e+08 | AP10: =MCML_Loan!$V$29 -> 1.3780218e+08 | AQ10: =MCML_Loan!$W$29 -> 1.4134717e+08 | AR10: =MCML_Loan!$X$29 -> 1.4496972e+08 | AS10: =MCML_Loan!$Y$29 -> 1.4855153e+08 | AT10: =MCML_Loan!$Z$29 -> 1.5174978e+08 | AU10: =MCML_Loan!$AA$29 -> 1.5524969e+08 | AV10: =MCML_Loan!$AB$29 -> 1.5859688e+08 | AW10: =MCML_Loan!$AC$29 -> 1.6201435e+08 | AX10: =MCML_Loan!$AD$29 -> 1.6528148e+08 | AY10: =MCML_Loan!$AE$29 -> 1.6861596e+08 | AZ10: =MCML_Loan!$AF$29 -> 1.7190873e+08 | BA10: =MCML_Loan!$AG$29 -> 1.7505479e+08 | BB10: =MCML_Loan!$AH$29 -> 1.7826374e+08 | BC10: =MCML_Loan!$AI$29 -> 1.8132841e+08 | BD10: =MCML_Loan!$AJ$29 -> 1.8445297e+08 | BE10: =MCML_Loan!$AK$29 -> 1.8753512e+08 | BF10: =MCML_Loan!$AL$29 -> 1.9028058e+08 | BG10: =MCML_Loan!$AM$29 -> 1.9327751e+08 | BH10: =MCML_Loan!$AN$29 -> 1.9613631e+08 | BI10: =MCML_Loan!$AO$29 -> 1.9904744e+08 | BJ10: =MCML_Loan!$AP$29 -> 2.0182293e+08 | BK10: =MCML_Loan!$AQ$29 -> 2.0464768e+08 | BL10: =MCML_Loan!$AR$29 -> 2.0742903e+08 | BM10: =MCML_Loan!$AS$29 -> 2.1007852e+08 | BN10: =MCML_Loan!$AT$29 -> 2.1277263e+08 | BO10: =MCML_Loan!$AU$29 -> 2.153374e+08 | BP10: =MCML_Loan!$AV$29 -> 2.1794369e+08 | BQ10: =MCML_Loan!$AW$29 -> 2.2050584e+08 | BR10: =MCML_Loan!$AX$29 -> 2.2278005e+08 | BS10: =MCML_Loan!$AY$29 -> 2.252535e+08 | BT10: =MCML_Loan!$AZ$29 -> 2.2760403e+08 | BU10: =MCML_Loan!$BA$29 -> 2.2998818e+08 | BV10: =MCML_Loan!$BB$29 -> 2.32252e+08 | BW10: =MCML_Loan!$BC$29 -> 2.3454626e+08 | BX10: =MCML_Loan!$BD$29 -> 2.3679535e+08 | BY10: =MCML_Loan!$BE$29 -> 2.3892803e+08 | BZ10: =MCML_Loan!$BF$29 -> 2.4108633e+08 | CA10: =MCML_Loan!$BG$29 -> 2.4313085e+08 | CB10: =MCML_Loan!$BH$29 -> 2.4519774e+08 | CC10: =MCML_Loan!$BI$29 -> 2.4721871e+08 | CD10: =MCML_Loan!$BJ$29 -> 2.4906618e+08 | CE10: =MCML_Loan!$BK$29 -> 2.5099482e+08 | CF10: =MCML_Loan!$BL$29 -> 2.5281636e+08 | CG10: =MCML_Loan!$BM$29 -> 2.5465208e+08 | CH10: =MCML_Loan!$BN$29 -> 2.5638338e+08 | CI10: =MCML_Loan!$BO$29 -> 2.5812553e+08 | CJ10: =MCML_Loan!$BP$29 -> 2.5982068e+08 | CK10: =MCML_Loan!$BQ$29 -> 2.614155e+08 | CL10: =MCML_Loan!$BR$29 -> 2.6301615e+08 | CM10: =MCML_Loan!$BS$29 -> 2.6451921e+08 | CN10: =MCML_Loan!$BT$29 -> 2.6602474e+08 | CO10: =MCML_Loan!$BU$29 -> 2.6748247e+08 | CP10: =MCML_Loan!$BV$29 -> 2.6875581e+08 | CQ10: =MCML_Loan!$BW$29 -> 2.7011745e+08 | CR10: =MCML_Loan!$BX$29 -> 2.7138845e+08 | CS10: =MCML_Loan!$BY$29 -> 2.7265338e+08 | CT10: =MCML_Loan!$BZ$29 -> 2.7383047e+08 | CU10: =MCML_Loan!$CA$29 -> 2.7499803e+08 | CV10: =MCML_Loan!$CB$29 -> 2.7611666e+08 | CW10: =MCML_Loan!$CC$29 -> 2.771517e+08 | CX10: =MCML_Loan!$CD$29 -> 2.7817199e+08 | CY10: =MCML_Loan!$CE$29 -> 2.7911154e+08 | CZ10: =MCML_Loan!$CF$29 -> 2.8003283e+08 | DA10: =MCML_Loan!$CG$29 -> 2.8090437e+08 | DB10: =MCML_Loan!$CH$29 -> 2.8164649e+08 | DC10: =MCML_Loan!$CI$29 -> 2.8241804e+08 | DD10: =MCML_Loan!$CJ$29 -> 2.8311607e+08 | DE10: =MCML_Loan!$CK$29 -> 2.8378695e+08 | DF10: =MCML_Loan!$CL$29 -> 2.8438725e+08 | DG10: =MCML_Loan!$CM$29 -> 2.849568e+08 | DH10: =MCML_Loan!$CN$29 -> 2.8547543e+08 | DI10: =MCML_Loan!$CO$29 -> 2.8592789e+08 | DJ10: =MCML_Loan!$CP$29 -> 2.8634417e+08 | DK10: =MCML_Loan!$CQ$29 -> 2.8669726e+08 | DL10: =MCML_Loan!$CR$29 -> 2.870105e+08 | DM10: =MCML_Loan!$CS$29 -> 2.8727198e+08 | DN10: =MCML_Loan!$CT$29 -> 2.8746123e+08 | DO10: =MCML_Loan!$CU$29 -> 2.8761863e+08 | DP10: =MCML_Loan!$CV$29 -> 2.8772035e+08 | DQ10: =MCML_Loan!$CW$29 -> 2.87773e+08
A11: interest received | B11: =B26 -> 0 | C11: =C26 -> 0 | D11: =D26 -> 1372338 | E11: =E26 -> 1372338 | F11: =F26 -> 1372338 | G11: =G26 -> 3563264 | H11: =H26 -> 3563264 | I11: =I26 -> 3563264 | ... DQ11: =DQ26 -> 2.87773e+08
A12: Interest overdue | B12: =IF((B10-B11)>0,(B10-B11),0) -> 0 | C12: =IF((C10-C11)>0,(C10-C11),0) -> 0 | D12: =IF((D10-D11)>0,(D10-D11),0) -> 0.33333333 | E12: =IF((E10-E11)>0,(E10-E11),0) -> 0.33333333 | F12: =IF((F10-F11)>0,(F10-F11),0) -> 0.33333333 | G12: =IF((G10-G11)>0,(G10-G11),0) -> 0.44444444 | H12: =IF((H10-H11)>0,(H10-H11),0) -> 0.44444444 | I12: =IF((I10-I11)>0,(I10-I11),0) -> 0.44444444 | ... DQ12: =IF((DQ10-DQ11)>0,(DQ10-DQ11),0) -> 0
A13: Interest receivable | B13: =B9-B11 -> 312989.44 | C13: =C9-C11 -> 1059348.9 | D13: =D9-D11 -> 409294.22 | E13: =E9-E11 -> 1155653.7 | F13: =F9-F11 -> 1877937 | G13: =G9-G11 -> 247640.44 | H13: =H9-H11 -> 674131.56 | I13: =I9-I11 -> 2721989.3 | ... DQ13: =DQ9-DQ11 -> 0
A14: LD and others | B14: =B28 -> 0 | C14: =C28 -> 0 | D14: =D28 -> 0 | E14: =E28 -> 0 | F14: =F28 -> 0 | G14: =G28 -> 0 | H14: =H28 -> 0 | I14: =I28 -> 0 | ... DQ14: =DQ28 -> 1443659
B19: =B1 -> 42948 | C19: =C1 -> 42979 | D19: =D1 -> 43009 | E19: =E1 -> 43040 | F19: =F1 -> 43070 | G19: =G1 -> 43101 | H19: =H1 -> 43132 | I19: =I1 -> 43160 | ... DQ19: =DQ1 -> 46569
A20: Repayment receipts:
A21: Repayment received | B21: 0 | C21: =C4-B5 -> 0 | D21: =D4-C5 -> 0 | E21: =E4-D5 -> 0 | F21: =F4-E5 -> 0 | G21: =G4-F5 -> 0 | H21: =H4-G5 -> 0 | I21: =I4-H5 -> 0 | J21: =J4-I5 -> 0 | ... AA21: =AA4-Z5 -> 0 | AB21: 39687500 | AE21: =12533698+15898958+11254844 -> 39687500 | AF21: 11365734 | AG21: =5270699+5170991+961930 -> 11403620 | AH21: 0 | AI21: 0 | AJ21: 0 | AK21: 0 | AL21: 0 | AM21: 0 | AN21: =AN4-AM5 -> 80896802 | AO21: =AO4-AN5 -> 11711288 | AP21: =AP4-AO5 -> 11750326 | AQ21: =AQ4-AP5 -> 11789493 | AR21: =AR4-AQ5 -> 11828792 | AS21: =AS4-AR5 -> 11868221 | AT21: =AT4-AS5 -> 11907782 | AU21: =AU4-AT5 -> 11947474 | ... DQ21: =DQ4-DP5 -> 15283539
A22: Repayment received (cumulative) | B22: =B21 -> 0 | C22: =B22+C21 -> 0 | D22: =C22+D21 -> 0 | E22: =D22+E21 -> 0 | F22: =E22+F21 -> 0 | G22: =F22+G21 -> 0 | H22: =G22+H21 -> 0 | I22: =H22+I21 -> 0 | J22: =I22+J21 -> 0 | ... DQ22: =DP22+DQ21 -> 1.27e+09
A24: Interest receipts:
A25: Interest received | B25: 0 | C25: =C10-B11 -> 0 | D25: 1372338 | G25: 2190926 | J25: 5500932 | M25: 10858322 | P25: 10858322 | S25: 13336812 | V25: 12841111 | Y25: 12841111 | AB25: 13264444 | AE25: 12439826 | AF25: 4101042 | AG25: 3799835 | AH25: 4022616 | AI25: 3983204 | AJ25: =1518095+2171138 -> 3689233 | AK25: 4029924 | AL25: 3739535 | AM25: 3577520 | AN25: =AN10-AM11 -> 4028302.7 | AO25: =AO10-AN11 -> 3623196.1 | AP25: =AP10-AO11 -> 3703630.5 | AQ25: =AQ10-AP11 -> 3544990.8 | AR25: =AR10-AQ11 -> 3622548.9 | AS25: =AS10-AR11 -> 3581805.3 | AT25: =AT10-AS11 -> 3198255.6 | AU25: =AU10-AT11 -> 3499910.1 | ... DQ25: =DQ10-DP11 -> 52643.301
A26: Interest received (cumulative) | B26: =B25 -> 0 | C26: =B26+C25 -> 0 | D26: =C26+D25 -> 1372338 | E26: =D26+E25 -> 1372338 | F26: =E26+F25 -> 1372338 | G26: =F26+G25 -> 3563264 | H26: =G26+H25 -> 3563264 | I26: =H26+I25 -> 3563264 | J26: =I26+J25 -> 9064196 | ... DQ26: =DP26+DQ25 -> 2.87773e+08
A27: LD/others | B27: 0 | C27: 0 | D27: 0 | E27: 0 | F27: 0 | G27: 0 | H27: 0 | I27: 0 | J27: 13693 | K27: 0 | L27: 0 | M27: 0 | N27: 0 | O27: 0 | P27: 0 | Q27: 0 | R27: 0 | S27: 0 | T27: 0 | U27: 0 | V27: 31119 | W27: 0 | X27: 0 | Y27: 0 | Z27: 0 | AA27: 0 | AB27: 0 | AC27: 0 | AD27: 0 | AE27: 26476 | AF27: 135207 | AG27: 173681 | AH27: 0 | AI27: 0 | AJ27: 0 | AK27: 476085 | AL27: 272235 | AM27: 315163 | AN27: 0 | AO27: 0 | AP27: 0 | AQ27: 0 | AR27: 0 | AS27: 0 | AT27: 0 | AU27: 0 | AV27: 0 | AW27: 0 | AX27: 0 | AY27: 0 | AZ27: 0 | BA27: 0 | BB27: 0 | BC27: 0 | BD27: 0 | BE27: 0 | BF27: 0 | BG27: 0 | BH27: 0 | BI27: 0 | BJ27: 0 | BK27: 0 | BL27: 0 | BM27: 0 | BN27: 0 | BO27: 0 | BP27: 0 | BQ27: 0 | BR27: 0 | BS27: 0 | BT27: 0 | BU27: 0 | BV27: 0 | BW27: 0 | BX27: 0 | BY27: 0 | BZ27: 0 | CA27: 0 | CB27: 0 | CC27: 0 | CD27: 0 | CE27: 0 | CF27: 0 | CG27: 0 | CH27: 0 | CI27: 0 | CJ27: 0 | CK27: 0 | CL27: 0 | CM27: 0 | CN27: 0 | CO27: 0 | CP27: 0 | CQ27: 0 | CR27: 0 | CS27: 0 | CT27: 0 | CU27: 0 | CV27: 0 | CW27: 0 | CX27: 0 | CY27: 0 | CZ27: 0 | DA27: 0 | DB27: 0 | DC27: 0 | DD27: 0 | DE27: 0 | DF27: 0 | DG27: 0 | DH27: 0 | DI27: 0 | DJ27: 0 | DK27: 0 | DL27: 0 | DM27: 0 | DN27: 0 | DO27: 0 | DP27: 0 | DQ27: 0
A28: LD/others (cumulative) | B28: =B27 -> 0 | C28: =B28+C27 -> 0 | D28: =C28+D27 -> 0 | E28: =D28+E27 -> 0 | F28: =E28+F27 -> 0 | G28: =F28+G27 -> 0 | H28: =G28+H27 -> 0 | I28: =H28+I27 -> 0 | J28: =I28+J27 -> 13693 | ... DQ28: =DP28+DQ27 -> 1443659
A30: Actual Payment date | D30: 42995 | G30: 43108 | J30: 43174 | M30: 43265 | P30: 43359 | S30: 43461 | V30: 43538 | Y30: 43629 | AB30: 43726 | AE30: 43828 | AF30: 43860 | AH30: 43880 | AK30: 43901 | AL30: 43901 | AM30: 44026 | AP30: 44026 | AR30: 44074 | AS30: 44081
A31: Actual Payment amount: | AG31: 20000000 | AJ31: 32000000 | AK31: 5170991 | AL31: 2500000 | AO31: 10000000 | AQ31: 10000000 | AR31: 17709240 | AS31: 17157741
A32: Interest | D32: 1372338 | G32: 2190926 | J32: 5500932 | M32: 10858322 | P32: 10858322 | S32: 13336812 | V32: 12841111 | Y32: 12841111 | AB32: 13264444 | AE32: 12439826 | AF32: 4101042 | AJ32: 3799835 | AM32: 4022616 | AN32: 3983204 | AO32: 1518095 | AP32: 2171138 | AQ32: 4029924 | AR32: 3739535 | AS32: 3577520
A33: Principal | AB33: 39687500 | AE33: 12533698 | AG33: 15898958 | AH33: 11254844 | AI33: 11365734 | AJ33: 5270699 | AK33: 5170991 | AL33: 961930
A34: LPC | J34: 13693 | V34: 31119 | AE34: 26476 | AI34: 135207 | AJ34: 173681 | AO34: 476085 | AR34: 272235 | AS34: 315163
A35: Total | D35: =D32+D33+D34 -> 1372338 | G35: =SUM(G32:G34) -> 2190926 | H35: =SUM(H32:H34) -> 0 | I35: =SUM(I32:I34) -> 0 | J35: =SUM(J32:J34) -> 5514625 | K35: =SUM(K32:K34) -> 0 | L35: =SUM(L32:L34) -> 0 | M35: =SUM(M32:M34) -> 10858322 | N35: =SUM(N32:N34) -> 0 | ... AE35: =SUM(AE32:AE34) -> 25000000 | AG35: =SUM(AG32:AG34) -> 15898958 | AH35: =SUM(AH32:AH34) -> 11254844 | AI35: =SUM(AI32:AI34) -> 11500941 | AJ35: =SUM(AJ32:AJ34) -> 9244215 | AK35: =SUM(AK32:AK34) -> 5170991 | AL35: =SUM(AL32:AL34) -> 961930 | AM35: =SUM(AM32:AM34) -> 4022616 | AN35: =SUM(AN32:AN34) -> 3983204 | ... DR35: =SUM(DR32:DR34) -> 0

Sheet MCML_Loan
A1: Project name: | C1: =Disbursement!B1 -> Meghna Cement Mills Limited (MCML)
A3: Agreement signing date | C3: 42899
A5: Loan Amount | C5: 1270000000 | G5: *If payment date is not a business day, then payment date shall be immediately the preceeding business day.
A7: Payment frequency | C7: Quarterly
A8: Interest Rate | C8: 0.07
A9: Maturity date | C9: 120 | D9: months | E9: =EDATE(C16,C9) -> 46587
A10: Moratorium period (Principal) | C10: 24 | D10: months | E10: =EDATE(C16,C10) -> 43665
A11: Principal | C11: Level principal
A12: Interest calculation | C12: 360 | D12: days basis
A13: Number of installments | C13: 32
A15: Drawdown
C16: =Disbursement!B8 -> 42935 | D16: =Disbursement!B9 -> 43151 | E16: =Disbursement!B10 -> 43382
C17: =Disbursement!C8 -> 123820000 | D17: =Disbursement!C9 -> 950080000 | E17: =Disbursement!C10 -> 196100000
C18: =C17 -> 123820000 | D18: =D17+C18 -> 1073900000 | E18: =E17+D18 -> 1270000000
A21: Period | B21: =B26 -> 42992 | C21: =C26 -> 43083 | D21: =D26 -> 43174 | E21: =E26 -> 43265 | F21: =F26 -> 43356 | G21: =G26 -> 43447 | H21: =H26 -> 43538 | I21: =I26 -> 43629 | ... CW21: =CW26 -> 46553
A22: Quarterly Interest Rate | B22: =(B28*$C$12)/(B27*(B26-C16)) -> 0.07 | C22: =(C28*$C$12)/(C27*(C26-B26)) -> 0.07 | D22: 0.0665411 | E22: =(E28*$C$12)/(E27*(E26-D26)) -> 0.04 | F22: =(F28*$C$12)/(F27*(F26-E26)) -> 0.04 | G22: =(G28*$C$12)/(G27*(G26-F26)) -> 0.041544094 | H22: =(H28*$C$12)/(H27*(H26-G26)) -> 0.04 | I22: =(I28*$C$12)/(I27*(I26-H26)) -> 0.04 | J22: 0.04 | K22: 0.04 | L22: 0.04 | M22: 0.04 | N22: 0.04 | O22: 0.04 | P22: 0.04 | Q22: 0.04 | R22: 0.04 | S22: 0.04 | T22: 0.04 | U22: 0.04 | V22: 0.04 | W22: 0.04 | X22: 0.04 | Y22: 0.04 | Z22: 0.04 | AA22: 0.04 | AB22: 0.04 | AC22: 0.04 | AD22: 0.04 | AE22: 0.04 | AF22: 0.04 | AG22: 0.04 | AH22: 0.04 | AI22: 0.04 | AJ22: 0.04 | AK22: 0.04 | AL22: 0.04 | AM22: 0.04 | AN22: 0.04 | AO22: 0.04 | AP22: 0.04 | AQ22: 0.04 | AR22: 0.04 | AS22: 0.04 | AT22: 0.04 | AU22: 0.04 | AV22: 0.04 | AW22: 0.04 | AX22: 0.04 | AY22: 0.04 | AZ22: 0.04 | BA22: 0.04 | BB22: 0.04 | BC22: 0.04 | BD22: 0.04 | BE22: 0.04 | BF22: 0.04 | BG22: 0.04 | BH22: 0.04 | BI22: 0.04 | BJ22: 0.04 | BK22: 0.04 | BL22: 0.04 | BM22: 0.04 | BN22: 0.04 | BO22: 0.04 | BP22: 0.04 | BQ22: 0.04 | BR22: 0.04 | BS22: 0.04 | BT22: 0.04 | BU22: 0.04 | BV22: 0.04 | BW22: 0.04 | BX22: 0.04 | BY22: 0.04 | BZ22: 0.04 | CA22: 0.04 | CB22: 0.04 | CC22: 0.04 | CD22: 0.04 | CE22: 0.04 | CF22: 0.04 | CG22: 0.04 | CH22: 0.04 | CI22: 0.04 | CJ22: 0.04 | CK22: 0.04 | CL22: 0.04 | CM22: 0.04 | CN22: 0.04 | CO22: 0.04 | CP22: 0.04 | CQ22: 0.04 | CR22: 0.04 | CS22: 0.04 | CT22: 0.04 | CU22: 0.04 | CV22: 0.04 | CW22: 0.04
G23: =D18*(E16-F26)*F22/360+E18*(G26-E16)*4.463228%/360 -> 13336808
A24: Cumulative
A25: Repayment Period | J25: 1 | K25: 2 | L25: 1 | M25: =L25+1 -> 2 | N25: =M25+1 -> 3 | O25: =N25+1 -> 4 | P25: =O25+1 -> 5 | Q25: =P25+1 -> 6 | R25: =Q25+1 -> 7 | S25: =R25+1 -> 8 | T25: =S25+1 -> 9 | ... CW25: =CV25+1 -> 90
A26: Repayment Date | B26: 42992 | C26: 43083 | D26: 43174 | E26: 43265 | F26: 43356 | G26: 43447 | H26: 43538 | I26: 43629 | J26: 43723 | K26: 43814 | L26: 43845 | M26: 43874 | N26: 43905 | O26: 43936 | P26: 43965 | Q26: 43997 | R26: 44027 | S26: 44056 | T26: 44089 | U26: 44119 | V26: 44150 | W26: 44180 | X26: 44211 | Y26: 44242 | Z26: 44270 | AA26: 44301 | AB26: 44331 | AC26: 44362 | AD26: 44392 | AE26: 44423 | AF26: 44454 | AG26: 44484 | AH26: 44515 | AI26: 44545 | AJ26: 44576 | AK26: 44607 | AL26: 44635 | AM26: 44666 | AN26: 44696 | AO26: 44727 | AP26: 44757 | AQ26: 44788 | AR26: 44819 | AS26: 44849 | AT26: 44880 | AU26: 44910 | AV26: 44941 | AW26: 44972 | AX26: 45000 | AY26: 45031 | AZ26: 45061 | BA26: 45092 | BB26: 45122 | BC26: 45153 | BD26: 45184 | BE26: 45214 | BF26: 45245 | BG26: 45275 | BH26: 45306 | BI26: 45337 | BJ26: 45366 | BK26: 45397 | BL26: 45427 | BM26: 45458 | BN26: 45488 | BO26: 45519 | BP26: 45550 | BQ26: 45580 | BR26: 45611 | BS26: 45641 | BT26: 45672 | BU26: 45703 | BV26: 45731 | BW26: 45762 | BX26: 45792 | BY26: 45823 | BZ26: 45853 | CA26: 45884 | CB26: 45915 | CC26: 45945 | CD26: 45976 | CE26: 46006 | CF26: 46037 | CG26: 46068 | CH26: 46096 | CI26: 46127 | CJ26: 46157 | CK26: 46188 | CL26: 46218 | CM26: 46249 | CN26: 46280 | CO26: 46310 | CP26: 46341 | CQ26: 46371 | CR26: 46402 | CS26: 46433 | CT26: 46461 | CU26: 46492 | CV26: 46522 | CW26: 46553
A27: Opening Balance | B27: =B40+B53+B66 -> 123820000 | C27: =C40+C53+C66 -> 123820000 | D27: =D40+D53+D66 -> 1073900000 | E27: =E40+E53+E66 -> 1073900000 | F27: =F40+F53+F66 -> 1073900000 | G27: =G40+G53+G66 -> 1270000000 | H27: =H40+H53+H66 -> 1270000000 | I27: =I40+I53+I66 -> 1270000000 | ... CW27: =CW40+CW53+CW66 -> 15283539
A28: Interest Payment | B28: =B41+B54+B67 -> 1372338.3 | C28: =C41+C54+C67 -> 2190926.1 | D28: =D41+D54+D67 -> 5500926.7 | E28: =E41+E54+E67 -> 10858322 | F28: =F41+F54+F67 -> 10858322 | G28: =G41+G54+G67 -> 13336808 | H28: =H41+H54+H67 -> 12841111 | I28: =I41+I54+I67 -> 12841111 | ... CW28: =CW41+CW54+CW67 -> 52643.301
A29: Cumulative interest | B29: =B28 -> 1372338.3 | C29: =B29+C28 -> 3563264.4 | D29: =C29+D28 -> 9064191.1 | E29: =D29+E28 -> 19922513 | F29: =E29+F28 -> 30780836 | G29: =G28+F29 -> 44117644 | H29: =H28+G29 -> 56958755 | I29: =I28+H29 -> 69799866 | J29: =J28+I29 -> 83064311 | K29: =K28+J29 -> 95504137 | L29: =L28+K29 -> 99605179 | M29: =M28+L29 -> 1.0340501e+08 | N29: =N28+M29 -> 1.0742763e+08 | ... CW29: =CW28+CV29 -> 2.87773e+08
A30: Principal Payment | B30: =B43+B56+B69 -> 0 | C30: =C43+C56+C69 -> 0 | D30: =D43+D56+D69 -> 0 | E30: =E43+E56+E69 -> 0 | F30: =F43+F56+F69 -> 0 | G30: =G43+G56+G69 -> 0 | H30: =H43+H56+H69 -> 0 | I30: =I43+I56+I69 -> 0 | ... CW30: =CW43+CW56+CW69 -> 15283539
A31: Cumulative repayment | B31: 0 | C31: =C30+B31 -> 0 | D31: =D30+C31 -> 0 | E31: =E30+D31 -> 0 | F31: =F30+E31 -> 0 | G31: =G30+F31 -> 0 | H31: =H30+G31 -> 0 | I31: =I30+H31 -> 0 | J31: =J30+I31 -> 39687500 | ... CW31: =CW30+CV31 -> 1.27e+09
A32: Total Debt Service | B32: =B28+B30 -> 1372338.3 | C32: =C28+C30 -> 2190926.1 | D32: =D28+D30 -> 5500926.7 | E32: =E28+E30 -> 10858322 | F32: =F28+F30 -> 10858322 | G32: =G28+G30 -> 13336808 | H32: =H28+H30 -> 12841111 | I32: =I28+I30 -> 12841111 | ... CW32: =CW28+CW30 -> 15336182
A33: Closing Balance | B33: =B27-B30 -> 123820000 | C33: =C27-C30 -> 123820000 | D33: =D27-D30 -> 1073900000 | E33: =E27-E30 -> 1073900000 | F33: =F27-F30 -> 1073900000 | G33: =G27-G30 -> 1270000000 | H33: =H27-H30 -> 1270000000 | I33: =I27-I30 -> 1270000000 | ... CW33: =CW27-CW30 -> -6.519258e-08
A35: Disbursement-1
A36: Period | B36: =B21 -> 42992 | C36: =C21 -> 43083 | D36: =D21 -> 43174 | E36: =E21 -> 43265 | F36: =F21 -> 43356 | G36: =G21 -> 43447 | H36: =H21 -> 43538 | I36: =I21 -> 43629 | ... CW36: =CW21 -> 46553
A37: Expected Interest Rate | B37: 0.07 | C37: 0.07 | D37: 0.04 | E37: 0.04 | F37: 0.04 | G37: 0.04 | H37: 0.04 | I37: 0.04 | J37: 0.04 | K37: 0.04 | L37: 0.04 | M37: 0.04 | N37: 0.04 | O37: 0.04 | P37: 0.04 | Q37: 0.04 | R37: 0.04 | S37: 0.04 | T37: 0.04 | U37: 0.04 | V37: 0.04 | W37: 0.04 | X37: 0.04 | Y37: 0.04 | Z37: 0.04 | AA37: 0.04 | AB37: 0.04 | AC37: 0.04 | AD37: 0.04 | AE37: 0.04 | AF37: 0.04 | AG37: 0.04 | AH37: 0.04 | AI37: 0.04 | AJ37: 0.04 | AK37: 0.04 | AL37: 0.04 | AM37: 0.04 | AN37: 0.04 | AO37: 0.04 | AP37: 0.04 | AQ37: 0.04 | AR37: 0.04 | AS37: 0.04 | AT37: 0.04 | AU37: 0.04 | AV37: 0.04 | AW37: 0.04 | AX37: 0.04 | AY37: 0.04 | AZ37: 0.04 | BA37: 0.04 | BB37: 0.04 | BC37: 0.04 | BD37: 0.04 | BE37: 0.04 | BF37: 0.04 | BG37: 0.04 | BH37: 0.04 | BI37: 0.04 | BJ37: 0.04 | BK37: 0.04 | BL37: 0.04 | BM37: 0.04 | BN37: 0.04 | BO37: 0.04 | BP37: 0.04 | BQ37: 0.04 | BR37: 0.04 | BS37: 0.04 | BT37: 0.04 | BU37: 0.04 | BV37: 0.04 | BW37: 0.04 | BX37: 0.04 | BY37: 0.04 | BZ37: 0.04 | CA37: 0.04 | CB37: 0.04 | CC37: 0.04 | CD37: 0.04 | CE37: 0.04 | CF37: 0.04 | CG37: 0.04 | CH37: 0.04 | CI37: 0.04 | CJ37: 0.04 | CK37: 0.04 | CL37: 0.04 | CM37: 0.04 | CN37: 0.04 | CO37: 0.04 | CP37: 0.04 | CQ37: 0.04 | CR37: 0.04 | CS37: 0.04 | CT37: 0.04 | CU37: 0.04 | CV37: 0.04 | CW37: 0.04
A38: Repayment Period | J38: =+J25 -> 1 | K38: =+K25 -> 2 | L38: =+L25 -> 1 | M38: =+M25 -> 2 | N38: =+N25 -> 3 | O38: =+O25 -> 4 | P38: =+P25 -> 5 | Q38: =+Q25 -> 6 | ... CW38: =+CW25 -> 90
A39: Repayment Date | B39: =B26 -> 42992 | C39: =C26 -> 43083 | D39: =D26 -> 43174 | E39: =E26 -> 43265 | F39: =F26 -> 43356 | G39: =G26 -> 43447 | H39: =H26 -> 43538 | I39: =I26 -> 43629 | ... CW39: =CW26 -> 46553
A40: Opening Balance | B40: =C17 -> 123820000 | C40: =B46 -> 123820000 | D40: =C46 -> 123820000 | E40: =D46 -> 123820000 | F40: =E46 -> 123820000 | G40: =F46 -> 123820000 | H40: =G46 -> 123820000 | I40: =H46 -> 123820000 | J40: =I46 -> 123820000 | ... CW40: =CV46 -> 1490084.9
A41: Interest Payment | B41: =C18*(B39-C16)*$B$37/360 -> 1372338.3 | C41: =B46*(C39-B39)*C37/360 -> 2190926.1 | D41: =C46*(D39-C39)*D37/360 -> 1251957.8 | E41: =D46*(E39-D39)*E37/360 -> 1251957.8 | F41: =E46*(F39-E39)*F37/360 -> 1251957.8 | G41: =F46*(G39-F39)*G37/360 -> 1251957.8 | H41: =G46*(H39-G39)*H37/360 -> 1251957.8 | I41: =H46*(I39-H39)*I37/360 -> 1251957.8 | J41: =I46*(J39-I39)*J37/360 -> 1293231.1 | ... CW41: =CV46*(CW39-CV39)*CW37/360 -> 5132.5146
A42: Cumulative interest | B42: =B41 -> 1372338.3 | C42: =B42+C41 -> 3563264.4 | D42: =C42+D41 -> 4815222.2 | E42: =D42+E41 -> 6067180 | F42: =E42+F41 -> 7319137.8 | G42: =G41+F42 -> 8571095.6 | H42: =H41+G42 -> 9823053.3 | I42: =I41+H42 -> 11075011 | J42: =J41+I42 -> 12368242 | K42: =K41+J42 -> 13581076 | L42: =L41+K42 -> 13980912 | M42: =M41+L42 -> 14351381 | N42: =N41+M42 -> 14743570 | ... CW42: =CW41+CV42 -> 32326533
A43: Principal Payment | B43: 0 | C43: 0 | D43: 0 | E43: 0 | F43: 0 | G43: 0 | H43: 0 | I43: 0 | J43: =$C$18/$C$13 -> 3869375 | K43: =$C$18/$C$13 -> 3869375 | L43: =-PPMT($L$37/12,L38,$CW$38,$L$40,0) -> 1108114.3 | M43: =-PPMT($L$37/12,M38,$CW$38,$L$40,0) -> 1111808 | N43: =-PPMT($L$37/12,N38,$CW$38,$L$40,0) -> 1115514.1 | O43: =-PPMT($L$37/12,O38,$CW$38,$L$40,0) -> 1119232.4 | P43: =-PPMT($L$37/12,P38,$CW$38,$L$40,0) -> 1122963.2 | Q43: =-PPMT($L$37/12,Q38,$CW$38,$L$40,0) -> 1126706.4 | R43: =-PPMT($L$37/12,R38,$CW$38,$L$40,0) -> 1130462.1 | S43: =-PPMT($L$37/12,S38,$CW$38,$L$40,0) -> 1134230.3 | ... CW43: =-PPMT($L$37/12,CW38,$CW$38,$L$40,0) -> 1490084.9
A44: Cumulative repayment | B44: 0 | C44: =C43+B44 -> 0 | D44: =D43+C44 -> 0 | E44: =E43+D44 -> 0 | F44: =F43+E44 -> 0 | G44: =G43+F44 -> 0 | H44: =H43+G44 -> 0 | I44: =I43+H44 -> 0 | J44: =J43+I44 -> 3869375 | ... CW44: =CW43+CV44 -> 1.2382e+08
A45: Total Debt Service | B45: =B41+B43 -> 1372338.3 | C45: =C41+C43 -> 2190926.1 | D45: =D41+D43 -> 1251957.8 | E45: =E41+E43 -> 1251957.8 | F45: =F41+F43 -> 1251957.8 | G45: =G41+G43 -> 1251957.8 | H45: =H41+H43 -> 1251957.8 | I45: =I41+I43 -> 1251957.8 | ... CW45: =CW41+CW43 -> 1495217.4
A46: Closing Balance | B46: =B40-B43 -> 123820000 | C46: =C40-C43 -> 123820000 | D46: =D40-D43 -> 123820000 | E46: =E40-E43 -> 123820000 | F46: =F40-F43 -> 123820000 | G46: =G40-G43 -> 123820000 | H46: =H40-H43 -> 123820000 | I46: =I40-I43 -> 123820000 | ... CW46: =CW40-CW43 -> -3.981404e-08
A48: Disbursement-2
A49: Period | B49: =B36 -> 42992 | C49: =C36 -> 43083 | D49: =D36 -> 43174 | E49: =E36 -> 43265 | F49: =F36 -> 43356 | G49: =G36 -> 43447 | H49: =H36 -> 43538 | I49: =I36 -> 43629 | ... CW49: =CW36 -> 46553
A50: Expected Interest Rate | B50: 0.07 | C50: 0.07 | D50: 0.07 | E50: 0.04 | F50: 0.04 | G50: 0.04 | H50: 0.04 | I50: 0.04 | J50: 0.04 | K50: 0.04 | L50: 0.04 | M50: 0.04 | N50: 0.04 | O50: 0.04 | P50: 0.04 | Q50: 0.04 | R50: 0.04 | S50: 0.04 | T50: 0.04 | U50: 0.04 | V50: 0.04 | W50: 0.04 | X50: 0.04 | Y50: 0.04 | Z50: 0.04 | AA50: 0.04 | AB50: 0.04 | AC50: 0.04 | AD50: 0.04 | AE50: 0.04 | AF50: 0.04 | AG50: 0.04 | AH50: 0.04 | AI50: 0.04 | AJ50: 0.04 | AK50: 0.04 | AL50: 0.04 | AM50: 0.04 | AN50: 0.04 | AO50: 0.04 | AP50: 0.04 | AQ50: 0.04 | AR50: 0.04 | AS50: 0.04 | AT50: 0.04 | AU50: 0.04 | AV50: 0.04 | AW50: 0.04 | AX50: 0.04 | AY50: 0.04 | AZ50: 0.04 | BA50: 0.04 | BB50: 0.04 | BC50: 0.04 | BD50: 0.04 | BE50: 0.04 | BF50: 0.04 | BG50: 0.04 | BH50: 0.04 | BI50: 0.04 | BJ50: 0.04 | BK50: 0.04 | BL50: 0.04 | BM50: 0.04 | BN50: 0.04 | BO50: 0.04 | BP50: 0.04 | BQ50: 0.04 | BR50: 0.04 | BS50: 0.04 | BT50: 0.04 | BU50: 0.04 | BV50: 0.04 | BW50: 0.04 | BX50: 0.04 | BY50: 0.04 | BZ50: 0.04 | CA50: 0.04 | CB50: 0.04 | CC50: 0.04 | CD50: 0.04 | CE50: 0.04 | CF50: 0.04 | CG50: 0.04 | CH50: 0.04 | CI50: 0.04 | CJ50: 0.04 | CK50: 0.04 | CL50: 0.04 | CM50: 0.04 | CN50: 0.04 | CO50: 0.04 | CP50: 0.04 | CQ50: 0.04 | CR50: 0.04 | CS50: 0.04 | CT50: 0.04 | CU50: 0.04 | CV50: 0.04 | CW50: 0.04
A51: Repayment Period | J51: =+J38 -> 1 | K51: =+K38 -> 2 | L51: =+L38 -> 1 | M51: =+M38 -> 2 | N51: =+N38 -> 3 | O51: =+O38 -> 4 | P51: =+P38 -> 5 | Q51: =+Q38 -> 6 | ... CW51: =+CW38 -> 90
A52: Repayment Date | B52: =B39 -> 42992 | C52: =C39 -> 43083 | D52: =D39 -> 43174 | E52: =E39 -> 43265 | F52: =F39 -> 43356 | G52: =G39 -> 43447 | H52: =H39 -> 43538 | I52: =I39 -> 43629 | ... CW52: =CW39 -> 46553
A53: Opening Balance | B53: 0 | C53: =B59 -> 0 | D53: =D17 -> 950080000 | E53: =D59 -> 950080000 | F53: =E59 -> 950080000 | G53: =F59 -> 950080000 | H53: =G59 -> 950080000 | I53: =H59 -> 950080000 | J53: =I59 -> 950080000 | K53: =J59 -> 920390000 | L53: =K59 -> 890700000 | ... CW53: =CV59 -> 11433531
A54: Interest Payment | B54: 0 | C54: 0 | D54: =D53*(D52-$D$16)*D50/360 -> 4248968.9 | E54: =D59*(E52-D52)*E50/360 -> 9606364.4 | F54: =E59*(F52-E52)*F50/360 -> 9606364.4 | G54: =F59*(G52-F52)*G50/360 -> 9606364.4 | H54: =G59*(H52-G52)*H50/360 -> 9606364.4 | I54: =H59*(I52-H52)*I50/360 -> 9606364.4 | J54: =I59*(J52-I52)*J50/360 -> 9923057.8 | K54: =J59*(K52-J52)*K50/360 -> 9306165.6 | L54: =K59*(L52-K52)*L50/360 -> 3067966.7 | ... CW54: =CV59*(CW52-CV52)*CW50/360 -> 39382.163
A55: Cumulative interest | B55: =B54 -> 0 | C55: =B55+C54 -> 0 | D55: =C55+D54 -> 4248968.9 | E55: =D55+E54 -> 13855333 | F55: =E55+F54 -> 23461698 | G55: =G54+F55 -> 33068062 | H55: =H54+G55 -> 42674427 | I55: =I54+H55 -> 52280791 | J55: =J54+I55 -> 62203849 | K55: =K54+J55 -> 71510014 | L55: =L54+K55 -> 74577981 | M55: =M54+L55 -> 77420617 | N55: =N54+M55 -> 80429912 | ... CW55: =CW54+CV55 -> 2.1534529e+08
A56: Principal Payment | B56: 0 | C56: 0 | D56: 0 | E56: 0 | F56: 0 | G56: 0 | H56: 0 | I56: 0 | J56: =$D$17/$C$13 -> 29690000 | K56: =$D$17/$C$13 -> 29690000 | L56: =-PPMT($L$50/12,L51,$CW$51,$L$53,0) -> 8502643 | M56: =-PPMT($L$50/12,M51,$CW$51,$L$53,0) -> 8530985.1 | N56: =-PPMT($L$50/12,N51,$CW$51,$L$53,0) -> 8559421.7 | O56: =-PPMT($L$50/12,O51,$CW$51,$L$53,0) -> 8587953.1 | P56: =-PPMT($L$50/12,P51,$CW$51,$L$53,0) -> 8616579.7 | Q56: =-PPMT($L$50/12,Q51,$CW$51,$L$53,0) -> 8645301.6 | R56: =-PPMT($L$50/12,R51,$CW$51,$L$53,0) -> 8674119.3 | S56: =-PPMT($L$50/12,S51,$CW$51,$L$53,0) -> 8703033 | ... CW56: =-PPMT($L$50/12,CW51,$CW$51,$L$53,0) -> 11433531
A57: Cumulative repayment | B57: 0 | C57: =C56+B57 -> 0 | D57: =D56+C57 -> 0 | E57: =E56+D57 -> 0 | F57: =F56+E57 -> 0 | G57: =G56+F57 -> 0 | H57: =H56+G57 -> 0 | I57: =I56+H57 -> 0 | J57: =J56+I57 -> 29690000 | ... CW57: =CW56+CV57 -> 9.5008e+08
A58: Total Debt Service | B58: =B54+B56 -> 0 | C58: =C54+C56 -> 0 | D58: =D54+D56 -> 4248968.9 | E58: =E54+E56 -> 9606364.4 | F58: =F54+F56 -> 9606364.4 | G58: =G54+G56 -> 9606364.4 | H58: =H54+H56 -> 9606364.4 | I58: =I54+I56 -> 9606364.4 | ... CW58: =CW54+CW56 -> 11472913
A59: Closing Balance | B59: =B53-B56 -> 0 | C59: =C53-C56 -> 0 | D59: =D53-D56 -> 950080000 | E59: =E53-E56 -> 950080000 | F59: =F53-F56 -> 950080000 | G59: =G53-G56 -> 950080000 | H59: =H53-H56 -> 950080000 | I59: =I53-I56 -> 950080000 | ... CW59: =CW53-CW56 -> -1.4901161e-08
A61: Disbursement-3
A62: Period | B62: =B49 -> 42992 | C62: =C49 -> 43083 | D62: =D49 -> 43174 | E62: =E49 -> 43265 | F62: =F49 -> 43356 | G62: =G49 -> 43447 | H62: =H49 -> 43538 | I62: =I49 -> 43629 | ... CW62: =CW49 -> 46553
A63: Expected Interest Rate | B63: 0.07 | C63: 0.07 | D63: 0.07 | E63: 0.07 | F63: 0.07 | G63: 0.07 | H63: 0.04 | I63: 0.04 | J63: 0.04 | K63: 0.04 | L63: 0.04 | M63: 0.04 | N63: 0.04 | O63: 0.04 | P63: 0.04 | Q63: 0.04 | R63: 0.04 | S63: 0.04 | T63: 0.04 | U63: 0.04 | V63: 0.04 | W63: 0.04 | X63: 0.04 | Y63: 0.04 | Z63: 0.04 | AA63: 0.04 | AB63: 0.04 | AC63: 0.04 | AD63: 0.04 | AE63: 0.04 | AF63: 0.04 | AG63: 0.04 | AH63: 0.04 | AI63: 0.04 | AJ63: 0.04 | AK63: 0.04 | AL63: 0.04 | AM63: 0.04 | AN63: 0.04 | AO63: 0.04 | AP63: 0.04 | AQ63: 0.04 | AR63: 0.04 | AS63: 0.04 | AT63: 0.04 | AU63: 0.04 | AV63: 0.04 | AW63: 0.04 | AX63: 0.04 | AY63: 0.04 | AZ63: 0.04 | BA63: 0.04 | BB63: 0.04 | BC63: 0.04 | BD63: 0.04 | BE63: 0.04 | BF63: 0.04 | BG63: 0.04 | BH63: 0.04 | BI63: 0.04 | BJ63: 0.04 | BK63: 0.04 | BL63: 0.04 | BM63: 0.04 | BN63: 0.04 | BO63: 0.04 | BP63: 0.04 | BQ63: 0.04 | BR63: 0.04 | BS63: 0.04 | BT63: 0.04 | BU63: 0.04 | BV63: 0.04 | BW63: 0.04 | BX63: 0.04 | BY63: 0.04 | BZ63: 0.04 | CA63: 0.04 | CB63: 0.04 | CC63: 0.04 | CD63: 0.04 | CE63: 0.04 | CF63: 0.04 | CG63: 0.04 | CH63: 0.04 | CI63: 0.04 | CJ63: 0.04 | CK63: 0.04 | CL63: 0.04 | CM63: 0.04 | CN63: 0.04 | CO63: 0.04 | CP63: 0.04 | CQ63: 0.04 | CR63: 0.04 | CS63: 0.04 | CT63: 0.04 | CU63: 0.04 | CV63: 0.04 | CW63: 0.04
A64: Repayment Period | J64: =+J51 -> 1 | K64: =+K51 -> 2 | L64: =+L51 -> 1 | M64: =+M51 -> 2 | N64: =+N51 -> 3 | O64: =+O51 -> 4 | P64: =+P51 -> 5 | Q64: =+Q51 -> 6 | ... CW64: =+CW51 -> 90
A65: Repayment Date | B65: =B52 -> 42992 | C65: =C52 -> 43083 | D65: =D52 -> 43174 | E65: =E52 -> 43265 | F65: =F52 -> 43356 | G65: =G52 -> 43447 | H65: =H52 -> 43538 | I65: =I52 -> 43629 | ... CW65: =CW52 -> 46553
A66: Opening Balance | B66: 0 | C66: =B72 -> 0 | D66: =C72 -> 0 | E66: =D72 -> 0 | F66: =E72 -> 0 | G66: =E17 -> 196100000 | H66: =G72 -> 196100000 | I66: =H72 -> 196100000 | J66: =I72 -> 196100000 | K66: =J72 -> 189971875 | L66: =K72 -> 183843750 | M66: =L72 -> 1.8208877e+08 | N66: =M72 -> 1.8032795e+08 | O66: =N72 -> 1.7856125e+08 | ... CW66: =CV72 -> 2359922.8
A67: Interest Payment | B67: 0 | C67: 0 | D67: =D66*(D65-$D$16)*D63/360 -> 0 | E67: =D72*(E65-D65)*E63/360 -> 0 | F67: =E72*(F65-E65)*F63/360 -> 0 | G67: =G66*(G65-E16)*G63/360 -> 2478486.1 | H67: =G72*(H65-G65)*H63/360 -> 1982788.9 | I67: =H72*(I65-H65)*I63/360 -> 1982788.9 | J67: =I72*(J65-I65)*J63/360 -> 2048155.6 | K67: =J72*(K65-J65)*K63/360 -> 1920826.7 | L67: =K72*(L65-K65)*L63/360 -> 633239.58 | M67: =L72*(M65-L65)*M63/360 -> 586730.49 | N67: =M72*(N65-M65)*N63/360 -> 621129.59 | O67: =N72*(O65-N65)*O63/360 -> 615044.31 | ... CW67: =CV72*(CW65-CV65)*CW63/360 -> 8128.623
A68: Cumulative interest | B68: =B67 -> 0 | C68: =B68+C67 -> 0 | D68: =C68+D67 -> 0 | E68: =D68+E67 -> 0 | F68: =E68+F67 -> 0 | G68: =G67+F68 -> 2478486.1 | H68: =H67+G68 -> 4461275 | I68: =I67+H68 -> 6444063.9 | J68: =J67+I68 -> 8492219.4 | K68: =K67+J68 -> 10413046 | L68: =L67+K68 -> 11046286 | M68: =M67+L68 -> 11633016 | N68: =N67+M68 -> 12254146 | ... CW68: =CW67+CV68 -> 40101175
A69: Principal Payment | B69: 0 | C69: 0 | D69: 0 | E69: 0 | F69: 0 | G69: 0 | H69: 0 | I69: 0 | J69: =$E$17/$C$13 -> 6128125 | K69: =$E$17/$C$13 -> 6128125 | L69: =-PPMT($L$63/12,L64,$CW$64,$L$66,0) -> 1754976.7 | M69: =-PPMT($L$63/12,M64,$CW$64,$L$66,0) -> 1760826.6 | N69: =-PPMT($L$63/12,N64,$CW$64,$L$66,0) -> 1766696.1 | O69: =-PPMT($L$63/12,O64,$CW$64,$L$66,0) -> 1772585.1 | P69: =-PPMT($L$63/12,P64,$CW$64,$L$66,0) -> 1778493.7 | Q69: =-PPMT($L$63/12,Q64,$CW$64,$L$66,0) -> 1784422 | R69: =-PPMT($L$63/12,R64,$CW$64,$L$66,0) -> 1790370.1 | S69: =-PPMT($L$63/12,S64,$CW$64,$L$66,0) -> 1796338 | ... CW69: =-PPMT($L$63/12,CW64,$CW$64,$L$66,0) -> 2359922.8
A70: Cumulative repayment | B70: 0 | C70: =C69+B70 -> 0 | D70: =D69+C70 -> 0 | E70: =E69+D70 -> 0 | F70: =F69+E70 -> 0 | G70: =G69+F70 -> 0 | H70: =H69+G70 -> 0 | I70: =I69+H70 -> 0 | J70: =J69+I70 -> 6128125 | ... CW70: =CW69+CV70 -> 1.961e+08
A71: Total Debt Service | B71: =B67+B69 -> 0 | C71: =C67+C69 -> 0 | D71: =D67+D69 -> 0 | E71: =E67+E69 -> 0 | F71: =F67+F69 -> 0 | G71: =G67+G69 -> 2478486.1 | H71: =H67+H69 -> 1982788.9 | I71: =I67+I69 -> 1982788.9 | ... CW71: =CW67+CW69 -> 2368051.4
A72: Closing Balance | B72: =B66-B69 -> 0 | C72: =C66-C69 -> 0 | D72: =D66-D69 -> 0 | E72: =E66-E69 -> 0 | F72: =F66-F69 -> 0 | G72: =G66-G69 -> 196100000 | H72: =H66-H69 -> 196100000 | I72: =I66-I69 -> 196100000 | ... CW72: =CW66-CW69 -> -1.0244548e-08
A80: Average Installment Size | B80: =B26 -> 42992 | C80: =C26 -> 43083 | D80: =D26 -> 43174 | E80: =E26 -> 43265 | F80: =F26 -> 43356 | G80: =G26 -> 43447 | H80: =H26 -> 43538 | I80: =I26 -> 43629 | ... CW80: =CW26 -> 46553
B81: =AVERAGE($B$32) -> 1372338.3 | C81: =AVERAGE($B$32:C32) -> 1781632.2 | D81: =AVERAGE($B$32:D32) -> 3021397 | E81: =AVERAGE($B$32:E32) -> 4980628.3 | F81: =AVERAGE($B$32:F32) -> 6156167.1 | G81: =AVERAGE($B$32:G32) -> 7352940.6 | H81: =AVERAGE($B$32:H32) -> 8136965 | I81: =AVERAGE($B$32:I32) -> 8724983.3 | J81: =AVERAGE($B$32:J32) -> 13639090 | K81: =AVERAGE($B$32:K32) -> 17487914 | L81: =AVERAGE($L$32) -> 15466776 | M81: =AVERAGE($L$32:M32) -> 15335115 | N81: =AVERAGE($L$32:N32) -> 15378159 | O81: =AVERAGE($L$32:O32) -> 15399363 | P81: =AVERAGE($L$32:P32) -> 15360944 | Q81: =AVERAGE($L$32:Q32) -> 15398512 | R81: =AVERAGE($L$32:R32) -> 15389366 | S81: =AVERAGE($L$32:S32) -> 15367085 | T81: =AVERAGE($L$32:T32) -> 15404153 | ... CW81: =AVERAGE($L$32:CW32) -> 15365487
A84: Annual Monitoring Fee
A85: Date | C85: 42816 | D85: 43264 | E85: =EDATE(D85,12) -> 43629 | F85: =EDATE(E85,12) -> 43995 | G85: =EDATE(F85,12) -> 44360 | H85: =EDATE(G85,12) -> 44725 | I85: =EDATE(H85,12) -> 45090 | J85: =EDATE(I85,12) -> 45456 | K85: =EDATE(J85,12) -> 45821
A86: Amount (BDT) | C86: 200000 | D86: 200000 | E86: 200000 | F86: 200000 | G86: 200000 | H86: 200000 | I86: 200000 | J86: 200000 | K86: 200000

Sheet Accrual_MCML 
A1: Project name: | B1: =MCML_Loan!C1 -> Meghna Cement Mills Limited (MCML)
A3: Assumptions:
A5: Agreement signing date | B5: =MCML_Loan!C3 -> 42899
A7: Loan Amount | B7: =MCML_Loan!C5 -> 1270000000 | C7: BDT
A9: Interest Rate | B9: =MCML_Loan!C8 -> 0.07
A10: Tenor | B10: 10 years
A11: Interest calculation | B11: 360 | C11: days basis
A12: Principal | B12: =MCML_Loan!C11 -> Level principal
A14: Drawdown
C15: =MCML_Loan!C16 -> 42935 | D15: =MCML_Loan!D16 -> 43151 | E15: =MCML_Loan!E16 -> 43382
C16: =MCML_Loan!C17 -> 123820000 | D16: =MCML_Loan!D17 -> 950080000 | E16: =MCML_Loan!E17 -> 196100000
C17: =C16 -> 123820000 | D17: =D16+C17 -> 1073900000 | E17: =E16+D17 -> 1270000000
A20: Expected Interest Rate | B20: 0.07 | C20: 0.07 | D20: 0.07 | E20: 0.07 | F20: 0.07 | G20: 0.04 | H20: 0.04 | I20: 0.04 | J20: 0.04 | K20: 0.04 | L20: 0.04 | M20: 0.04 | N20: 0.04 | O20: 0.04 | P20: 0.04 | Q20: 0.04 | R20: 0.04 | S20: 0.04 | T20: 0.04 | U20: 0.04 | V20: 0.04 | W20: 0.04 | X20: 0.04 | Y20: 0.04 | Z20: 0.04 | AA20: 0.04 | AB20: 0.04 | AC20: 0.04 | AD20: 0.04 | AE20: 0.04 | AF20: 0.04 | AG20: 0.04 | AH20: 0.04 | AI20: 0.04 | AJ20: 0.04 | AK20: 0.04 | AL20: 0.04 | AM20: 0.04 | AN20: 0.04 | AO20: 0.04 | AP20: 0.04 | AQ20: 0.04 | AR20: 0.04 | AS20: 0.04 | AT20: 0.04 | AU20: 0.04 | AV20: 0.04 | AW20: 0.04 | AX20: 0.04 | AY20: 0.04 | AZ20: 0.04 | BA20: 0.04 | BB20: 0.04 | BC20: 0.04 | BD20: 0.04 | BE20: 0.04 | BF20: 0.04 | BG20: 0.04 | BH20: 0.04 | BI20: 0.04 | BJ20: 0.04 | BK20: 0.04 | BL20: 0.04 | BM20: 0.04 | BN20: 0.04 | BO20: 0.04 | BP20: 0.04 | BQ20: 0.04 | BR20: 0.04 | BS20: 0.04 | BT20: 0.04 | BU20: 0.04 | BV20: 0.04 | BW20: 0.04 | BX20: 0.04 | BY20: 0.04 | BZ20: 0.04 | CA20: 0.04 | CB20: 0.04 | CC20: 0.04 | CD20: 0.04 | CE20: 0.04 | CF20: 0.04 | CG20: 0.04 | CH20: 0.04 | CI20: 0.04 | CJ20: 0.04 | CK20: 0.04 | CL20: 0.04 | CM20: 0.04 | CN20: 0.04 | CO20: 0.04 | CP20: 0.04 | CQ20: 0.04 | CR20: 0.04 | CS20: 0.04 | CT20: 0.04 | CU20: 0.04 | CV20: 0.04 | CW20: 0.04 | CX20: 0.04 | CY20: 0.04 | CZ20: 0.04 | DA20: 0.04 | DB20: 0.04 | DC20: 0.04 | DD20: 0.04 | DE20: 0.04 | DF20: 0.04 | DG20: 0.04 | DH20: 0.04 | DI20: 0.04 | DJ20: 0.04 | DK20: 0.04 | DL20: 0.04 | DM20: 0.04 | DN20: 0.04 | DO20: 0.04 | DP20: 0.04 | DQ20: 0.04 | DR20: 0.04 | DS20: 0.04
A21: Cumulative Accrual
A22: Months | B22: 42948 | C22: =EDATE(B22,1) -> 42979 | D22: =EDATE(C22,1) -> 43009 | E22: =EDATE(D22,1) -> 43040 | F22: =EDATE(E22,1) -> 43070 | G22: =EDATE(F22,1) -> 43101 | H22: =EDATE(G22,1) -> 43132 | I22: =EDATE(H22,1) -> 43160 | J22: =EDATE(I22,1) -> 43191 | ... DQ22: =EDATE(DP22,1) -> 46569
A23: Opening Balance | B23: =B35+B47+B59 -> 123820000 | C23: =C35+C47+C59 -> 123820000 | D23: =D35+D47+D59 -> 123820000 | E23: =E35+E47+E59 -> 123820000 | F23: =F35+F47+F59 -> 123820000 | G23: =G35+G47+G59 -> 123820000 | H23: =H35+H47+H59 -> 123820000 | I23: =I35+I47+I59 -> 1073900000 | ... DQ23: =DQ35+DQ47+DQ59 -> 15283539
A24: Interest Payment | B24: =B36+B48+B60 -> 312989.44 | C24: =C36+C48+C60 -> 746359.44 | D24: =D36+D48+D60 -> 722283.33 | E24: =E36+E48+E60 -> 746359.44 | F24: =F36+F48+F60 -> 722283.33 | G24: =G36+G48+G60 -> 560629.44 | H24: =H36+H48+H60 -> 426491.11 | I24: =I36+I48+I60 -> 2047857.8 | ... DQ24: =DQ36+DQ48+DQ60 -> 23774.394
A25: Cumulative interest | B25: =B24 -> 312989.44 | C25: =B25+C24 -> 1059348.9 | D25: =C25+D24 -> 1781632.2 | E25: =D25+E24 -> 2527991.7 | F25: =E25+F24 -> 3250275 | G25: =F25+G24 -> 3810904.4 | H25: =G25+H24 -> 4237395.6 | I25: =H25+I24 -> 6285253.3 | J25: =I25+J24 -> 11092669 | ... DQ25: =DP25+DQ24 -> 2.87773e+08
A26: Principal Payment | B26: =B38+B50+B62 -> 0 | C26: =C38+C50+C62 -> 0 | D26: =D38+D50+D62 -> 0 | E26: =E38+E50+E62 -> 0 | F26: =F38+F50+F62 -> 0 | G26: =G38+G50+G62 -> 0 | H26: =H38+H50+H62 -> 0 | I26: =I38+I50+I62 -> 0 | ... DQ26: =DQ38+DQ50+DQ62 -> 15283539
A27: Cumulative repayment | B27: =B26 -> 0 | C27: =B27+C26 -> 0 | D27: =C27+D26 -> 0 | E27: =D27+E26 -> 0 | F27: =E27+F26 -> 0 | G27: =F27+G26 -> 0 | H27: =G27+H26 -> 0 | I27: =H27+I26 -> 0 | J27: =I27+J26 -> 0 | ... DQ27: =DP27+DQ26 -> 1.27e+09
A28: Total Debt Service | B28: =B26+B24 -> 312989.44 | C28: =C26+C24 -> 746359.44 | D28: =D26+D24 -> 722283.33 | E28: =E26+E24 -> 746359.44 | F28: =F26+F24 -> 722283.33 | G28: =G26+G24 -> 560629.44 | H28: =H26+H24 -> 426491.11 | I28: =I26+I24 -> 2047857.8 | ... DQ28: =DQ26+DQ24 -> 15307313
A29: Closing Balance | B29: =B23-B26 -> 123820000 | C29: =C23-C26 -> 123820000 | D29: =D23-D26 -> 123820000 | E29: =E23-E26 -> 123820000 | F29: =F23-F26 -> 123820000 | G29: =G23-G26 -> 123820000 | H29: =H23-H26 -> 123820000 | I29: =I23-I26 -> 1073900000 | ... DQ29: =DQ23-DQ26 -> -6.519258e-08
DQ30: =+DQ25-MCML_Loan!CW29 -> 0
A31: Disbursement-1
A32: Period | B32: 42947 | C32: =EDATE(B32,1) -> 42978 | D32: =EDATE(C32,1) -> 43008 | E32: =EDATE(D32,1) -> 43038 | F32: =EDATE(E32,1) -> 43069 | G32: =EDATE(F32,1) -> 43099 | H32: =EDATE(G32,1) -> 43130 | I32: =EDATE(H32,1) -> 43159 | J32: =EDATE(I32,1) -> 43187 | ... DS32: =EDATE(DR32,1) -> 46627
A33: Expected Interest Rate | B33: 0.07 | C33: 0.07 | D33: 0.07 | E33: 0.07 | F33: 0.07 | G33: 0.04 | H33: 0.04 | I33: 0.04 | J33: 0.04 | K33: 0.04 | L33: 0.04 | M33: 0.04 | N33: 0.04 | O33: 0.04 | P33: 0.04 | Q33: 0.04 | R33: 0.04 | S33: 0.04 | T33: 0.04 | U33: 0.04 | V33: 0.04 | W33: 0.04 | X33: 0.04 | Y33: 0.04 | Z33: 0.04 | AA33: 0.04 | AB33: 0.04 | AC33: 0.04 | AD33: 0.04 | AE33: 0.04 | AF33: 0.04 | AG33: 0.04 | AH33: 0.04 | AI33: 0.04 | AJ33: 0.04 | AK33: 0.04 | AL33: 0.04 | AM33: 0.04 | AN33: 0.04 | AO33: 0.04 | AP33: 0.04 | AQ33: 0.04 | AR33: 0.04 | AS33: 0.04 | AT33: 0.04 | AU33: 0.04 | AV33: 0.04 | AW33: 0.04 | AX33: 0.04 | AY33: 0.04 | AZ33: 0.04 | BA33: 0.04 | BB33: 0.04 | BC33: 0.04 | BD33: 0.04 | BE33: 0.04 | BF33: 0.04 | BG33: 0.04 | BH33: 0.04 | BI33: 0.04 | BJ33: 0.04 | BK33: 0.04 | BL33: 0.04 | BM33: 0.04 | BN33: 0.04 | BO33: 0.04 | BP33: 0.04 | BQ33: 0.04 | BR33: 0.04 | BS33: 0.04 | BT33: 0.04 | BU33: 0.04 | BV33: 0.04 | BW33: 0.04 | BX33: 0.04 | BY33: 0.04 | BZ33: 0.04 | CA33: 0.04 | CB33: 0.04 | CC33: 0.04 | CD33: 0.04 | CE33: 0.04 | CF33: 0.04 | CG33: 0.04 | CH33: 0.04 | CI33: 0.04 | CJ33: 0.04 | CK33: 0.04 | CL33: 0.04 | CM33: 0.04 | CN33: 0.04 | CO33: 0.04 | CP33: 0.04 | CQ33: 0.04 | CR33: 0.04 | CS33: 0.04 | CT33: 0.04 | CU33: 0.04 | CV33: 0.04 | CW33: 0.04 | CX33: 0.04 | CY33: 0.04 | CZ33: 0.04 | DA33: 0.04 | DB33: 0.04 | DC33: 0.04 | DD33: 0.04 | DE33: 0.04 | DF33: 0.04 | DG33: 0.04 | DH33: 0.04 | DI33: 0.04 | DJ33: 0.04 | DK33: 0.04 | DL33: 0.04 | DM33: 0.04 | DN33: 0.04 | DO33: 0.04 | DP33: 0.04 | DQ33: 0.04 | DR33: 0.04 | DS33: 0.04
A34: Months | B34: 42948 | C34: =EDATE(B34,1) -> 42979 | D34: =EDATE(C34,1) -> 43009 | E34: =EDATE(D34,1) -> 43040 | F34: =EDATE(E34,1) -> 43070 | G34: =EDATE(F34,1) -> 43101 | H34: =EDATE(G34,1) -> 43132 | I34: =EDATE(H34,1) -> 43160 | J34: =EDATE(I34,1) -> 43191 | ... DQ34: =EDATE(DP34,1) -> 46569
A35: Opening Balance | B35: =C16 -> 123820000 | C35: =B41+F27 -> 123820000 | D35: =C41 -> 123820000 | E35: =D41 -> 123820000 | F35: =E41 -> 123820000 | G35: =F41 -> 123820000 | H35: =G41 -> 123820000 | I35: =H41 -> 123820000 | J35: =I41 -> 123820000 | K35: =J41 -> 123820000 | ... DQ35: =DP41 -> 1490084.9
A36: Interest Payment | B36: =B35*(B34-C15)*B33/360 -> 312989.44 | C36: =C35*(C34-B34)*C33/360 -> 746359.44 | D36: =D35*(D34-C34)*D33/360 -> 722283.33 | E36: =E35*(E34-D34)*E33/360 -> 746359.44 | F36: =F35*(F34-E34)*F33/360 -> 722283.33 | G36: =G35*(MCML_Loan!$C$26-F34)*F33/360+G41*(G34-MCML_Loan!$C$26)*G33/360 -> 560629.44 | H36: =H35*(H34-G34)*H33/360 -> 426491.11 | I36: =I35*(I34-H34)*I33/360 -> 385217.78 | J36: =J35*(J34-I34)*J33/360 -> 426491.11 | K36: =K35*(K34-J34)*K33/360 -> 412733.33 | L36: =L35*(L34-K34)*L33/360 -> 426491.11 | M36: =M35*(M34-L34)*M33/360 -> 412733.33 | N36: =N35*(N34-M34)*N33/360 -> 426491.11 | O36: =O35*(O34-N34)*O33/360 -> 426491.11 | ... AA36: =AA35*(AA34-Z34)*AA33/360 -> 426491.11 | AB36: =AB35*(MCML_Loan!$J$26-AA34)*AA33/360+AB41*(AB34-MCML_Loan!$J$26)*AB33/360 -> 405854.44 | AC36: =AC35*(AC34-AB34)*AC33/360 -> 413163.26 | AD36: =AD35*(AD34-AC34)*AD33/360 -> 399835.42 | AE36: =AE35*(MCML_Loan!$K$26-AD34)*AD33/360+AE41*(AE34-MCML_Loan!$K26)*AE33/360 -> 405854.44 | AF36: =+AF35*(MCML_Loan!L39-'Accrual_MCML '!AE34)*'Accrual_MCML '!AE33/360+'Accrual_MCML '!AF41*('Accrual_MCML '!AF34-MCML_Loan!L39)*'Accrual_MCML '!AF33/360 -> 397742.31 | AG36: =+AG35*(MCML_Loan!M39-'Accrual_MCML '!AF34)*'Accrual_MCML '!AF33/360+'Accrual_MCML '!AG41*('Accrual_MCML '!AG34-MCML_Loan!M39)*'Accrual_MCML '!AG33/360 -> 368368.91 | AH36: =+AH35*(MCML_Loan!N39-'Accrual_MCML '!AG34)*'Accrual_MCML '!AG33/360+'Accrual_MCML '!AH41*('Accrual_MCML '!AH34-MCML_Loan!N39)*'Accrual_MCML '!AH33/360 -> 390081.94 | AI36: =+AI35*(MCML_Loan!O39-'Accrual_MCML '!AH34)*'Accrual_MCML '!AH33/360+'Accrual_MCML '!AI41*('Accrual_MCML '!AI34-MCML_Loan!O39)*'Accrual_MCML '!AI33/360 -> 373829.63 | AJ36: =+AJ35*(MCML_Loan!P39-'Accrual_MCML '!AI34)*'Accrual_MCML '!AI33/360+'Accrual_MCML '!AJ41*('Accrual_MCML '!AJ34-MCML_Loan!P39)*'Accrual_MCML '!AJ33/360 -> 382245.63 | AK36: =+AK35*(MCML_Loan!Q39-'Accrual_MCML '!AJ34)*'Accrual_MCML '!AJ33/360+'Accrual_MCML '!AK41*('Accrual_MCML '!AK34-MCML_Loan!Q39)*'Accrual_MCML '!AK33/360 -> 366342.36 | AL36: =+AL35*(MCML_Loan!R39-'Accrual_MCML '!AK34)*'Accrual_MCML '!AK33/360+'Accrual_MCML '!AL41*('Accrual_MCML '!AL34-MCML_Loan!R39)*'Accrual_MCML '!AL33/360 -> 374607.38 | AM36: =+AM35*(MCML_Loan!S39-'Accrual_MCML '!AL34)*'Accrual_MCML '!AL33/360+'Accrual_MCML '!AM41*('Accrual_MCML '!AM34-MCML_Loan!S39)*'Accrual_MCML '!AM33/360 -> 370454.39 | ... DQ36: =+DQ35*(MCML_Loan!CW39-'Accrual_MCML '!DP34)*'Accrual_MCML '!DP33/360+'Accrual_MCML '!DQ41*('Accrual_MCML '!DQ34-MCML_Loan!CW39)*'Accrual_MCML '!DQ33/360 -> 2317.9098
A37: Cumulative interest | B37: =B36 -> 312989.44 | C37: =B37+C36 -> 1059348.9 | D37: =C37+D36 -> 1781632.2 | E37: =D37+E36 -> 2527991.7 | F37: =E37+F36 -> 3250275 | G37: =F37+G36 -> 3810904.4 | H37: =G37+H36 -> 4237395.6 | I37: =H37+I36 -> 4622613.3 | J37: =I37+J36 -> 5049104.4 | ... DQ37: =DP37+DQ36 -> 32326533
A38: Principal Payment | B38: 0 | C38: =B38 -> 0 | D38: =C38 -> 0 | E38: =D38 -> 0 | F38: =E38 -> 0 | G38: =F38 -> 0 | H38: =G38 -> 0 | I38: =H38 -> 0 | J38: =I38 -> 0 | ... AA38: =Z38 -> 0 | AB38: =MCML_Loan!$J$43 -> 3869375 | AC38: =Z38 -> 0 | AD38: =AA38 -> 0 | AE38: =MCML_Loan!$K$43 -> 3869375 | AF38: =+MCML_Loan!L43 -> 1108114.3 | AG38: =+MCML_Loan!M43 -> 1111808 | AH38: =+MCML_Loan!N43 -> 1115514.1 | AI38: =+MCML_Loan!O43 -> 1119232.4 | AJ38: =+MCML_Loan!P43 -> 1122963.2 | AK38: =+MCML_Loan!Q43 -> 1126706.4 | AL38: =+MCML_Loan!R43 -> 1130462.1 | AM38: =+MCML_Loan!S43 -> 1134230.3 | ... DQ38: =+MCML_Loan!CW43 -> 1490084.9
A39: Cumulative repayment | B39: =B38 -> 0 | C39: =B39+C38 -> 0 | D39: =C39+D38 -> 0 | E39: =D39+E38 -> 0 | F39: =E39+F38 -> 0 | G39: =F39+G38 -> 0 | H39: =G39+H38 -> 0 | I39: =H39+I38 -> 0 | J39: =I39+J38 -> 0 | ... DQ39: =DP39+DQ38 -> 1.2382e+08
A40: Total Debt Service | B40: =B38+B36 -> 312989.44 | C40: =C38+C36 -> 746359.44 | D40: =D38+D36 -> 722283.33 | E40: =E38+E36 -> 746359.44 | F40: =F38+F36 -> 722283.33 | G40: =G38+G36 -> 560629.44 | H40: =H38+H36 -> 426491.11 | I40: =I38+I36 -> 385217.78 | ... DQ40: =DQ38+DQ36 -> 1492402.8
A41: Closing Balance | B41: =B35-B38 -> 123820000 | C41: =C35-C38 -> 123820000 | D41: =D35-D38 -> 123820000 | E41: =E35-E38 -> 123820000 | F41: =F35-F38 -> 123820000 | G41: =G35-G38 -> 123820000 | H41: =H35-H38 -> 123820000 | I41: =I35-I38 -> 123820000 | ... DQ41: =DQ35-DQ38 -> -3.981404e-08
A43: Disbursement-2
A44: Period | B44: 42947 | C44: =EDATE(B44,1) -> 42978 | D44: =EDATE(C44,1) -> 43008 | E44: =EDATE(D44,1) -> 43038 | F44: =EDATE(E44,1) -> 43069 | G44: =EDATE(F44,1) -> 43099 | H44: =EDATE(G44,1) -> 43130 | I44: =EDATE(H44,1) -> 43159 | J44: =EDATE(I44,1) -> 43187 | ... DS44: =EDATE(DR44,1) -> 46627
A45: Expected Interest Rate | B45: 0.07 | C45: 0.07 | D45: 0.07 | E45: 0.07 | F45: 0.07 | G45: 0.07 | H45: 0.07 | I45: 0.07 | J45: 0.04 | K45: 0.04 | L45: 0.04 | M45: 0.04 | N45: 0.04 | O45: 0.04 | P45: 0.04 | Q45: 0.04 | R45: 0.04 | S45: 0.04 | T45: 0.04 | U45: 0.04 | V45: 0.04 | W45: 0.04 | X45: 0.04 | Y45: 0.04 | Z45: 0.04 | AA45: 0.04 | AB45: 0.04 | AC45: 0.04 | AD45: 0.04 | AE45: 0.04 | AF45: 0.04 | AG45: 0.04 | AH45: 0.04 | AI45: 0.04 | AJ45: 0.04 | AK45: 0.04 | AL45: 0.04 | AM45: 0.04 | AN45: 0.04 | AO45: 0.04 | AP45: 0.04 | AQ45: 0.04 | AR45: 0.04 | AS45: 0.04 | AT45: 0.04 | AU45: 0.04 | AV45: 0.04 | AW45: 0.04 | AX45: 0.04 | AY45: 0.04 | AZ45: 0.04 | BA45: 0.04 | BB45: 0.04 | BC45: 0.04 | BD45: 0.04 | BE45: 0.04 | BF45: 0.04 | BG45: 0.04 | BH45: 0.04 | BI45: 0.04 | BJ45: 0.04 | BK45: 0.04 | BL45: 0.04 | BM45: 0.04 | BN45: 0.04 | BO45: 0.04 | BP45: 0.04 | BQ45: 0.04 | BR45: 0.04 | BS45: 0.04 | BT45: 0.04 | BU45: 0.04 | BV45: 0.04 | BW45: 0.04 | BX45: 0.04 | BY45: 0.04 | BZ45: 0.04 | CA45: 0.04 | CB45: 0.04 | CC45: 0.04 | CD45: 0.04 | CE45: 0.04 | CF45: 0.04 | CG45: 0.04 | CH45: 0.04 | CI45: 0.04 | CJ45: 0.04 | CK45: 0.04 | CL45: 0.04 | CM45: 0.04 | CN45: 0.04 | CO45: 0.04 | CP45: 0.04 | CQ45: 0.04 | CR45: 0.04 | CS45: 0.04 | CT45: 0.04 | CU45: 0.04 | CV45: 0.04 | CW45: 0.04 | CX45: 0.04 | CY45: 0.04 | CZ45: 0.04 | DA45: 0.04 | DB45: 0.04 | DC45: 0.04 | DD45: 0.04 | DE45: 0.04 | DF45: 0.04 | DG45: 0.04 | DH45: 0.04 | DI45: 0.04 | DJ45: 0.04 | DK45: 0.04 | DL45: 0.04 | DM45: 0.04 | DN45: 0.04 | DO45: 0.04 | DP45: 0.04 | DQ45: 0.04 | DR45: 0.04 | DS45: 0.04
A46: Months | B46: 42948 | C46: =EDATE(B46,1) -> 42979 | D46: =EDATE(C46,1) -> 43009 | E46: =EDATE(D46,1) -> 43040 | F46: =EDATE(E46,1) -> 43070 | G46: =EDATE(F46,1) -> 43101 | H46: =EDATE(G46,1) -> 43132 | I46: =EDATE(H46,1) -> 43160 | J46: =EDATE(I46,1) -> 43191 | ... DQ46: =EDATE(DP46,1) -> 46569
A47: Opening Balance | I47: =D16 -> 950080000 | J47: =I53 -> 950080000 | K47: =J53 -> 950080000 | L47: =K53 -> 950080000 | M47: =L53 -> 950080000 | N47: =M53 -> 950080000 | O47: =N53 -> 950080000 | P47: =O53 -> 950080000 | Q47: =P53 -> 950080000 | ... DQ47: =DP53 -> 11433531
A48: Interest Payment | I48: =I47*(I46-D15)*I45/360 -> 1662640 | J48: =J47*(MCML_Loan!$D$52-I46)*I45/360+J53*(J46-MCML_Loan!$D$52)*J45/360 -> 4380924.4 | K48: =K47*(K46-J46)*K45/360 -> 3166933.3 | L48: =L47*(L46-K46)*L45/360 -> 3272497.8 | M48: =M47*(M46-L46)*M45/360 -> 3166933.3 | N48: =N47*(N46-M46)*N45/360 -> 3272497.8 | O48: =O47*(O46-N46)*O45/360 -> 3272497.8 | P48: =P47*(P46-O46)*P45/360 -> 3166933.3 | Q48: =Q47*(Q46-P46)*Q45/360 -> 3272497.8 | R48: =R47*(R46-Q46)*R45/360 -> 3166933.3 | ... AA48: =AA47*(AA46-Z46)*AA45/360 -> 3272497.8 | AB48: =AB47*(MCML_Loan!$J$26-AA46)*AA45/360+AB53*(AB46-MCML_Loan!$J$26)*AB45/360 -> 3114151.1 | AC48: =AC47*(AC46-AB46)*AC45/360 -> 3170232.2 | AD48: =AD47*(AD46-AC46)*AD45/360 -> 3067966.7 | AE48: =AE47*(MCML_Loan!$K$26-AD46)*AD45/360+AE53*(AE46-MCML_Loan!$K$26)*AE45/360 -> 3114151.1 | AF48: =+AF47*(MCML_Loan!L52-'Accrual_MCML '!AE46)*'Accrual_MCML '!AE45/360+'Accrual_MCML '!AF53*('Accrual_MCML '!AF46-MCML_Loan!L52)*'Accrual_MCML '!AF45/360 -> 3051906.1 | AG48: =+AG47*(MCML_Loan!M52-'Accrual_MCML '!AF46)*'Accrual_MCML '!AF45/360+'Accrual_MCML '!AG53*('Accrual_MCML '!AG46-MCML_Loan!M52)*'Accrual_MCML '!AG45/360 -> 2826521.8 | AH48: =+AH47*(MCML_Loan!N52-'Accrual_MCML '!AG46)*'Accrual_MCML '!AG45/360+'Accrual_MCML '!AH53*('Accrual_MCML '!AH46-MCML_Loan!N52)*'Accrual_MCML '!AH45/360 -> 2993127.5 | AI48: =+AI47*(MCML_Loan!O52-'Accrual_MCML '!AH46)*'Accrual_MCML '!AH45/360+'Accrual_MCML '!AI53*('Accrual_MCML '!AI46-MCML_Loan!O52)*'Accrual_MCML '!AI45/360 -> 2868422.4 | AJ48: =+AJ47*(MCML_Loan!P52-'Accrual_MCML '!AI46)*'Accrual_MCML '!AI45/360+'Accrual_MCML '!AJ53*('Accrual_MCML '!AJ46-MCML_Loan!P52)*'Accrual_MCML '!AJ45/360 -> 2932998.9 | AK48: =+AK47*(MCML_Loan!Q52-'Accrual_MCML '!AJ46)*'Accrual_MCML '!AJ45/360+'Accrual_MCML '!AK53*('Accrual_MCML '!AK46-MCML_Loan!Q52)*'Accrual_MCML '!AK45/360 -> 2810972 | AL48: =+AL47*(MCML_Loan!R52-'Accrual_MCML '!AK46)*'Accrual_MCML '!AK45/360+'Accrual_MCML '!AL53*('Accrual_MCML '!AL46-MCML_Loan!R52)*'Accrual_MCML '!AL45/360 -> 2874390.1 | AM48: =+AM47*(MCML_Loan!S52-'Accrual_MCML '!AL46)*'Accrual_MCML '!AL45/360+'Accrual_MCML '!AM53*('Accrual_MCML '!AM46-MCML_Loan!S52)*'Accrual_MCML '!AM45/360 -> 2842523.9 | ... DQ48: =+DQ47*(MCML_Loan!CW52-'Accrual_MCML '!DP46)*'Accrual_MCML '!DP45/360+'Accrual_MCML '!DQ53*('Accrual_MCML '!DQ46-MCML_Loan!CW52)*'Accrual_MCML '!DQ45/360 -> 17785.493
A49: Cumulative interest | I49: =H49+I48 -> 1662640 | J49: =I49+J48 -> 6043564.4 | K49: =J49+K48 -> 9210497.8 | L49: =K49+L48 -> 12482996 | M49: =L49+M48 -> 15649929 | N49: =M49+N48 -> 18922427 | O49: =N49+O48 -> 22194924 | P49: =O49+P48 -> 25361858 | ... DQ49: =DP49+DQ48 -> 2.1534529e+08
A50: Principal Payment | I50: =H50 -> 0 | J50: =I50 -> 0 | K50: =J50 -> 0 | L50: =K50 -> 0 | M50: =L50 -> 0 | N50: =M50 -> 0 | O50: =N50 -> 0 | P50: =O50 -> 0 | ... AA50: =Z50 -> 0 | AB50: =MCML_Loan!$J$56 -> 29690000 | AC50: =Z50 -> 0 | AD50: =AA50 -> 0 | AE50: =MCML_Loan!$K$56 -> 29690000 | AF50: =+MCML_Loan!L56 -> 8502643 | AG50: =+MCML_Loan!M56 -> 8530985.1 | AH50: =+MCML_Loan!N56 -> 8559421.7 | AI50: =+MCML_Loan!O56 -> 8587953.1 | AJ50: =+MCML_Loan!P56 -> 8616579.7 | AK50: =+MCML_Loan!Q56 -> 8645301.6 | AL50: =+MCML_Loan!R56 -> 8674119.3 | AM50: =+MCML_Loan!S56 -> 8703033 | ... DQ50: =+MCML_Loan!CW56 -> 11433531
A51: Cumulative repayment | I51: =H51+I50 -> 0 | J51: =I51+J50 -> 0 | K51: =J51+K50 -> 0 | L51: =K51+L50 -> 0 | M51: =L51+M50 -> 0 | N51: =M51+N50 -> 0 | O51: =N51+O50 -> 0 | P51: =O51+P50 -> 0 | ... DQ51: =DP51+DQ50 -> 9.5008e+08
A52: Total Debt Service | I52: =I50+I48 -> 1662640 | J52: =J50+J48 -> 4380924.4 | K52: =K50+K48 -> 3166933.3 | L52: =L50+L48 -> 3272497.8 | M52: =M50+M48 -> 3166933.3 | N52: =N50+N48 -> 3272497.8 | O52: =O50+O48 -> 3272497.8 | P52: =P50+P48 -> 3166933.3 | ... DQ52: =DQ50+DQ48 -> 11451317
A53: Closing Balance | I53: =I47-I50 -> 950080000 | J53: =J47-J50 -> 950080000 | K53: =K47-K50 -> 950080000 | L53: =L47-L50 -> 950080000 | M53: =M47-M50 -> 950080000 | N53: =N47-N50 -> 950080000 | O53: =O47-O50 -> 950080000 | P53: =P47-P50 -> 950080000 | ... DQ53: =DQ47-DQ50 -> -1.4901161e-08
A55: Disbursement-3
A56: Period | B56: 42947 | C56: =EDATE(B56,1) -> 42978 | D56: =EDATE(C56,1) -> 43008 | E56: =EDATE(D56,1) -> 43038 | F56: =EDATE(E56,1) -> 43069 | G56: =EDATE(F56,1) -> 43099 | H56: =EDATE(G56,1) -> 43130 | I56: =EDATE(H56,1) -> 43159 | J56: =EDATE(I56,1) -> 43187 | ... DS56: =EDATE(DR56,1) -> 46627
A57: Expected Interest Rate | B57: 0.07 | C57: 0.07 | D57: 0.07 | E57: 0.07 | F57: 0.07 | G57: 0.07 | H57: 0.07 | I57: 0.07 | J57: 0.07 | K57: 0.07 | L57: 0.07 | M57: 0.07 | N57: 0.07 | O57: 0.07 | P57: 0.07 | Q57: 0.07 | R57: 0.07 | S57: 0.04 | T57: 0.04 | U57: 0.04 | V57: 0.04 | W57: 0.04 | X57: 0.04 | Y57: 0.04 | Z57: 0.04 | AA57: 0.04 | AB57: 0.04 | AC57: 0.04 | AD57: 0.04 | AE57: 0.04 | AF57: 0.04 | AG57: 0.04 | AH57: 0.04 | AI57: 0.04 | AJ57: 0.04 | AK57: 0.04 | AL57: 0.04 | AM57: 0.04 | AN57: 0.04 | AO57: 0.04 | AP57: 0.04 | AQ57: 0.04 | AR57: 0.04 | AS57: 0.04 | AT57: 0.04 | AU57: 0.04 | AV57: 0.04 | AW57: 0.04 | AX57: 0.04 | AY57: 0.04 | AZ57: 0.04 | BA57: 0.04 | BB57: 0.04 | BC57: 0.04 | BD57: 0.04 | BE57: 0.04 | BF57: 0.04 | BG57: 0.04 | BH57: 0.04 | BI57: 0.04 | BJ57: 0.04 | BK57: 0.04 | BL57: 0.04 | BM57: 0.04 | BN57: 0.04 | BO57: 0.04 | BP57: 0.04 | BQ57: 0.04 | BR57: 0.04 | BS57: 0.04 | BT57: 0.04 | BU57: 0.04 | BV57: 0.04 | BW57: 0.04 | BX57: 0.04 | BY57: 0.04 | BZ57: 0.04 | CA57: 0.04 | CB57: 0.04 | CC57: 0.04 | CD57: 0.04 | CE57: 0.04 | CF57: 0.04 | CG57: 0.04 | CH57: 0.04 | CI57: 0.04 | CJ57: 0.04 | CK57: 0.04 | CL57: 0.04 | CM57: 0.04 | CN57: 0.04 | CO57: 0.04 | CP57: 0.04 | CQ57: 0.04 | CR57: 0.04 | CS57: 0.04 | CT57: 0.04 | CU57: 0.04 | CV57: 0.04 | CW57: 0.04 | CX57: 0.04 | CY57: 0.04 | CZ57: 0.04 | DA57: 0.04 | DB57: 0.04 | DC57: 0.04 | DD57: 0.04 | DE57: 0.04 | DF57: 0.04 | DG57: 0.04 | DH57: 0.04 | DI57: 0.04 | DJ57: 0.04 | DK57: 0.04 | DL57: 0.04 | DM57: 0.04 | DN57: 0.04 | DO57: 0.04 | DP57: 0.04 | DQ57: 0.04 | DR57: 0.04 | DS57: 0.04
A58: Months | B58: 42948 | C58: =EDATE(B58,1) -> 42979 | D58: =EDATE(C58,1) -> 43009 | E58: =EDATE(D58,1) -> 43040 | F58: =EDATE(E58,1) -> 43070 | G58: =EDATE(F58,1) -> 43101 | H58: =EDATE(G58,1) -> 43132 | I58: =EDATE(H58,1) -> 43160 | J58: =EDATE(I58,1) -> 43191 | ... DQ58: =EDATE(DP58,1) -> 46569
A59: Opening Balance | I59: 0 | J59: 0 | K59: 0 | L59: 0 | M59: 0 | N59: 0 | O59: 0 | P59: 0 | Q59: =E16 -> 196100000 | R59: =Q65 -> 196100000 | S59: =R65 -> 196100000 | T59: =S65 -> 196100000 | U59: =T65 -> 196100000 | V59: =U65 -> 196100000 | W59: =V65 -> 196100000 | X59: =W65 -> 196100000 | Y59: =X65 -> 196100000 | ... DQ59: =DP65 -> 2359922.8
A60: Interest Payment | I60: 0 | J60: 0 | K60: 0 | L60: 0 | M60: 0 | N60: 0 | O60: 0 | P60: 0 | Q60: =Q59*(Q58-E15)*Q57/360 -> 877002.78 | R60: =R59*(R58-Q58)*R57/360 -> 1143916.7 | S60: =S59*(MCML_Loan!$G$26-R58)*R57/360+S65*(S58-MCML_Loan!$G$26)*S57/360 -> 871555.56 | T60: =T59*(T58-S58)*T57/360 -> 675455.56 | U60: =U59*(U58-T58)*U57/360 -> 610088.89 | V60: =V59*(V58-U58)*V57/360 -> 675455.56 | W60: =W59*(W58-V58)*W57/360 -> 653666.67 | X60: =X59*(X58-W58)*X57/360 -> 675455.56 | Y60: =Y59*(Y58-X58)*Y57/360 -> 653666.67 | Z60: =Z59*(Z58-Y58)*Z57/360 -> 675455.56 | AA60: =AA59*(AA58-Z58)*AA57/360 -> 675455.56 | AB60: =AB59*(MCML_Loan!$J$26-AA58)*AA57/360+AB65*(AB58-MCML_Loan!$J$26)*AB57/360 -> 642772.22 | AC60: =AC59*(AC58-AB58)*AC57/360 -> 654347.57 | AD60: =AD59*(AD58-AC58)*AD57/360 -> 633239.58 | AE60: =AE59*(MCML_Loan!$K$26-AD58)*AD57/360+AE65*(AE58-MCML_Loan!$K$26)*AE57/360 -> 642772.22 | AF60: =+AF59*(MCML_Loan!L65-'Accrual_MCML '!AE58)*'Accrual_MCML '!AE57/360+'Accrual_MCML '!AF65*('Accrual_MCML '!AF58-MCML_Loan!L65)*'Accrual_MCML '!AF57/360 -> 629924.63 | AG60: =+AG59*(MCML_Loan!M65-'Accrual_MCML '!AF58)*'Accrual_MCML '!AF57/360+'Accrual_MCML '!AG65*('Accrual_MCML '!AG58-MCML_Loan!M65)*'Accrual_MCML '!AG57/360 -> 583404.49 | AH60: =+AH59*(MCML_Loan!N65-'Accrual_MCML '!AG58)*'Accrual_MCML '!AG57/360+'Accrual_MCML '!AH65*('Accrual_MCML '!AH58-MCML_Loan!N65)*'Accrual_MCML '!AH57/360 -> 617792.5 | AI60: =+AI59*(MCML_Loan!O65-'Accrual_MCML '!AH58)*'Accrual_MCML '!AH57/360+'Accrual_MCML '!AI65*('Accrual_MCML '!AI58-MCML_Loan!O65)*'Accrual_MCML '!AI57/360 -> 592052.91 | AJ60: =+AJ59*(MCML_Loan!P65-'Accrual_MCML '!AI58)*'Accrual_MCML '!AI57/360+'Accrual_MCML '!AJ65*('Accrual_MCML '!AJ58-MCML_Loan!P65)*'Accrual_MCML '!AJ57/360 -> 605381.75 | AK60: =+AK59*(MCML_Loan!Q65-'Accrual_MCML '!AJ58)*'Accrual_MCML '!AJ57/360+'Accrual_MCML '!AK65*('Accrual_MCML '!AK58-MCML_Loan!Q65)*'Accrual_MCML '!AK57/360 -> 580194.93 | AL60: =+AL59*(MCML_Loan!R65-'Accrual_MCML '!AK58)*'Accrual_MCML '!AK57/360+'Accrual_MCML '!AL65*('Accrual_MCML '!AL58-MCML_Loan!R65)*'Accrual_MCML '!AL57/360 -> 593284.66 | AM60: =+AM59*(MCML_Loan!S65-'Accrual_MCML '!AL58)*'Accrual_MCML '!AL57/360+'Accrual_MCML '!AM65*('Accrual_MCML '!AM58-MCML_Loan!S65)*'Accrual_MCML '!AM57/360 -> 586707.37 | ... DQ60: =+DQ59*(MCML_Loan!CW65-'Accrual_MCML '!DP58)*'Accrual_MCML '!DP57/360+'Accrual_MCML '!DQ65*('Accrual_MCML '!DQ58-MCML_Loan!CW65)*'Accrual_MCML '!DQ57/360 -> 3670.991
A61: Cumulative interest | I61: =H61+I60 -> 0 | J61: =I61+J60 -> 0 | K61: =J61+K60 -> 0 | L61: =K61+L60 -> 0 | M61: =L61+M60 -> 0 | N61: =M61+N60 -> 0 | O61: =N61+O60 -> 0 | P61: =O61+P60 -> 0 | ... DQ61: =DP61+DQ60 -> 40101175
A62: Principal Payment | I62: =H62 -> 0 | J62: =I62 -> 0 | K62: =J62 -> 0 | L62: =K62 -> 0 | M62: =L62 -> 0 | N62: =M62 -> 0 | O62: =N62 -> 0 | P62: =O62 -> 0 | ... AA62: =Z62 -> 0 | AB62: =MCML_Loan!$J$69 -> 6128125 | AC62: =Z62 -> 0 | AD62: =AA62 -> 0 | AE62: =MCML_Loan!$K$69 -> 6128125 | AF62: =+MCML_Loan!L69 -> 1754976.7 | AG62: =+MCML_Loan!M69 -> 1760826.6 | AH62: =+MCML_Loan!N69 -> 1766696.1 | AI62: =+MCML_Loan!O69 -> 1772585.1 | AJ62: =+MCML_Loan!P69 -> 1778493.7 | AK62: =+MCML_Loan!Q69 -> 1784422 | AL62: =+MCML_Loan!R69 -> 1790370.1 | AM62: =+MCML_Loan!S69 -> 1796338 | ... DQ62: =+MCML_Loan!CW69 -> 2359922.8
A63: Cumulative repayment | I63: =H63+I62 -> 0 | J63: =I63+J62 -> 0 | K63: =J63+K62 -> 0 | L63: =K63+L62 -> 0 | M63: =L63+M62 -> 0 | N63: =M63+N62 -> 0 | O63: =N63+O62 -> 0 | P63: =O63+P62 -> 0 | ... DQ63: =DP63+DQ62 -> 1.961e+08
A64: Total Debt Service | I64: =I62+I60 -> 0 | J64: =J62+J60 -> 0 | K64: =K62+K60 -> 0 | L64: =L62+L60 -> 0 | M64: =M62+M60 -> 0 | N64: =N62+N60 -> 0 | O64: =O62+O60 -> 0 | P64: =P62+P60 -> 0 | ... DQ64: =DQ62+DQ60 -> 2363593.8
A65: Closing Balance | I65: =I59-I62 -> 0 | J65: =J59-J62 -> 0 | K65: =K59-K62 -> 0 | L65: =L59-L62 -> 0 | M65: =M59-M62 -> 0 | N65: =N59-N62 -> 0 | O65: =O59-O62 -> 0 | P65: =P59-P62 -> 0 | ... DQ65: =DQ59-DQ62 -> -1.0244548e-08

Sheet Repayment Schedule
A1: Project name: | C1: =MCML_Loan!C1 -> Meghna Cement Mills Limited (MCML)
A3: Financial Close | C3: =MCML_Loan!C3 -> 42899
A5: Loan Amount | C5: =MCML_Loan!C5 -> 1270000000
A7: Interest Rate | C7: =MCML_Loan!C8 -> 0.07
A9: Number of installments | C9: =MCML_Loan!C13 -> 32
A11: Drawdown (IDCOL)
C12: =MCML_Loan!C16 -> 42935 | D12: =MCML_Loan!D16 -> 43151 | E12: =MCML_Loan!E16 -> 43382
C13: =MCML_Loan!C17 -> 123820000 | D13: =MCML_Loan!D17 -> 950080000 | E13: =MCML_Loan!E17 -> 196100000
C14: =C13 -> 123820000 | D14: =C14+D13 -> 1073900000 | E14: =D14+E13 -> 1270000000
A16: {=+TRANSPOSE(MCML_Loan!A26:CW33)} -> Repayment Date | B16: Opening Balance | C16: Interest Payment | D16: Cumulative interest | E16: Principal Payment | F16: Cumulative repayment | G16: Total Debt Service | H16: Closing Balance
A17: 42992 | B17: 123820000 | C17: 1372338.3 | D17: 1372338.3 | E17: 0 | F17: 0 | G17: 1372338.3 | H17: 123820000
A18: 43083 | B18: 123820000 | C18: 2190926.1 | D18: 3563264.4 | E18: 0 | F18: 0 | G18: 2190926.1 | H18: 123820000
A19: 43174 | B19: 1073900000 | C19: 5500926.7 | D19: 9064191.1 | E19: 0 | F19: 0 | G19: 5500926.7 | H19: 1073900000
A20: 43265 | B20: 1073900000 | C20: 10858322 | D20: 19922513 | E20: 0 | F20: 0 | G20: 10858322 | H20: 1073900000
A21: 43356 | B21: 1073900000 | C21: 10858322 | D21: 30780836 | E21: 0 | F21: 0 | G21: 10858322 | H21: 1073900000
A22: 43447 | B22: 1270000000 | C22: 13336808 | D22: 44117644 | E22: 0 | F22: 0 | G22: 13336808 | H22: 1270000000
A23: 43538 | B23: 1270000000 | C23: 12841111 | D23: 56958755 | E23: 0 | F23: 0 | G23: 12841111 | H23: 1270000000
A24: 43629 | B24: 1270000000 | C24: 12841111 | D24: 69799866 | E24: 0 | F24: 0 | G24: 12841111 | H24: 1270000000
A25: 43723 | B25: 1270000000 | C25: 13264444 | D25: 83064311 | E25: 39687500 | F25: 39687500 | G25: 52951944 | H25: 1230312500
A26: 43814 | B26: 1230312500 | C26: 12439826 | D26: 95504137 | E26: 39687500 | F26: 79375000 | G26: 52127326 | H26: 1190625000
A27: 43845 | B27: 1190625000 | C27: 4101041.7 | D27: 99605179 | E27: 11365734 | F27: 90740734 | G27: 15466776 | H27: 1.1792593e+09
A28: 43874 | B28: 1.1792593e+09 | C28: 3799835.4 | D28: 1.0340501e+08 | E28: 11403620 | F28: 1.0214435e+08 | G28: 15203455 | H28: 1.1678556e+09
... A116: 46553 | B116: 15283539 | C116: 52643.301 | D116: 2.87773e+08 | E116: 15283539 | F116: 1.27e+09 | G116: 15336182 | H116: -6.519258e-08
