Workbook

Sheet Disbursement
A1: Borrower: | B1: Pretty Auto Bricks Ltd.
A2: Currency: | B2: BDT
A3: Type | B3: IDCOL Loan
A4: Source: | B4: IDCOL Current Account/Repayment Account in BDT under REREDP (IDA-3679)
A7: Disbursement Number | B7: Disbursement Date | C7: Disbursement | D7: Cumulative Disbursement | E7: Source
A8: 1 | B8: 42509 | C8: 83974322 | D8: =C8 -> 83974322 | E8: IDA-3679
A9: 2 | B9: 42618 | C9: 77325561 | D9: =D8+C9 -> 1.6129988e+08 | E9: IDCOL Current Account
A10: 3 | B10: 42690 | C10: 64878865 | D10: =D9+C10 -> 2.2617875e+08 | E10: IDCOL Current Account
A11: 4 | B11: 42732 | C11: 46696351 | D11: =D10+C11 -> 2.728751e+08 | E11: IDCOL Current Account
A12: 5 | B12: 42745 | C12: 18977877 | D12: =D11+C12 -> 2.9185298e+08 | E12: IDCOL Current Account
A13: 6 | B13: 42801 | C13: 45817024 | D13: =D12+C13 -> 337670000 | E13: IDCOL Current Account

Sheet Summary
B1: =Accrual_PABL!D23 -> 42522 | C1: =Accrual_PABL!E23 -> 42552 | D1: =Accrual_PABL!F23 -> 42583 | E1: =Accrual_PABL!G23 -> 42614 | F1: =Accrual_PABL!H23 -> 42644 | G1: =Accrual_PABL!I23 -> 42675 | H1: =Accrual_PABL!J23 -> 42705 | I1: =Accrual_PABL!K23 -> 42736 | ... CF1: =Accrual_PABL!CH23 -> 45017
A2: Principal
A3: Opening balance | B3: =Accrual_PABL!D24 -> 83974322 | C3: =Accrual_PABL!E24 -> 83974322 | D3: =Accrual_PABL!F24 -> 83974322 | E3: =Accrual_PABL!G24 -> 83974322 | F3: =Accrual_PABL!H24 -> 1.6129988e+08 | G3: =Accrual_PABL!I24 -> 1.6129988e+08 | H3: =Accrual_PABL!J24 -> 2.2617875e+08 | I3: =Accrual_PABL!K24 -> 2.728751e+08 | ... N3: =Accrual_PABL!P24 -> 337670000 | O3: =N3 -> 337670000 | P3: =O3 -> 337670000 | Q3: =P3 -> 337670000 | R3: =Q3 -> 337670000 | S3: =R3 -> 337670000 | T3: =S3 -> 337670000 | U3: =T3 -> 337670000 | V3: =U3 -> 337670000 | ... CF3: =CE3 -> 337670000
A4: Repayment due | B4: =Accrual_PABL!D28 -> 0 | C4: =Accrual_PABL!E28 -> 0 | D4: =Accrual_PABL!F28 -> 0 | E4: =Accrual_PABL!G28 -> 0 | F4: =Accrual_PABL!H28 -> 0 | G4: =Accrual_PABL!I28 -> 0 | H4: =Accrual_PABL!J28 -> 0 | I4: =Accrual_PABL!K28 -> 0 | ... CF4: =Accrual_PABL!CH28 -> 337670000
A5: Loan Repayment | B5: =B22 -> 0 | C5: =C22 -> 0 | D5: =D22 -> 0 | E5: =E22 -> 0 | F5: =F22 -> 0 | G5: =G22 -> 0 | H5: =H22 -> 0 | I5: =I22 -> 0 | ... CF5: =CF22 -> 337670000
A6: Repayment overdue | B6: =IF((B4-B5)>0,(B4-B5),0) -> 0 | C6: =IF((C4-C5)>0,(C4-C5),0) -> 0 | D6: =IF((D4-D5)>0,(D4-D5),0) -> 0 | E6: =IF((E4-E5)>0,(E4-E5),0) -> 0 | F6: =IF((F4-F5)>0,(F4-F5),0) -> 0 | G6: =IF((G4-G5)>0,(G4-G5),0) -> 0 | H6: =IF((H4-H5)>0,(H4-H5),0) -> 0 | I6: =IF((I4-I5)>0,(I4-I5),0) -> 0 | ... CF6: =IF((CF4-CF5)>0,(CF4-CF5),0) -> 0
A7: Loan outstanding | B7: =B3-B5 -> 83974322 | C7: =C3-C5 -> 83974322 | D7: =D3-D5 -> 83974322 | E7: =E3-E5 -> 83974322 | F7: =F3-F5 -> 1.6129988e+08 | G7: =G3-G5 -> 1.6129988e+08 | H7: =H3-H5 -> 2.2617875e+08 | I7: =I3-I5 -> 2.728751e+08 | ... CF7: =CF3-CF5 -> 0
A8: Interest
A9: Interest accrued | B9: =Accrual_PABL!D26 -> 303240.61 | C9: =Accrual_PABL!E26 -> 1003026.6 | D9: =Accrual_PABL!F26 -> 1726138.8 | E9: =Accrual_PABL!G26 -> 2449251.1 | F9: =Accrual_PABL!H26 -> 3707499.5 | G9: =Accrual_PABL!I26 -> 5096470.7 | H9: =Accrual_PABL!J26 -> 6710965 | I9: =Accrual_PABL!K26 -> 8710500.1 | ... CF9: =Accrual_PABL!CH26 -> 1.3187443e+08
A10: Interest due | B10: 0 | C10: =PABL_Loan!$C$32 -> 629807.42 | D10: =C10 -> 629807.42 | E10: =D10 -> 629807.42 | F10: =PABL_Loan!$D$32 -> 2990611.1 | G10: =F10 -> 2990611.1 | H10: =G10 -> 2990611.1 | I10: =PABL_Loan!$E$32 -> 7590549 | J10: =I10 -> 7590549 | K10: =J10 -> 7590549 | L10: =PABL_Loan!$F$32 -> 14683001 | M10: =L10 -> 14683001 | N10: =M10 -> 14683001 | O10: =PABL_Loan!$G$32 -> 23312345 | P10: =O10 -> 23312345 | Q10: =P10 -> 23312345 | R10: =PABL_Loan!$H$32 -> 31584035 | S10: =R10 -> 31584035 | T10: =S10 -> 31584035 | U10: =PABL_Loan!$I$32 -> 39673195 | V10: =U10 -> 39673195 | W10: =V10 -> 39673195 | X10: =PABL_Loan!$J$32 -> 47312336 | Y10: =X10 -> 47312336 | Z10: =Y10 -> 47312336 | AA10: =PABL_Loan!$K$32 -> 54833966 | AB10: =AA10 -> 54833966 | AC10: =AB10 -> 54833966 | AD10: =PABL_Loan!$L$32 -> 62061146 | AE10: =AD10 -> 62061146 | AF10: =AE10 -> 62061146 | AG10: =PABL_Loan!$M$32 -> 68911239 | AH10: =AG10 -> 68911239 | AI10: =AH10 -> 68911239 | AJ10: =PABL_Loan!$N$32 -> 75383424 | AK10: =AJ10 -> 75383424 | AL10: =AK10 -> 75383424 | AM10: =PABL_Loan!$O$32 -> 81682345 | AN10: =AM10 -> 81682345 | AO10: =AN10 -> 81682345 | AP10: =PABL_Loan!$P$32 -> 87656248 | AQ10: =AP10 -> 87656248 | AR10: =AQ10 -> 87656248 | AS10: =PABL_Loan!$Q$32 -> 93235696 | AT10: =AS10 -> 93235696 | AU10: =AT10 -> 93235696 | AV10: =PABL_Loan!$R$32 -> 98477382 | AW10: =AV10 -> 98477382 | AX10: =AW10 -> 98477382 | AY10: =PABL_Loan!$S$32 -> 1.0342666e+08 | AZ10: =AY10 -> 1.0342666e+08 | BA10: =AZ10 -> 1.0342666e+08 | BB10: =PABL_Loan!$T$32 -> 1.0801718e+08 | BC10: =BB10 -> 1.0801718e+08 | BD10: =BC10 -> 1.0801718e+08 | BE10: =PABL_Loan!$U$32 -> 1.1219407e+08 | BF10: =BE10 -> 1.1219407e+08 | BG10: =BF10 -> 1.1219407e+08 | BH10: =PABL_Loan!$V$32 -> 1.1595634e+08 | BI10: =BH10 -> 1.1595634e+08 | BJ10: =BI10 -> 1.1595634e+08 | BK10: =PABL_Loan!$W$32 -> 1.1941586e+08 | BL10: =BK10 -> 1.1941586e+08 | BM10: =BL10 -> 1.1941586e+08 | BN10: =PABL_Loan!$X$32 -> 1.2247939e+08 | BO10: =BN10 -> 1.2247939e+08 | BP10: =BO10 -> 1.2247939e+08 | BQ10: =PABL_Loan!$Y$32 -> 1.2510812e+08 | BR10: =BQ10 -> 1.2510812e+08 | BS10: =BR10 -> 1.2510812e+08 | BT10: =PABL_Loan!$Z$32 -> 1.2730096e+08 | BU10: =BT10 -> 1.2730096e+08 | BV10: =BU10 -> 1.2730096e+08 | BW10: =PABL_Loan!$AA$32 -> 1.2911608e+08 | BX10: =BW10 -> 1.2911608e+08 | BY10: =BX10 -> 1.2911608e+08 | BZ10: =PABL_Loan!$AB$32 -> 1.3049409e+08 | CA10: =BZ10 -> 1.3049409e+08 | CB10: =CA10 -> 1.3049409e+08 | CC10: =PABL_Loan!$AC$32 -> 1.3141394e+08 | CD10: =CC10 -> 1.3141394e+08 | CE10: =CD10 -> 1.3141394e+08 | CF10: =PABL_Loan!$AD$32 -> 1.3187443e+08
A11: interest received | B11: =B26 -> 0 | C11: =C26 -> 629807 | D11: =D26 -> 629807 | E11: =E26 -> 629807 | F11: =F26 -> 2990611 | G11: =G26 -> 2990611 | H11: =H26 -> 2990611 | I11: =I26 -> 7590549 | ... CF11: =CF26 -> 1.3187443e+08
A12: Interest overdue | B12: =IF((B10-B11)>0,(B10-B11),0) -> 0 | C12: =IF((C10-C11)>0,(C10-C11),0) -> 0.416875 | D12: =IF((D10-D11)>0,(D10-D11),0) -> 0.416875 | E12: =IF((E10-E11)>0,(E10-E11),0) -> 0.416875 | F12: =IF((F10-F11)>0,(F10-F11),0) -> 0.098652778 | G12: =IF((G10-G11)>0,(G10-G11),0) -> 0.098652778 | H12: =IF((H10-H11)>0,(H10-H11),0) -> 0.098652778 | I12: =IF((I10-I11)>0,(I10-I11),0) -> 0 | ... CF12: =IF((CF10-CF11)>0,(CF10-CF11),0) -> 0
A13: Interest receivable | B13: =B9-B11 -> 303240.61 | C13: =C9-C11 -> 373219.63 | D13: =D9-D11 -> 1096331.8 | E13: =E9-E11 -> 1819444.1 | F13: =F9-F11 -> 716888.47 | G13: =G9-G11 -> 2105859.7 | H13: =H9-H11 -> 3720354 | I13: =I9-I11 -> 1119951.1 | ... CF13: =CF9-CF11 -> 0
A14: LD and others | B14: =B28 -> 0 | C14: =C28 -> 0 | D14: =D28 -> 0 | E14: =E28 -> 0 | F14: =F28 -> 0 | G14: =G28 -> 0 | H14: =H28 -> 0 | I14: =I28 -> 27543 | ... CF14: =CF28 -> 123129
B19: =B1 -> 42522 | C19: =C1 -> 42552 | D19: =D1 -> 42583 | E19: =E1 -> 42614 | F19: =F1 -> 42644 | G19: =G1 -> 42675 | H19: =H1 -> 42705 | I19: =I1 -> 42736 | ... CF19: =CF1 -> 45017
A20: Repayment receipts:
A21: Repayment received | B21: 0 | C21: =C4-B5 -> 0 | D21: =D4-C5 -> 0 | E21: =E4-D5 -> 0 | F21: =F4-E5 -> 0 | G21: =G4-F5 -> 0 | H21: =H4-G5 -> 0 | I21: =I4-H5 -> 0 | J21: =J4-I5 -> 0 | ... N21: =N4-M5 -> 0 | O21: 0 | R21: 0 | U21: 0 | X21: =X4-W5 -> 43345337 | Y21: =Y4-X5 -> 0 | Z21: =Z4-Y5 -> 0 | AA21: =AA4-Z5 -> 11521965 | AB21: =AB4-AA5 -> 0 | AC21: =AC4-AB5 -> 0 | AD21: =AD4-AC5 -> 11810015 | AE21: =AE4-AD5 -> 0 | ... CF21: =CF4-CE5 -> 18419592
A22: Repayment received (cumulative) | B22: =B21 -> 0 | C22: =B22+C21 -> 0 | D22: =C22+D21 -> 0 | E22: =D22+E21 -> 0 | F22: =E22+F21 -> 0 | G22: =F22+G21 -> 0 | H22: =G22+H21 -> 0 | I22: =H22+I21 -> 0 | J22: =I22+J21 -> 0 | ... CF22: =CE22+CF21 -> 337670000
A24: Interest receipts:
A25: Interest received | B25: 0 | C25: 629807 | F25: 2360804 | I25: =2600000+1999938 -> 4599938 | L25: 7092452 | O25: 8629344 | R25: 8271690 | U25: 3000000 | X25: =X10-W11 -> 12728301 | Y25: =Y10-X11 -> 0 | Z25: =Z10-Y11 -> 0 | AA25: =AA10-Z11 -> 7521630.3 | AB25: =AB10-AA11 -> 0 | AC25: =AC10-AB11 -> 0 | AD25: =AD10-AC11 -> 7227180 | AE25: =AE10-AD11 -> 0 | ... CF25: =CF10-CE11 -> 460489.81
A26: Interest received (cumulative) | B26: =+B25 -> 0 | C26: =B26+C25 -> 629807 | D26: =C26+D25 -> 629807 | E26: =D26+E25 -> 629807 | F26: =E26+F25 -> 2990611 | G26: =F26+G25 -> 2990611 | H26: =G26+H25 -> 2990611 | I26: =H26+I25 -> 7590549 | J26: =I26+J25 -> 7590549 | ... CF26: =CE26+CF25 -> 1.3187443e+08
A27: LD/others | B27: 0 | C27: 0 | D27: 0 | E27: 0 | F27: 0 | G27: 0 | H27: 0 | I27: 27543 | J27: 0 | L27: 19933 | M27: 0 | O27: 75653 | P27: 0 | R27: 0 | S27: 0 | U27: 0 | V27: 0 | W27: 0 | X27: 0 | Y27: 0 | Z27: 0 | AA27: 0 | AB27: 0 | AC27: 0 | AD27: 0 | AE27: 0 | AF27: 0 | AG27: 0 | AH27: 0 | AI27: 0 | AJ27: 0 | AK27: 0 | AL27: 0 | AM27: 0 | AN27: 0 | AO27: 0 | AP27: 0 | AQ27: 0 | AR27: 0 | AS27: 0 | AT27: 0 | AU27: 0 | AV27: 0 | AW27: 0 | AX27: 0 | AY27: 0 | AZ27: 0 | BA27: 0 | BB27: 0 | BC27: 0 | BD27: 0 | BE27: 0 | BF27: 0 | BG27: 0 | BH27: 0 | BI27: 0 | BJ27: 0 | BK27: 0 | BL27: 0 | BM27: 0 | BN27: 0 | BO27: 0 | BP27: 0 | BQ27: 0 | BR27: 0 | BS27: 0 | BT27: 0 | BU27: 0 | BV27: 0 | BW27: 0 | BX27: 0 | BY27: 0 | BZ27: 0 | CA27: 0 | CB27: 0 | CC27: 0 | CD27: 0 | CE27: 0 | CF27: 0
A28: LD/others (cumulative) | B28: =+B27 -> 0 | C28: =B28+C27 -> 0 | D28: =C28+D27 -> 0 | E28: =D28+E27 -> 0 | F28: =E28+F27 -> 0 | G28: =F28+G27 -> 0 | H28: =G28+H27 -> 0 | I28: =H28+I27 -> 27543 | J28: =I28+J27 -> 27543 | ... CF28: =CE28+CF27 -> 123129
A30: Actual Payment date | C30: 42534 | F30: 42663 | H30: 42732 | I30: 42732 | L30: 42841 | P30: 43010 | R30: 43010
A31: Actual Payment amount: | Q31: 16976687
A32: Interest | C32: 629807 | F32: 2360804 | H32: 2600000 | I32: 1999938 | L32: 7092452 | P32: 8629344 | Q32: 8271690 | R32: 3000000
A33: Principal
A34: LPC | I34: 27543 | L34: 19933 | P34: 75653
A35: Total | B35: =SUM(B32:B34) -> 0 | C35: =SUM(C32:C34) -> 629807 | D35: =SUM(D32:D34) -> 0 | E35: =SUM(E32:E34) -> 0 | F35: =SUM(F32:F34) -> 2360804 | G35: =SUM(G32:G34) -> 0 | H35: =SUM(H32:H34) -> 2600000 | I35: =SUM(I32:I34) -> 2027481 | ... DP35: =SUM(DP32:DP34) -> 0

Sheet PABL_Loan
A1: Project name: | C1: =Disbursement!B1 -> Pretty Auto Bricks Ltd.
A3: Agreement date | C3: 41673
A5: Loan Amount | C5: 337670000 | F5: Interest Grace | H5: 0 | I5: months
F6: Principal Grace | H6: 12 | I6: months
A7: First Drawdown Date | C7: =C22 -> 42509
F8: Interest Grace Ends | H8: =EDATE(C22,H5) -> 42509
A9: Request Date | C9: 42502 | F9: Principal Grace Ends | H9: =EDATE(C22,H6) -> 42874
A11: Interest Rate | C11: 0.1
A13: Tenor | C13: 7 years
A15: Principal | C15: Annuity
A17: Interest calculation | C17: 360 | D17: days basis
A19: Number of installments | C19: 24
A21: Drawdown
C22: =Disbursement!B8 -> 42509 | D22: =Disbursement!B9 -> 42618 | E22: =Disbursement!B10 -> 42690 | F22: =Disbursement!B11 -> 42732 | G22: =Disbursement!B12 -> 42745 | H22: =Disbursement!B13 -> 42801
C23: =Disbursement!C8 -> 83974322 | D23: =Disbursement!C9 -> 77325561 | E23: =Disbursement!C10 -> 64878865 | F23: =Disbursement!C11 -> 46696351 | G23: =Disbursement!C12 -> 18977877 | H23: =Disbursement!C13 -> 45817024
C24: =C23 -> 83974322 | D24: =D23+C24 -> 1.6129988e+08 | E24: =E23+D24 -> 2.2617875e+08 | F24: =F23+E24 -> 2.728751e+08 | G24: =G23+F24 -> 2.9185298e+08 | H24: =H23+G24 -> 337670000
A27: Repayment
A28: Repayment Period | G28: 1 | H28: 2 | I28: 3 | J28: 4 | K28: 5 | L28: 6 | M28: 7 | N28: 8 | O28: 9 | P28: 10 | Q28: 11 | R28: 12 | S28: 13 | T28: 14 | U28: 15 | V28: 16 | W28: 17 | X28: 18 | Y28: 19 | Z28: 20 | AA28: 21 | AB28: 22 | AC28: 23 | AD28: 24
A29: Repayment Date | C29: 42536 | D29: 42628 | E29: 42719 | F29: 42809 | G29: 42901 | H29: 42992 | I29: 43084 | J29: 43174 | K29: 43266 | L29: 43358 | M29: 43449 | N29: 43539 | O29: 43631 | P29: 43723 | Q29: 43814 | R29: 43905 | S29: 43997 | T29: 44089 | U29: 44180 | V29: 44270 | W29: 44362 | X29: 44454 | Y29: 44545 | Z29: 44635 | AA29: 44727 | AB29: 44819 | AC29: 44910 | AD29: 45000
A30: Opening Balance | C30: =C23 -> 83974322 | D30: =C36+D23 -> 1.6129988e+08 | E30: =D36+E23 -> 2.2617875e+08 | F30: =E36+F23+G23+H23 -> 337670000 | G30: =F36 -> 337670000 | H30: =G36 -> 3.2723167e+08 | I30: =H36 -> 3.1653238e+08 | J30: =I36 -> 3.055656e+08 | K30: =J36 -> 2.9432466e+08 | L30: =K36 -> 2.828027e+08 | M30: =L36 -> 2.7099268e+08 | N30: =M36 -> 2.5888742e+08 | ... AD30: =AC36 -> 18419592
A31: Interest Payment | C31: =C24*(C29-C22)*$C$11/360 -> 629807.42 | D31: =C36*(D22-C29)*$C$11/360+D24*(D29-D22)*$C$11/360 -> 2360803.7 | E31: =D36*(E22-D29)*C11/360+E30*(E29-E22)*C11/360 -> 4599937.9 | F31: =E36*(F22-E29)*$C$11/360+F24*(G22-F22)*$C$11/360+G24*(H22-G22)*$C$11/360+H24*(F29-H22)*$C$11/360 -> 7092451.9 | G31: =F36*(G29-F29)*$C$11/360 -> 8629344.4 | H31: =G36*(H29-G29)*$C$11/360 -> 8271689.4 | I31: =H36*(I29-H29)*$C$11/360 -> 8089160.8 | J31: =I36*(J29-I29)*$C$11/360 -> 7639140.1 | K31: =J36*(K29-J29)*$C$11/360 -> 7521630.3 | L31: =K36*(L29-K29)*$C$11/360 -> 7227180 | M31: =L36*(M29-L29)*$C$11/360 -> 6850092.8 | N31: =M36*(N29-M29)*$C$11/360 -> 6472185.4 | ... AD31: =AC36*(AD29-AC29)*$C$11/360 -> 460489.81
A32: Cumulative interest | C32: =C31 -> 629807.42 | D32: =D31+C32 -> 2990611.1 | E32: =E31+D32 -> 7590549 | F32: =F31+E32 -> 14683001 | G32: =G31+F32 -> 23312345 | H32: =H31+G32 -> 31584035 | I32: =I31+H32 -> 39673195 | J32: =J31+I32 -> 47312336 | K32: =K31+J32 -> 54833966 | ... AD32: =AD31+AC32 -> 1.3187443e+08
A33: Principal Payment | C33: 0 | D33: 0 | E33: 0 | F33: 0 | G33: =-PPMT($C$11/4,G28,$C$19,$G$30) -> 10438332 | H33: =-PPMT($C$11/4,H28,$C$19,$G$30) -> 10699290 | I33: =-PPMT($C$11/4,I28,$C$19,$G$30) -> 10966773 | J33: =-PPMT($C$11/4,J28,$C$19,$G$30) -> 11240942 | K33: =-PPMT($C$11/4,K28,$C$19,$G$30) -> 11521965 | L33: =-PPMT($C$11/4,L28,$C$19,$G$30) -> 11810015 | M33: =-PPMT($C$11/4,M28,$C$19,$G$30) -> 12105265 | N33: =-PPMT($C$11/4,N28,$C$19,$G$30) -> 12407897 | ... AD33: =-PPMT($C$11/4,AD28,$C$19,$G$30) -> 18419592
A34: Cumulative repayment | C34: =C33+B34 -> 0 | D34: =D33+C34 -> 0 | E34: =E33+D34 -> 0 | F34: =F33+E34 -> 0 | G34: =G33+F34 -> 10438332 | H34: =H33+G34 -> 21137622 | I34: =I33+H34 -> 32104395 | J34: =J33+I34 -> 43345337 | ... AD34: =AD33+AC34 -> 337670000
A35: Total Debt Service | C35: =C31+C33 -> 629807.42 | D35: =D33+D31 -> 2360803.7 | E35: =E33+E31 -> 4599937.9 | F35: =F33+F31 -> 7092451.9 | G35: =G33+G31 -> 19067676 | H35: =H33+H31 -> 18970980 | I35: =I33+I31 -> 19055933 | J35: =J33+J31 -> 18880082 | K35: =K33+K31 -> 19043596 | ... AD35: =AD33+AD31 -> 18880082
A36: Closing Balance | C36: =C30-C33 -> 83974322 | D36: =D30-D33 -> 1.6129988e+08 | E36: =E30-E33 -> 2.2617875e+08 | F36: =F30-F33 -> 337670000 | G36: =G30-G33 -> 3.2723167e+08 | H36: =H30-H33 -> 3.1653238e+08 | I36: =I30-I33 -> 3.055656e+08 | J36: =J30-J33 -> 2.9432466e+08 | ... AD36: =AD30-AD33 -> 9.6857548e-08
A39: Average Installment Size
A40: Date | C40: =C29 -> 42536 | D40: =D29 -> 42628 | E40: =E29 -> 42719 | F40: =F29 -> 42809 | G40: =G29 -> 42901 | H40: =H29 -> 42992 | I40: =I29 -> 43084 | J40: =J29 -> 43174 | ... AD40: =AD29 -> 45000
A41: Average Installment | C41: =AVERAGE(C35) -> 629807.42 | D41: =AVERAGE($C$35:D35) -> 1495305.5 | E41: =AVERAGE($C$35:E35) -> 2530183 | F41: =AVERAGE($C$35:F35) -> 3670750.2 | G41: =AVERAGE(G35) -> 19067676 | H41: =AVERAGE($G$35:H35) -> 19019328 | I41: =AVERAGE($G$35:I35) -> 19031530 | J41: =AVERAGE($G$35:J35) -> 18993668 | K41: =AVERAGE($G$35:K35) -> 19003653 | L41: =AVERAGE($G$35:L35) -> 19009244 | M41: =AVERAGE($G$35:M35) -> 19001546 | N41: =AVERAGE($G$35:N35) -> 18986363 | O41: =AVERAGE($G$35:O35) -> 18989769 | ... AD41: =AVERAGE($G$35:AD35) -> 18952560
A43: Annual Monitoring Fee
A44: Date | C44: 42038 | D44: =EDATE(C44,12) -> 42403 | E44: =EDATE(D44,12) -> 42769 | F44: =EDATE(E44,12) -> 43134 | G44: =EDATE(F44,12) -> 43499 | H44: =EDATE(G44,12) -> 43864 | I44: =EDATE(H44,12) -> 44230 | J44: =EDATE(I44,12) -> 44595 | K44: =EDATE(J44,12) -> 44960
A45: Amount (BDT) | C45: 200000 | D45: 200000 | E45: 200000 | F45: 200000 | G45: 200000 | H45: 200000 | I45: 200000 | J45: 200000 | K45: 200000

Sheet Accrual_PABL
A1: Project name: | B1: =PABL_Loan!C1 -> Pretty Auto Bricks Ltd.
A3: Assumptions:
A5: Agreement date | B5: =PABL_Loan!C3 -> 41673
A7: Loan Amount | B7: =PABL_Loan!C5 -> 337670000 | C7: BDT
A9: Drawdown Date | B9: =PABL_Loan!C7 -> 42509
A11: Interest Rate | B11: 0.1
A12: Tenor | B12: 7 years
A13: Interest calculation | B13: 360 | C13: days basis
A14: Principal | B14: =PABL_Loan!C15 -> Annuity
A16: Drawdown
C17: =PABL_Loan!C22 -> 42509 | D17: =PABL_Loan!D22 -> 42618 | E17: =PABL_Loan!E22 -> 42690 | F17: =PABL_Loan!F22 -> 42732 | G17: =PABL_Loan!G22 -> 42745 | H17: =PABL_Loan!H22 -> 42801
C18: =PABL_Loan!C23 -> 83974322 | D18: =PABL_Loan!D23 -> 77325561 | E18: =PABL_Loan!E23 -> 64878865 | F18: =PABL_Loan!F23 -> 46696351 | G18: =PABL_Loan!G23 -> 18977877 | H18: =PABL_Loan!H23 -> 45817024
C19: =C18 -> 83974322 | D19: =C19+D18 -> 1.6129988e+08 | E19: =D19+E18 -> 2.2617875e+08 | F19: =E19+F18 -> 2.728751e+08 | G19: =F19+G18 -> 2.9185298e+08 | H19: =G19+H18 -> 337670000
A22: Accrual of interest
A23: Months | D23: 42522 | E23: =EDATE(D23,1) -> 42552 | F23: =EDATE(E23,1) -> 42583 | G23: =EDATE(F23,1) -> 42614 | H23: =EDATE(G23,1) -> 42644 | I23: =EDATE(H23,1) -> 42675 | J23: =EDATE(I23,1) -> 42705 | K23: =EDATE(J23,1) -> 42736 | L23: =EDATE(K23,1) -> 42767 | ... CH23: =EDATE(CG23,1) -> 45017
A24: Opening Balance | D24: =C18 -> 83974322 | E24: =D30 -> 83974322 | F24: =E30 -> 83974322 | G24: =F30 -> 83974322 | H24: =G30+D18 -> 1.6129988e+08 | I24: =H30 -> 1.6129988e+08 | J24: =I30+E18 -> 2.2617875e+08 | K24: =J30+F18 -> 2.728751e+08 | L24: =K30+G18 -> 2.9185298e+08 | M24: =L30 -> 2.9185298e+08 | N24: =M30+H18 -> 337670000 | O24: =N30 -> 337670000 | P24: =O30 -> 337670000 | Q24: =P30 -> 337670000 | R24: =Q30 -> 3.2723167e+08 | S24: =R30 -> 3.2723167e+08 | T24: =S30 -> 3.2723167e+08 | U24: =T30 -> 3.1653238e+08 | V24: =U30 -> 3.1653238e+08 | ... CH24: =CG30 -> 18419592
A25: Interest Payment | D25: =D24*(D23-C17)*$B$11/360 -> 303240.61 | E25: =E24*(E23-D23)*$B$11/360 -> 699786.02 | F25: =F24*(F23-E23)*$B$11/360 -> 723112.22 | G25: =G24*(G23-F23)*$B$11/360 -> 723112.22 | H25: =G30*(D17-G23)*$B$11/360+D19*(H23-D17)*$B$11/360 -> 1258248.4 | I25: =I24*(I23-H23)*$B$11/360 -> 1388971.2 | J25: =I30*(E17-I23)*B11/360+J24*(J23-E17)*B11/360 -> 1614494.3 | K25: =J30*(F17-J23)*$B$11/360+F19*(K23-F17)*$B$11/360 -> 1999535.2 | L25: =K30*(G17-K23)*$B$11/360+G19*(L23-G17)*$B$11/360 -> 2465733.7 | M25: =M24*(M23-L23)*$B$11/360 -> 2269967.6 | N25: =M30*(H17-M23)*$B$11/360+N24*(N23-H17)*$B$11/360 -> 2831352.2 | O25: =O24*(O23-N23)*$B$11/360 -> 2813916.7 | P25: =P24*(P23-O23)*$B$11/360 -> 2907713.9 | Q25: =Q24*(PABL_Loan!$G$29-P23)*$B$11/360+Q30*(Q23-PABL_Loan!$G$29)*$B$11/360 -> 2767524.1 | R25: =R24*(R23-Q23)*$B$11/360 -> 2817828.3 | S25: =S24*(S23-R23)*$B$11/360 -> 2817828.3 | T25: =T24*(PABL_Loan!$H$29-S23)*$B$11/360+T30*(T23-PABL_Loan!$H$29)*$B$11/360 -> 2676406.1 | U25: =U24*(U23-T23)*$B$11/360 -> 2725695.5 | V25: =V24*(V23-U23)*$B$11/360 -> 2637769.8 | W25: =W24*(PABL_Loan!$I$29-V23)*$B$11/360+W30*(W23-PABL_Loan!$I$29)*$B$11/360 -> 2673907.9 | X25: =X24*(X23-W23)*$B$11/360 -> 2631259.4 | Y25: =Y24*(Y23-X23)*$B$11/360 -> 2376621.4 | Z25: =Z24*(PABL_Loan!$J$29-Y23)*$B$11/360+Z30*(Z23-PABL_Loan!$J$29)*$B$11/360 -> 2578177.2 | AA25: =AA24*(AA23-Z23)*$B$11/360 -> 2452705.5 | AB25: =AB24*(AB23-AA23)*$B$11/360 -> 2534462.4 | AC25: =AC24*(PABL_Loan!$K$29-AB23)*$B$11/360+AC30*(AC23-PABL_Loan!$K$29)*$B$11/360 -> 2401496.8 | AD25: =AD24*(AD23-AC23)*$B$11/360 -> 2435245.5 | AE25: =AE24*(AE23-AD23)*$B$11/360 -> 2435245.5 | AF25: =AF24*(PABL_Loan!$L$29-AE23)*$B$11/360+AF30*(AF23-PABL_Loan!$L$29)*$B$11/360 -> 2304200.2 | AG25: =AG24*(AG23-AF23)*$B$11/360 -> 2333548.1 | AH25: =AH24*(AH23-AG23)*$B$11/360 -> 2258272.4 | AI25: =AI24*(PABL_Loan!$M$29-AH23)*$B$11/360+AI30*(AI23-PABL_Loan!$M$29)*$B$11/360 -> 2276384.4 | AJ25: =AJ24*(AJ23-AI23)*$B$11/360 -> 2229308.3 | AK25: =AK24*(AK23-AJ23)*$B$11/360 -> 2013568.8 | AL25: =AL24*(PABL_Loan!$N$29-AK23)*$B$11/360+AL30*(AL23-PABL_Loan!$N$29)*$B$11/360 -> 2170715.5 | AM25: =AM24*(AM23-AL23)*$B$11/360 -> 2053996 | AN25: =AN24*(AN23-AM23)*$B$11/360 -> 2122462.5 | AO25: =AO24*(PABL_Loan!$O$29-AN23)*$B$11/360+AO30*(AO23-PABL_Loan!$O$29)*$B$11/360 -> 1997471.1 | AP25: =AP24*(AP23-AO23)*$B$11/360 -> 2012945.6 | AQ25: =AQ24*(AQ23-AP23)*$B$11/360 -> 2012945.6 | AR25: =AR24*(PABL_Loan!$P$29-AQ23)*$B$11/360+AR30*(AR23-PABL_Loan!$P$29)*$B$11/360 -> 1890073.9 | AS25: =AS24*(AS23-AR23)*$B$11/360 -> 1900690.8 | AT25: =AT24*(AT23-AS23)*$B$11/360 -> 1839378.2 | AU25: =AU24*(PABL_Loan!$Q$29-AT23)*$B$11/360+AU30*(AU23-PABL_Loan!$Q$29)*$B$11/360 -> 1837592.7 | AV25: =AV24*(AV23-AU23)*$B$11/360 -> 1785629.6 | AW25: =AW24*(AW23-AV23)*$B$11/360 -> 1670427.7 | AX25: =AX24*(PABL_Loan!$R$29-AW23)*$B$11/360+AX30*(AX23-PABL_Loan!$R$29)*$B$11/360 -> 1720954 | AY25: =AY24*(AY23-AX23)*$B$11/360 -> 1613895.3 | AZ25: =AZ24*(AZ23-AY23)*$B$11/360 -> 1667691.8 | BA25: =BA24*(PABL_Loan!$S$29-AZ23)*$B$11/360+BA30*(BA23-PABL_Loan!$S$29)*$B$11/360 -> 1551502.4 | BB25: =BB24*(BB23-BA23)*$B$11/360 -> 1546805.6 | BC25: =BC24*(BC23-BB23)*$B$11/360 -> 1546805.6 | BD25: =BD24*(PABL_Loan!$T$29-BC23)*$B$11/360+BD30*(BD23-PABL_Loan!$T$29)*$B$11/360 -> 1432956 | BE25: =BE24*(BE23-BD23)*$B$11/360 -> 1422897.3 | BF25: =BF24*(BF23-BE23)*$B$11/360 -> 1376997.4 | BG25: =BG24*(PABL_Loan!$U$29-BF23)*$B$11/360+BG30*(BG23-PABL_Loan!$U$29)*$B$11/360 -> 1353248.8 | BH25: =BH24*(BH23-BG23)*$B$11/360 -> 1295891.2 | BI25: =BI24*(BI23-BH23)*$B$11/360 -> 1170482.4 | BJ25: =BJ24*(PABL_Loan!$V$29-BI23)*$B$11/360+BJ30*(BJ23-PABL_Loan!$V$29)*$B$11/360 -> 1224501.5 | BK25: =BK24*(BK23-BJ23)*$B$11/360 -> 1128106.5 | BL25: =BL24*(BL23-BK23)*$B$11/360 -> 1165710 | BM25: =BM24*(PABL_Loan!$W$29-BL23)*$B$11/360+BM30*(BM23-PABL_Loan!$W$29)*$B$11/360 -> 1059236.4 | BN25: =BN24*(BN23-BM23)*$B$11/360 -> 1032274.3 | BO25: =BO24*(BO23-BN23)*$B$11/360 -> 1032274.3 | BP25: =BP24*(PABL_Loan!$X$29-BO23)*$B$11/360+BP30*(BP23-PABL_Loan!$X$29)*$B$11/360 -> 928383.32 | BQ25: =BQ24*(BQ23-BP23)*$B$11/360 -> 895502.67 | BR25: =BR24*(BR23-BQ23)*$B$11/360 -> 866615.49 | BS25: =BS24*(PABL_Loan!$Y$29-BR23)*$B$11/360+BS30*(BS23-PABL_Loan!$Y$29)*$B$11/360 -> 818623.78 | BT25: =BT24*(BT23-BS23)*$B$11/360 -> 755311.76 | BU25: =BU24*(BU23-BT23)*$B$11/360 -> 682217.07 | BV25: =BV24*(PABL_Loan!$Z$29-BU23)*$B$11/360+BV30*(BV23-PABL_Loan!$Z$29)*$B$11/360 -> 676510.89 | BW25: =BW24*(BW23-BV23)*$B$11/360 -> 591886.51 | BX25: =BX24*(BX23-BW23)*$B$11/360 -> 611616.06 | BY25: =BY24*(PABL_Loan!$AA$29-BX23)*$B$11/360+BY30*(BY23-PABL_Loan!$AA$29)*$B$11/360 -> 515866.86 | BZ25: =BZ24*(BZ23-BY23)*$B$11/360 -> 464327.98 | CA25: =CA24*(CA23-BZ23)*$B$11/360 -> 464327.98 | CB25: =CB24*(PABL_Loan!$AB$29-CA23)*$B$11/360+CB30*(CB23-PABL_Loan!$AB$29)*$B$11/360 -> 371429.51 | CC25: =CC24*(CC23-CB23)*$B$11/360 -> 313357.7 | CD25: =CD24*(CD23-CC23)*$B$11/360 -> 303249.38 | CE25: =CE24*(PABL_Loan!$AC$29-CD23)*$B$11/360+CE30*(CE23-PABL_Loan!$AC$29)*$B$11/360 -> 228497.79 | CF25: =CF24*(CF23-CE23)*$B$11/360 -> 158613.16 | CG25: =CG24*(CG23-CF23)*$B$11/360 -> 143263.5 | CH25: =CH24*(PABL_Loan!$AD$29-CG23)*$B$11/360+CH30*(CH23-PABL_Loan!$AD$29)*$B$11/360 -> 71631.748
A26: Cumulative interest | D26: =C26+D25 -> 303240.61 | E26: =D26+E25 -> 1003026.6 | F26: =E26+F25 -> 1726138.8 | G26: =F26+G25 -> 2449251.1 | H26: =G26+H25 -> 3707499.5 | I26: =H26+I25 -> 5096470.7 | J26: =I26+J25 -> 6710965 | K26: =J26+K25 -> 8710500.1 | ... CH26: =CG26+CH25 -> 1.3187443e+08
A27: Principal Payment | D27: 0 | E27: 0 | F27: 0 | G27: 0 | H27: 0 | I27: 0 | J27: 0 | K27: 0 | L27: 0 | M27: 0 | N27: 0 | O27: =L27 -> 0 | P27: =M27 -> 0 | Q27: =PABL_Loan!$G$33 -> 10438332 | R27: =O27 -> 0 | S27: =P27 -> 0 | T27: =PABL_Loan!$H$33 -> 10699290 | U27: =R27 -> 0 | V27: =S27 -> 0 | W27: =PABL_Loan!$I$33 -> 10966773 | X27: =U27 -> 0 | Y27: =V27 -> 0 | Z27: =PABL_Loan!$J$33 -> 11240942 | AA27: =X27 -> 0 | AB27: =Y27 -> 0 | AC27: =PABL_Loan!$K$33 -> 11521965 | AD27: =AA27 -> 0 | AE27: =AB27 -> 0 | AF27: =PABL_Loan!$L$33 -> 11810015 | AG27: =AD27 -> 0 | AH27: =AE27 -> 0 | AI27: =PABL_Loan!$M$33 -> 12105265 | AJ27: =AG27 -> 0 | AK27: =AH27 -> 0 | AL27: =PABL_Loan!$N$33 -> 12407897 | AM27: =AJ27 -> 0 | AN27: =AK27 -> 0 | AO27: =PABL_Loan!$O$33 -> 12718094 | AP27: =AM27 -> 0 | AQ27: =AN27 -> 0 | AR27: =PABL_Loan!$P$33 -> 13036046 | AS27: =AP27 -> 0 | AT27: =AQ27 -> 0 | AU27: =PABL_Loan!$Q$33 -> 13361948 | AV27: =AS27 -> 0 | AW27: =AT27 -> 0 | AX27: =PABL_Loan!$R$33 -> 13695996 | AY27: =AV27 -> 0 | AZ27: =AW27 -> 0 | BA27: =PABL_Loan!$S$33 -> 14038396 | BB27: =AY27 -> 0 | BC27: =AZ27 -> 0 | BD27: =PABL_Loan!$T$33 -> 14389356 | BE27: =BB27 -> 0 | BF27: =BC27 -> 0 | BG27: =PABL_Loan!$U$33 -> 14749090 | BH27: =BE27 -> 0 | BI27: =BF27 -> 0 | BJ27: =PABL_Loan!$V$33 -> 15117817 | BK27: =BH27 -> 0 | BL27: =BI27 -> 0 | BM27: =PABL_Loan!$W$33 -> 15495763 | BN27: =BK27 -> 0 | BO27: =BL27 -> 0 | BP27: =PABL_Loan!$X$33 -> 15883157 | BQ27: =BN27 -> 0 | BR27: =BO27 -> 0 | BS27: =PABL_Loan!$Y$33 -> 16280236 | BT27: =BQ27 -> 0 | BU27: =BR27 -> 0 | BV27: =PABL_Loan!$Z$33 -> 16687241 | BW27: =BT27 -> 0 | BX27: =BU27 -> 0 | BY27: =PABL_Loan!$AA$33 -> 17104423 | BZ27: =BW27 -> 0 | CA27: =BX27 -> 0 | CB27: =PABL_Loan!$AB$33 -> 17532033 | CC27: =BZ27 -> 0 | CD27: =CA27 -> 0 | CE27: =PABL_Loan!$AC$33 -> 17970334 | CF27: =CC27 -> 0 | CG27: =CD27 -> 0 | CH27: =PABL_Loan!$AD$33 -> 18419592
A28: Cumulative repayment | D28: =C28+D27 -> 0 | E28: =D28+E27 -> 0 | F28: =E28+F27 -> 0 | G28: =F28+G27 -> 0 | H28: =G28+H27 -> 0 | I28: =H28+I27 -> 0 | J28: =I28+J27 -> 0 | K28: =J28+K27 -> 0 | ... CH28: =CG28+CH27 -> 337670000
A29: Total Debt Service | D29: =D27+D25 -> 303240.61 | E29: =E27+E25 -> 699786.02 | F29: =F27+F25 -> 723112.22 | G29: =G27+G25 -> 723112.22 | H29: =H27+H25 -> 1258248.4 | I29: =I27+I25 -> 1388971.2 | J29: =J27+J25 -> 1614494.3 | K29: =K27+K25 -> 1999535.2 | ... CH29: =CH27+CH25 -> 18491224
A30: Closing Balance | D30: =D24-D27 -> 83974322 | E30: =E24-E27 -> 83974322 | F30: =F24-F27 -> 83974322 | G30: =G24-G27 -> 83974322 | H30: =H24-H27 -> 1.6129988e+08 | I30: =I24-I27 -> 1.6129988e+08 | J30: =J24-J27 -> 2.2617875e+08 | K30: =K24-K27 -> 2.728751e+08 | ... CH30: =CH24-CH27 -> 9.6857548e-08
CH32: =CH26-PABL_Loan!AD32 -> 0

Sheet Repayment Schedule
A1: Project name: | C1: =PABL_Loan!C1 -> Pretty Auto Bricks Ltd.
A4: Agreement date | C4: =Accrual_PABL!B5 -> 41673
A6: Loan Amount | C6: =PABL_Loan!C5 -> 337670000
A8: Drawdown Date | C8: =PABL_Loan!C7 -> 42509
A10: Interest Rate | C10: 0.1
A11: Tenor | C11: 7 years
A12: Principal | C12: =Accrual_PABL!B14 -> Annuity
A13: Interest calculation | C13: 360 | D13: days basis
A14: Number of installments | C14: 24
A16: Drawdown
C17: =PABL_Loan!C22 -> 42509 | D17: =PABL_Loan!D22 -> 42618 | E17: =PABL_Loan!E22 -> 42690 | F17: =PABL_Loan!F22 -> 42732
C18: =PABL_Loan!C23 -> 83974322 | D18: =PABL_Loan!D23 -> 77325561 | E18: =PABL_Loan!E23 -> 64878865 | F18: =PABL_Loan!F23 -> 46696351
C19: =C18 -> 83974322 | D19: =D18+C19 -> 1.6129988e+08 | E19: =E18+D19 -> 2.2617875e+08 | F19: =F18+E19 -> 2.728751e+08
A23: Repayment Date | B23: Opening Balance | C23: Interest Payment | D23: Cumulative interest | E23: Principal Payment | F23: Cumulative repayment | G23: Total Debt Service | H23: Closing Balance
A24: {=TRANSPOSE(PABL_Loan!C29:AD36)} -> 42536 | B24: 83974322 | C24: 629807.42 | D24: 629807.42 | E24: 0 | F24: 0 | G24: 629807.42 | H24: 83974322
A25: 42628 | B25: 1.6129988e+08 | C25: 2360803.7 | D25: 2990611.1 | E25: 0 | F25: 0 | G25: 2360803.7 | H25: 1.6129988e+08
A26: 42719 | B26: 2.2617875e+08 | C26: 4599937.9 | D26: 7590549 | E26: 0 | F26: 0 | G26: 4599937.9 | H26: 2.2617875e+08
A27: 42809 | B27: 337670000 | C27: 7092451.9 | D27: 14683001 | E27: 0 | F27: 0 | G27: 7092451.9 | H27: 337670000
A28: 42901 | B28: 337670000 | C28: 8629344.4 | D28: 23312345 | E28: 10438332 | F28: 10438332 | G28: 19067676 | H28: 3.2723167e+08
A29: 42992 | B29: 3.2723167e+08 | C29: 8271689.4 | D29: 31584035 | E29: 10699290 | F29: 21137622 | G29: 18970980 | H29: 3.1653238e+08
A30: 43084 | B30: 3.1653238e+08 | C30: 8089160.8 | D30: 39673195 | E30: 10966773 | F30: 32104395 | G30: 19055933 | H30: 3.055656e+08
A31: 43174 | B31: 3.055656e+08 | C31: 7639140.1 | D31: 47312336 | E31: 11240942 | F31: 43345337 | G31: 18880082 | H31: 2.9432466e+08
A32: 43266 | B32: 2.9432466e+08 | C32: 7521630.3 | D32: 54833966 | E32: 11521965 | F32: 54867302 | G32: 19043596 | H32: 2.828027e+08
A33: 43358 | B33: 2.828027e+08 | C33: 7227180 | D33: 62061146 | E33: 11810015 | F33: 66677317 | G33: 19037195 | H33: 2.7099268e+08
A34: 43449 | B34: 2.7099268e+08 | C34: 6850092.8 | D34: 68911239 | E34: 12105265 | F34: 78782582 | G34: 18955358 | H34: 2.5888742e+08
A35: 43539 | B35: 2.5888742e+08 | C35: 6472185.4 | D35: 75383424 | E35: 12407897 | F35: 91190479 | G35: 18880082 | H35: 2.4647952e+08
A36: 43631 | B36: 2.4647952e+08 | C36: 6298921.1 | D36: 81682345 | E36: 12718094 | F36: 1.0390857e+08 | G36: 19017015 | H36: 2.3376143e+08
... A51: 45000 | B51: 18419592 | C51: 460489.81 | D51: 1.3187443e+08 | E51: 18419592 | F51: 337670000 | G51: 18880082 | H51: 9.6857548e-08
