Workbook

Sheet Disbursement
A1: Borrower: | B1: PARTEX PETRO LIMITED (PPL)
A2: Currency: | B2: BDT
A3: Type | B3: IDCOL Loan
A4: Source: | B4: IDCOL Current Account
A7: Disbursement Number | B7: Disbursement Date | C7: Disbursement | D7: Cumulative Disbursement | E7: Source
A8: 1 (Part I) | B8: 42808 | C8: 90000000 | D8: =C8 -> 90000000 | E8: IDCOL Current Account
A9: 1 (Part II) | B9: 42808 | C9: 8715714.3 | D9: =D8+C9 -> 98715714 | E9: IDCOL Current Account
A10: 2-9 | B10: 43143 | C10: 39593464 | D10: =D9+C10 -> 1.3830918e+08 | E10: IDCOL Current Account
A11: 10-13 | B11: 43380 | C11: 3.7954566e+08 | D11: =D10+C11 -> 5.1785483e+08 | E11: IDCOL Current Account

Sheet Summary
B1: =Accrual_PPL!D23 -> 42826 | C1: =Accrual_PPL!E23 -> 42856 | D1: =Accrual_PPL!F23 -> 42887 | E1: =Accrual_PPL!G23 -> 42917 | F1: =Accrual_PPL!H23 -> 42948 | G1: =Accrual_PPL!I23 -> 42979 | H1: =Accrual_PPL!J23 -> 43009 | I1: =Accrual_PPL!K23 -> 43040 | ... CT1: =Accrual_PPL!CV23 -> 45748
A2: Principal
A3: Opening balance | B3: =Accrual_PPL!D24 -> 98715714 | C3: =Accrual_PPL!E24 -> 99181872 | D3: =Accrual_PPL!F24 -> 99181872 | E3: =Accrual_PPL!G24+PPL_Loan!D31 -> 1.0168897e+08 | F3: =Accrual_PPL!H24 -> 1.0168897e+08 | G3: =Accrual_PPL!I24 -> 1.0168897e+08 | H3: =Accrual_PPL!J24+PPL_Loan!E31 -> 1.0416058e+08 | I3: =Accrual_PPL!K24 -> 1.0416058e+08 | J3: =Accrual_PPL!L24 -> 1.0416058e+08 | K3: =Accrual_PPL!M24+PPL_Loan!F31 -> 1.0659605e+08 | L3: =Accrual_PPL!N24 -> 1.0659605e+08 | M3: =Accrual_PPL!O24 -> 1.4618952e+08 | N3: =Accrual_PPL!P24+PPL_Loan!G31 -> 1.4919765e+08 | O3: =Accrual_PPL!Q24 -> 1.4919765e+08 | P3: =Accrual_PPL!R24 -> 1.4919765e+08 | Q3: =Accrual_PPL!S24+PPL_Loan!H31 -> 1.5330058e+08 | R3: =Accrual_PPL!T24 -> 1.5330058e+08 | S3: =Accrual_PPL!U24 -> 1.5330058e+08 | T3: =Accrual_PPL!V24+PPL_Loan!I31 -> 1.5761003e+08 | U3: =Accrual_PPL!W24 -> 5.3715569e+08 | V3: =Accrual_PPL!X24 -> 5.3715569e+08 | W3: =Accrual_PPL!Y24+PPL_Loan!J31 -> 5.512798e+08 | X3: =Accrual_PPL!Z24 -> 5.512798e+08 | Y3: =Accrual_PPL!AA24 -> 5.512798e+08 | Z3: =Accrual_PPL!AB24+PPL_Loan!K31 -> 5.6660844e+08 | AA3: =Accrual_PPL!AC24 -> 5.6660844e+08 | AB3: =Accrual_PPL!AD24 -> 5.6660844e+08 | AC3: =Accrual_PPL!AE24+PPL_Loan!L31 -> 5.823633e+08 | AD3: =Accrual_PPL!AF24 -> 5.823633e+08 | AE3: =Accrual_PPL!AG24 -> 5.823633e+08 | AF3: =Accrual_PPL!AH24+PPL_Loan!M31 -> 5.9873418e+08 | AG3: =Accrual_PPL!AI24 -> 5.9873418e+08 | AH3: =Accrual_PPL!AJ24 -> 5.9873418e+08 | AI3: =Accrual_PPL!AK24+PPL_Loan!N31 -> 6.1538232e+08 | AJ3: =Accrual_PPL!AL24 -> 6.1538232e+08 | AK3: =Accrual_PPL!AM24 -> 6.1538232e+08 | AL3: =Accrual_PPL!AN24+PPL_Loan!O31 -> 6.326814e+08 | AM3: =AL3 -> 6.326814e+08 | AN3: =AM3 -> 6.326814e+08 | AO3: =AN3 -> 6.326814e+08 | AP3: =AO3 -> 6.326814e+08 | AQ3: =AP3 -> 6.326814e+08 | AR3: =AQ3 -> 6.326814e+08 | AS3: =AR3 -> 6.326814e+08 | AT3: =AS3 -> 6.326814e+08 | ... CT3: =CS3 -> 6.326814e+08
A4: Repayment due | B4: =Accrual_PPL!D28 -> 0 | C4: =Accrual_PPL!E28 -> 0 | D4: =Accrual_PPL!F28 -> 0 | E4: =Accrual_PPL!G28 -> 0 | F4: =Accrual_PPL!H28 -> 0 | G4: =Accrual_PPL!I28 -> 0 | H4: =Accrual_PPL!J28 -> 0 | I4: =Accrual_PPL!K28 -> 0 | ... CT4: =Accrual_PPL!CV28 -> 6.326814e+08
A5: Loan Repayment | B5: =B22 -> 0 | C5: =C22 -> 0 | D5: =D22 -> 0 | E5: =E22 -> 0 | F5: =F22 -> 0 | G5: =G22 -> 0 | H5: =H22 -> 0 | I5: =I22 -> 0 | ... CT5: =CT22 -> 6.326814e+08
A6: Repayment overdue | B6: =IF((B4-B5)>0,(B4-B5),0) -> 0 | C6: =IF((C4-C5)>0,(C4-C5),0) -> 0 | D6: =IF((D4-D5)>0,(D4-D5),0) -> 0 | E6: =IF((E4-E5)>0,(E4-E5),0) -> 0 | F6: =IF((F4-F5)>0,(F4-F5),0) -> 0 | G6: =IF((G4-G5)>0,(G4-G5),0) -> 0 | H6: =IF((H4-H5)>0,(H4-H5),0) -> 0 | I6: =IF((I4-I5)>0,(I4-I5),0) -> 0 | ... CT6: =IF((CT4-CT5)>0,(CT4-CT5),0) -> 0
A7: Loan outstanding | B7: =B3-B5 -> 98715714 | C7: =C3-C5 -> 99181872 | D7: =D3-D5 -> 99181872 | E7: =E3-E5 -> 1.0168897e+08 | F7: =F3-F5 -> 1.0168897e+08 | G7: =G3-G5 -> 1.0168897e+08 | H7: =H3-H5 -> 1.0416058e+08 | I7: =I3-I5 -> 1.0416058e+08 | ... CT7: =CT3-CT5 -> 0
A8: Interest
A9: Interest accrued | B9: =Accrual_PPL!D26 -> 493708.06 | C9: =Accrual_PPL!E26 -> 1320223.7 | D9: =Accrual_PPL!F26 -> 2174289.8 | E9: =Accrual_PPL!G26 -> 3001501.8 | F9: =Accrual_PPL!H26 -> 3877156.8 | G9: =Accrual_PPL!I26 -> 4687137.7 | H9: =Accrual_PPL!J26 -> 5471625.2 | I9: =Accrual_PPL!K26 -> 6301293.1 | ... CT9: =Accrual_PPL!CV26 -> 2.999588e+08
A10: Interest due | B10: 0 | C10: =PPL_Loan!$C$32 -> 0 | D10: =C10 -> 0 | E10: =D10 -> 0 | F10: =PPL_Loan!$D$32 -> 0 | G10: =F10 -> 0 | H10: =G10 -> 0 | I10: =PPL_Loan!$E$32 -> 0 | J10: =I10 -> 0 | K10: =J10 -> 0 | L10: =PPL_Loan!$F$32 -> 0 | M10: =L10 -> 0 | N10: =M10 -> 0 | O10: =PPL_Loan!$G$32 -> 0 | P10: =O10 -> 0 | Q10: =P10 -> 0 | R10: =PPL_Loan!$H$32 -> 0 | S10: =R10 -> 0 | T10: =S10 -> 0 | U10: =PPL_Loan!$I$32 -> 0 | V10: =U10 -> 0 | W10: =V10 -> 0 | X10: =PPL_Loan!$J$32 -> 0 | Y10: =X10 -> 0 | Z10: =Y10 -> 0 | AA10: =PPL_Loan!$K$32 -> 0 | AB10: =AA10 -> 0 | AC10: =AB10 -> 0 | AD10: =PPL_Loan!$L$32 -> 0 | AE10: =AD10 -> 0 | AF10: =AE10 -> 0 | AG10: =PPL_Loan!$M$32 -> 0 | AH10: =AG10 -> 0 | AI10: =AH10 -> 0 | AJ10: =PPL_Loan!$N$32 -> 0 | AK10: =AJ10 -> 0 | AL10: =PPL_Loan!$O$32 -> 0 | AM10: =AL10 -> 0 | AN10: =AM10 -> 0 | AO10: =PPL_Loan!$P$32 -> 17592058 | AP10: =AO10 -> 17592058 | AQ10: =AP10 -> 17592058 | AR10: =PPL_Loan!$Q$32 -> 34488166 | AS10: =AR10 -> 34488166 | AT10: =AS10 -> 34488166 | AU10: =PPL_Loan!$R$32 -> 50321018 | AV10: =AU10 -> 50321018 | AW10: =AV10 -> 50321018 | AX10: =PPL_Loan!$S$32 -> 65274267 | AY10: =AX10 -> 65274267 | AZ10: =AY10 -> 65274267 | BA10: =PPL_Loan!$T$32 -> 79347913 | BB10: =BA10 -> 79347913 | BC10: =BB10 -> 79347913 | BD10: =PPL_Loan!$U$32 -> 92686946 | BE10: =BD10 -> 92686946 | BF10: =BE10 -> 92686946 | BG10: =PPL_Loan!$V$32 -> 1.0500139e+08 | BH10: =BG10 -> 1.0500139e+08 | BI10: =BH10 -> 1.0500139e+08 | BJ10: =PPL_Loan!$W$32 -> 1.1643622e+08 | BK10: =BJ10 -> 1.1643622e+08 | BL10: =BK10 -> 1.1643622e+08 | BM10: =PPL_Loan!$X$32 -> 1.2699146e+08 | BN10: =BM10 -> 1.2699146e+08 | BO10: =BN10 -> 1.2699146e+08 | BP10: =PPL_Loan!$Y$32 -> 1.3677342e+08 | BQ10: =BP10 -> 1.3677342e+08 | BR10: =BQ10 -> 1.3677342e+08 | BS10: =PPL_Loan!$Z$32 -> 1.4556944e+08 | BT10: =BS10 -> 1.4556944e+08 | BU10: =BT10 -> 1.4556944e+08 | BV10: =PPL_Loan!$AA$32 -> 1.5348587e+08 | BW10: =BV10 -> 1.5348587e+08 | BX10: =BW10 -> 1.5348587e+08 | BY10: =PPL_Loan!$AB$32 -> 1.6052269e+08 | BZ10: =BY10 -> 1.6052269e+08 | CA10: =BZ10 -> 1.6052269e+08 | CB10: =PPL_Loan!$AC$32 -> 1.6674758e+08 | CC10: =CB10 -> 1.6674758e+08 | CD10: =CC10 -> 1.6674758e+08 | CE10: =PPL_Loan!$AD$32 -> 1.7202519e+08 | CF10: =PPL_Loan!$AD$32 -> 1.7202519e+08 | CG10: =PPL_Loan!$AD$32 -> 1.7202519e+08 | CH10: =PPL_Loan!$AE$32 -> 1.7647154e+08 | CI10: =PPL_Loan!$AD$32 -> 1.7202519e+08 | CJ10: =PPL_Loan!$AD$32 -> 1.7202519e+08 | CK10: =PPL_Loan!$AF$32 -> 1.7998995e+08 | CL10: =PPL_Loan!$AD$32 -> 1.7202519e+08 | CM10: =PPL_Loan!$AD$32 -> 1.7202519e+08 | CN10: =PPL_Loan!$AG$32 -> 1.8265776e+08 | CO10: =PPL_Loan!$AD$32 -> 1.7202519e+08 | CP10: =PPL_Loan!$AD$32 -> 1.7202519e+08 | CQ10: =PPL_Loan!$AH$32 -> 1.8441696e+08 | CR10: =PPL_Loan!$AD$32 -> 1.7202519e+08 | CS10: =PPL_Loan!$AD$32 -> 1.7202519e+08 | CT10: =PPL_Loan!$AI$32 -> 1.8513224e+08
A11: interest received | B11: =B26 -> 0 | C11: =C26 -> 0 | D11: =D26 -> 0 | E11: =E26 -> 0 | F11: =F26 -> 0 | G11: =G26 -> 0 | H11: =H26 -> 0 | I11: =I26 -> 0 | ... CT11: =CT26 -> 1.8513224e+08
A12: Interest overdue | B12: =IF((B10-B11)>0,(B10-B11),0) -> 0 | C12: =IF((C10-C11)>0,(C10-C11),0) -> 0 | D12: =IF((D10-D11)>0,(D10-D11),0) -> 0 | E12: =IF((E10-E11)>0,(E10-E11),0) -> 0 | F12: =IF((F10-F11)>0,(F10-F11),0) -> 0 | G12: =IF((G10-G11)>0,(G10-G11),0) -> 0 | H12: =IF((H10-H11)>0,(H10-H11),0) -> 0 | I12: =IF((I10-I11)>0,(I10-I11),0) -> 0 | ... CT12: =IF((CT10-CT11)>0,(CT10-CT11),0) -> 0
A13: Interest receivable | B13: =B9-B11 -> 493708.06 | C13: =C9-C11 -> 1320223.7 | D13: =D9-D11 -> 2174289.8 | E13: =E9-E11 -> 3001501.8 | F13: =F9-F11 -> 3877156.8 | G13: =G9-G11 -> 4687137.7 | H13: =H9-H11 -> 5471625.2 | I13: =I9-I11 -> 6301293.1 | ... CT13: =CT9-CT11 -> 1.1482656e+08
A14: LD and others | B14: =B28 -> 0 | C14: =C28 -> 0 | D14: =D28 -> 0 | E14: =E28 -> 0 | F14: =F28 -> 0 | G14: =G28 -> 0 | H14: =H28 -> 0 | I14: =I28 -> 0 | ... CT14: =CT28 -> 0
B19: =B1 -> 42826 | C19: =C1 -> 42856 | D19: =D1 -> 42887 | E19: =E1 -> 42917 | F19: =F1 -> 42948 | G19: =G1 -> 42979 | H19: =H1 -> 43009 | I19: =I1 -> 43040 | ... CT19: =CT1 -> 45748
A20: Repayment receipts:
A21: Repayment received | AL21: =AL4-AK5 -> 0 | AO21: 0 | AR21: 0 | AU21: =AU4-AT5 -> 94902209 | AX21: =AX4-AW5 -> 31634070 | BA21: =BA4-AZ5 -> 31634070 | BD21: =BD4-BC5 -> 31634070 | BG21: =BG4-BF5 -> 31634070 | BJ21: =BJ4-BI5 -> 31634070 | BM21: =BM4-BL5 -> 31634070 | BP21: =BP4-BO5 -> 31634070 | BS21: =BS4-BR5 -> 31634070 | BV21: =BV4-BU5 -> 31634070 | BY21: =BY4-BX5 -> 31634070 | CB21: =CB4-CA5 -> 31634070 | CE21: =CE4-CD5 -> 31634070 | CH21: =CH4-CG5 -> 31634070 | CK21: =CK4-CJ5 -> 31634070 | CN21: =CN4-CM5 -> 31634070 | CQ21: =CQ4-CP5 -> 31634070 | CT21: =CT4-CS5 -> 31634070
A22: Repayment received (cumulative) | B22: =B21 -> 0 | C22: =B22+C21 -> 0 | D22: =C22+D21 -> 0 | E22: =D22+E21 -> 0 | F22: =E22+F21 -> 0 | G22: =F22+G21 -> 0 | H22: =G22+H21 -> 0 | I22: =H22+I21 -> 0 | J22: =I22+J21 -> 0 | ... CT22: =CS22+CT21 -> 6.326814e+08
A24: Interest receipts:
A25: Interest received | B25: 0 | C25: 0 | L25: 0 | AL25: =AL10-AK11 -> 0 | AO25: 0 | AR25: 0 | AU25: =AU10-AT11 -> 50321018 | AX25: =AX10-AW11 -> 14953249 | BA25: =BA10-AZ11 -> 14073646 | BD25: =BD10-BC11 -> 13339033 | BG25: =BG10-BF11 -> 12314440 | BJ25: =BJ10-BI11 -> 11434838 | BM25: =BM10-BL11 -> 10555235 | BP25: =BP10-BO11 -> 9781957.4 | BS25: =BS10-BR11 -> 8796028.9 | BV25: =BV10-BU11 -> 7916426 | BY25: =BY10-BX11 -> 7036823.1 | CB25: =CB10-CA11 -> 6224882 | CE25: =CE10-CD11 -> 5277617.3 | CH25: =CH10-CG11 -> 4446344.3 | CK25: =CK10-CJ11 -> 3518411.5 | CN25: =CN10-CM11 -> 2667806.6 | CQ25: =CQ10-CP11 -> 1759205.8 | CT25: =CT10-CS11 -> 715281.47
A26: Interest received (cumulative) | B26: =+B25 -> 0 | C26: =B26+C25 -> 0 | D26: =C26+D25 -> 0 | E26: =D26+E25 -> 0 | F26: =E26+F25 -> 0 | G26: =F26+G25 -> 0 | H26: =G26+H25 -> 0 | I26: =H26+I25 -> 0 | J26: =I26+J25 -> 0 | ... CT26: =CS26+CT25 -> 1.8513224e+08
A27: LD/others | B27: 0 | C27: 0 | D27: 0 | E27: 0 | F27: 0 | G27: 0 | H27: 0 | I27: 0 | J27: 0 | L27: 0 | M27: 0 | O27: 0 | P27: 0 | R27: 0 | S27: 0 | U27: 0 | V27: 0 | W27: 0 | X27: 0 | Y27: 0 | Z27: 0 | AA27: 0 | AB27: 0 | AC27: 0 | AD27: 0 | AE27: 0 | AF27: 0 | AG27: 0 | AH27: 0 | AI27: 0 | AJ27: 0 | AK27: 0 | AL27: 0 | AM27: 0 | AN27: 0 | AO27: 0 | AP27: 0 | AQ27: 0 | AR27: 0 | AS27: 0 | AT27: 0 | AU27: 0 | AV27: 0 | AW27: 0 | AX27: 0 | AY27: 0 | AZ27: 0 | BA27: 0 | BB27: 0 | BC27: 0 | BD27: 0 | BE27: 0 | BF27: 0 | BG27: 0 | BH27: 0 | BI27: 0 | BJ27: 0 | BK27: 0 | BL27: 0 | BM27: 0 | BN27: 0 | BO27: 0 | BP27: 0 | BQ27: 0 | BR27: 0 | BS27: 0 | BT27: 0 | BU27: 0 | BV27: 0 | BW27: 0 | BX27: 0 | BY27: 0 | BZ27: 0 | CA27: 0 | CB27: 0 | CC27: 0 | CD27: 0 | CE27: 0 | CF27: 0 | CG27: 0 | CH27: 0 | CI27: 0 | CJ27: 0 | CK27: 0 | CL27: 0 | CM27: 0 | CN27: 0 | CO27: 0 | CP27: 0 | CQ27: 0 | CR27: 0 | CS27: 0 | CT27: 0
A28: LD/others (cumulative) | B28: =+B27 -> 0 | C28: =B28+C27 -> 0 | D28: =C28+D27 -> 0 | E28: =D28+E27 -> 0 | F28: =E28+F27 -> 0 | G28: =F28+G27 -> 0 | H28: =G28+H27 -> 0 | I28: =H28+I27 -> 0 | J28: =I28+J27 -> 0 | ... CT28: =CS28+CT27 -> 0
A30: Actual Payment date
A31: Actual Payment amount:
A32: Interest
A33: Principal
A34: LPC
A35: Total | B35: =SUM(B32:B34) -> 0 | C35: =SUM(C32:C34) -> 0 | D35: =SUM(D32:D34) -> 0 | E35: =SUM(E32:E34) -> 0 | F35: =SUM(F32:F34) -> 0 | G35: =SUM(G32:G34) -> 0 | H35: =SUM(H32:H34) -> 0 | I35: =SUM(I32:I34) -> 0 | ... DP35: =SUM(DP32:DP34) -> 0

Sheet PPL_Loan
A1: Project name: | C1: =Disbursement!B1 -> PARTEX PETRO LIMITED (PPL)
A3: Agreement date | C3: 42723
A5: Loan Amount | C5: 980000000 | F5: Interest Grace | H5: 36 | I5: months
F6: Principal Grace | H6: 39 | I6: months
A7: First Drawdown Date | C7: =C22 -> 42808
F8: Interest Grace Ends | H8: =EDATE(C22,H5) -> 43904
A9: Request Date | C9: 42796 | F9: Principal Grace Ends | H9: =EDATE(C22,H6) -> 43996
A11: Interest Rate | C11: 0.1
A13: Tenor | C13: 8 years
A15: Principal | C15: Level principal
A17: Interest calculation | C17: 360 | D17: days basis
A19: Number of installments | C19: 20
A21: Drawdown
C22: =Disbursement!B8 -> 42808 | D22: =Disbursement!B9 -> 42808 | E22: =Disbursement!B10 -> 43143 | F22: =Disbursement!B11 -> 43380 | K22: Effective date | L22: Revised interest rate
C23: =Disbursement!C8 -> 90000000 | D23: =Disbursement!C9 -> 8715714.3 | E23: =Disbursement!C10 -> 39593464 | F23: =Disbursement!C11 -> 3.7954566e+08 | K23: 42948 | L23: 0.0925
C24: =C23 -> 90000000 | D24: =D23+C24 -> 98715714 | E24: =E23+D24 -> 1.3830918e+08 | F24: =F23+E24 -> 5.1785483e+08 | K24: 43191 | L24: 0.11
AI26: =AI29-AH29 -> 74
A27: Repayment | C27: Interest capitalized
A28: Repayment Period | P28: 1 | Q28: =P28+1 -> 2 | R28: =Q28+1 -> 3 | S28: =R28+1 -> 4 | T28: =S28+1 -> 5 | U28: =T28+1 -> 6 | V28: =U28+1 -> 7 | W28: =V28+1 -> 8 | X28: =W28+1 -> 9 | ... AI28: =AH28+1 -> 20
A29: Repayment Date | C29: 42825 | D29: =EDATE(C29,3) -> 42916 | E29: =EDATE(D29,3) -> 43008 | F29: =EDATE(E29,3) -> 43099 | G29: =EDATE(F29,3)+1 -> 43190 | H29: =EDATE(G29,3) -> 43281 | I29: =EDATE(H29,3) -> 43373 | J29: =EDATE(I29,3) -> 43464 | K29: =EDATE(J29,3)+1 -> 43555 | L29: =EDATE(K29,3) -> 43646 | M29: =EDATE(L29,3) -> 43738 | N29: =EDATE(M29,3) -> 43829 | O29: =EDATE(N29,3)+1 -> 43921 | P29: =EDATE(O29,3) -> 44012 | Q29: =EDATE(P29,3) -> 44104 | R29: =EDATE(Q29,3) -> 44195 | S29: =EDATE(R29,3)+1 -> 44286 | T29: =EDATE(S29,3) -> 44377 | U29: =EDATE(T29,3) -> 44469 | V29: =EDATE(U29,3) -> 44560 | W29: =EDATE(V29,3)+1 -> 44651 | X29: =EDATE(W29,3) -> 44742 | Y29: =EDATE(X29,3) -> 44834 | Z29: =EDATE(Y29,3) -> 44925 | AA29: =EDATE(Z29,3)+1 -> 45016 | AB29: =EDATE(AA29,3) -> 45107 | AC29: =EDATE(AB29,3) -> 45199 | AD29: =EDATE(AC29,3) -> 45290 | AE29: =EDATE(AD29,3)+1 -> 45382 | AF29: =EDATE(AE29,3) -> 45473 | AG29: =EDATE(AF29,3) -> 45565 | AH29: =EDATE(AG29,3) -> 45656 | AI29: =EDATE(AH29,3)-16 -> 45730
A30: Opening Balance | C30: =C23+D23 -> 98715714 | D30: =C36 -> 99181872 | E30: =D36 -> 1.0168897e+08 | F30: =E36 -> 1.0416058e+08 | G30: =F36+E23 -> 1.4618952e+08 | H30: =G36 -> 1.4919765e+08 | I30: =H36 -> 1.5330058e+08 | J30: =I36+F23 -> 5.3715569e+08 | K30: =J36 -> 5.512798e+08 | L30: =K36 -> 5.6660844e+08 | M30: =L36 -> 5.823633e+08 | N30: =M36 -> 5.9873418e+08 | O30: =N36 -> 6.1538232e+08 | P30: =O36 -> 6.326814e+08 | Q30: =P36 -> 6.0104733e+08 | R30: =Q36 -> 5.6941326e+08 | ... AI30: =AH36 -> 31634070
A31: Interest Payment | C31: =C30*(C29-C22)*$C$11/360 -> 466157.54 | D31: =C36*(D29-C29)*$C$11/360 -> 2507097.3 | E31: =D36*(K23-D29)*$C$11/360+D36*(E29-K23)*$L$23/360 -> 2471606.9 | F31: =E36*(F29-E29)*$L$23/360 -> 2435476.8 | G31: =F36*($E$22-F29)*$L$23/360+(F36+E23)*(G29-$E$22+1)*$L$23/360 -> 3008131.6 | H31: =G36*(H29-G29-1)*$L$24/360 -> 4102935.3 | I31: =H36*(I29-H29)*$L$24/360 -> 4309449.8 | J31: =I36*(F22-I29)*$L$24/360+J30*(J29-F22)*$L$24/360 -> 14124106 | K31: =J36*(K29-J29)*$L$24/360 -> 15328641 | L31: =K36*(L29-K29)*$L$24/360 -> 15754862 | M31: =L36*(M29-L29)*$L$24/360 -> 16370879 | N31: =M36*(N29-M29)*$L$24/360 -> 16648136 | O31: =N36*(O29-N29)*$L$24/360 -> 17299081 | P31: =O36*(P29-O29)*$L$24/360 -> 17592058 | Q31: =P36*(Q29-P29)*$L$24/360 -> 16896108 | R31: =Q36*(R29-Q29)*$L$24/360 -> 15832852 | ... AI31: =AH36*(AI29-AH29)*$L$24/360 -> 715281.47
A32: Cumulative interest | C32: 0 | D32: 0 | E32: 0 | F32: 0 | G32: 0 | H32: 0 | I32: 0 | J32: 0 | K32: 0 | L32: 0 | M32: 0 | N32: 0 | O32: 0 | P32: =P31+O32 -> 17592058 | Q32: =Q31+P32 -> 34488166 | R32: =R31+Q32 -> 50321018 | S32: =S31+R32 -> 65274267 | T32: =T31+S32 -> 79347913 | U32: =U31+T32 -> 92686946 | V32: =V31+U32 -> 1.0500139e+08 | W32: =W31+V32 -> 1.1643622e+08 | ... AI32: =AI31+AH32 -> 1.8513224e+08
A33: Principal Payment | C33: 0 | D33: 0 | E33: 0 | F33: 0 | G33: 0 | H33: 0 | I33: 0 | J33: 0 | K33: 0 | L33: 0 | M33: 0 | N33: 0 | O33: 0 | P33: =$O$36/$C$19 -> 31634070 | Q33: =$O$36/$C$19 -> 31634070 | R33: =$O$36/$C$19 -> 31634070 | S33: =$O$36/$C$19 -> 31634070 | T33: =$O$36/$C$19 -> 31634070 | U33: =$O$36/$C$19 -> 31634070 | V33: =$O$36/$C$19 -> 31634070 | W33: =$O$36/$C$19 -> 31634070 | ... AI33: =$O$36/$C$19 -> 31634070
A34: Cumulative repayment | C34: =C33+B34 -> 0 | D34: =D33+C34 -> 0 | E34: =E33+D34 -> 0 | F34: =F33+E34 -> 0 | G34: =G33+F34 -> 0 | H34: =H33+G34 -> 0 | I34: =I33+H34 -> 0 | J34: =J33+I34 -> 0 | ... AI34: =AI33+AH34 -> 6.326814e+08
A35: Total Debt Service | C35: =C31+C33 -> 466157.54 | D35: =D33+D31 -> 2507097.3 | E35: =E33+E31 -> 2471606.9 | F35: =F33+F31 -> 2435476.8 | G35: =G33+G31 -> 3008131.6 | H35: =H33+H31 -> 4102935.3 | I35: =I33+I31 -> 4309449.8 | J35: =J33+J31 -> 14124106 | K35: =K33+K31 -> 15328641 | ... AI35: =AI33+AI31 -> 32349351
A36: Closing Balance | C36: =C30+C31 -> 99181872 | D36: =D30+D31 -> 1.0168897e+08 | E36: =E30+E31 -> 1.0416058e+08 | F36: =F30+F31 -> 1.0659605e+08 | G36: =G30+G31 -> 1.4919765e+08 | H36: =H30+H31 -> 1.5330058e+08 | I36: =I30+I31 -> 1.5761003e+08 | J36: =J30+J31 -> 5.512798e+08 | ... O36: =O30+O31 -> 6.326814e+08 | P36: =P30-P33 -> 6.0104733e+08 | Q36: =Q30-Q33 -> 5.6941326e+08 | R36: =R30-R33 -> 5.3777919e+08 | S36: =S30-S33 -> 5.0614512e+08 | T36: =T30-T33 -> 4.7451105e+08 | U36: =U30-U33 -> 4.4287698e+08 | V36: =V30-V33 -> 4.1124291e+08 | W36: =W30-W33 -> 3.7960884e+08 | ... AI36: =AI30-AI33 -> 0
A39: Total Interest Capitalized | B39: =SUM(C31:O31) -> 1.1482656e+08
A41: Particulars | C41: 42825 | D41: =EOMONTH(C41,1) -> 42855 | E41: =EOMONTH(D41,1) -> 42886 | F41: =EOMONTH(E41,1) -> 42916 | G41: =EOMONTH(F41,1) -> 42947 | H41: =EOMONTH(G41,1) -> 42978 | I41: =EOMONTH(H41,1) -> 43008 | J41: =EOMONTH(I41,1) -> 43039 | K41: =EOMONTH(J41,1) -> 43069 | ... CU41: =EOMONTH(CT41,1) -> 45747
A42: Total interest accrued | C42: =SUM(Accrual_PPL!$D$25) -> 493708.06 | D42: =SUM(Accrual_PPL!$D$25:E25) -> 1320223.7 | E42: =SUM(Accrual_PPL!$D$25:F25) -> 2174289.8 | F42: =SUM(Accrual_PPL!$D$25:G25) -> 3001501.8 | G42: =SUM(Accrual_PPL!$D$25:H25) -> 3877156.8 | H42: =SUM(Accrual_PPL!$D$25:I25) -> 4687137.7 | I42: =SUM(Accrual_PPL!$D$25:J25) -> 5471625.2 | J42: =SUM(Accrual_PPL!$D$25:K25) -> 6301293.1 | K42: =SUM(Accrual_PPL!$D$25:L25) -> 7104197.6 | ... CU42: =SUM(Accrual_PPL!$D$25:CV25) -> 2.999588e+08
A43: Total interest capitalized | C43: =SUM($C$31) -> 466157.54 | D43: =SUM($C$31) -> 466157.54 | E43: =SUM($C$31) -> 466157.54 | F43: =SUM($C$31:$D$31) -> 2973254.9 | G43: =SUM($C$31:$D$31) -> 2973254.9 | H43: =SUM($C$31:$D$31) -> 2973254.9 | I43: =SUM($C$31:$E$31) -> 5444861.7 | J43: =SUM($C$31:$E$31) -> 5444861.7 | K43: =SUM($C$31:$E$31) -> 5444861.7 | L43: =SUM($C$31:$F$31) -> 7880338.5 | M43: =SUM($C$31:$F$31) -> 7880338.5 | N43: =SUM($C$31:$F$31) -> 7880338.5 | O43: =SUM($C$31:$G$31) -> 10888470 | P43: =SUM($C$31:$G$31) -> 10888470 | Q43: =SUM($C$31:$G$31) -> 10888470 | R43: =SUM($C$31:$H$31) -> 14991406 | S43: =SUM($C$31:$H$31) -> 14991406 | T43: =SUM($C$31:$H$31) -> 14991406 | U43: =SUM($C$31:$I$31) -> 19300855 | V43: =SUM($C$31:$I$31) -> 19300855 | W43: =SUM($C$31:$I$31) -> 19300855 | X43: =SUM($C$31:$J$31) -> 33424962 | Y43: =SUM($C$31:$J$31) -> 33424962 | Z43: =SUM($C$31:$J$31) -> 33424962 | AA43: =SUM($C$31:$K$31) -> 48753603 | AB43: =SUM($C$31:$K$31) -> 48753603 | AC43: =SUM($C$31:$K$31) -> 48753603 | AD43: =SUM($C$31:$L$31) -> 64508465 | AE43: =SUM($C$31:$L$31) -> 64508465 | AF43: =SUM($C$31:$L$31) -> 64508465 | AG43: =SUM($C$31:$M$31) -> 80879345 | AH43: =SUM($C$31:$M$31) -> 80879345 | AI43: =SUM($C$31:$M$31) -> 80879345 | AJ43: =SUM($C$31:$N$31) -> 97527481 | AK43: =SUM($C$31:$N$31) -> 97527481 | AL43: =SUM($C$31:$N$31) -> 97527481 | AM43: =SUM($C$31:$O$31) -> 1.1482656e+08 | AN43: =SUM($C$31:$O$31) -> 1.1482656e+08 | AO43: =SUM($C$31:$O$31) -> 1.1482656e+08 | AP43: =SUM($C$31:$O$31) -> 1.1482656e+08 | AQ43: =SUM($C$31:$O$31) -> 1.1482656e+08 | AR43: =SUM($C$31:$O$31) -> 1.1482656e+08 | AS43: =SUM($C$31:$O$31) -> 1.1482656e+08 | AT43: =SUM($C$31:$O$31) -> 1.1482656e+08 | ... CU43: =SUM($C$31:$O$31) -> 1.1482656e+08
A44: Net interest accrued | C44: =C42-C43 -> 27550.52 | D44: =D42-D43 -> 854066.12 | E44: =E42-E43 -> 1708132.2 | F44: =F42-F43 -> 28246.936 | G44: =G42-G43 -> 903901.95 | H44: =H42-H43 -> 1713882.8 | I44: =I42-I43 -> 26763.481 | J44: =J42-J43 -> 856431.4 | ... CU44: =CU42-CU43 -> 1.8513224e+08
A45: Total interest received | C45: =Summary!B26 -> 0 | D45: =Summary!C26 -> 0 | E45: =Summary!D26 -> 0 | F45: =Summary!E26 -> 0 | G45: =Summary!F26 -> 0 | H45: =Summary!G26 -> 0 | I45: =Summary!H26 -> 0 | J45: =Summary!I26 -> 0 | ... CU45: =Summary!CT26 -> 1.8513224e+08
A46: Total interest receivable | C46: =C44-C45 -> 27550.52 | D46: =D44-D45 -> 854066.12 | E46: =E44-E45 -> 1708132.2 | F46: =F44-F45 -> 28246.936 | G46: =G44-G45 -> 903901.95 | H46: =H44-H45 -> 1713882.8 | I46: =I44-I45 -> 26763.481 | J46: =J44-J45 -> 856431.4 | ... CU46: =CU44-CU45 -> 0
A53: Average Installment Size
A54: Date | C54: =C29 -> 42825 | D54: =D29 -> 42916 | E54: =E29 -> 43008 | F54: =F29 -> 43099 | G54: =G29 -> 43190 | H54: =H29 -> 43281 | I54: =I29 -> 43373 | J54: =J29 -> 43464 | ... AI54: =AI29 -> 45730
A55: Average Installment | C55: =AVERAGE($P$35) -> 49226128 | D55: =AVERAGE($P$35) -> 49226128 | E55: =AVERAGE($P$35) -> 49226128 | F55: =AVERAGE($P$35) -> 49226128 | G55: =AVERAGE($P$35) -> 49226128 | H55: =AVERAGE($P$35) -> 49226128 | I55: =AVERAGE($P$35) -> 49226128 | J55: =AVERAGE($P$35) -> 49226128 | ... P55: =AVERAGE($P$35) -> 49226128 | Q55: =AVERAGE($P$35:Q35) -> 48878153 | R55: =AVERAGE($P$35:R35) -> 48407742 | S55: =AVERAGE($P$35:S35) -> 47952637 | T55: =AVERAGE($P$35:T35) -> 47503652 | U55: =AVERAGE($P$35:U35) -> 47081894 | V55: =AVERAGE($P$35:V35) -> 46634268 | W55: =AVERAGE($P$35:W35) -> 46188598 | X55: =AVERAGE($P$35:X35) -> 45744232 | ... AI55: =AVERAGE($P$35:AI35) -> 40890682

Sheet Accrual_PPL
A1: Project name: | B1: =PPL_Loan!C1 -> PARTEX PETRO LIMITED (PPL)
A3: Assumptions:
A5: Agreement date | B5: =PPL_Loan!C3 -> 42723
A7: Loan Amount | B7: =PPL_Loan!C5 -> 980000000 | C7: BDT
A9: Drawdown Date | B9: =PPL_Loan!C7 -> 42808
A11: Interest Rate | B11: =PPL_Loan!C11 -> 0.1
A12: Tenor | B12: =PPL_Loan!C13 -> 8 years
A13: Interest calculation | B13: 360 | C13: days basis
A14: Principal | B14: =PPL_Loan!C15 -> Level principal
A16: Drawdown
C17: =PPL_Loan!C22 -> 42808 | D17: =PPL_Loan!D22 -> 42808 | E17: =PPL_Loan!E22 -> 43143 | F17: =PPL_Loan!F22 -> 43380 | N17: Effective date | O17: Revised interest rate
C18: =PPL_Loan!C23 -> 90000000 | D18: =PPL_Loan!D23 -> 8715714.3 | E18: =PPL_Loan!E23 -> 39593464 | F18: =PPL_Loan!F23 -> 3.7954566e+08 | N18: 42948 | O18: 0.0925
C19: =C18 -> 90000000 | D19: =C19+D18 -> 98715714 | E19: =D19+E18 -> 1.3830918e+08 | F19: =E19+F18 -> 5.1785483e+08 | N19: 43191 | O19: 0.11
A22: Accrual of interest
A23: Months | D23: 42826 | E23: =EDATE(D23,1) -> 42856 | F23: =EDATE(E23,1) -> 42887 | G23: =EDATE(F23,1) -> 42917 | H23: =EDATE(G23,1) -> 42948 | I23: =EDATE(H23,1) -> 42979 | J23: =EDATE(I23,1) -> 43009 | K23: =EDATE(J23,1) -> 43040 | L23: =EDATE(K23,1) -> 43070 | ... CV23: =EDATE(CU23,1) -> 45748
A24: Opening Balance | D24: =C18+D18 -> 98715714 | E24: =D30 -> 99181872 | F24: =E30 -> 99181872 | G24: =F30 -> 99181872 | H24: =G30 -> 1.0168897e+08 | I24: =H30 -> 1.0168897e+08 | J24: =I30 -> 1.0168897e+08 | K24: =J30 -> 1.0416058e+08 | L24: =K30 -> 1.0416058e+08 | ... N24: =M30 -> 1.0659605e+08 | O24: =N30+E18 -> 1.4618952e+08 | P24: =O30 -> 1.4618952e+08 | Q24: =P30 -> 1.4919765e+08 | R24: =Q30 -> 1.4919765e+08 | S24: =R30 -> 1.4919765e+08 | T24: =S30 -> 1.5330058e+08 | U24: =T30 -> 1.5330058e+08 | V24: =U30 -> 1.5330058e+08 | W24: =V30+F18 -> 5.3715569e+08 | X24: =W30 -> 5.3715569e+08 | Y24: =X30 -> 5.3715569e+08 | Z24: =Y30 -> 5.512798e+08 | AA24: =Z30 -> 5.512798e+08 | AB24: =AA30 -> 5.512798e+08 | AC24: =AB30 -> 5.6660844e+08 | AD24: =AC30 -> 5.6660844e+08 | AE24: =AD30 -> 5.6660844e+08 | ... CV24: =CU30 -> 31634070
A25: Interest Payment | D25: =D24*(PPL_Loan!$C$29-C17)*$B$11/360+D30*(D23-PPL_Loan!$C$29)*$B$11/360 -> 493708.06 | E25: =E24*(E23-D23)*$B$11/360 -> 826515.6 | F25: =F24*(F23-E23)*$B$11/360 -> 854066.12 | G25: =G24*(PPL_Loan!$D$29-F23)*$B$11/360+G30*(G23-PPL_Loan!$D$29)*$B$11/360 -> 827212.01 | H25: =H24*(H23-G23)*$B$11/360 -> 875655.01 | I25: =I24*(I23-H23)*$O$18/360 -> 809980.89 | J25: =J24*(PPL_Loan!$E$29-I23)*$O$18/360+J30*(J23-PPL_Loan!$E$29)*$O$18/360 -> 784487.54 | K25: =K24*(K23-J23)*$O$18/360 -> 829667.92 | L25: =L24*(L23-K23)*$O$18/360 -> 802904.44 | M25: =M24*(PPL_Loan!$F$29-L23)*$O$18/360+M30*(M23-PPL_Loan!$F$29)*$O$18/360 -> 830919.49 | N25: =N24*(N23-M23)*$O$18/360 -> 849067.17 | O25: =N30*($E$17-N23)*$O$18/360+(N30+E18)*(O23-$E$17)*$O$18/360 -> 939845.83 | P25: =P24*(PPL_Loan!$G$29-O23+1)*$O$18/360+P30*(P23-PPL_Loan!$G$29-1)*$O$18/360 -> 1164440.1 | Q25: =Q24*(Q23-P23)*$O$19/360 -> 1367645.1 | R25: =R24*(R23-Q23)*$O$19/360 -> 1413233.3 | S25: =S24*(PPL_Loan!$H$29-R23)*$O$19/360+S30*(S23-PPL_Loan!$H$29)*$O$19/360 -> 1368898.8 | T25: =T24*(T23-S23)*$O$19/360 -> 1452097.2 | U25: =U24*(U23-T23)*$O$19/360 -> 1452097.2 | V25: =V24*(PPL_Loan!$I$29-U23)*$O$19/360+V30*(V23-PPL_Loan!$I$29)*$O$19/360 -> 1406572.1 | W25: =V30*(F17-V23)*$O$19/360+W24*(W23-F17)*$O$19/360 -> 4392224.4 | X25: =X24*(X23-W23)*$O$19/360 -> 4923927.2 | Y25: =Y24*(PPL_Loan!$J$29-X23)*$O$19/360+Y30*(Y23-PPL_Loan!$J$29)*$O$19/360 -> 5096689.5 | Z25: =Z24*(Z23-Y23)*$O$19/360 -> 5221844.7 | AA25: =AA24*(AA23-Z23)*$O$19/360 -> 4716504.9 | AB25: =AB24*(PPL_Loan!$K$29-AA23)*$O$19/360+AB30*(AB23-PPL_Loan!$K$29)*$O$19/360 -> 5226528.5 | AC25: =AC24*(AC23-AB23)*$O$19/360 -> 5193910.7 | AD25: =AD24*(AD23-AC23)*$O$19/360 -> 5367041 | AE25: =AE24*(PPL_Loan!$L$29-AD23)*$O$19/360+AE30*(AE23-PPL_Loan!$L$29)*$O$19/360 -> 5198724.7 | AF25: =AF24*(AF23-AE23)*$O$19/360 -> 5516274.6 | AG25: =AG24*(AG23-AF23)*$O$19/360 -> 5516274.6 | AH25: =AH24*(PPL_Loan!$M$29-AG23)*$O$19/360+AH30*(AH23-PPL_Loan!$M$29)*$O$19/360 -> 5343332.5 | AI25: =AI24*(AI23-AH23)*$O$19/360 -> 5671343.2 | AJ25: =AJ24*(AJ23-AI23)*$O$19/360 -> 5488396.6 | AK25: =AK24*(PPL_Loan!$N$29-AJ23)*$O$19/360+AK30*(AK23-PPL_Loan!$N$29)*$O$19/360 -> 5681517.1 | AL25: =AL24*(AL23-AK23)*$O$19/360 -> 5829038 | AM25: =AM24*(AM23-AL23)*$O$19/360 -> 5452971.1 | AN25: =AN24*(PPL_Loan!$O$29-AM23)*$O$19/360+AN30*(AN23-PPL_Loan!$O$29)*$O$19/360 -> 5834323.9 | AO25: =AO24*(AO23-AN23)*$O$19/360 -> 5799579.5 | AP25: =AP24*(AP23-AO23)*$O$19/360 -> 5992898.8 | AQ25: =AQ24*(PPL_Loan!$P$29-AP23)*$O$19/360+AQ30*(AQ23-PPL_Loan!$P$29)*$O$19/360 -> 5789913.5 | AR25: =AR24*(AR23-AQ23)*$O$19/360 -> 5693253.8 | AS25: =AS24*(AS23-AR23)*$O$19/360 -> 5693253.8 | AT25: =AT24*(PPL_Loan!$Q$29-AS23)*$O$19/360+AT30*(AT23-PPL_Loan!$Q$29)*$O$19/360 -> 5499934.5 | AU25: =AU24*(AU23-AT23)*$O$19/360 -> 5393608.9 | AV25: =AV24*(AV23-AU23)*$O$19/360 -> 5219621.5 | AW25: =AW24*(PPL_Loan!$R$29-AV23)*$O$19/360+AW30*(AW23-PPL_Loan!$R$29)*$O$19/360 -> 5374277 | AX25: =AX24*(AX23-AW23)*$O$19/360 -> 5093964 | AY25: =AY24*(AY23-AX23)*$O$19/360 -> 4600999.7 | AZ25: =AZ24*(PPL_Loan!$S$29-AY23)*$O$19/360+AZ30*(AZ23-PPL_Loan!$S$29)*$O$19/360 -> 5084298 | BA25: =BA24*(BA23-AZ23)*$O$19/360 -> 4639663.6 | BB25: =BB24*(BB23-BA23)*$O$19/360 -> 4794319 | BC25: =BC24*(PPL_Loan!$T$29-BB23)*$O$19/360+BC30*(BC23-PPL_Loan!$T$29)*$O$19/360 -> 4629997.6 | BD25: =BD24*(BD23-BC23)*$O$19/360 -> 4494674.1 | BE25: =BE24*(BE23-BD23)*$O$19/360 -> 4494674.1 | BF25: =BF24*(PPL_Loan!$U$29-BE23)*$O$19/360+BF30*(BF23-PPL_Loan!$U$29)*$O$19/360 -> 4340018.6 | BG25: =BG24*(BG23-BF23)*$O$19/360 -> 4195029.1 | BH25: =BH24*(BH23-BG23)*$O$19/360 -> 4059705.6 | BI25: =BI24*(PPL_Loan!$V$29-BH23)*$O$19/360+BI30*(BI23-PPL_Loan!$V$29)*$O$19/360 -> 4175697.2 | BJ25: =BJ24*(BJ23-BI23)*$O$19/360 -> 3895384.2 | BK25: =BK24*(BK23-BJ23)*$O$19/360 -> 3518411.5 | BL25: =BL24*(PPL_Loan!$W$29-BK23)*$O$19/360+BL30*(BL23-PPL_Loan!$W$29)*$O$19/360 -> 3885718.2 | BM25: =BM24*(BM23-BL23)*$O$19/360 -> 3479747.7 | BN25: =BN24*(BN23-BM23)*$O$19/360 -> 3595739.3 | BO25: =BO24*(PPL_Loan!$X$29-BN23)*$O$19/360+BO30*(BO23-PPL_Loan!$X$29)*$O$19/360 -> 3470081.7 | BP25: =BP24*(BP23-BO23)*$O$19/360 -> 3296094.3 | BQ25: =BQ24*(BQ23-BP23)*$O$19/360 -> 3296094.3 | BR25: =BR24*(PPL_Loan!$Y$29-BQ23)*$O$19/360+BR30*(BR23-PPL_Loan!$Y$29)*$O$19/360 -> 3180102.7 | BS25: =BS24*(BS23-BR23)*$O$19/360 -> 2996449.4 | BT25: =BT24*(BT23-BS23)*$O$19/360 -> 2899789.7 | BU25: =BU24*(PPL_Loan!$Z$29-BT23)*$O$19/360+BU30*(BU23-PPL_Loan!$Z$29)*$O$19/360 -> 2977117.5 | BV25: =BV24*(BV23-BU23)*$O$19/360 -> 2696804.5 | BW25: =BW24*(BW23-BV23)*$O$19/360 -> 2435823.4 | BX25: =BX24*(PPL_Loan!$AA$29-BW23)*$O$19/360+BX30*(BX23-PPL_Loan!$AA$29)*$O$19/360 -> 2687138.5 | BY25: =BY24*(BY23-BX23)*$O$19/360 -> 2319831.8 | BZ25: =BZ24*(BZ23-BY23)*$O$19/360 -> 2397159.5 | CA25: =CA24*(PPL_Loan!$AB$29-BZ23)*$O$19/360+CA30*(CA23-PPL_Loan!$AB$29)*$O$19/360 -> 2310165.8 | CB25: =CB24*(CB23-CA23)*$O$19/360 -> 2097514.6 | CC25: =CC24*(CC23-CB23)*$O$19/360 -> 2097514.6 | CD25: =CD24*(PPL_Loan!$AC$29-CC23)*$O$19/360+CD30*(CD23-PPL_Loan!$AC$29)*$O$19/360 -> 2020186.8 | CE25: =CE24*(CE23-CD23)*$O$19/360 -> 1797869.6 | CF25: =CF24*(CF23-CE23)*$O$19/360 -> 1739873.8 | CG25: =CG24*(PPL_Loan!$AD$29-CF23)*$O$19/360+CG30*(CG23-PPL_Loan!$AD$29)*$O$19/360 -> 1778537.7 | CH25: =CH24*(CH23-CG23)*$O$19/360 -> 1498224.7 | CI25: =CI24*(CI23-CH23)*$O$19/360 -> 1401565 | CJ25: =CJ24*(PPL_Loan!$AE$29-CI23)*$O$19/360+CJ30*(CJ23-PPL_Loan!$AE$29)*$O$19/360 -> 1488558.7 | CK25: =CK24*(CK23-CJ23)*$O$19/360 -> 1159915.9 | CL25: =CL24*(CL23-CK23)*$O$19/360 -> 1198579.8 | CM25: =CM24*(PPL_Loan!$AF$29-CL23)*$O$19/360+CM30*(CM23-PPL_Loan!$AF$29)*$O$19/360 -> 1150249.9 | CN25: =CN24*(CN23-CM23)*$O$19/360 -> 898934.82 | CO25: =CO24*(CO23-CN23)*$O$19/360 -> 898934.82 | CP25: =CP24*(PPL_Loan!$AG$29-CO23)*$O$19/360+CP30*(CP23-PPL_Loan!$AG$29)*$O$19/360 -> 860270.95 | CQ25: =CQ24*(CQ23-CP23)*$O$19/360 -> 599289.88 | CR25: =CR24*(CR23-CQ23)*$O$19/360 -> 579957.95 | CS25: =CS24*(PPL_Loan!$AH$29-CR23)*$O$19/360+CS30*(CS23-PPL_Loan!$AH$29)*$O$19/360 -> 579957.95 | CT25: =CT24*(CT23-CS23)*$O$19/360 -> 299644.94 | CU25: =CU24*(CU23-CT23)*$O$19/360 -> 270647.04 | CV25: =CV24*(PPL_Loan!$AI$29-CU23)*$O$19/360+CV30*(CV23-PPL_Loan!$AI$29)*$O$19/360 -> 125657.56
A26: Cumulative interest | D26: =C26+D25 -> 493708.06 | E26: =D26+E25 -> 1320223.7 | F26: =E26+F25 -> 2174289.8 | G26: =F26+G25 -> 3001501.8 | H26: =G26+H25 -> 3877156.8 | I26: =H26+I25 -> 4687137.7 | J26: =I26+J25 -> 5471625.2 | K26: =J26+K25 -> 6301293.1 | ... CV26: =CU26+CV25 -> 2.999588e+08
A27: Principal Payment | D27: 0 | E27: 0 | F27: 0 | G27: 0 | H27: 0 | I27: 0 | J27: 0 | K27: 0 | L27: 0 | M27: 0 | N27: 0 | O27: =L27 -> 0 | P27: =M27 -> 0 | Q27: =PPL_Loan!$G$33 -> 0 | R27: =O27 -> 0 | S27: =P27 -> 0 | T27: =PPL_Loan!$H$33 -> 0 | U27: =R27 -> 0 | V27: =S27 -> 0 | W27: =PPL_Loan!$I$33 -> 0 | X27: =U27 -> 0 | Y27: =V27 -> 0 | Z27: =PPL_Loan!$J$33 -> 0 | AA27: =X27 -> 0 | AB27: =Y27 -> 0 | AC27: =PPL_Loan!$K$33 -> 0 | AD27: =AA27 -> 0 | AE27: =AB27 -> 0 | AF27: =PPL_Loan!$L$33 -> 0 | AG27: =AD27 -> 0 | AH27: =AE27 -> 0 | AI27: =PPL_Loan!$M$33 -> 0 | AJ27: =AG27 -> 0 | AK27: =AH27 -> 0 | AL27: =PPL_Loan!$N$33 -> 0 | AM27: =AJ27 -> 0 | AN27: =AK27 -> 0 | AO27: =PPL_Loan!$O$33 -> 0 | AP27: =AM27 -> 0 | AQ27: =PPL_Loan!$P$33 -> 31634070 | AR27: =AO27 -> 0 | AS27: =AP27 -> 0 | AT27: =PPL_Loan!$Q$33 -> 31634070 | AU27: =AR27 -> 0 | AV27: =AS27 -> 0 | AW27: =PPL_Loan!$R$33 -> 31634070 | AX27: =AU27 -> 0 | AY27: =AV27 -> 0 | AZ27: =PPL_Loan!$S$33 -> 31634070 | BA27: =AX27 -> 0 | BB27: =AY27 -> 0 | BC27: =PPL_Loan!$T$33 -> 31634070 | BD27: =BA27 -> 0 | BE27: =BB27 -> 0 | BF27: =PPL_Loan!$U$33 -> 31634070 | BG27: =BD27 -> 0 | BH27: =BE27 -> 0 | BI27: =PPL_Loan!$V$33 -> 31634070 | BJ27: =BG27 -> 0 | BK27: =BH27 -> 0 | BL27: =PPL_Loan!$W$33 -> 31634070 | BM27: =BJ27 -> 0 | BN27: =BK27 -> 0 | BO27: =PPL_Loan!$X$33 -> 31634070 | BP27: =BM27 -> 0 | BQ27: =BN27 -> 0 | BR27: =PPL_Loan!$Y$33 -> 31634070 | BS27: =BP27 -> 0 | BT27: =BQ27 -> 0 | BU27: =PPL_Loan!$Z$33 -> 31634070 | BV27: =BS27 -> 0 | BW27: =BT27 -> 0 | BX27: =PPL_Loan!$AA$33 -> 31634070 | BY27: =BV27 -> 0 | BZ27: =BW27 -> 0 | CA27: =PPL_Loan!$AB$33 -> 31634070 | CB27: =BY27 -> 0 | CC27: =BZ27 -> 0 | CD27: =PPL_Loan!$AC$33 -> 31634070 | CE27: =CB27 -> 0 | CF27: =CC27 -> 0 | CG27: =PPL_Loan!$AD$33 -> 31634070 | CH27: =CE27 -> 0 | CI27: =CF27 -> 0 | CJ27: =PPL_Loan!$AD$33 -> 31634070 | CK27: =CH27 -> 0 | CL27: =CI27 -> 0 | CM27: =PPL_Loan!$AD$33 -> 31634070 | CN27: =CK27 -> 0 | CO27: =CL27 -> 0 | CP27: =PPL_Loan!$AD$33 -> 31634070 | CQ27: =CN27 -> 0 | CR27: =CO27 -> 0 | CS27: =PPL_Loan!$AD$33 -> 31634070 | CT27: =CQ27 -> 0 | CU27: =CR27 -> 0 | CV27: =PPL_Loan!$AD$33 -> 31634070
A28: Cumulative repayment | D28: =C28+D27 -> 0 | E28: =D28+E27 -> 0 | F28: =E28+F27 -> 0 | G28: =F28+G27 -> 0 | H28: =G28+H27 -> 0 | I28: =H28+I27 -> 0 | J28: =I28+J27 -> 0 | K28: =J28+K27 -> 0 | ... CV28: =CU28+CV27 -> 6.326814e+08
A29: Total Debt Service | D29: =D27+D25 -> 493708.06 | E29: =E27+E25 -> 826515.6 | F29: =F27+F25 -> 854066.12 | G29: =G27+G25 -> 827212.01 | H29: =H27+H25 -> 875655.01 | I29: =I27+I25 -> 809980.89 | J29: =J27+J25 -> 784487.54 | K29: =K27+K25 -> 829667.92 | ... CV29: =CV27+CV25 -> 31759727
A30: Closing Balance | D30: =PPL_Loan!$C$36 -> 99181872 | E30: =E24-E27 -> 99181872 | F30: =F24-F27 -> 99181872 | G30: =PPL_Loan!$D$36 -> 1.0168897e+08 | H30: =H24-H27 -> 1.0168897e+08 | I30: =I24-I27 -> 1.0168897e+08 | J30: =PPL_Loan!$E$36 -> 1.0416058e+08 | K30: =K24-K27 -> 1.0416058e+08 | L30: =L24-L27 -> 1.0416058e+08 | M30: =PPL_Loan!$F$36 -> 1.0659605e+08 | N30: =N24-N27 -> 1.0659605e+08 | O30: =O24-O27 -> 1.4618952e+08 | P30: =PPL_Loan!$G$36 -> 1.4919765e+08 | Q30: =Q24-Q27 -> 1.4919765e+08 | R30: =R24-R27 -> 1.4919765e+08 | S30: =PPL_Loan!$H$36 -> 1.5330058e+08 | T30: =T24-T27 -> 1.5330058e+08 | U30: =U24-U27 -> 1.5330058e+08 | V30: =PPL_Loan!$I$36 -> 1.5761003e+08 | W30: =W24-W27 -> 5.3715569e+08 | X30: =X24-X27 -> 5.3715569e+08 | Y30: =PPL_Loan!$J$36 -> 5.512798e+08 | Z30: =Z24-Z27 -> 5.512798e+08 | AA30: =AA24-AA27 -> 5.512798e+08 | AB30: =PPL_Loan!$K$36 -> 5.6660844e+08 | AC30: =AC24-AC27 -> 5.6660844e+08 | AD30: =AD24-AD27 -> 5.6660844e+08 | AE30: =PPL_Loan!$L$36 -> 5.823633e+08 | AF30: =AF24-AF27 -> 5.823633e+08 | AG30: =AG24-AG27 -> 5.823633e+08 | AH30: =PPL_Loan!$M$36 -> 5.9873418e+08 | AI30: =AI24-AI27 -> 5.9873418e+08 | AJ30: =AJ24-AJ27 -> 5.9873418e+08 | AK30: =PPL_Loan!$N$36 -> 6.1538232e+08 | AL30: =AL24-AL27 -> 6.1538232e+08 | AM30: =AM24-AM27 -> 6.1538232e+08 | AN30: =+PPL_Loan!O36 -> 6.326814e+08 | AO30: =AO24-AO27 -> 6.326814e+08 | AP30: =AP24-AP27 -> 6.326814e+08 | AQ30: =AQ24-AQ27 -> 6.0104733e+08 | AR30: =AR24-AR27 -> 6.0104733e+08 | AS30: =AS24-AS27 -> 6.0104733e+08 | AT30: =AT24-AT27 -> 5.6941326e+08 | AU30: =AU24-AU27 -> 5.6941326e+08 | AV30: =AV24-AV27 -> 5.6941326e+08 | ... CV30: =CV24-CV27 -> 0
CV33: =SUM(D25:CV25)-SUM(PPL_Loan!C31:AI31) -> 0

Sheet Repayment Schedule
A1: Project name: | C1: =PPL_Loan!C1 -> PARTEX PETRO LIMITED (PPL)
A4: Agreement date | C4: =Accrual_PPL!B5 -> 42723
A6: Loan Amount | C6: =PPL_Loan!C5 -> 980000000
A8: Drawdown Date | C8: =PPL_Loan!C7 -> 42808
A10: Interest Rate | C10: 0.1
A11: Tenor | C11: 7 years
A12: Principal | C12: =Accrual_PPL!B14 -> Level principal
A13: Interest calculation | C13: 360 | D13: days basis
A14: Number of installments | C14: 24
A16: Drawdown
C17: =PPL_Loan!C22 -> 42808 | D17: =PPL_Loan!D22 -> 42808
C18: =PPL_Loan!C23 -> 90000000 | D18: =PPL_Loan!D23 -> 8715714.3
C19: =C18 -> 90000000 | D19: =D18+C19 -> 98715714
A23: Repayment Date | B23: Opening Balance | C23: Interest Payment | D23: Cumulative interest | E23: Principal Payment | F23: Cumulative repayment | G23: Total Debt Service | H23: Closing Balance
A24: {=TRANSPOSE(PPL_Loan!C29:AI36)} -> 42825 | B24: 98715714 | C24: 466157.54 | D24: 0 | E24: 0 | F24: 0 | G24: 466157.54 | H24: 99181872
A25: 42916 | B25: 99181872 | C25: 2507097.3 | D25: 0 | E25: 0 | F25: 0 | G25: 2507097.3 | H25: 1.0168897e+08
A26: 43008 | B26: 1.0168897e+08 | C26: 2471606.9 | D26: 0 | E26: 0 | F26: 0 | G26: 2471606.9 | H26: 1.0416058e+08
A27: 43099 | B27: 1.0416058e+08 | C27: 2435476.8 | D27: 0 | E27: 0 | F27: 0 | G27: 2435476.8 | H27: 1.0659605e+08
A28: 43190 | B28: 1.4618952e+08 | C28: 3008131.6 | D28: 0 | E28: 0 | F28: 0 | G28: 3008131.6 | H28: 1.4919765e+08
A29: 43281 | B29: 1.4919765e+08 | C29: 4102935.3 | D29: 0 | E29: 0 | F29: 0 | G29: 4102935.3 | H29: 1.5330058e+08
A30: 43373 | B30: 1.5330058e+08 | C30: 4309449.8 | D30: 0 | E30: 0 | F30: 0 | G30: 4309449.8 | H30: 1.5761003e+08
A31: 43464 | B31: 5.3715569e+08 | C31: 14124106 | D31: 0 | E31: 0 | F31: 0 | G31: 14124106 | H31: 5.512798e+08
A32: 43555 | B32: 5.512798e+08 | C32: 15328641 | D32: 0 | E32: 0 | F32: 0 | G32: 15328641 | H32: 5.6660844e+08
A33: 43646 | B33: 5.6660844e+08 | C33: 15754862 | D33: 0 | E33: 0 | F33: 0 | G33: 15754862 | H33: 5.823633e+08
A34: 43738 | B34: 5.823633e+08 | C34: 16370879 | D34: 0 | E34: 0 | F34: 0 | G34: 16370879 | H34: 5.9873418e+08
A35: 43829 | B35: 5.9873418e+08 | C35: 16648136 | D35: 0 | E35: 0 | F35: 0 | G35: 16648136 | H35: 6.1538232e+08
A36: 43921 | B36: 6.1538232e+08 | C36: 17299081 | D36: 0 | E36: 0 | F36: 0 | G36: 17299081 | H36: 6.326814e+08
... A56: 45730 | B56: 31634070 | C56: 715281.47 | D56: 1.8513224e+08 | E56: 31634070 | F56: 6.326814e+08 | G56: 32349351 | H56: 0
