Workbook

Sheet Disbursement
A1: Borrower: | B1: Sena Kalyan Sangstha-Edible Oil Project (SKS Edible Oil)
A2: Currency: | B2: BDT
A3: Type | B3: IDCOL Loan
A7: Disbursement Number | B7: Disbursement Date | C7: Disbursement | D7: Cumulative Disbursement
A8: 1-2 | B8: 43240 | C8: 1500000000 | D8: =C8 -> 1500000000
A9: 2 (i) | B9: 43646 | C9: 200000000 | D9: =+D8+C9 -> 1700000000
A10: 2 (ii) | B10: 43774 | C10: 300000000 | D10: =+D9+C10 -> 2000000000

Sheet Summary
B1: ='Accrual_SKS Edible Oil'!B23 -> 43252 | C1: ='Accrual_SKS Edible Oil'!C23 -> 43282 | D1: ='Accrual_SKS Edible Oil'!D23 -> 43313 | E1: ='Accrual_SKS Edible Oil'!E23 -> 43344 | F1: ='Accrual_SKS Edible Oil'!F23 -> 43374 | G1: ='Accrual_SKS Edible Oil'!G23 -> 43405 | H1: ='Accrual_SKS Edible Oil'!H23 -> 43435 | I1: ='Accrual_SKS Edible Oil'!I23 -> 43466 | ... DR1: ='Accrual_SKS Edible Oil'!DR23 -> 46905
A2: Principal
A3: Opening balance | B3: ='Accrual_SKS Edible Oil'!B24 -> 1500000000 | C3: ='Accrual_SKS Edible Oil'!C24+'SKS Edible Oil_Loan'!B29 -> 1508937500 | D3: ='Accrual_SKS Edible Oil'!D24+'SKS Edible Oil_Loan'!C29 -> 1.5110417e+09 | E3: ='Accrual_SKS Edible Oil'!E24+'SKS Edible Oil_Loan'!D29 -> 1.5122708e+09 | F3: ='Accrual_SKS Edible Oil'!F24+'SKS Edible Oil_Loan'!E29 -> 1.5122708e+09 | G3: ='Accrual_SKS Edible Oil'!G24+'SKS Edible Oil_Loan'!F29 -> 1511875000 | H3: ='Accrual_SKS Edible Oil'!H24+'SKS Edible Oil_Loan'!G29 -> 1.5122708e+09 | I3: ='Accrual_SKS Edible Oil'!I24+'SKS Edible Oil_Loan'!H29 -> 1511875000 | J3: ='Accrual_SKS Edible Oil'!J24+'SKS Edible Oil_Loan'!I29 -> 1.5122708e+09 | ... N3: ='Accrual_SKS Edible Oil'!N24+'SKS Edible Oil_Loan'!M29 -> 1.5138542e+09 | O3: ='Accrual_SKS Edible Oil'!O24 -> 1.8422917e+09 | P3: ='Accrual_SKS Edible Oil'!P24 -> 1.8422917e+09 | Q3: ='Accrual_SKS Edible Oil'!Q24 -> 1.8422917e+09 | R3: ='Accrual_SKS Edible Oil'!R24 -> 1.8422917e+09 | S3: ='Accrual_SKS Edible Oil'!S24 -> 1.8422917e+09 | T3: ='Accrual_SKS Edible Oil'!T24 -> 2.1422917e+09 | U3: ='Accrual_SKS Edible Oil'!U24 -> 2.1422917e+09 | V3: ='Accrual_SKS Edible Oil'!V24 -> 2.1422917e+09 | ... Y3: ='Accrual_SKS Edible Oil'!Y24 -> 2.1422917e+09 | Z3: ='Accrual_SKS Edible Oil'!Z24+SUM('SKS Edible Oil_Loan'!N29:Y29) -> 2.3336583e+09 | AA3: ='Accrual_SKS Edible Oil'!AA24 -> 2.3336583e+09 | AB3: =AA3 -> 2.3336583e+09 | AC3: =AB3 -> 2.3336583e+09 | AD3: =AC3 -> 2.3336583e+09 | AE3: =AD3 -> 2.3336583e+09 | AF3: =AE3 -> 2.3336583e+09 | AG3: =AF3 -> 2.3336583e+09 | AH3: =AG3 -> 2.3336583e+09 | AI3: =AH3 -> 2.3336583e+09 | ... DR3: =DQ3 -> 2.3336583e+09
A4: Repayment due | B4: ='Accrual_SKS Edible Oil'!B28 -> 0 | C4: ='Accrual_SKS Edible Oil'!C28 -> 0 | D4: ='Accrual_SKS Edible Oil'!D28 -> 0 | E4: ='Accrual_SKS Edible Oil'!E28 -> 0 | F4: ='Accrual_SKS Edible Oil'!F28 -> 0 | G4: ='Accrual_SKS Edible Oil'!G28 -> 0 | H4: ='Accrual_SKS Edible Oil'!H28 -> 0 | I4: ='Accrual_SKS Edible Oil'!I28 -> 0 | ... DR4: ='Accrual_SKS Edible Oil'!DR28 -> 2.3336583e+09
A5: Loan Repayment | B5: =B22 -> 0 | C5: =C22 -> 0 | D5: =D22 -> 0 | E5: =E22 -> 0 | F5: =F22 -> 0 | G5: =G22 -> 0 | H5: =H22 -> 0 | I5: =I22 -> 0 | ... DR5: =DR22 -> 2.3336583e+09
A6: Repayment overdue | B6: =IF((B4-B5)>0,(B4-B5),0) -> 0 | C6: =IF((C4-C5)>0,(C4-C5),0) -> 0 | D6: =IF((D4-D5)>0,(D4-D5),0) -> 0 | E6: =IF((E4-E5)>0,(E4-E5),0) -> 0 | F6: =IF((F4-F5)>0,(F4-F5),0) -> 0 | G6: =IF((G4-G5)>0,(G4-G5),0) -> 0 | H6: =IF((H4-H5)>0,(H4-H5),0) -> 0 | I6: =IF((I4-I5)>0,(I4-I5),0) -> 0 | ... DR6: =IF((DR4-DR5)>0,(DR4-DR5),0) -> 0
A7: Loan outstanding | B7: =B3-B5 -> 1500000000 | C7: =C3-C5 -> 1508937500 | D7: =D3-D5 -> 1.5110417e+09 | E7: =E3-E5 -> 1.5122708e+09 | F7: =F3-F5 -> 1.5122708e+09 | G7: =G3-G5 -> 1511875000 | H7: =H3-H5 -> 1.5122708e+09 | I7: =I3-I5 -> 1511875000 | ... DR7: =DR3-DR5 -> 0
A8: Interest
A9: Interest accrued | B9: ='Accrual_SKS Edible Oil'!B26 -> 4125000 | C9: ='Accrual_SKS Edible Oil'!C26 -> 14437500 | D9: ='Accrual_SKS Edible Oil'!D26 -> 26708333 | E9: ='Accrual_SKS Edible Oil'!E26 -> 38979167 | F9: ='Accrual_SKS Edible Oil'!F26 -> 50854167 | G9: ='Accrual_SKS Edible Oil'!G26 -> 63125000 | H9: ='Accrual_SKS Edible Oil'!H26 -> 75000000 | I9: ='Accrual_SKS Edible Oil'!I26 -> 87270833 | ... DR9: ='Accrual_SKS Edible Oil'!DR26 -> 1.352099e+09
A10: Interest due | B10: 0 | C10: ='SKS Edible Oil_Loan'!B30 -> 0 | D10: ='SKS Edible Oil_Loan'!C30 -> 0 | E10: ='SKS Edible Oil_Loan'!D30 -> 0 | F10: ='SKS Edible Oil_Loan'!E30 -> 0 | G10: ='SKS Edible Oil_Loan'!F30 -> 0 | H10: ='SKS Edible Oil_Loan'!G30 -> 0 | I10: ='SKS Edible Oil_Loan'!H30 -> 0 | J10: ='SKS Edible Oil_Loan'!I30 -> 0 | ... DR10: ='SKS Edible Oil_Loan'!DQ30 -> 1.0184407e+09 | DS10: =+DR10+SUM('SKS Edible Oil_Loan'!B29:Y29)-Summary!DR9 -> 0
A11: interest received | B11: =B26 -> 0 | C11: =C26 -> 0 | D11: =D26 -> 0 | E11: =E26 -> 0 | F11: =F26 -> 0 | G11: =G26 -> 0 | H11: =H26 -> 0 | I11: =I26 -> 0 | ... DR11: =DR26 -> 1.0184407e+09
A12: Interest overdue | B12: =IF((B10-B11)>0,(B10-B11),0) -> 0 | C12: =IF((C10-C11)>0,(C10-C11),0) -> 0 | D12: =IF((D10-D11)>0,(D10-D11),0) -> 0 | E12: =IF((E10-E11)>0,(E10-E11),0) -> 0 | F12: =IF((F10-F11)>0,(F10-F11),0) -> 0 | G12: =IF((G10-G11)>0,(G10-G11),0) -> 0 | H12: =IF((H10-H11)>0,(H10-H11),0) -> 0 | I12: =IF((I10-I11)>0,(I10-I11),0) -> 0 | ... DR12: =IF((DR10-DR11)>0,(DR10-DR11),0) -> 0
A13: Interest receivable | B13: =B9-B11 -> 4125000 | C13: =C9-C11 -> 14437500 | D13: =D9-D11 -> 26708333 | E13: =E9-E11 -> 38979167 | F13: =F9-F11 -> 50854167 | G13: =G9-G11 -> 63125000 | H13: =H9-H11 -> 75000000 | I13: =I9-I11 -> 87270833 | ... DR13: =DR9-DR11 -> 3.3365828e+08
A14: LD and others | B14: =B28 -> 0 | C14: =C28 -> 0 | D14: =D28 -> 0 | E14: =E28 -> 0 | F14: =F28 -> 0 | G14: =G28 -> 0 | H14: =H28 -> 0 | I14: =I28 -> 0 | ... DR14: =DR28 -> 0
B19: =B1 -> 43252 | C19: =C1 -> 43282 | D19: =D1 -> 43313 | E19: =E1 -> 43344 | F19: =F1 -> 43374 | G19: =G1 -> 43405 | H19: =H1 -> 43435 | I19: =I1 -> 43466 | ... DR19: =DR1 -> 46905
A20: Repayment receipts:
A21: Repayment received | B21: 0 | C21: =C4-B5 -> 0 | D21: =D4-C5 -> 0 | E21: =E4-D5 -> 0 | F21: =F4-E5 -> 0 | G21: =G4-F5 -> 0 | H21: =H4-G5 -> 0 | I21: =I4-H5 -> 0 | J21: =J4-I5 -> 0 | ... Z21: =Z4-Y5 -> 0 | AA21: 0 | AB21: 0 | AC21: 0 | AD21: 0 | AE21: 0 | AF21: 0 | AG21: 0 | AH21: 0 | AI21: =AI4-AH5 -> 1.5163785e+08 | AJ21: =AJ4-AI5 -> 17522587 | AK21: =AK4-AJ5 -> 17661308 | AL21: =AL4-AK5 -> 17801126 | AM21: =AM4-AL5 -> 17942052 | AN21: =AN4-AM5 -> 18084093 | AO21: =AO4-AN5 -> 18227259 | AP21: =AP4-AO5 -> 18371558 | ... DR21: =DR4-DQ5 -> 34523604
A22: Repayment received (cumulative) | B22: =B21 -> 0 | C22: =B22+C21 -> 0 | D22: =C22+D21 -> 0 | E22: =D22+E21 -> 0 | F22: =E22+F21 -> 0 | G22: =F22+G21 -> 0 | H22: =G22+H21 -> 0 | I22: =H22+I21 -> 0 | J22: =I22+J21 -> 0 | ... DR22: =DQ22+DR21 -> 2.3336583e+09
A24: Interest receipts:
A25: Interest received | B25: 0 | C25: =C10-B11 -> 0 | D25: =D10-C11 -> 0 | E25: =E10-D11 -> 0 | F25: =F10-E11 -> 0 | G25: =G10-F11 -> 0 | H25: =H10-G11 -> 0 | I25: =I10-H11 -> 0 | J25: =J10-I11 -> 0 | ... Z25: =Z10-Y11 -> 0 | AA25: 0 | AB25: 0 | AC25: 0 | AD25: 0 | AE25: 0 | AF25: 0 | AG25: 0 | AH25: 0 | AI25: =AI10-AH11 -> 1.6202706e+08 | AJ25: =AJ10-AI11 -> 16122707 | AK25: =AK10-AJ11 -> 17706795 | AL25: =AL10-AK11 -> 15862737 | AM25: =AM10-AL11 -> 18540350 | AN25: =AN10-AM11 -> 16712822 | AO25: =AO10-AN11 -> 17121979 | AP25: =AP10-AO11 -> 16972869 | ... DR25: =DR10-DQ11 -> 291532.65
A26: Interest received (cumulative) | B26: =B25 -> 0 | C26: =B26+C25 -> 0 | D26: =C26+D25 -> 0 | E26: =D26+E25 -> 0 | F26: =E26+F25 -> 0 | G26: =F26+G25 -> 0 | H26: =G26+H25 -> 0 | I26: =H26+I25 -> 0 | J26: =I26+J25 -> 0 | ... DR26: =DQ26+DR25 -> 1.0184407e+09
A27: LD/others | B27: 0 | C27: 0 | D27: 0 | E27: 0 | F27: 0 | G27: 0 | H27: 0 | I27: 0 | J27: 0 | K27: 0 | L27: 0 | M27: 0 | N27: 0 | O27: 0 | P27: 0 | Q27: 0 | R27: 0 | S27: 0 | T27: 0 | U27: 0 | V27: 0 | W27: 0 | X27: 0 | Y27: 0 | Z27: 0 | AA27: 0 | AB27: 0 | AC27: 0 | AD27: 0 | AE27: 0 | AF27: 0 | AG27: 0 | AH27: 0 | AI27: 0 | AJ27: 0 | AK27: 0 | AL27: 0 | AM27: 0 | AN27: 0 | AO27: 0 | AP27: 0 | AQ27: 0 | AR27: 0 | AS27: 0 | AT27: 0 | AU27: 0 | AV27: 0 | AW27: 0 | AX27: 0 | AY27: 0 | AZ27: 0 | BA27: 0 | BB27: 0 | BC27: 0 | BD27: 0 | BE27: 0 | BF27: 0 | BG27: 0 | BH27: 0 | BI27: 0 | BJ27: 0 | BK27: 0 | BL27: 0 | BM27: 0 | BN27: 0 | BO27: 0 | BP27: 0 | BQ27: 0 | BR27: 0 | BS27: 0 | BT27: 0 | BU27: 0 | BV27: 0 | BW27: 0 | BX27: 0 | BY27: 0 | BZ27: 0 | CA27: 0 | CB27: 0 | CC27: 0 | CD27: 0 | CE27: 0 | CF27: 0 | CG27: 0 | CH27: 0 | CI27: 0 | CJ27: 0 | CK27: 0 | CL27: 0 | CM27: 0 | CN27: 0 | CO27: 0 | CP27: 0 | CQ27: 0 | CR27: 0 | CS27: 0 | CT27: 0 | CU27: 0 | CV27: 0 | CW27: 0 | CX27: 0 | CY27: 0 | CZ27: 0 | DA27: 0 | DB27: 0 | DC27: 0 | DD27: 0 | DE27: 0 | DF27: 0 | DG27: 0 | DH27: 0 | DI27: 0 | DJ27: 0 | DK27: 0 | DL27: 0 | DM27: 0 | DN27: 0 | DO27: 0 | DP27: 0 | DQ27: 0 | DR27: 0
A28: LD/others (cumulative) | B28: =B27 -> 0 | C28: =B28+C27 -> 0 | D28: =C28+D27 -> 0 | E28: =D28+E27 -> 0 | F28: =E28+F27 -> 0 | G28: =F28+G27 -> 0 | H28: =G28+H27 -> 0 | I28: =H28+I27 -> 0 | J28: =I28+J27 -> 0 | ... DR28: =DQ28+DR27 -> 0
A30: Actual Payment date
A31: Actual Payment amount:
A32: Interest
A33: Principal
A34: LPC
A35: Total | B35: =SUM(B32:B34) -> 0 | C35: =SUM(C32:C34) -> 0 | D35: =SUM(D32:D34) -> 0 | E35: =SUM(E32:E34) -> 0 | F35: =SUM(F32:F34) -> 0 | G35: =SUM(G32:G34) -> 0 | H35: =SUM(H32:H34) -> 0 | I35: =SUM(I32:I34) -> 0 | ... DR35: =SUM(DR32:DR34) -> 0

Sheet SKS Edible Oil_Loan
A1: Project name: | C1: =Disbursement!B1 -> Sena Kalyan Sangstha-Edible Oil Project (SKS Edible Oil)
A3: Agreement signing date | C3: 43215
A5: Loan Amount | C5: 2355000000
A7: Payment frequency | C7: Monthly | G7: *If payment date is not a business day, then payment date shall be immediately the preceeding business day.
A8: Interest Rate | C8: 0.0825
A9: Maturity date | C9: 120 | D9: months
A10: Moratorium period (Principal) | C10: 24 | D10: months
A11: Principal | C11: Annuity
A12: Interest calculation | C12: 360 | D12: days basis
A13: Number of installments | C13: 96
A15: Drawdown
C16: =Disbursement!B8 -> 43240 | D16: =Disbursement!B9 -> 43646 | E16: =Disbursement!B10 -> 43774
C17: =Disbursement!C8 -> 1500000000 | D17: =Disbursement!C9 -> 200000000 | E17: =Disbursement!C10 -> 300000000
C18: =C17 -> 1500000000 | D18: =+C18+D17 -> 1700000000 | E18: =+D18+E17 -> 2000000000
C20: 43282
A21: Period | B21: =B27 -> 43266 | C21: =C27 -> 43296 | D21: =D27 -> 43327 | E21: =E27 -> 43358 | F21: =F27 -> 43388 | G21: =G27 -> 43419 | H21: =H27 -> 43449 | I21: =I27 -> 43480 | ... DQ21: =DQ27 -> 46888
A22: Expected Interest Rate | B22: 0.0825 | C22: 0.095 | D22: 0.095 | E22: 0.095 | F22: 0.095 | G22: 0.095 | H22: 0.095 | I22: 0.095 | J22: 0.095 | K22: 0.095 | L22: 0.095 | M22: 0.095 | N22: 0.095 | O22: 0.095 | P22: 0.095 | Q22: 0.095 | R22: 0.095 | S22: 0.095 | T22: 0.095 | U22: 0.095 | V22: 0.095 | W22: 0.095 | X22: 0.095 | Y22: 0.095 | Z22: 0.095 | AA22: 0.095 | AB22: 0.095 | AC22: 0.095 | AD22: 0.095 | AE22: 0.095 | AF22: 0.095 | AG22: 0.095 | AH22: 0.095 | AI22: 0.095 | AJ22: 0.095 | AK22: 0.095 | AL22: 0.095 | AM22: 0.095 | AN22: 0.095 | AO22: 0.095 | AP22: 0.095 | AQ22: 0.095 | AR22: 0.095 | AS22: 0.095 | AT22: 0.095 | AU22: 0.095 | AV22: 0.095 | AW22: 0.095 | AX22: 0.095 | AY22: 0.095 | AZ22: 0.095 | BA22: 0.095 | BB22: 0.095 | BC22: 0.095 | BD22: 0.095 | BE22: 0.095 | BF22: 0.095 | BG22: 0.095 | BH22: 0.095 | BI22: 0.095 | BJ22: 0.095 | BK22: 0.095 | BL22: 0.095 | BM22: 0.095 | BN22: 0.095 | BO22: 0.095 | BP22: 0.095 | BQ22: 0.095 | BR22: 0.095 | BS22: 0.095 | BT22: 0.095 | BU22: 0.095 | BV22: 0.095 | BW22: 0.095 | BX22: 0.095 | BY22: 0.095 | BZ22: 0.095 | CA22: 0.095 | CB22: 0.095 | CC22: 0.095 | CD22: 0.095 | CE22: 0.095 | CF22: 0.095 | CG22: 0.095 | CH22: 0.095 | CI22: 0.095 | CJ22: 0.095 | CK22: 0.095 | CL22: 0.095 | CM22: 0.095 | CN22: 0.095 | CO22: 0.095 | CP22: 0.095 | CQ22: 0.095 | CR22: 0.095 | CS22: 0.095 | CT22: 0.095 | CU22: 0.095 | CV22: 0.095 | CW22: 0.095 | CX22: 0.095 | CY22: 0.095 | CZ22: 0.095 | DA22: 0.095 | DB22: 0.095 | DC22: 0.095 | DD22: 0.095 | DE22: 0.095 | DF22: 0.095 | DG22: 0.095 | DH22: 0.095 | DI22: 0.095 | DJ22: 0.095 | DK22: 0.095 | DL22: 0.095 | DM22: 0.095 | DN22: 0.095 | DO22: 0.095 | DP22: 0.095 | DQ22: 0.095
A25: Repayment | B25: Principal Moratorium-Interest Capitalized
A26: Repayment Period | Z26: 1 | AA26: =Z26+1 -> 2 | AB26: =AA26+1 -> 3 | AC26: =AB26+1 -> 4 | AD26: =AC26+1 -> 5 | AE26: =AD26+1 -> 6 | AF26: =AE26+1 -> 7 | AG26: =AF26+1 -> 8 | AH26: =AG26+1 -> 9 | ... DQ26: =DP26+1 -> 96
A27: Repayment Date | B27: 43266 | C27: 43296 | D27: 43327 | E27: 43358 | F27: 43388 | G27: 43419 | H27: 43449 | I27: 43480 | J27: 43511 | K27: 43539 | L27: 43570 | M27: 43605 | N27: 43631 | O27: 43661 | P27: 43692 | Q27: 43723 | R27: 43753 | S27: 43784 | T27: 43814 | U27: 43845 | V27: 43876 | W27: 43905 | X27: 43936 | Y27: 43971 | Z27: 43997 | AA27: 44027 | AB27: 44056 | AC27: 44089 | AD27: 44119 | AE27: 44150 | AF27: 44180 | AG27: 44210 | AH27: 44242 | AI27: 44270 | AJ27: 44301 | AK27: 44329 | AL27: 44362 | AM27: 44392 | AN27: 44423 | AO27: 44454 | AP27: 44483 | AQ27: 44515 | AR27: 44545 | AS27: 44574 | AT27: 44607 | AU27: 44635 | AV27: 44665 | AW27: 44696 | AX27: 44727 | AY27: 44756 | AZ27: 44788 | BA27: 44819 | BB27: 44847 | BC27: 44880 | BD27: 44910 | BE27: 44941 | BF27: 44972 | BG27: 45000 | BH27: 45029 | BI27: 45061 | BJ27: 45092 | BK27: 45120 | BL27: 45153 | BM27: 45183 | BN27: 45214 | BO27: 45245 | BP27: 45274 | BQ27: 45306 | BR27: 45337 | BS27: 45365 | BT27: 45397 | BU27: 45427 | BV27: 45456 | BW27: 45488 | BX27: 45519 | BY27: 45550 | BZ27: 45580 | CA27: 45610 | CB27: 45641 | CC27: 45672 | CD27: 45701 | CE27: 45729 | CF27: 45762 | CG27: 45792 | CH27: 45823 | CI27: 45853 | CJ27: 45883 | CK27: 45915 | CL27: 45945 | CM27: 45974 | CN27: 46006 | CO27: 46037 | CP27: 46068 | CQ27: 46096 | CR27: 46127 | CS27: 46156 | CT27: 46188 | CU27: 46218 | CV27: 46247 | CW27: 46280 | CX27: 46310 | CY27: 46341 | CZ27: 46371 | DA27: 46401 | DB27: 46433 | DC27: 46461 | DD27: 46492 | DE27: 46520 | DF27: 46553 | DG27: 46583 | DH27: 46614 | DI27: 46645 | DJ27: 46674 | DK27: 46706 | DL27: 46736 | DM27: 46765 | DN27: 46798 | DO27: 46827 | DP27: 46856 | DQ27: 46888
A28: Opening Balance | B28: =C17 -> 1500000000 | C28: =B34 -> 1500000000 | D28: =C34 -> 1500000000 | E28: =D34 -> 1500000000 | F28: =E34 -> 1500000000 | G28: =F34 -> 1500000000 | H28: =G34 -> 1500000000 | I28: =H34 -> 1500000000 | J28: =I34 -> 1500000000 | ... N28: =M34 -> 1.6422917e+09 | O28: =N34+D17 -> 1.8422917e+09 | P28: =O34 -> 1.8422917e+09 | Q28: =P34 -> 1.8422917e+09 | R28: =Q34 -> 1.8422917e+09 | S28: =R34+E17 -> 2.1422917e+09 | T28: =S34 -> 2.1422917e+09 | U28: =T34 -> 2.1422917e+09 | V28: =U34 -> 2.1422917e+09 | W28: =V34 -> 2.1422917e+09 | X28: =W34 -> 2.1422917e+09 | Y28: =X34 -> 2.1422917e+09 | Z28: =Y34 -> 2.3336583e+09 | AA28: =Z34 -> 2.3173362e+09 | ... DQ28: =DP34 -> 34523604
A29: Interest Payment | B29: =C18*(B27-C16)*B22/360 -> 8937500 | C29: =C28*(C20-B27)*B22/360+C28*(C27-C20)*C22/360 -> 11041667 | D29: =D28*(D27-C27)*D22/360 -> 12270833 | E29: =E28*(E27-D27)*E22/360 -> 12270833 | F29: =F28*(F27-E27)*F22/360 -> 11875000 | G29: =G28*(G27-F27)*G22/360 -> 12270833 | H29: =H28*(H27-G27)*H22/360 -> 11875000 | I29: =I28*(I27-H27)*I22/360 -> 12270833 | J29: =J28*(J27-I27)*J22/360 -> 12270833 | K29: =K28*(K27-J27)*K22/360 -> 11083333 | ... N29: =N28*(N27-M27)*N22/360 -> 11267946 | O29: =+N34*(D16-N27)*O22/360+O28*(O27-D16)*O22/360 -> 13793142 | P29: =P28*(P27-O27)*P22/360 -> 15070969 | Q29: =Q28*(Q27-P27)*Q22/360 -> 15070969 | R29: =R28*(R27-Q27)*R22/360 -> 14584809 | S29: =+R34*(E16-R27)*S22/360+S28*(S27-E16)*S22/360 -> 15862636 | T29: =T28*(T27-S27)*T22/360 -> 16959809 | U29: =U28*(U27-T27)*U22/360 -> 17525136 | V29: =V28*(V27-U27)*V22/360 -> 17525136 | W29: =W28*(W27-V27)*W22/360 -> 16394482 | X29: =X28*(X27-W27)*X22/360 -> 17525136 | Y29: =Y28*(Y27-X27)*Y22/360 -> 19786444 | Z29: =Z28*(Z27-Y27)*Z22/360 -> 16011489 | AA29: =AA28*(AA27-Z27)*AA22/360 -> 18345578 | ... DQ29: =DQ28*(DQ27-DP27)*DQ22/360 -> 291532.65
A30: Cumulative interest | B30: 0 | C30: =B30 -> 0 | D30: =C30 -> 0 | E30: =D30 -> 0 | F30: =E30 -> 0 | G30: =F30 -> 0 | H30: =G30 -> 0 | I30: =H30 -> 0 | J30: =I30 -> 0 | ... Y30: =X30 -> 0 | Z30: =Z29+Y30 -> 16011489 | AA30: =AA29+Z30 -> 34357067 | AB30: =AB29+AA30 -> 51965227 | AC30: =AC29+AB30 -> 71857701 | AD30: =AD29+AC30 -> 89809458 | AE30: =AE29+AD30 -> 1.082218e+08 | AF30: =AF29+AE30 -> 1.2590579e+08 | AG30: =AG29+AF30 -> 1.434543e+08 | ... DQ30: =DQ29+DP30 -> 1.0184407e+09
A31: Principal Payment | B31: 0 | C31: 0 | D31: 0 | E31: 0 | F31: 0 | G31: 0 | H31: 0 | I31: 0 | J31: 0 | K31: 0 | L31: 0 | M31: 0 | N31: 0 | O31: 0 | P31: 0 | Q31: 0 | R31: 0 | S31: 0 | T31: 0 | U31: 0 | V31: 0 | W31: 0 | X31: 0 | Y31: 0 | Z31: =-PPMT(Z22/12,Z26,$C$13,$Z$28) -> 16322121 | AA31: =-PPMT(AA22/12,AA26,$C$13,$Z$28) -> 16451338 | AB31: =-PPMT(AB22/12,AB26,$C$13,$Z$28) -> 16581578 | AC31: =-PPMT(AC22/12,AC26,$C$13,$Z$28) -> 16712848 | AD31: =-PPMT(AD22/12,AD26,$C$13,$Z$28) -> 16845158 | AE31: =-PPMT(AE22/12,AE26,$C$13,$Z$28) -> 16978516 | AF31: =-PPMT(AF22/12,AF26,$C$13,$Z$28) -> 17112929 | AG31: =-PPMT(AG22/12,AG26,$C$13,$Z$28) -> 17248407 | ... DQ31: =-PPMT(DQ22/12,DQ26,$C$13,$Z$28) -> 34523604
A32: Cumulative repayment | B32: 0 | C32: =C31+B32 -> 0 | D32: =D31+C32 -> 0 | E32: =E31+D32 -> 0 | F32: =F31+E32 -> 0 | G32: =G31+F32 -> 0 | H32: =H31+G32 -> 0 | I32: =I31+H32 -> 0 | J32: =J31+I32 -> 0 | ... DQ32: =DQ31+DP32 -> 2.3336583e+09
A33: Total Debt Service | B33: 0 | C33: =B33 -> 0 | D33: =C33 -> 0 | E33: =D33 -> 0 | F33: =E33 -> 0 | G33: =F33 -> 0 | H33: =G33 -> 0 | I33: =H33 -> 0 | J33: =I33 -> 0 | ... Y33: =X33 -> 0 | Z33: =Z29+Z31 -> 32333610 | AA33: =AA29+AA31 -> 34796916 | AB33: =AB29+AB31 -> 34189738 | AC33: =AC29+AC31 -> 36605322 | AD33: =AD29+AD31 -> 34796916 | AE33: =AE29+AE31 -> 35390862 | AF33: =AF29+AF31 -> 34796916 | AG33: =AG29+AG31 -> 34796916 | ... DQ33: =DQ29+DQ31 -> 34815137
A34: Closing Balance | B34: =B28-B31 -> 1500000000 | C34: =C28-C31 -> 1500000000 | D34: =D28-D31 -> 1500000000 | E34: =E28-E31 -> 1500000000 | F34: =F28-F31 -> 1500000000 | G34: =G28-G31 -> 1500000000 | H34: =H28-H31 -> 1500000000 | I34: =I28-I31 -> 1500000000 | ... L34: =L28-L31 -> 1500000000 | M34: =M28+SUM(B29:M29) -> 1.6422917e+09 | N34: =N28-N31 -> 1.6422917e+09 | O34: =O28-O31 -> 1.8422917e+09 | P34: =P28-P31 -> 1.8422917e+09 | Q34: =Q28-Q31 -> 1.8422917e+09 | R34: =R28-R31 -> 1.8422917e+09 | S34: =S28-S31 -> 2.1422917e+09 | T34: =T28-T31 -> 2.1422917e+09 | U34: =U28-U31 -> 2.1422917e+09 | ... X34: =X28-X31 -> 2.1422917e+09 | Y34: =Y28+SUM(N29:Y29) -> 2.3336583e+09 | Z34: =Z28-Z31 -> 2.3173362e+09 | AA34: =AA28-AA31 -> 2.3008848e+09 | AB34: =AB28-AB31 -> 2.2843032e+09 | AC34: =AC28-AC31 -> 2.2675904e+09 | AD34: =AD28-AD31 -> 2.2507452e+09 | AE34: =AE28-AE31 -> 2.2337667e+09 | AF34: =AF28-AF31 -> 2.2166538e+09 | AG34: =AG28-AG31 -> 2.1994054e+09 | ... DQ34: =DQ28-DQ31 -> 2.0861626e-07
A37: Average Installment Size | B37: =B27 -> 43266 | C37: =C27 -> 43296 | D37: =D27 -> 43327 | E37: =E27 -> 43358 | F37: =F27 -> 43388 | G37: =G27 -> 43419 | H37: =H27 -> 43449 | I37: =I27 -> 43480 | ... DQ37: =DQ27 -> 46888
B38: =AVERAGE($Z$33) -> 32333610 | C38: =AVERAGE($Z$33) -> 32333610 | D38: =AVERAGE($Z$33) -> 32333610 | E38: =AVERAGE($Z$33) -> 32333610 | F38: =AVERAGE($Z$33) -> 32333610 | G38: =AVERAGE($Z$33) -> 32333610 | H38: =AVERAGE($Z$33) -> 32333610 | I38: =AVERAGE($Z$33) -> 32333610 | ... Z38: =AVERAGE($Z$33) -> 32333610 | AA38: =AVERAGE($Z$33:AA33) -> 33565263 | AB38: =AVERAGE($Z$33:AB33) -> 33773421 | AC38: =AVERAGE($Z$33:AC33) -> 34481396 | AD38: =AVERAGE($Z$33:AD33) -> 34544500 | AE38: =AVERAGE($Z$33:AE33) -> 34685561 | AF38: =AVERAGE($Z$33:AF33) -> 34701469 | AG38: =AVERAGE($Z$33:AG33) -> 34713399 | AH38: =AVERAGE($Z$33:AH33) -> 34851656 | ... DQ38: =AVERAGE($Z$33:DQ33) -> 34917698
A40: Total Interest Capitalized | B40: =SUM(B29:Y29) -> 3.3365828e+08
A42: Particulars | B42: 43251 | C42: =EOMONTH(B42,1) -> 43281 | D42: =EOMONTH(C42,1) -> 43312 | E42: =EOMONTH(D42,1) -> 43343 | F42: =EOMONTH(E42,1) -> 43373 | G42: =EOMONTH(F42,1) -> 43404 | H42: =EOMONTH(G42,1) -> 43434 | I42: =EOMONTH(H42,1) -> 43465 | J42: =EOMONTH(I42,1) -> 43496 | ... DR42: =EOMONTH(DQ42,1) -> 46904
A43: Total interest accrued | B43: =SUM('Accrual_SKS Edible Oil'!$B$25) -> 4125000 | C43: =SUM('Accrual_SKS Edible Oil'!$B$25:C25) -> 14437500 | D43: =SUM('Accrual_SKS Edible Oil'!$B$25:D25) -> 26708333 | E43: =SUM('Accrual_SKS Edible Oil'!$B$25:E25) -> 38979167 | F43: =SUM('Accrual_SKS Edible Oil'!$B$25:F25) -> 50854167 | G43: =SUM('Accrual_SKS Edible Oil'!$B$25:G25) -> 63125000 | H43: =SUM('Accrual_SKS Edible Oil'!$B$25:H25) -> 75000000 | I43: =SUM('Accrual_SKS Edible Oil'!$B$25:I25) -> 87270833 | J43: =SUM('Accrual_SKS Edible Oil'!$B$25:J25) -> 99541667 | ... DR43: =SUM('Accrual_SKS Edible Oil'!$B$25:DR25) -> 1.352099e+09
A44: Total interest capitalized | B44: 0 | C44: =SUM($B$29) -> 8937500 | D44: =SUM($B$29:C29) -> 19979167 | E44: =SUM($B$29:D29) -> 32250000 | F44: =SUM($B$29:E29) -> 44520833 | G44: =SUM($B$29:F29) -> 56395833 | H44: =SUM($B$29:G29) -> 68666667 | I44: =SUM($B$29:H29) -> 80541667 | J44: =SUM($B$29:I29) -> 92812500 | K44: =SUM($B$29:J29) -> 1.0508333e+08 | ... N44: =SUM($B$29:M29) -> 1.4229167e+08 | O44: =SUM($B$29:M29) -> 1.4229167e+08 | P44: =SUM($B$29:M29) -> 1.4229167e+08 | Q44: =SUM($B$29:M29) -> 1.4229167e+08 | R44: =SUM($B$29:M29) -> 1.4229167e+08 | S44: =SUM($B$29:M29) -> 1.4229167e+08 | T44: =SUM($B$29:M29) -> 1.4229167e+08 | U44: =SUM($B$29:M29) -> 1.4229167e+08 | V44: =SUM($B$29:M29) -> 1.4229167e+08 | W44: =SUM($B$29:M29) -> 1.4229167e+08 | X44: =SUM($B$29:M29) -> 1.4229167e+08 | Y44: =SUM($B$29:M29) -> 1.4229167e+08 | Z44: =SUM($B$29:Y29) -> 3.3365828e+08 | AA44: =Z44 -> 3.3365828e+08 | AB44: =AA44 -> 3.3365828e+08 | AC44: =AB44 -> 3.3365828e+08 | AD44: =AC44 -> 3.3365828e+08 | AE44: =AD44 -> 3.3365828e+08 | AF44: =AE44 -> 3.3365828e+08 | AG44: =AF44 -> 3.3365828e+08 | AH44: =AG44 -> 3.3365828e+08 | ... DR44: =DQ44 -> 3.3365828e+08
A45: Net interest accrued | B45: =B43-B44 -> 4125000 | C45: =C43-C44 -> 5500000 | D45: =D43-D44 -> 6729166.7 | E45: =E43-E44 -> 6729166.7 | F45: =F43-F44 -> 6333333.3 | G45: =G43-G44 -> 6729166.7 | H45: =H43-H44 -> 6333333.3 | I45: =I43-I44 -> 6729166.7 | ... DR45: =DR43-DR44 -> 1.0184407e+09
A46: Total interest received | B46: =Summary!B26 -> 0 | C46: =Summary!C26 -> 0 | D46: =Summary!D26 -> 0 | E46: =Summary!E26 -> 0 | F46: =Summary!F26 -> 0 | G46: =Summary!G26 -> 0 | H46: =Summary!H26 -> 0 | I46: =Summary!I26 -> 0 | ... DR46: =Summary!DR26 -> 1.0184407e+09
A47: Total interest receivable | B47: =B45-B46 -> 4125000 | C47: =C45-C46 -> 5500000 | D47: =D45-D46 -> 6729166.7 | E47: =E45-E46 -> 6729166.7 | F47: =F45-F46 -> 6333333.3 | G47: =G45-G46 -> 6729166.7 | H47: =H45-H46 -> 6333333.3 | I47: =I45-I46 -> 6729166.7 | ... DR47: =DR45-DR46 -> 0

Sheet Accrual_SKS Edible Oil
A1: Project name: | B1: ='SKS Edible Oil_Loan'!C1 -> Sena Kalyan Sangstha-Edible Oil Project (SKS Edible Oil)
A3: Assumptions:
A5: Agreement signing date | B5: ='SKS Edible Oil_Loan'!C3 -> 43215
A7: Loan Amount | B7: ='SKS Edible Oil_Loan'!C5 -> 2355000000 | C7: BDT
A9: Interest Rate | B9: ='SKS Edible Oil_Loan'!C8 -> 0.0825
A10: Tenor | B10: 10 years
A11: Interest calculation | B11: 360 | C11: days basis
A12: Principal | B12: ='SKS Edible Oil_Loan'!C11 -> Annuity
A14: Drawdown
C15: ='SKS Edible Oil_Loan'!C16 -> 43240 | D15: ='SKS Edible Oil_Loan'!D16 -> 43646 | E15: ='SKS Edible Oil_Loan'!E16 -> 43774
C16: ='SKS Edible Oil_Loan'!C17 -> 1500000000 | D16: ='SKS Edible Oil_Loan'!D17 -> 200000000 | E16: ='SKS Edible Oil_Loan'!E17 -> 300000000
C17: =C16 -> 1500000000 | D17: =D16+C17 -> 1700000000 | E17: =E16+D17 -> 2000000000
A19: Period | B19: 43235 | C19: =EDATE(B19,1) -> 43266 | D19: =EDATE(C19,1) -> 43296 | E19: =EDATE(D19,1) -> 43327 | F19: =EDATE(E19,1) -> 43358 | G19: =EDATE(F19,1) -> 43388 | H19: =EDATE(G19,1) -> 43419 | I19: =EDATE(H19,1) -> 43449 | J19: =EDATE(I19,1) -> 43480 | ... DR19: =EDATE(DQ19,1) -> 46888
A20: Expected Interest Rate | B20: 0.0825 | C20: 0.0825 | D20: 0.095 | E20: 0.095 | F20: 0.095 | G20: 0.095 | H20: 0.095 | I20: 0.095 | J20: 0.095 | K20: 0.095 | L20: 0.095 | M20: 0.095 | N20: 0.095 | O20: 0.095 | P20: 0.095 | Q20: 0.095 | R20: 0.095 | S20: 0.095 | T20: 0.095 | U20: 0.095 | V20: 0.095 | W20: 0.095 | X20: 0.095 | Y20: 0.095 | Z20: 0.095 | AA20: 0.095 | AB20: 0.095 | AC20: 0.095 | AD20: 0.095 | AE20: 0.095 | AF20: 0.095 | AG20: 0.095 | AH20: 0.095 | AI20: 0.095 | AJ20: 0.095 | AK20: 0.095 | AL20: 0.095 | AM20: 0.095 | AN20: 0.095 | AO20: 0.095 | AP20: 0.095 | AQ20: 0.095 | AR20: 0.095 | AS20: 0.095 | AT20: 0.095 | AU20: 0.095 | AV20: 0.095 | AW20: 0.095 | AX20: 0.095 | AY20: 0.095 | AZ20: 0.095 | BA20: 0.095 | BB20: 0.095 | BC20: 0.095 | BD20: 0.095 | BE20: 0.095 | BF20: 0.095 | BG20: 0.095 | BH20: 0.095 | BI20: 0.095 | BJ20: 0.095 | BK20: 0.095 | BL20: 0.095 | BM20: 0.095 | BN20: 0.095 | BO20: 0.095 | BP20: 0.095 | BQ20: 0.095 | BR20: 0.095 | BS20: 0.095 | BT20: 0.095 | BU20: 0.095 | BV20: 0.095 | BW20: 0.095 | BX20: 0.095 | BY20: 0.095 | BZ20: 0.095 | CA20: 0.095 | CB20: 0.095 | CC20: 0.095 | CD20: 0.095 | CE20: 0.095 | CF20: 0.095 | CG20: 0.095 | CH20: 0.095 | CI20: 0.095 | CJ20: 0.095 | CK20: 0.095 | CL20: 0.095 | CM20: 0.095 | CN20: 0.095 | CO20: 0.095 | CP20: 0.095 | CQ20: 0.095 | CR20: 0.095 | CS20: 0.095 | CT20: 0.095 | CU20: 0.095 | CV20: 0.095 | CW20: 0.095 | CX20: 0.095 | CY20: 0.095 | CZ20: 0.095 | DA20: 0.095 | DB20: 0.095 | DC20: 0.095 | DD20: 0.095 | DE20: 0.095 | DF20: 0.095 | DG20: 0.095 | DH20: 0.095 | DI20: 0.095 | DJ20: 0.095 | DK20: 0.095 | DL20: 0.095 | DM20: 0.095 | DN20: 0.095 | DO20: 0.095 | DP20: 0.095 | DQ20: 0.095 | DR20: 0.095
A22: Accrual of interest
A23: Months | B23: 43252 | C23: =EDATE(B23,1) -> 43282 | D23: =EDATE(C23,1) -> 43313 | E23: =EDATE(D23,1) -> 43344 | F23: =EDATE(E23,1) -> 43374 | G23: =EDATE(F23,1) -> 43405 | H23: =EDATE(G23,1) -> 43435 | I23: =EDATE(H23,1) -> 43466 | J23: =EDATE(I23,1) -> 43497 | ... DR23: =EDATE(DQ23,1) -> 46905
A24: Opening Balance | B24: =C17 -> 1500000000 | C24: =B30 -> 1500000000 | D24: =C30 -> 1500000000 | E24: =D30 -> 1500000000 | F24: =E30 -> 1500000000 | G24: =F30 -> 1500000000 | H24: =G30 -> 1500000000 | I24: =H30 -> 1500000000 | J24: =I30 -> 1500000000 | ... N24: =M30 -> 1500000000 | O24: =N30+D16 -> 1.8422917e+09 | P24: =O30 -> 1.8422917e+09 | Q24: =P30 -> 1.8422917e+09 | R24: =Q30 -> 1.8422917e+09 | S24: =R30 -> 1.8422917e+09 | T24: =S30+E16 -> 2.1422917e+09 | U24: =T30 -> 2.1422917e+09 | V24: =U30 -> 2.1422917e+09 | W24: =V30 -> 2.1422917e+09 | X24: =W30 -> 2.1422917e+09 | Y24: =X30 -> 2.1422917e+09 | Z24: =Y30 -> 2.1422917e+09 | AA24: =Z30 -> 2.3336583e+09 | AB24: =AA30 -> 2.3173362e+09 | ... DR24: =DQ30 -> 34523604
A25: Interest Payment | B25: =B24*(B23-C15)*B20/360 -> 4125000 | C25: =C24*('SKS Edible Oil_Loan'!B27-B23)*C20/360+C30*(C23-'SKS Edible Oil_Loan'!B27)*C20/360 -> 10312500 | D25: =D24*('SKS Edible Oil_Loan'!C27-C23)*D20/360+D30*(D23-'SKS Edible Oil_Loan'!C27)*D20/360 -> 12270833 | E25: =E24*('SKS Edible Oil_Loan'!D27-D23)*E20/360+E30*(E23-'SKS Edible Oil_Loan'!D27)*E20/360 -> 12270833 | F25: =F24*('SKS Edible Oil_Loan'!E27-E23)*F20/360+F30*(F23-'SKS Edible Oil_Loan'!E27)*F20/360 -> 11875000 | G25: =G24*('SKS Edible Oil_Loan'!F27-F23)*G20/360+G30*(G23-'SKS Edible Oil_Loan'!F27)*G20/360 -> 12270833 | H25: =H24*('SKS Edible Oil_Loan'!G27-G23)*H20/360+H30*(H23-'SKS Edible Oil_Loan'!G27)*H20/360 -> 11875000 | I25: =I24*('SKS Edible Oil_Loan'!H27-H23)*I20/360+I30*(I23-'SKS Edible Oil_Loan'!H27)*I20/360 -> 12270833 | J25: =J24*('SKS Edible Oil_Loan'!I27-I23)*J20/360+J30*(J23-'SKS Edible Oil_Loan'!I27)*J20/360 -> 12270833 | ... N25: =N24*('SKS Edible Oil_Loan'!M27-M23)*N20/360+N30*(N23-'SKS Edible Oil_Loan'!M27)*N20/360 -> 12721424 | O25: =N30*(D15-N23)*N20/360+O30*(O23-D15)*O20/360 -> 13054253 | P25: =P24*('SKS Edible Oil_Loan'!O27-O23)*P20/360+P30*(P23-'SKS Edible Oil_Loan'!O27)*P20/360 -> 15070969 | Q25: =Q24*('SKS Edible Oil_Loan'!P27-P23)*Q20/360+Q30*(Q23-'SKS Edible Oil_Loan'!P27)*Q20/360 -> 15070969 | R25: =R24*('SKS Edible Oil_Loan'!Q27-Q23)*R20/360+R30*(R23-'SKS Edible Oil_Loan'!Q27)*R20/360 -> 14584809 | S25: =S24*('SKS Edible Oil_Loan'!R27-R23)*S20/360+S30*(S23-'SKS Edible Oil_Loan'!R27)*S20/360 -> 15070969 | T25: =+S30*(E15-S23)*T20/360+T24*(T23-E15)*T20/360 -> 16643142 | U25: =U24*('SKS Edible Oil_Loan'!T27-T23)*U20/360+U30*(U23-'SKS Edible Oil_Loan'!T27)*U20/360 -> 17525136 | V25: =V24*('SKS Edible Oil_Loan'!U27-U23)*V20/360+V30*(V23-'SKS Edible Oil_Loan'!U27)*V20/360 -> 17525136 | W25: =W24*('SKS Edible Oil_Loan'!V27-V23)*W20/360+W30*(W23-'SKS Edible Oil_Loan'!V27)*W20/360 -> 16394482 | X25: =X24*('SKS Edible Oil_Loan'!W27-W23)*X20/360+X30*(X23-'SKS Edible Oil_Loan'!W27)*X20/360 -> 17525136 | Y25: =Y24*('SKS Edible Oil_Loan'!X27-X23)*Y20/360+Y30*(Y23-'SKS Edible Oil_Loan'!X27)*Y20/360 -> 16959809 | Z25: =Z24*('SKS Edible Oil_Loan'!Y27-Y23)*Z20/360+Z30*(Z23-'SKS Edible Oil_Loan'!Y27)*Z20/360 -> 18131130 | AA25: =AA24*('SKS Edible Oil_Loan'!Z27-Z23)*AA20/360+AA30*(AA23-'SKS Edible Oil_Loan'!Z27)*AA20/360 -> 18405879 | AB25: =AB24*('SKS Edible Oil_Loan'!AA27-AA23)*AB20/360+AB30*(AB23-'SKS Edible Oil_Loan'!AA27)*AB20/360 -> 18883295 | ... DR25: =DR24*('SKS Edible Oil_Loan'!DQ27-DQ23)*DR20/360+DR30*(DR23-'SKS Edible Oil_Loan'!DQ27)*DR20/360 -> 127545.54
A26: Cumulative interest | B26: =B25 -> 4125000 | C26: =B26+C25 -> 14437500 | D26: =C26+D25 -> 26708333 | E26: =D26+E25 -> 38979167 | F26: =E26+F25 -> 50854167 | G26: =F26+G25 -> 63125000 | H26: =G26+H25 -> 75000000 | I26: =H26+I25 -> 87270833 | J26: =I26+J25 -> 99541667 | ... DR26: =DQ26+DR25 -> 1.352099e+09
A27: Principal Payment | B27: 0 | C27: 0 | D27: 0 | E27: 0 | F27: 0 | G27: 0 | H27: 0 | I27: 0 | J27: 0 | K27: 0 | L27: 0 | M27: 0 | N27: 0 | O27: 0 | P27: 0 | Q27: 0 | R27: 0 | S27: 0 | T27: 0 | U27: 0 | V27: 0 | W27: 0 | X27: 0 | Y27: 0 | Z27: 0 | AA27: ='SKS Edible Oil_Loan'!Z31 -> 16322121 | AB27: ='SKS Edible Oil_Loan'!AA31 -> 16451338 | AC27: ='SKS Edible Oil_Loan'!AB31 -> 16581578 | AD27: ='SKS Edible Oil_Loan'!AC31 -> 16712848 | AE27: ='SKS Edible Oil_Loan'!AD31 -> 16845158 | AF27: ='SKS Edible Oil_Loan'!AE31 -> 16978516 | AG27: ='SKS Edible Oil_Loan'!AF31 -> 17112929 | AH27: ='SKS Edible Oil_Loan'!AG31 -> 17248407 | ... DR27: ='SKS Edible Oil_Loan'!DQ31 -> 34523604
A28: Cumulative repayment | B28: =B27 -> 0 | C28: =B28+C27 -> 0 | D28: =C28+D27 -> 0 | E28: =D28+E27 -> 0 | F28: =E28+F27 -> 0 | G28: =F28+G27 -> 0 | H28: =G28+H27 -> 0 | I28: =H28+I27 -> 0 | J28: =I28+J27 -> 0 | ... DR28: =DQ28+DR27 -> 2.3336583e+09
A29: Total Debt Service | B29: =B27+B25 -> 4125000 | C29: =C27+C25 -> 10312500 | D29: =D27+D25 -> 12270833 | E29: =E27+E25 -> 12270833 | F29: =F27+F25 -> 11875000 | G29: =G27+G25 -> 12270833 | H29: =H27+H25 -> 11875000 | I29: =I27+I25 -> 12270833 | ... DR29: =DR27+DR25 -> 34651149
A30: Closing Balance | B30: =B24-B27 -> 1500000000 | C30: =C24-C27 -> 1500000000 | D30: =D24-D27 -> 1500000000 | E30: =E24-E27 -> 1500000000 | F30: =F24-F27 -> 1500000000 | G30: =G24-G27 -> 1500000000 | H30: =H24-H27 -> 1500000000 | I30: =I24-I27 -> 1500000000 | ... M30: =M24-M27 -> 1500000000 | N30: ='SKS Edible Oil_Loan'!M34 -> 1.6422917e+09 | O30: =O24-O27 -> 1.8422917e+09 | P30: =P24-P27 -> 1.8422917e+09 | Q30: =Q24-Q27 -> 1.8422917e+09 | R30: =R24-R27 -> 1.8422917e+09 | S30: =S24-S27 -> 1.8422917e+09 | T30: =T24-T27 -> 2.1422917e+09 | U30: =U24-U27 -> 2.1422917e+09 | V30: =V24-V27 -> 2.1422917e+09 | ... Y30: =Y24-Y27 -> 2.1422917e+09 | Z30: ='SKS Edible Oil_Loan'!Y34 -> 2.3336583e+09 | AA30: =AA24-AA27 -> 2.3173362e+09 | AB30: =AB24-AB27 -> 2.3008848e+09 | AC30: =AC24-AC27 -> 2.2843032e+09 | AD30: =AD24-AD27 -> 2.2675904e+09 | AE30: =AE24-AE27 -> 2.2507452e+09 | AF30: =AF24-AF27 -> 2.2337667e+09 | AG30: =AG24-AG27 -> 2.2166538e+09 | AH30: =AH24-AH27 -> 2.1994054e+09 | ... DR30: =DR24-DR27 -> 2.0861626e-07
DR32: =+DR26-SUM('SKS Edible Oil_Loan'!B29:DQ29) -> 0

Sheet Repayment Schedule
A1: Project name: | C1: ='SKS Edible Oil_Loan'!C1 -> Sena Kalyan Sangstha-Edible Oil Project (SKS Edible Oil)
A3: Financial Close | C3: ='SKS Edible Oil_Loan'!C3 -> 43215
A5: Loan Amount | C5: ='SKS Edible Oil_Loan'!C5 -> 2355000000
A7: Interest Rate | C7: ='SKS Edible Oil_Loan'!C8 -> 0.0825
A9: Number of installments | C9: ='SKS Edible Oil_Loan'!C13 -> 96
A11: Drawdown
C12: ='SKS Edible Oil_Loan'!C16 -> 43240
C13: ='SKS Edible Oil_Loan'!C17 -> 1500000000
C14: =C13 -> 1500000000
A16: Repayment Date | B16: Opening Balance | C16: Interest Payment | D16: Cumulative interest | E16: Principal Payment | F16: Cumulative repayment | G16: Total Debt Service | H16: Closing Balance
A17: {=TRANSPOSE('SKS Edible Oil_Loan'!B27:DQ34)} -> 43266 | B17: 1500000000 | C17: 8937500 | D17: 0 | E17: 0 | F17: 0 | G17: 0 | H17: 1500000000
A18: 43296 | B18: 1500000000 | C18: 11041667 | D18: 0 | E18: 0 | F18: 0 | G18: 0 | H18: 1500000000
A19: 43327 | B19: 1500000000 | C19: 12270833 | D19: 0 | E19: 0 | F19: 0 | G19: 0 | H19: 1500000000
A20: 43358 | B20: 1500000000 | C20: 12270833 | D20: 0 | E20: 0 | F20: 0 | G20: 0 | H20: 1500000000
A21: 43388 | B21: 1500000000 | C21: 11875000 | D21: 0 | E21: 0 | F21: 0 | G21: 0 | H21: 1500000000
A22: 43419 | B22: 1500000000 | C22: 12270833 | D22: 0 | E22: 0 | F22: 0 | G22: 0 | H22: 1500000000
A23: 43449 | B23: 1500000000 | C23: 11875000 | D23: 0 | E23: 0 | F23: 0 | G23: 0 | H23: 1500000000
A24: 43480 | B24: 1500000000 | C24: 12270833 | D24: 0 | E24: 0 | F24: 0 | G24: 0 | H24: 1500000000
A25: 43511 | B25: 1500000000 | C25: 12270833 | D25: 0 | E25: 0 | F25: 0 | G25: 0 | H25: 1500000000
A26: 43539 | B26: 1500000000 | C26: 11083333 | D26: 0 | E26: 0 | F26: 0 | G26: 0 | H26: 1500000000
A27: 43570 | B27: 1500000000 | C27: 12270833 | D27: 0 | E27: 0 | F27: 0 | G27: 0 | H27: 1500000000
A28: 43605 | B28: 1500000000 | C28: 13854167 | D28: 0 | E28: 0 | F28: 0 | G28: 0 | H28: 1.6422917e+09
A29: 43631 | B29: 1.6422917e+09 | C29: 11267946 | D29: 0 | E29: 0 | F29: 0 | G29: 0 | H29: 1.6422917e+09
... A40: 43971 | B40: 2.1422917e+09 | C40: 19786444 | D40: 0 | E40: 0 | F40: 0 | G40: 0 | H40: 2.3336583e+09
A41: 43997 | B41: 2.3336583e+09 | C41: 16011489 | D41: 16011489 | E41: 16322121 | F41: 16322121 | G41: 32333610 | H41: 2.3173362e+09 | J41: 16011489 | K41: =+J41-C41 -> -0.0030208342
A42: 44027 | B42: 2.3173362e+09 | C42: 18345578 | D42: 34357067 | E42: 16451338 | F42: 32773459 | G42: 34796916 | H42: 2.3008848e+09 | J42: 18345578 | K42: =+J42-C42 -> 0.0046085976
A43: 44056 | B43: 2.3008848e+09 | C43: 17608160 | D43: 51965227 | E43: 16581578 | F43: 49355036 | G43: 34189738 | H43: 2.2843032e+09 | J43: 17608160 | K43: =+J43-C43 -> 0.0013083555
A44: 44089 | B44: 2.2843032e+09 | C44: 19892474 | D44: 71857701 | E44: 16712848 | F44: 66067885 | G44: 36605322 | H44: 2.2675904e+09 | J44: 19892474 | K44: =+J44-C44 -> -0.0013535768
A45: 44119 | B45: 2.2675904e+09 | C45: 17951757 | D45: 89809458 | E45: 16845158 | F45: 82913043 | G45: 34796916 | H45: 2.2507452e+09 | J45: 17951757 | K45: =+J45-C45 -> 0.0037471764
A46: 44150 | B46: 2.2507452e+09 | C46: 18412346 | D46: 1.082218e+08 | E46: 16978516 | F46: 99891559 | G46: 35390862 | H46: 2.2337667e+09 | J46: 18412346 | K46: =+J46-C46 -> -0.0022433028
A47: 44180 | B47: 2.2337667e+09 | C47: 17683987 | D47: 1.2590579e+08 | E47: 17112929 | F47: 1.1700449e+08 | G47: 34796916 | H47: 2.2166538e+09 | J47: 17683987 | K47: =+J47-C47 -> -0.0011817403
A48: 44210 | B48: 2.2166538e+09 | C48: 17548509 | D48: 1.434543e+08 | E48: 17248407 | F48: 1.3425289e+08 | G48: 34796916 | H48: 2.1994054e+09 | J48: 17548509 | K48: =+J48-C48 -> 0.0047111213
A49: 44242 | B49: 2.1994054e+09 | C49: 18572757 | D49: 1.6202706e+08 | E49: 17384956 | F49: 1.5163785e+08 | G49: 35957713 | H49: 2.1820204e+09 | J49: 18572757 | K49: =+J49-C49 -> 0.0023162365
A50: 44270 | B50: 2.1820204e+09 | C50: 16122707 | D50: 1.7814976e+08 | E50: 17522587 | F50: 1.6916044e+08 | G50: 33645294 | H50: 2.1644978e+09 | J50: 16122707 | K50: =+J50-C50 -> -0.0017492101
A51: 44301 | B51: 2.1644978e+09 | C51: 17706795 | D51: 1.9585656e+08 | E51: 17661308 | F51: 1.8682175e+08 | G51: 35368103 | H51: 2.1468365e+09 | J51: 17706795 | K51: =+J51-C51 -> -0.0033178329
A52: 44329 | B52: 2.1468365e+09 | C52: 15862737 | D52: 2.117193e+08 | E52: 17801126 | F52: 2.0462287e+08 | G52: 33663863 | H52: 2.1290354e+09 | J52: 15862737 | K52: =+J52-C52 -> -0.00013871305
... A136: 46888 | B136: 34523604 | C136: 291532.65 | D136: 1.0184407e+09 | E136: 34523604 | F136: 2.3336583e+09 | G136: 34815137 | H136: 2.0861626e-07 | J136: 291532.65 | K136: =+J136-C136 -> -0.0047566544
